Workbook
Name 积分定价: '2.0大富翁抽奖'!$E$129
Name 骰子价值: '2.0大富翁抽奖'!$E$20

Sheet 路线图
A3: 时间 | C3: 1 | D3: 2 | E3: 3 | F3: 4 | G3: 5 | H3: 6 | I3: 7 | J3: 8 | K3: 9 | L3: 10 | M3: 11 | N3: 12 | O3: 13 | P3: 14 | Q3: 第3周 | R3: 第4周 | S3: 第5周 | T3: 第6周 | U3: 第7周 | V3: 第8周 | W3: 第9周 | X3: 第10周 | Y3: 第11周 | Z3: 第12周 | AA3: 第13周 | AB3: 第14周 | AC3: 第15周 | AD3: 第16周 | AE3: 第17周
A4: 满活跃非r主线 | C4: 10 | D4: 15 | E4: 20 | F4: 25 | G4: 30 | H4: 35 | I4: 40 | J4: 45 | K4: 47 | L4: 49 | M4: 51 | N4: 53 | O4: 55 | P4: 57
A5: 满活跃小R主线（四卡党） | C5: 15 | D5: 25 | E5: 35 | F5: 45 | G5: 48 | H5: 50 | I5: 54 | J5: 55 | K5: 57 | L5: 59 | M5: 61 | N5: 63 | O5: 65 | P5: 67
A6: 满活跃中R主线（四卡党+活动）1000+，日产200抽 | C6: 25 | D6: 35 | E6: 45 | F6: 48 | G6: 50 | H6: 54 | I6: 55 | J6: 57 | K6: 60 | L6: 63 | M6: 66 | N6: 69 | O6: 71 | P6: 73
A7: 满活跃大R主线3000+ | C7: 35 | D7: 40 | E7: 45 | F7: 50 | G7: 55 | H7: 57 | I7: 60 | J7: 63 | K7: 66 | L7: 69 | M7: 73 | N7: 75 | O7: 77 | P7: 80 | Q7: 90.5 | R7: 101 | S7: 108 | T7: 115 | U7: 122 | V7: 129 | W7: 136 | X7: 143 | Y7: 150 | Z7: 157 | AA7: 164 | AB7: 171 | AC7: 178 | AD7: 185 | AE7: 192
A8: 养成 梦灵线 | B8: 梦灵 | C8: 2-3紫（5级 | D8: 东方/镭射 | E8: 亚瑟 | F8: 蜘蛛 | G8: 唐小僧 | H8: 神灯 | I8: 关羽 | J8: 后羿/诸葛/我爱沙 | Q8: 海拉/妲己 | R8: 白素贞 | S8: 零日骇客UP活动 (31天）（35天进普池） | W8: 雅典娜UP (59天） | AB8: 女娲UP (73天） | AE8: 杨戬UP (102天）
B9: 挂件 解锁条件-主角等级 | C9: 弹幕流/全图流/爆发流 | D9: 能量流 | F9: 召唤流 | H9: 共鸣流 | J9: 赛季挂件 (S0) | W9: 赛季挂件 (S1)
B10: 符文 | C10: 开启
A11: 养成 主角线 | B11: 装备 | C11: 开启 | E11: 红装 | Q11: 粉装 | T11: 彩装 | U11: 彩虹装
B12: 武器 | C12: 开局+1 | E12: 开局+1 | P12: 开局+1 | T12: 开局+1
B13: 秘宝 | H13: 开启
B14: 藏品 | Q14: 藏品系统（15天） （静默开启）
B15: 载具 | R15: 载具系统 （22天）
B16: 宠物 | V16: 宠物系统 （60天）
A17: 玩法 | B17: 荧幕争锋 | C17: 开启
B18: 梦域巡航 | C18: 难度1 | E18: 难度2 | H18: 难度3 | L18: 难度4 | P18: 难度5 | Q18: 难度6/难度7 | R18: 难度8 | S18: 难度9 | T18: 难度10 彩虹关1(藏品) | V18: 彩虹2 | Y18: 彩虹3 | AA18: 彩虹4
B19: 海底捞金 | C19: 开启
B20: 贪吃大作战 | E20: 开启 | Q20: 升级
B21: 梦隙迷廊 | R21: 开启
B22: 宠物玩法 | V22: 开启
B23: 赛季玩法 | X23: S1玩法
A24: 活动 | B24: 赛季循环 （长周期投辅线） | C24: S0赛季-梦境启航（过度赛季） | V24: S1赛季-我有一座恐怖屋（主推射手、法师)
C25: 主投：红梦灵及皮肤、红色符文（好词条） 辅投：橙、紫梦灵及皮肤、符文祝福石 进度：B级冒险家+散件 荣誉：主角氛围特效-白日梦想（S） | V25: 主投：粉梦灵皮肤、红色符文（好词条） 辅投：橙、红梦灵及皮肤、符文祝福石 进度：B级 小鬼当家+散件 荣誉：主角氛围特效-百鬼夜行（S）
B26: 周循环 （循环投养成） | D26: 开服冲刺//根据抽数达成配置奖励，同时玩家首日抽卡次数保留到开服冲刺 | J26: 招募冲刺【根据第7天招募次数达成中位数来设置首档和后续的奖励】 | Q26: 符文冲刺(boss) | R26: 秘宝冲刺 （排行投皮肤） | S26: 招募冲刺 | T26: 符文冲刺(boss) | U26: 秘宝冲刺 | V26: 招募冲刺 （跨服） | W26: 符文冲刺 | X26: 秘宝冲刺 | Y26: 招募冲刺 | Z26: 符文冲刺 | AA26: 秘宝冲刺 | AB26: 招募冲刺
Q27: 悬赏（1档） | T27: 悬赏（2档） | W27: 悬赏（3档） | Z27: 悬赏（4档）
Q28: 红符文、随机橙藏品、指定橙藏品 第三周（符文产品） 第四周（载具产品） 第五周（招募冲刺 | T28: 红符文、载具粉零件 第6周（彩虹关的藏品 | W28: 载具粉零件、红符文、指定橙藏品... | Z28: 载具粉零件、红符文、指定橙藏品...
B29: 限时活动 （短周期投核心线) | G29: 橙卡试炼 | K29: 时装抽奖【星轨探测】聚焦皮肤 | O29: 红卡试炼(13-16天) | S29: 粉卡试炼 | V29: 粉卡试炼 | Y29: 粉卡试炼 | AB29: 粉卡试炼
G30: 橙卡皮肤 专属符文（红卡预告） | K30: 天使套-A （S0） | O30: 红卡皮肤 专属符文 | S30: 粉卡皮肤 专属符文 | V30: 粉卡皮肤 专属符文 | Y30: 粉卡皮 肤专属符文 | AB30: 粉卡皮肤 专属符文
B34: 1.梦灵节奏适当压缩了一点（粉卡阶段采用的蔚蓝上一版本的节奏，因为我们存量不够）
B36: 2.三类活动线的做了调整：
B37: 月活动→赛季：主要做主轴目标和荣誉追求，投放辅线的资源
B38: 周循环活动：做中小R的钻石消耗和付费转化，主要承载中小R的长期目标和小额付费转化，投放养成资源
B39: 限时活动：拉收，短周期，投放核心资源
B40: 一个核心调整思路就是要把一些投放内容隔离到只有限时活动投放
B42: 3.目前盘下来，需要一个大颗粒度的投放内容去支撑上面这个投放结构，目前考虑下来还是藏品比较合适。对应的秘宝的价值要做上去，现在被当成藏品在投放。
B44: 首周：
B45: 1.关卡战力压制
B46: 2.梦灵节点追求
B48: 次周：
B49: 1.符文概率调整
... B59: 1.载具系统

Sheet 甘特图
A2: 功能新增 | P2: 藏品 | W2: 载具 | AF2: 粉卡
A3: 天数 | B3: 1 | C3: 2 | D3: 3 | E3: 4 | F3: 5 | G3: 6 | H3: 7 | I3: 8 | J3: 9 | K3: 10 | L3: 11 | M3: 12 | N3: 13 | O3: 14 | P3: 15 | Q3: 16 | R3: 17 | S3: 18 | T3: 19 | U3: 20 | V3: 21 | W3: 22 | X3: 23 | Y3: 24 | Z3: 25 | AA3: 26 | AB3: 27 | AC3: 28 | AD3: 29 | AE3: 30 | AF3: 31 | AG3: 32 | AH3: 33 | AI3: 34 | AJ3: 35 | AK3: 36 | AL3: 37 | AM3: 38 | AN3: 39 | AO3: 40 | AP3: 41 | AQ3: 42 | AR3: 43 | AS3: 44 | AT3: 45 | AU3: 46 | AV3: 47 | AW3: 48 | AX3: 49 | AY3: 50 | AZ3: 51 | BA3: 52 | BB3: 53 | BC3: 54 | BD3: 55 | BE3: 56 | BF3: 57 | BG3: 58 | BH3: 59 | BI3: 60 | BJ3: 61 | BK3: 62 | BL3: 63
A4: 活动 | B4: 6元首冲
A5: 活动 | B5: 每日特惠(1、6、18) 优化1、6、18元随机宝箱，提高返利
A6: 活动 | B6: 日/周/月礼包
A7: 活动 | B7: 每日充值(25元赠送1个传说祝福石)
A8: 活动 | B8: 大小月卡 18/30
A9: 活动 | B9: 体力战令28/68 | P9: 体力战令28/68（68元增加自选，加一些材料） | AD9: 体力战令28/68（68元增加自选）
A10: 活动 | B10: 周卡（新增金币扫荡） | I10: 周卡（金币扫荡） | P10: 周卡（金币扫荡） | W10: 周卡（（组队双倍）（金币扫荡） | AD10: 周卡（（组队双倍）（金币扫荡） | AK10: 周卡（（组队双倍）（金币扫荡）
A11: 活动 | B11: 钻石战令Ⅰ Ⅱ | W11: 载具战令
A12: 活动 | B12: 七日目标//玩法活跃引导
A13: 活动 | B13: 章节礼包
A14: 活动 | B14: 招募狂欢（3200） | I14: 招募冲刺（红卡魂魄） | P14: 符文冲刺（符文宝石） | W14: 秘宝冲刺（秘宝皮肤） | AD14: 招募冲刺（粉卡魂魄）（藏品） | AK14: 符文冲刺（符文宝石） | AR14: 秘宝冲刺（皮肤+藏品） | AY14: 招募冲刺（粉卡魂魄）（藏品） | BF14: 符文冲刺（符文宝石）
A15: 活动 | F15: 橙卡试炼【皮肤、符文】 | L15: 红卡试炼【符文、皮肤】
A16: 活动 | D16: 礼包
A17: 活动 | P17: 悬赏活动1【符文洗炼藏品】 | W17: 悬赏活动2【组队藏品】 | AD17: 悬赏活动3【招募藏品】 | AK17: 悬赏活动1【周卡迷廊藏品】 | AR17: 悬赏活动2【组队藏品】 | AY17: 悬赏活动3【招募藏品】 | BF17: 悬赏活动1【符文洗炼藏品、符文】
A18: 活动 | B18: 月度活动（红色皮肤、专属符文（限制1个4档）主要是投放皮肤） | AF18: 次月活动（粉卡皮肤）
A19: 限时活动 | I19: 皮肤（天使套）直抽月光炼梦改【5+5】A | P19: 神秘套【月光炼梦】 | AB19: 载具转盘（主投皮肤）星轨探测改（A）
A20: 限时UP | W20: 宇宙套【月光炼梦】 | AF20: 限时up（15天）（骇客） | AU20: 限时up（15天）（雅典娜）

Sheet 价值表
H2: 主要投放途径
B3: 序号 | C3: 道具名称 | D3: 道具ID | E3: 类别 | F3: 钻石价值 | G3: RMB售价 | H3: 途径1 | I3: 途径2 | J3: 标准折扣 | K3: 备注 | L3: 整体思路
B4: 1 | C4: 钻石 | D4: 1 | E4: 货币类 | F4: 1 | G4: 0.1 | H4: 任务/成就/主线三星 | I4: 充值 | J4: 5 | L4: 做各阶层的能力阶梯
B5: 2 | C5: 体力 | D5: 13 | F5: 2 | G5: 0.2 | H5: 快捷购买 | J5: 7
B6: 3 | C6: 金币 | D6: 2 | F6: 0.05 | G6: 0.005 | H6: 日周月商店 | J6: 5
B7: 4 | C7: 心梦宝石 | D7: 44 | F7: 10 | G7: 1.4 | H7: 每日特惠 | I7: 排行冲刺 | J7: 2 | L7: 做中R的付费质感（前期中R）
B8: 5 | C8: 战令宝箱 | D8: 20003 | F8: 30
B9: 6 | C9: 每日特惠宝箱 | D9: 20033 | F9: 40
B10: 7 | C10: 咩菲特的雕像 | D10: 5800004 | F10: 30 | G10: 3
B11: 8 | C11: 织梦宝箱 | D11: 5800005 | F11: 50
B12: 9 | C12: 筑梦快递箱 | D12: 20034 | F12: 250
B13: 10 | C13: 筑梦典藏箱 | D13: 20035 | F13: 700
B14: 11 | C14: 巡航门票 | D14: 28 | F14: 200 | G14: 20
B15: 12 | C15: 超能特饮 | D15: 5104001 | F15: 2 | G15: 0.2
B16: 13 | C16: 能量特饮 | D16: 5103001 | E16: 梦灵类 | F16: 1 | G16: 0.1 | H16: 体力产出 | J16: 5 | L16: 做非R的基础体验
B19: 14 | C19: 梦境招募器 | D19: 11 | F19: 30 | G19: 3 | H19: 情绪净化/主线任务 | I19: 商店购买 | J19: 6 | L19: 做各阶层的能力阶梯（前期质变）
B20: 15 | C20: 梦愿水晶 | D20: 35 | F20: 100 | G20: 10 | H20: 招募累计 | K20: 心愿招募
B21: 16 | C21: 神灯 | F21: 120 | G21: 10 | H21: 商店购买 | J21: 10 | K21: 限定招募 | L21: 做大R的付费边界（后期质变）
B22: 17 | C22: 稀有梦灵 | D22: 1310100 | F22: =F27*10 -> 60 | G22: =F27 -> 6 | H22: 英雄招募 | J22: 8 | L22: 本体；碎片*10
B23: 18 | C23: 史诗梦灵 | D23: 1420200 | F23: =F28*10 -> 120 | G23: =F28 -> 12 | H23: 英雄招募 | J23: 8 | L23: 本体；碎片*10
B24: 19 | C24: 传说梦灵 | D24: 1130100 | F24: =F29*10 -> 240 | G24: =F29 -> 24 | H24: 英雄招募 | J24: 8 | L24: 本体；碎片*10
B25: 20 | C25: 神话梦灵 | F25: =F30*10 -> 480 | G25: =F30 -> 48 | H25: 英雄招募 | J25: 8 | L25: 本体；碎片*10
B26: 21 | C26: 彩虹梦灵 | F26: =F31*10 -> 960 | G26: =F31 -> 96 | H26: 英雄招募 | J26: 8 | L26: 本体；碎片*10
B27: 22 | C27: 稀有梦灵碎片 | D27: 13101001 | F27: 6 | H27: 英雄招募 | J27: 8
B28: 23 | C28: 史诗梦灵碎片 | D28: 14202001 | F28: 12 | G28: 1.2 | H28: 英雄招募 | J28: 8
B29: 24 | C29: 传说梦灵碎片 | D29: 11301001 | F29: 24 | G29: 2.4 | H29: 英雄招募 | J29: 8
B30: 25 | C30: 神话梦灵碎片 | F30: 48 | G30: 4.8 | H30: 英雄招募 | J30: 8
B31: 26 | C31: 彩虹梦灵碎片 | F31: 96 | H31: 英雄招募 | J31: 8
C33: 零号骇客 | D33: 1610100 | F33: 暂不定价 | K33: 原估值引用已隐藏的旧粉卡试炼；现行配置无可复核估值锚，暂不定价
B34: 27 | C34: 公会贡献 | D34: 50 | F34: 0.1 | G34: 0.01
B35: 28 | C35: 转运石 | D35: 5523001 | F35: 0.33 | G35: 0.033 | J35: 5
B36: 29 | C36: 织梦能量 | D36: 47 | E36: 暂不定价 | F36: 暂不定价 | G36: 暂不定价 | K36: 友情值ID待核；ID47线上名称织梦能量
C37: 传说祝福石 | D37: 5305010 | F37: 1500 | G37: 150
C38: 神话祝福石 | F38: 5000 | G38: 500
C39: 创世祝福石 | F39: 16000 | G39: 1600
B41: 30 | C41: 装备图纸 | D41: 50002 | E41: 装备类 | F41: 3 | G41: 0.3 | H41: 体力产出 | J41: 6 | L41: 做非R长线活跃养成
B42: 31 | C42: 锻造晶石 | D42: 50001 | F42: 0.1 | G42: 0.01 | H42: 体力产出 | J42: 5 | K42: 装备洗练 | L42: 做非R的基础体验
B43: 32 | C43: 主线装备箱 | F43: 15 | H43: 体力产出
B44: 33 | C44: 队长大箱子 | F44: 50 | H44: 体力产出
B45: 34 | C45: 队长小箱子 | F45: 15 | H45: 体力产出
B46: 34 | C46: 随机普通装备 | H46: 体力产出
B47: 35 | C47: 随机优秀装备 | H47: 体力产出
B48: 36 | C48: 随机稀有装备 | H48: 体力产出
B49: 37 | C49: 随机史诗装备 | H49: 体力产出
B50: 38 | C50: 随机传说装备 | H50: 体力产出
B51: 39 | C51: 随机神话装备 | H51: 体力产出 | I51: 285.71429
B52: 40 | C52: 随机创世装备 | H52: 体力产出 | I52: 47619.048
C53: 专属传说符文 | D53: 5600207 | F53: =F67 -> 4096
I54: 1500
B55: 41 | C55: 星之初愿 | D55: 9 | E55: 宝石类 | F55: 50 | G55: 5 | H55: 商店购买 | K55: 宝石低抽
B56: 42 | C56: 星辉秘契 | D56: 30 | F56: 280 | G56: 28 | H56: 商店购买 | J56: 5 | K56: 宝石高抽
B57: 43 | C57: 符引结晶 | D57: 5303001 | F57: 5 | G57: 0.5 | H57: 体力产出 | J57: 8 | K57: 低级洗练石
B58: 44 | C58: 幻梦晶核 | D58: 5305001 | F58: 60 | G58: 6 | H58: 商店购买 | J58: 5 | K58: 高级洗练石 | L58: 做中R的付费质感
C59: 传说祝福石 | D59: 5305010 | F59: 1500 | G59: 150
C60: 神话祝福石 | D60: 5305008 | F60: 5000 | G60: 500
C61: 创世祝福石 | D61: 5305009 | F61: 16000 | G61: 1600
B63: 45 | C63: 普通符文 | D63: 5301000 | F63: 16 | G63: 1.6 | H63: 体力产出 | K63: 白宝石
B64: 46 | C64: 优秀符文 | D64: 5302000 | F64: 64 | G64: 6.4 | H64: 体力产出 | K64: 绿宝石
B65: 47 | C65: 稀有符文 | D65: 5303000 | F65: 256 | G65: 25.6 | H65: 体力产出 | K65: 蓝宝石
B66: 48 | C66: 史诗符文 | D66: 5304000 | F66: 1024 | G66: 102.4 | H66: 体力产出 | K66: 紫宝石
B67: 49 | C67: 传说符文 | D67: 5305000 | F67: 4096 | G67: 409.6 | H67: 体力产出 | K67: 橙宝石 | L67: 做中R的付费质感
B68: 50 | C68: 神话符文 | D68: 5306000 | F68: 16384 | G68: 1638.4 | H68: 体力产出 | K68: 红宝石 | L68: 做大R的付费质感
B69: 51 | C69: 创世符文 | D69: 5307000 | F69: 65536 | G69: 6553.6 | H69: 体力产出 | K69: 彩宝石 | L69: 做大R的付费边界
C70: 传说英雄随机珍稀符文 | F70: 700 | G70: 70 | L70: 梦灵试炼（橙卡）
C71: 传说英雄随机稀世符文 | F71: 2500 | G71: 250 | L71: 梦灵试炼（红卡）
C72: 绝世英雄传说随机专属符文 | F72: 3000 | G72: 300
C73: 绝世英雄神话随机专属符文 | F73: 6000 | G73: 600
B75: 52 | C75: 符文宝箱 | D75: 5401000 | F75: 17.728
B76: 53 | C76: 织梦微尘 | D76: 5203001 | E76: 基因类 | F76: 3 | G76: 0.3 | H76: 体力产出 | J76: 6 | K76: 基因低级材料 | L76: 做各阶层的能力阶梯
B77: 54 | C77: 潜能棱晶 | D77: 5205001 | F77: 500 | G77: 50 | H77: 主线三星 | K77: 基因高级材料
B78: 55 | C78: 加速沙漏 | D78: 5204001 | F78: 5 | G78: 0.5 | H78: 体力产出 | L78: 通过SS类活动做分层
B80: 56 | C80: 咸鱼之王 | D80: 5525002 | E80: 暂不定价 | F80: 暂不定价 | G80: 暂不定价 | H80: 公会活动 | K80: 原表晶石；ID5525002线上名称咸鱼之王
B81: 57 | C81: 竞技场币 | F81: 0.02 | G81: 0.002
E82: 玩法类
C83: 贪吃币 | D83: 59 | E83: 暂不定价 | F83: 暂不定价 | G83: 暂不定价 | K83: boss积分ID待核；ID59线上名称贪吃币
E84: 活动抽奖道具
B85: 56 | C85: 星路通票 | D85: 5600077 | F85: 60 | H85: 运营活动 | K85: 限对应活动抽奖替代价
C86: 星路里程 | F86: 30
C87: 普通骰子 | D87: 5600112 | F87: 30 | K87: 限山河巡游310100
C88: 金骰子 | D88: 5600113 | F88: 200 | K88: 本期规划名义价
C89: 大富翁积分 | F89: 0.5
C90: 战利品宝箱 | F90: 200
C91: 祈星券 | D91: 100050 | F91: 60 | K91: 限祈星转盘40008
C92: 祈愿水晶 | F92: 1500
C93: 试炼抽奖券 | D93: 5600078 | E93: 暂不定价 | F93: 暂不定价 | G93: 暂不定价 | I93: 实际售卖rmb | K93: ID5600078仅见1条小鱼干流水，名称待核
B95: 58 | C95: 史诗梦灵皮肤 | F95: 1500 | H95: 运营活动 | I95: 30
B96: 59 | C96: 传说梦灵皮肤 | F96: 4000 | H96: 运营活动 | I96: 128
B97: 60 | C97: 神话梦灵皮肤 | F97: 8000 | H97: 运营活动 | I97: 198
C98: 史诗武器皮肤 | F98: 2000
B99: 61 | C99: 传说武器皮肤 | F99: 4000 | I99: 128
B100: 62 | C100: 神话武器皮肤 | F100: 8000 | I100: 168
B101: 63 | C101: 史诗时装皮肤 | F101: 2500
B102: 64 | C102: 传说时装皮肤 | F102: 7000 | I102: 266 | L102: 做中小R的钻销体系+大R的付费隔绝
B103: 65 | C103: 神话时装皮肤 | F103: 12000 | I103: 328 | L103: 做中小R的钻销体系+大R的付费隔绝
C104: 史诗秘宝皮肤 | F104: 2000
B105: 66 | C105: 传说秘宝皮肤 | F105: 6000
B106: 67 | C106: 神话秘宝皮肤 | F106: 12000
B108: 68 | C108: 史诗主角挂件 | F108: 500
B109: 69 | C109: 传说主角挂件 | F109: 1000
B110: 70 | C110: 神话主角挂件 | F110: 1500
...

Sheet 活动评级标准
C4: 稀缺度
C6: 稀缺度 | D6: 定义 | E6: 投放约束 | M6: 设计思路
C7: 常规 | D7: 存在稳定、重复获取渠道 | E7: 可进入日常、常驻商店和普通礼包 | N7: 基于日周月礼包锚定性价比折算返利
C8: 受限 | D8: 稳定出现，但存在周期或数量限制 | E8: 可进入周循环、战令、限购礼包 | N8: 分层 | O8: 档位 | P8: 整体思路 | Q8: 总计花费 | R8: 返利比($) | S8: 总价/每月($)
C9: 稀缺 | D9: 只在少量运营活动中周期投放 | E9: 控制月度总量，禁止日常大量投放 | S9: 首充 | T9: 大小月卡 | U9: 周卡 | V9: 日周月礼包 | W9: 钻石基金 | X9: 战令 | Y9: 每日特惠 | Z9: 月度活动 | AA9: 节日活动 | AB9: 冲刺活动 | AC9: 皮肤转盘
C10: 限定 | D10: 赛季、联动、首发或特定时间独占 | E10: 限定渠道、限定周期，返场需单独审核 | N10: 非R | O10: 1 | P10: 豹子头 | Q10: 0
N11: 小R | O11: 1 | P11: 首冲玩家 | Q11: =SUM($S$10:AC11) -> 6 | R11: 50 | S11: 6
C12: 材料返利比 | O12: 2 | P12: 购买部分特权 | Q12: =SUM($S$10:AC12) -> 54 | R12: 20 | T12: 48
O13: 3 | P13: 特权买齐 | Q13: =SUM($S$10:AC13) -> 200 | R13: 10 | U13: 48 | W13: 98
C14: 直购档位/RMB | D14: 标准返比 | E14: 示例 | H14: 月卡、周卡、基金、战令类，返比>1000% | N14: 中R | O14: 1 | P14: 追求主养成模块 | Q14: =SUM($S$10:AC14) -> 824 | R14: 10 | X14: 192 | AB14: 432
C15: 6 | D15: 10 | E15: 6元=6高抽+60钻 | H15: 基础资源 | I15: 30元=36小时 | O15: 2 | P15: 追求多个养成模块 | Q15: =SUM($S$10:AC15) -> 1280 | R15: 5 | Z15: 180 | AA15: 108 | AC15: 168
C16: 12 | D16: 8 | I16: 68元=72小时 | O16: 4 | P16: 追求全部养成模块 在边界上不付费 | Q16: =SUM($S$10:AC16) -> 3304 | R16: 2.5 | Y16: 750 | Z16: 490 | AA16: 294 | AC16: 490
C17: 30 | D17: 6 | E17: 30元=10心愿抽+300钻 | N17: 大R | O17: 1 | P17: 每月活动拉满 | Q17: =SUM($S$10:AC17) -> 10928 | R17: 2 | V17: 5000 | AA17: 1640 | AB17: 984
C18: 68 | D18: 5 | I18: 基金 | J18: 10 | O18: 2 | P18: 每周礼包拉满 | Q18: =SUM($S$10:AC18) -> 25928 | R18: 1.5 | V18: 15000
C19: 98 | D19: 4 | I19: 战令 | J19: 15 | O19: 3 | P19: 每日消费拉满 | Q19: =SUM($S$10:AC19) -> 55928 | R19: 1 | V19: 30000
C20: 128 | D20: 3.5 | N20: 超R | O20: 1 | P20: 付费内容拉满 | Q20: =SUM($S$10:AC20) -> 255928 | R20: 1 | V20: 200000
C21: 198 | D21: 3
C22: 328 | D22: 2.5
C23: 648 | D23: 2 | N23: 基于养成系统对应
N24: 类 | O24: 模块 | P24: 贡献占比/每月
C25: 钻石消耗活动直购礼包返利比 | P25: 首充 | Q25: 大小月卡 | R25: 周卡 | S25: 日周月礼包 | T25: 钻石基金 | U25: 战令 | V25: 每日特惠 | W25: 月度活动 | X25: 节日活动 | Y25: 冲刺活动 | Z25: 皮肤转盘 | AA25: 充值返利
C26: 直购档位/RMB | D26: 标准返比 | E26: 示例 | N26: 梦灵 | O26: 梦灵升级 | P26: 20
C27: 6 | D27: 10
C28: 30 | D28: 4
C29: 98 | D29: 2.5
C30: 328 | D30: 1.5
C32: 活动返利比
C34: 活动评级 | D34: 标准返比
C35: S | D35: 3
C36: A | D36: 200%-225%
C37: B | D37: 150%-175%

Sheet 商店
A1: 5 | B1: 6 | C1: 0.5
G5: 单价（人民币） | N5: 道具id | O5: 道具【梦境】 | P5: 单价（钻石） | Q5: 单价（人民币） | R5: 稀有程度 | S5: 特殊运营活动价格（人民币） | T5: 类型 | U5: 品质 | V5: 针对玩家 | W5: 备注
A6: 刷新权重 | B6: 总权重 | C6: 刷新几率 | D6: 每日个数 | G6: =IFERROR(VLOOKUP(D6,O:Q,3,0),"") | N6: 1 | O6: 钻石 | P6: 1 | Q6: 0.1 | R6: 常规 | T6: 货币 | U6: 橙 | W6: /
A7: 梦幻遥感 | B7: 1200 | C7: =$B$1*B7/SUM($B$7:$B$13) -> 0.72 | D7: =C7*$A$1 -> 3.6 | G7: =IFERROR(VLOOKUP(D7,O:Q,3,0),"") | N7: 2 | O7: 金币 | P7: 0.05 | Q7: 0.005 | R7: 常规 | T7: 货币 | U7: 蓝 | W7: /
A8: 职业经验 | B8: 2400 | C8: =$B$1*B8/SUM($B$7:$B$13) -> 1.44 | D8: =C8*$A$1 -> 7.2 | G8: =IFERROR(VLOOKUP(D8,O:Q,3,0),"") | N8: 9800301 | O8: 金币吸收器 | P8: 50 | Q8: 5
A9: 装备图纸 | B9: 2400 | C9: =$B$1*B9/SUM($B$7:$B$13) -> 1.44 | D9: =C9*$A$1 -> 7.2 | G9: =IFERROR(VLOOKUP(D9,O:Q,3,0),"") | N9: 44 | O9: 心梦宝石 | P9: 14 | Q9: 1.4 | R9: 受限 | T9: 兑换道具 | U9: 橙 | W9: 每日特惠/循环冲刺活动，兑换商店货币）
A10: 洗练石 | B10: 400 | C10: =$B$1*B10/SUM($B$7:$B$13) -> 0.24 | D10: =C10*$A$1 -> 1.2 | G10: =IFERROR(VLOOKUP(D10,O:Q,3,0),"") | N10: 13 | O10: 体力 | P10: 2 | Q10: 0.2 | R10: 常规 | T10: 消耗道具 | U10: 紫
A11: 锤子 | B11: 1200 | C11: =$B$1*B11/SUM($B$7:$B$13) -> 0.72 | D11: =C11*$A$1 -> 3.6 | G11: =IFERROR(VLOOKUP(D11,O:Q,3,0),"") | N11: 20002 | O11: 梦境奇迹宝箱 | P11: 10 | Q11: 1 | R11: 受限 | T11: 消耗道具 | U11: 紫 | W11: 每日特惠礼包
A12: 英雄碎片 | B12: 2400 | C12: =$B$1*B12/SUM($B$7:$B$13) -> 1.44 | D12: =C12*$A$1 -> 7.2 | G12: =IFERROR(VLOOKUP(D12,O:Q,3,0),"") | N12: 20038 | O12: 梦境惊喜宝箱 | P12: 80 | Q12: 8 | R12: 受限 | W12: 每日特惠礼包
C13: 5800005 | G13: =IFERROR(VLOOKUP(D13,O:Q,3,0),"") | N13: 5600208 | O13: 悬赏线索 | P13: 3 | Q13: 0.3 | R13: 受限 | U13: 橙 | W13: 悬赏活动产出的价值
G14: =IFERROR(VLOOKUP(D14,O:Q,3,0),"") | N14: 5203001 | O14: 织梦微尘 | P14: 3 | Q14: 0.3 | R14: 受限 | T14: 队长道具 | U14: 蓝 | W14: /
G15: =IFERROR(VLOOKUP(D15,O:Q,3,0),"") | N15: 5103001 | O15: 随机能量特饮 | P15: 1 | Q15: 0.1 | R15: 常规 | T15: 梦灵道具 | U15: 蓝 | W15: /
G16: =IFERROR(VLOOKUP(D16,O:Q,3,0),"") | N16: 5104001 | O16: 超能特饮 | P16: 2 | Q16: 0.2 | R16: 常规 | T16: 梦灵道具 | U16: 紫 | W16: /
G17: =IFERROR(VLOOKUP(D17,O:Q,3,0),"") | L17: 万能特饮 | N17: 5600014 | O17: 随机史诗梦灵碎片 | P17: 12 | Q17: 1.2 | R17: 常规 | T17: 梦灵 | U17: 紫 | W17: /
A18: id | B18: 物品 | C18: 随机库 | D18: 随机权重 | E18: 购买消耗 | G18: =IFERROR(VLOOKUP(D18,O:Q,3,0),"") | H18: 原价 | I18: 商店备注 | L18: 做非R的基础体验，随机职业特饮 | N18: 5600015 | O18: 随机史诗梦灵碎片 | P18: 24 | Q18: 2.4 | R18: 受限 | T18: 梦灵 | U18: 橙
A19: 31001 | B19: 11,2}] | G19: =IFERROR(VLOOKUP(D19,O:Q,3,0),"") | O19: 随机史诗梦灵碎片 | P19: 48 | Q19: 4.8 | R19: 稀缺 | T19: 梦灵 | U19: 红
G20: =IFERROR(VLOOKUP(D20,O:Q,3,0),"") | O20: 随机史诗梦灵碎片 | P20: 96 | Q20: 9.6 | R20: 稀缺 | T20: 梦灵
A21: 31101 | B21: 11 | C21: 311 | D21: =INT(VLOOKUP(J21,$A$7:$D$12,2,0)/COUNTIF($J$21:$J$194,J21)) -> 200 | E21: 2,6000}] | G21: =IFERROR(VLOOKUP(D21,O:Q,3,0),"") | H21: [] | I21: 梦幻摇杆*5 | J21: 梦幻遥感 | K21: 5 | L21: 11 | M21: =SUBSTITUTE(SUBSTITUTE(SUBSTITUTE(E21,""&#REF!,""),"}]",""),",","") -> #REF! | O21: 自选史诗梦灵碎片 | P21: 12 | Q21: 1.2 | R21: 受限 | T21: 梦灵 | W21: /
A22: 31102 | B22: 11,10}] | C22: 311 | D22: =INT(VLOOKUP(J22,$A$7:$D$12,2,0)/COUNTIF($J$21:$J$194,J22)) -> 200 | E22: 2,12000}] | G22: =IFERROR(VLOOKUP(D22,O:Q,3,0),"") | H22: [] | I22: 梦幻摇杆*10 | J22: 梦幻遥感 | K22: 10 | L22: 11 | O22: 自选传说梦灵碎片 | P22: 24 | Q22: 2.4 | R22: 受限 | T22: 梦灵
A23: 31103 | O23: 自选神话梦灵碎片 | P23: 48 | Q23: 4.8 | R23: 稀缺 | T23: 梦灵
A24: 31104 | B24: 11,20}] | C24: 1310100 | D24: 稀有梦灵 | E24: 2,24000}] | G24: =F24*0.1 -> 0 | H24: [] | I24: 梦幻摇杆*20 | J24: 梦幻遥感 | K24: 20 | L24: 本体；碎片*10 | O24: 自选创世梦灵碎片 | P24: 96 | Q24: 9.6 | R24: 稀缺 | T24: 梦灵
A25: 31105 | B25: 11 | C25: 1420200 | D25: =INT(VLOOKUP(J25,$A$7:$D$12,2,0)/COUNTIF($J$21:$J$194,J25)) -> 200 | E25: 1,120}] | G25: =F25*0.1 -> 0 | H25: [] | I25: 梦幻摇杆*5 | J25: 梦幻遥感 | K25: 5 | L25: 本体；碎片*10 | O25: 随机史诗梦灵 | P25: 120 | Q25: 12 | R25: 受限 | T25: 梦灵 | W25: 48
A26: 31106 | B26: 11,10}] | C26: 1130100 | D26: =INT(VLOOKUP(J26,$A$7:$D$12,2,0)/COUNTIF($J$21:$J$194,J26)) -> 200 | E26: 1,240}] | G26: =F26*0.1 -> 0 | H26: [] | I26: 梦幻摇杆*10 | J26: 梦幻遥感 | K26: 10 | L26: 本体；碎片*10 | O26: 随机传说梦灵 | P26: 240 | Q26: 24 | R26: 受限 | T26: 梦灵 | W26: 96
A27: 31107 | B27: 11,20}] | C27: 311 | D27: =INT(VLOOKUP(J27,$A$7:$D$12,2,0)/COUNTIF($J$21:$J$194,J27)) -> 200 | E27: 1,480}] | G27: =F27*0.1 -> 0 | H27: [] | I27: 梦幻摇杆*20 | J27: 梦幻遥感 | K27: 20 | L27: 本体 | O27: 随机神话梦灵 | P27: 480 | Q27: 48 | R27: 稀缺 | T27: 梦灵 | W27: 192
A28: 31108 | B28: 5103002,50}] | C28: 311 | D28: =INT(VLOOKUP(J28,$A$7:$D$12,2,0)/COUNTIF($J$21:$J$194,J28)) -> 400 | E28: 2,2000}] | G28: =F28*0.1 -> 0 | I28: 职业经验*50 | J28: 职业经验 | K28: 50 | L28: 本体 | O28: 随机创世梦灵 | P28: 960 | Q28: 96 | R28: 稀缺 | T28: 梦灵 | W28: 384
A29: 31109 | B29: 5103002,100}] | D29: 随机稀有梦灵碎片 | E29: 2,4000}] | G29: =F29*0.1 -> 0 | I29: 职业经验*100 | J29: 职业经验 | K29: 100 | L29: 5103001 | M29: =SUBSTITUTE(SUBSTITUTE(SUBSTITUTE(E30,""&#REF!,""),"}]",""),",","") -> #REF! | O29: 自选史诗梦灵 | P29: 120 | Q29: 12 | R29: 受限 | T29: 梦灵
A30: 31110 | B30: 5103002,200}] | D30: 随机史诗梦灵碎片 | E30: 2,8000}] | G30: =F30*0.1 -> 0 | I30: 职业经验*200 | J30: 职业经验 | K30: 200 | L30: 5103001 | M30: =SUBSTITUTE(SUBSTITUTE(SUBSTITUTE(E31,""&#REF!,""),"}]",""),",","") -> #REF! | O30: 自选传说梦灵 | P30: 240 | Q30: 24 | R30: 受限 | T30: 梦灵
A31: 31111 | B31: 5103002,50}] | D31: 随机传说梦灵碎片 | E31: 1,50}] | G31: =F31*0.1 -> 0 | I31: 职业经验*50 | J31: 职业经验 | K31: =K28 -> 50 | L31: 5103001 | M31: =SUBSTITUTE(SUBSTITUTE(SUBSTITUTE(E32,""&#REF!,""),"}]",""),",","") -> #REF! | O31: 自选神话梦灵 | P31: 480 | Q31: 48 | R31: 稀缺 | T31: 梦灵 | W31: /
A32: 31112 | B32: 5103002,100}] | C32: 311 | D32: 随机神话梦灵碎片 | E32: 1,100}] | G32: =F32*0.1 -> 0 | I32: 职业经验*100 | J32: 职业经验 | K32: =K29 -> 100 | L32: 5103001 | M32: =SUBSTITUTE(SUBSTITUTE(SUBSTITUTE(E33,""&#REF!,""),"}]",""),",","") -> #REF! | O32: 自选创世梦灵 | P32: 960 | Q32: 96 | R32: 稀缺 | T32: 梦灵
A33: 31113 | B33: 5103002,200}] | C33: 311 | D33: 随机彩虹梦灵碎片 | E33: 1,200}] | G33: =F33*0.1 -> 0 | I33: 职业经验*200 | J33: 职业经验 | K33: =K30 -> 200 | L33: 5103001 | M33: =SUBSTITUTE(SUBSTITUTE(SUBSTITUTE(E39,""&#REF!,""),"}]",""),",","") -> #REF! | N33: 50002 | O33: 装备图纸 | P33: 3 | Q33: 0.3 | R33: 常规 | T33: 装备道具 | U33: 蓝 | W33: /
D34: 自选稀有梦灵碎片 | F34: 6 | G34: 0.6
D35: 自选史诗梦灵碎片 | F35: 12 | G35: 1.2
D36: 自选传说梦灵碎片 | F36: 24 | G36: 2.4
D37: 自选神话梦灵碎片 | F37: 48 | G37: 4.8
D38: 自选创世梦灵碎片 | F38: 96 | G38: 9.6
A39: 31114 | B39: 50003,10}] | C39: 311 | D39: =INT(VLOOKUP(J39,$A$7:$D$12,2,0)/COUNTIF($J$21:$J$194,J39)) -> 68 | E39: 2,1000}] | G39: =IFERROR(VLOOKUP(D39,O:Q,2,0),"") | I39: 头盔图纸*10 | J39: 装备图纸 | K39: 10 | L39: 50002 | M39: =SUBSTITUTE(SUBSTITUTE(SUBSTITUTE(E40,""&#REF!,""),"}]",""),",","") -> #REF! | O39: 固定部位装备图纸 | P39: 5 | Q39: 0.5 | R39: 受限 | T39: 装备道具 | W39: /
A40: 31115 | B40: 50003,20}] | C40: 311 | D40: =INT(VLOOKUP(J40,$A$7:$D$12,2,0)/COUNTIF($J$21:$J$194,J40)) -> 68 | E40: 2,2000}] | G40: =IFERROR(VLOOKUP(D40,O:Q,2,0),"") | I40: 头盔图纸*20 | J40: 装备图纸 | K40: 20 | L40: 50002 | M40: =SUBSTITUTE(SUBSTITUTE(SUBSTITUTE(E41,""&#REF!,""),"}]",""),",","") -> #REF! | N40: 50001 | O40: 锻造晶石 | P40: 0.1 | Q40: 0.01 | R40: 常规 | T40: 装备道具 | U40: 蓝 | W40: /
A41: 31116 | B41: 50003,40}] | C41: 311 | D41: =INT(VLOOKUP(J41,$A$7:$D$12,2,0)/COUNTIF($J$21:$J$194,J41)) -> 68 | E41: 2,4000}] | G41: =IFERROR(VLOOKUP(D41,O:Q,2,0),"") | I41: 头盔图纸*40 | J41: 装备图纸 | K41: 40 | L41: 50002 | M41: =SUBSTITUTE(SUBSTITUTE(SUBSTITUTE(E42,""&#REF!,""),"}]",""),",","") -> #REF! | N41: 5303001 | O41: 符引结晶 | P41: 5 | Q41: 0.5 | R41: 常规 | T41: 符文 | U41: 蓝 | W41: 200个合成1个，紫色的需要符引结晶
A42: 31117 | B42: 50003,10}] | C42: 311 | D42: =INT(VLOOKUP(J42,$A$7:$D$12,2,0)/COUNTIF($J$21:$J$194,J42)) -> 68 | E42: 1,40}] | G42: =IFERROR(VLOOKUP(D42,O:Q,2,0),"") | I42: 头盔图纸*10 | J42: 装备图纸 | K42: =K39 -> 10 | L42: 50002 | M42: =SUBSTITUTE(SUBSTITUTE(SUBSTITUTE(E43,""&#REF!,""),"}]",""),",","") -> #REF! | N42: 5305001 | O42: 幻梦晶核 | P42: 60 | Q42: 6 | R42: 受限 | T42: 符文 | U42: 橙 | W42: /
A43: 31118 | B43: 50003,20}] | C43: 311 | D43: =INT(VLOOKUP(J43,$A$7:$D$12,2,0)/COUNTIF($J$21:$J$194,J43)) -> 68 | E43: 1,80}] | G43: =IFERROR(VLOOKUP(D43,O:Q,2,0),"") | I43: 头盔图纸*20 | J43: 装备图纸 | K43: =K40 -> 20 | L43: 50002 | M43: =SUBSTITUTE(SUBSTITUTE(SUBSTITUTE(E44,""&#REF!,""),"}]",""),",","") -> #REF! | N43: 5305010 | O43: 传说祝福石 | P43: 1500 | Q43: 150 | R43: 稀缺 | T43: 符文 | U43: 橙
A44: 31119 | B44: 50003,40}] | C44: 311 | D44: =INT(VLOOKUP(J44,$A$7:$D$12,2,0)/COUNTIF($J$21:$J$194,J44)) -> 68 | E44: 1,160}] | G44: =IFERROR(VLOOKUP(D44,O:Q,2,0),"") | I44: 头盔图纸*40 | J44: 装备图纸 | K44: =K41 -> 40 | L44: 50002 | M44: =SUBSTITUTE(SUBSTITUTE(SUBSTITUTE(E46,""&#REF!,""),"}]",""),",","") -> #REF! | N44: 5305008 | O44: 神话祝福石 | P44: 5000 | Q44: 500 | R44: 稀缺 | T44: 符文 | U44: 红
A45: 31120 | M45: =SUBSTITUTE(SUBSTITUTE(SUBSTITUTE(E48,""&#REF!,""),"}]",""),",","") -> #REF! | N45: 5305009 | O45: 创世祝福石 | P45: 16000 | Q45: 1600 | R45: 稀缺 | T45: 符文 | U45: 粉
A46: 31121 | B46: 50004,10}] | C46: 311 | D46: =INT(VLOOKUP(J46,$A$7:$D$12,2,0)/COUNTIF($J$21:$J$194,J46)) -> 68 | E46: 2,1000}] | G46: =IFERROR(VLOOKUP(D46,O:Q,3,0),"") | I46: 衣服图纸*10 | J46: 装备图纸 | K46: =K42 -> 10 | L46: 50002 | M46: =SUBSTITUTE(SUBSTITUTE(SUBSTITUTE(E49,""&#REF!,""),"}]",""),",","") -> #REF! | N46: 5301000 | O46: 普通符文 | P46: 16 | Q46: 1.6 | R46: 常规 | T46: 符文
A47: 31122 | D47: 固定部位装备图纸 | E47: 2,1000}] | F47: 5 | G47: 0.5 | J47: 装备图纸 | M47: =SUBSTITUTE(SUBSTITUTE(SUBSTITUTE(E50,""&#REF!,""),"}]",""),",","") -> #REF! | N47: 5302000 | O47: 优秀符文 | P47: 64 | Q47: 6.4 | R47: 常规 | T47: 符文
A48: 31123 | B48: 50004,20}] | C48: 311 | D48: =INT(VLOOKUP(J48,$A$7:$D$12,2,0)/COUNTIF($J$21:$J$194,J48)) -> 68 | E48: 2,2000}] | G48: =IFERROR(VLOOKUP(D48,O:Q,3,0),"") | I48: 衣服图纸*20 | J48: 装备图纸 | K48: =K43 -> 20 | L48: 50002 | M48: =SUBSTITUTE(SUBSTITUTE(SUBSTITUTE(E51,""&#REF!,""),"}]",""),",","") -> #REF! | N48: 5303000 | O48: 稀有符文 | P48: 256 | Q48: 25.6 | R48: 常规 | T48: 符文
A49: 31124 | B49: 50004,40}] | C49: 311 | D49: =INT(VLOOKUP(J49,$A$7:$D$12,2,0)/COUNTIF($J$21:$J$194,J49)) -> 68 | E49: 2,4000}] | G49: =IFERROR(VLOOKUP(D49,O:Q,3,0),"") | I49: 衣服图纸*40 | J49: 装备图纸 | K49: =K44 -> 40 | L49: 50002 | M49: =SUBSTITUTE(SUBSTITUTE(SUBSTITUTE(E52,""&#REF!,""),"}]",""),",","") -> #REF! | N49: 5304000 | O49: 史诗符文 | P49: 1024 | Q49: 102.4 | R49: 受限 | T49: 符文 | W49: 日常获取4折
A50: 31125 | B50: 50004,10}] | C50: 311 | D50: =INT(VLOOKUP(J50,$A$7:$D$12,2,0)/COUNTIF($J$21:$J$194,J50)) -> 68 | E50: 1,40}] | G50: =IFERROR(VLOOKUP(D50,O:Q,3,0),"") | I50: 衣服图纸*10 | J50: 装备图纸 | K50: =K46 -> 10 | L50: 50002 | M50: =SUBSTITUTE(SUBSTITUTE(SUBSTITUTE(E53,""&#REF!,""),"}]",""),",","") -> #REF! | N50: 5305000 | O50: 传说符文 | P50: 4096 | Q50: 409.6 | R50: 稀缺 | T50: 符文 | W50: 1638.4
A51: 31126 | B51: 50004,20}] | C51: 311 | D51: =INT(VLOOKUP(J51,$A$7:$D$12,2,0)/COUNTIF($J$21:$J$194,J51)) -> 68 | E51: 1,80}] | G51: =IFERROR(VLOOKUP(D51,O:Q,3,0),"") | I51: 衣服图纸*20 | J51: 装备图纸 | K51: =K48 -> 20 | L51: 50002 | M51: =SUBSTITUTE(SUBSTITUTE(SUBSTITUTE(E54,""&#REF!,""),"}]",""),",","") -> #REF! | N51: 5306000 | O51: 神话符文 | P51: 16384 | Q51: 1638.4 | R51: 稀缺 | T51: 符文 | W51: 6553.6
A52: 31127 | B52: 50004,40}] | C52: 311 | D52: =INT(VLOOKUP(J52,$A$7:$D$12,2,0)/COUNTIF($J$21:$J$194,J52)) -> 68 | E52: 1,160}] | G52: =IFERROR(VLOOKUP(D52,O:Q,3,0),"") | I52: 衣服图纸*40 | J52: 装备图纸 | K52: =K49 -> 40 | L52: 50002 | M52: =SUBSTITUTE(SUBSTITUTE(SUBSTITUTE(E55,""&#REF!,""),"}]",""),",","") -> #REF! | N52: 5307000 | O52: 创世符文 | P52: 65536 | Q52: 6553.6 | R52: 稀缺 | T52: 符文 | W52: 26214.4
A53: 31128 | B53: 50005,10}] | C53: 311 | D53: =INT(VLOOKUP(J53,$A$7:$D$12,2,0)/COUNTIF($J$21:$J$194,J53)) -> 68 | E53: 2,1000}] | G53: =IFERROR(VLOOKUP(D53,O:Q,3,0),"") | I53: 护臂图纸*10 | J53: 装备图纸 | K53: =K50 -> 10 | L53: 50002 | M53: =SUBSTITUTE(SUBSTITUTE(SUBSTITUTE(E56,""&#REF!,""),"}]",""),",","") -> #REF! | O53: 自选普通符文 | P53: 16 | Q53: 1.6 | R53: 受限 | T53: 符文
A54: 31129 | B54: 50005,20}] | C54: 311 | D54: =INT(VLOOKUP(J54,$A$7:$D$12,2,0)/COUNTIF($J$21:$J$194,J54)) -> 68 | E54: 2,2000}] | G54: =IFERROR(VLOOKUP(D54,O:Q,3,0),"") | I54: 护臂图纸*20 | J54: 装备图纸 | K54: =K51 -> 20 | L54: 50002 | M54: =SUBSTITUTE(SUBSTITUTE(SUBSTITUTE(E57,""&#REF!,""),"}]",""),",","") -> #REF! | O54: 自选优秀符文 | P54: 64 | Q54: 6.4 | R54: 受限 | T54: 符文
A55: 31130 | B55: 50005,40}] | C55: 311 | D55: =INT(VLOOKUP(J55,$A$7:$D$12,2,0)/COUNTIF($J$21:$J$194,J55)) -> 68 | E55: 2,4000}] | G55: =IFERROR(VLOOKUP(D55,O:Q,3,0),"") | I55: 护臂图纸*40 | J55: 装备图纸 | K55: =K52 -> 40 | L55: 50002 | M55: =SUBSTITUTE(SUBSTITUTE(SUBSTITUTE(E58,""&#REF!,""),"}]",""),",","") -> #REF! | O55: 自选稀有符文 | P55: 256 | Q55: 25.6 | R55: 受限 | T55: 符文
A56: 31131 | B56: 50005,10}] | C56: 311 | D56: =INT(VLOOKUP(J56,$A$7:$D$12,2,0)/COUNTIF($J$21:$J$194,J56)) -> 68 | E56: 1,40}] | G56: =IFERROR(VLOOKUP(D56,O:Q,3,0),"") | I56: 护臂图纸*10 | J56: 装备图纸 | K56: =K53 -> 10 | L56: 50002 | M56: =SUBSTITUTE(SUBSTITUTE(SUBSTITUTE(E59,""&#REF!,""),"}]",""),",","") -> #REF! | O56: 自选史诗符文 | P56: 1024 | Q56: 102.4 | R56: 受限 | T56: 符文
A57: 31132 | B57: 50005,20}] | C57: 311 | D57: =INT(VLOOKUP(J57,$A$7:$D$12,2,0)/COUNTIF($J$21:$J$194,J57)) -> 68 | E57: 1,80}] | G57: =IFERROR(VLOOKUP(D57,O:Q,3,0),"") | I57: 护臂图纸*20 | J57: 装备图纸 | K57: =K54 -> 20 | L57: 50002 | M57: =SUBSTITUTE(SUBSTITUTE(SUBSTITUTE(#REF!,""&#REF!,""),"}]",""),",","") -> #REF! | O57: 自选传说符文 | P57: 4096 | Q57: 409.6 | R57: 稀缺 | T57: 符文
A58: 31133 | B58: 50005,40}] | C58: 311 | D58: =INT(VLOOKUP(J58,$A$7:$D$12,2,0)/COUNTIF($J$21:$J$194,J58)) -> 68 | E58: 1,160}] | G58: =IFERROR(VLOOKUP(D58,O:Q,3,0),"") | I58: 护臂图纸*40 | J58: 装备图纸 | K58: =K55 -> 40 | L58: 50002 | M58: =SUBSTITUTE(SUBSTITUTE(SUBSTITUTE(E60,""&#REF!,""),"}]",""),",","") -> #REF! | O58: 自选神话符文 | P58: 16384 | Q58: 1638.4 | R58: 稀缺 | T58: 符文
A59: 31134 | B59: 50006,10}] | C59: 311 | D59: =INT(VLOOKUP(J59,$A$7:$D$12,2,0)/COUNTIF($J$21:$J$194,J59)) -> 68 | E59: 2,1000}] | G59: =IFERROR(VLOOKUP(D59,O:Q,3,0),"") | I59: 裤子图纸*10 | J59: 装备图纸 | K59: =K56 -> 10 | L59: 50002 | M59: =SUBSTITUTE(SUBSTITUTE(SUBSTITUTE(E61,""&#REF!,""),"}]",""),",","") -> #REF! | O59: 自选创世符文 | P59: 65536 | Q59: 6553.6 | R59: 稀缺 | T59: 符文 | W59: 0.3
A60: 31135 | B60: 50006,40}] | C60: 311 | D60: =INT(VLOOKUP(J60,$A$7:$D$12,2,0)/COUNTIF($J$21:$J$194,J60)) -> 68 | E60: 2,4000}] | G60: =IFERROR(VLOOKUP(D60,O:Q,3,0),"") | I60: 裤子图纸*40 | J60: 装备图纸 | K60: =K58 -> 40 | L60: 50002 | M60: =SUBSTITUTE(SUBSTITUTE(SUBSTITUTE(E62,""&#REF!,""),"}]",""),",","") -> #REF! | O60: 1【普通】 | P60: 319 | R60: 常规 | T60: 符文 | U60: 紫 | W60: 1
A61: 31136 | B61: 50006,10}] | C61: 311 | D61: =INT(VLOOKUP(J61,$A$7:$D$12,2,0)/COUNTIF($J$21:$J$194,J61)) -> 68 | E61: 1,40}] | G61: =IFERROR(VLOOKUP(D61,O:Q,3,0),"") | I61: 裤子图纸*10 | J61: 装备图纸 | K61: =K59 -> 10 | L61: 50002 | M61: =SUBSTITUTE(SUBSTITUTE(SUBSTITUTE(E63,""&#REF!,""),"}]",""),",","") -> #REF! | O61: 2【普通】 | P61: 319 | R61: 常规 | T61: 符文 | U61: 紫 | W61: 10
A62: 31137 | B62: 50006,20}] | C62: 311 | D62: =INT(VLOOKUP(J62,$A$7:$D$12,2,0)/COUNTIF($J$21:$J$194,J62)) -> 68 | E62: 1,80}] | G62: =IFERROR(VLOOKUP(D62,O:Q,3,0),"") | I62: 裤子图纸*20 | J62: 装备图纸 | K62: =#REF! -> #REF! | L62: 50002 | M62: =SUBSTITUTE(SUBSTITUTE(SUBSTITUTE(E68,""&#REF!,""),"}]",""),",","") -> #REF! | O62: 3【普通】 | P62: 325 | R62: 常规 | T62: 符文 | U62: 紫
A63: 31138 | B63: 50006,40}] | C63: 311 | D63: =INT(VLOOKUP(J63,$A$7:$D$12,2,0)/COUNTIF($J$21:$J$194,J63)) -> 68 | E63: 1,160}] | G63: =IFERROR(VLOOKUP(D63,O:Q,3,0),"") | I63: 裤子图纸*40 | J63: 装备图纸 | K63: =K60 -> 40 | L63: 50002 | M63: =SUBSTITUTE(SUBSTITUTE(SUBSTITUTE(E69,""&#REF!,""),"}]",""),",","") -> #REF! | O63: 4【专属】 | P63: 1736 | R63: 受限 | T63: 符文 | U63: 紫
A64: 31139 | D64: 传说祝福石 | F64: 1500 | G64: 150 | L64: 橙 | M64: =SUBSTITUTE(SUBSTITUTE(SUBSTITUTE(E70,""&#REF!,""),"}]",""),",","") -> #REF! | O64: 5【稀有】 | R64: 稀缺 | T64: 符文 | U64: 紫
A65: 31140 | D65: 神话祝福石 | F65: 5000 | G65: 500 | L65: 红 | M65: =SUBSTITUTE(SUBSTITUTE(SUBSTITUTE(E71,""&#REF!,""),"}]",""),",","") -> #REF! | O65: 6【宝属性】 | P65: 29577 | R65: 稀缺 | T65: 符文 | U65: 紫 | W65: 洗练定价【获取+洗练价格】80洗一次，200合一个，合2.5一个，主要是暴击率的洗练
A66: 31141 | D66: 创世祝福石 | F66: 16000 | G66: 1600 | L66: 粉 | M66: =SUBSTITUTE(SUBSTITUTE(SUBSTITUTE(E72,""&#REF!,""),"}]",""),",","") -> #REF! | O66: 8【专属】 | R66: 受限 | T66: 符文 | U66: 紫
A67: 31142 | M67: =SUBSTITUTE(SUBSTITUTE(SUBSTITUTE(E73,""&#REF!,""),"}]",""),",","") -> #REF! | O67: 1【普通】 | P67: 305 | R67: 受限 | T67: 符文 | U67: 橙
A68: 31143 | B68: 50007,10}] | C68: 311 | D68: =INT(VLOOKUP(J68,$A$7:$D$12,2,0)/COUNTIF($J$21:$J$194,J68)) -> 68 | E68: 2,1000}] | G68: =IFERROR(VLOOKUP(D68,O:Q,3,0),"") | I68: 鞋子图纸*10 | J68: 装备图纸 | K68: =K61 -> 10 | L68: 50002 | M68: =SUBSTITUTE(SUBSTITUTE(SUBSTITUTE(E74,""&#REF!,""),"}]",""),",","") -> #REF! | O68: 2【普通】 | P68: 305 | R68: 受限 | T68: 符文 | U68: 橙
A69: 31144 | B69: 50007,20}] | C69: 311 | D69: =INT(VLOOKUP(J69,$A$7:$D$12,2,0)/COUNTIF($J$21:$J$194,J69)) -> 68 | E69: 2,2000}] | G69: =IFERROR(VLOOKUP(D69,O:Q,3,0),"") | I69: 鞋子图纸*20 | J69: 装备图纸 | K69: =K62 -> #REF! | L69: 50002 | M69: =SUBSTITUTE(SUBSTITUTE(SUBSTITUTE(E76,""&#REF!,""),"}]",""),",","") -> #REF! | O69: 3【普通】 | P69: 268 | R69: 受限 | T69: 符文 | U69: 橙
A70: 31145 | B70: 50007,40}] | C70: 311 | D70: =INT(VLOOKUP(J70,$A$7:$D$12,2,0)/COUNTIF($J$21:$J$194,J70)) -> 68 | E70: 2,4000}] | G70: =IFERROR(VLOOKUP(D70,O:Q,3,0),"") | I70: 鞋子图纸*40 | J70: 装备图纸 | K70: =K63 -> 40 | L70: 50002 | M70: =SUBSTITUTE(SUBSTITUTE(SUBSTITUTE(E77,""&#REF!,""),"}]",""),",","") -> #REF! | O70: 4【专属】 | P70: 2600 | R70: 稀缺 | T70: 符文 | U70: 橙
A71: 31146 | B71: 50007,10}] | C71: 311 | D71: =INT(VLOOKUP(J71,$A$7:$D$12,2,0)/COUNTIF($J$21:$J$194,J71)) -> 68 | E71: 1,40}] | G71: =IFERROR(VLOOKUP(D71,O:Q,3,0),"") | I71: 鞋子图纸*10 | J71: 装备图纸 | K71: =K68 -> 10 | L71: 50002 | M71: =SUBSTITUTE(SUBSTITUTE(SUBSTITUTE(E78,""&#REF!,""),"}]",""),",","") -> #REF! | O71: 5【稀有】 | P71: 4000 | R71: 稀缺 | T71: 符文 | U71: 橙
A72: 31147 | B72: 50007,20}] | C72: 311 | D72: =INT(VLOOKUP(J72,$A$7:$D$12,2,0)/COUNTIF($J$21:$J$194,J72)) -> 68 | E72: 1,80}] | G72: =IFERROR(VLOOKUP(D72,O:Q,3,0),"") | I72: 鞋子图纸*20 | J72: 装备图纸 | K72: =K69 -> #REF! | L72: 50002 | M72: =SUBSTITUTE(SUBSTITUTE(SUBSTITUTE(E79,""&#REF!,""),"}]",""),",","") -> #REF! | O72: 6【宝属性】 | P72: 12857 | R72: 稀缺 | T72: 符文 | U72: 橙 | W72: 洗练定价【独立洗练价格】
A73: 31148 | B73: 50007,40}] | C73: 311 | D73: =INT(VLOOKUP(J73,$A$7:$D$12,2,0)/COUNTIF($J$21:$J$194,J73)) -> 68 | E73: 1,160}] | G73: =IFERROR(VLOOKUP(D73,O:Q,3,0),"") | I73: 鞋子图纸*40 | J73: 装备图纸 | K73: =K70 -> 40 | L73: 50002 | M73: =SUBSTITUTE(SUBSTITUTE(SUBSTITUTE(#REF!,""&#REF!,""),"}]",""),",","") -> #REF! | O73: 8【专属】 | P73: 8571 | R73: 稀缺 | T73: 符文 | U73: 橙
A74: 31149 | B74: 50008,10}] | C74: 311 | D74: =INT(VLOOKUP(J74,$A$7:$D$12,2,0)/COUNTIF($J$21:$J$194,J74)) -> 68 | E74: 2,1000}] | G74: =IFERROR(VLOOKUP(D74,O:Q,3,0),"") | I74: 手套图纸*10 | J74: 装备图纸 | K74: =K71 -> 10 | L74: 50002 | M74: =SUBSTITUTE(SUBSTITUTE(SUBSTITUTE(E80,""&#REF!,""),"}]",""),",","") -> #REF! | O74: 1【普通】 | P74: 610 | R74: 受限 | T74: 符文 | U74: 红
A75: 31150 | M75: =SUBSTITUTE(SUBSTITUTE(SUBSTITUTE(E81,""&#REF!,""),"}]",""),",","") -> #REF! | O75: 2【普通】 | P75: 610 | R75: 受限 | T75: 符文 | U75: 红
A76: 31151 | B76: 50008,20}] | C76: 311 | D76: =INT(VLOOKUP(J76,$A$7:$D$12,2,0)/COUNTIF($J$21:$J$194,J76)) -> 68 | E76: 2,2000}] | G76: =IFERROR(VLOOKUP(D76,O:Q,3,0),"") | I76: 手套图纸*20 | J76: 装备图纸 | K76: =K72 -> #REF! | L76: 50002 | M76: =SUBSTITUTE(SUBSTITUTE(SUBSTITUTE(E82,""&#REF!,""),"}]",""),",","") -> #REF! | O76: 3【普通】 | P76: 537 | R76: 受限 | T76: 符文 | U76: 红
A77: 31152 | B77: 50008,40}] | C77: 311 | D77: =INT(VLOOKUP(J77,$A$7:$D$12,2,0)/COUNTIF($J$21:$J$194,J77)) -> 68 | E77: 2,4000}] | G77: =IFERROR(VLOOKUP(D77,O:Q,3,0),"") | I77: 手套图纸*40 | J77: 装备图纸 | K77: =K73 -> 40 | L77: 50002 | M77: =SUBSTITUTE(SUBSTITUTE(SUBSTITUTE(E83,""&#REF!,""),"}]",""),",","") -> #REF! | O77: 4【专属】 | P77: 5200 | R77: 稀缺 | T77: 符文 | U77: 红
A78: 31153 | B78: 50008,10}] | C78: 311 | D78: =INT(VLOOKUP(J78,$A$7:$D$12,2,0)/COUNTIF($J$21:$J$194,J78)) -> 68 | E78: 1,40}] | G78: =IFERROR(VLOOKUP(D78,O:Q,3,0),"") | I78: 手套图纸*10 | J78: 装备图纸 | K78: =K74 -> 10 | L78: 50002 | M78: =SUBSTITUTE(SUBSTITUTE(SUBSTITUTE(E84,""&#REF!,""),"}]",""),",","") -> #REF! | O78: 5【稀有】 | P78: 8000 | R78: 稀缺 | T78: 符文 | U78: 红
A79: 31154 | B79: 50008,20}] | C79: 311 | D79: =INT(VLOOKUP(J79,$A$7:$D$12,2,0)/COUNTIF($J$21:$J$194,J79)) -> 68 | E79: 1,80}] | G79: =IFERROR(VLOOKUP(D79,O:Q,3,0),"") | I79: 手套图纸*20 | J79: 装备图纸 | K79: =K76 -> #REF! | L79: 50002 | M79: =SUBSTITUTE(SUBSTITUTE(SUBSTITUTE(E85,""&#REF!,""),"}]",""),",","") -> #REF! | O79: 6【宝属性】 | P79: 25714 | R79: 稀缺 | T79: 符文 | U79: 红 | W79: 洗练定价【独立洗练价格】
A80: 31155 | B80: 5305001,1}] | C80: 311 | D80: =INT(VLOOKUP(J80,$A$7:$D$12,2,0)/COUNTIF($J$21:$J$194,J80)) -> 400 | E80: 1,48}] | G80: =IFERROR(VLOOKUP(D80,O:Q,3,0),"") | I80: 洗练石 | J80: 洗练石 | K80: 1 | L80: 5305001 | M80: =SUBSTITUTE(SUBSTITUTE(SUBSTITUTE(E86,""&#REF!,""),"}]",""),",","") -> #REF! | O80: 8【专属】 | P80: 17143 | R80: 稀缺 | T80: 符文 | U80: 红
A81: 31156 | B81: 1310100,1}] | C81: 311 | D81: =INT(VLOOKUP(J81,$A$7:$D$12,2,0)/COUNTIF($J$21:$J$194,J81)) -> 21 | E81: 2,240}] | G81: =IFERROR(VLOOKUP(D81,O:Q,3,0),"") | I81: 寒冰射手*1 | J81: 英雄碎片 | K81: 1 | L81: 1310100 | M81: =SUBSTITUTE(SUBSTITUTE(SUBSTITUTE(E87,""&#REF!,""),"}]",""),",","") -> #REF! | O81: 1【普通】 | P81: 1017 | R81: 稀缺 | T81: 符文 | U81: 粉
A82: 31157 | B82: 1210400,1}] | C82: 311 | D82: =INT(VLOOKUP(J82,$A$7:$D$12,2,0)/COUNTIF($J$21:$J$194,J82)) -> 21 | E82: 2,240}] | G82: =IFERROR(VLOOKUP(D82,O:Q,3,0),"") | I82: 炽焰巫师*1 | J82: 英雄碎片 | K82: 1 | L82: 1310100 | M82: =SUBSTITUTE(SUBSTITUTE(SUBSTITUTE(E88,""&#REF!,""),"}]",""),",","") -> #REF! | O82: 2【普通】 | P82: 1017 | R82: 稀缺 | T82: 符文 | U82: 粉
A83: 31158 | B83: 1230100,1}] | C83: 311 | D83: =INT(VLOOKUP(J83,$A$7:$D$12,2,0)/COUNTIF($J$21:$J$194,J83)) -> 21 | E83: 2,240}] | G83: =IFERROR(VLOOKUP(D83,O:Q,3,0),"") | I83: 吟游诗人*1 | J83: 英雄碎片 | K83: 1 | L83: 1310100 | M83: =SUBSTITUTE(SUBSTITUTE(SUBSTITUTE(E89,""&#REF!,""),"}]",""),",","") -> #REF! | O83: 3【普通】 | P83: 894 | R83: 稀缺 | T83: 符文 | U83: 粉
A84: 31159 | B84: 1420200,1}] | C84: 311 | D84: =INT(VLOOKUP(J84,$A$7:$D$12,2,0)/COUNTIF($J$21:$J$194,J84)) -> 21 | E84: 2,360}] | G84: =IFERROR(VLOOKUP(D84,O:Q,3,0),"") | I84: 摇滚巨石*1 | J84: 英雄碎片 | K84: 1 | L84: 1420200 | M84: =SUBSTITUTE(SUBSTITUTE(SUBSTITUTE(E90,""&#REF!,""),"}]",""),",","") -> #REF! | O84: 4【专属】 | P84: 8667 | R84: 稀缺 | T84: 符文 | U84: 粉
A85: 31160 | B85: 1320100,1}] | C85: 311 | D85: =INT(VLOOKUP(J85,$A$7:$D$12,2,0)/COUNTIF($J$21:$J$194,J85)) -> 21 | E85: 2,360}] | G85: =IFERROR(VLOOKUP(D85,O:Q,3,0),"") | I85: 果冻少女*1 | J85: 英雄碎片 | K85: 1 | L85: 1420200 | M85: =SUBSTITUTE(SUBSTITUTE(SUBSTITUTE(E91,""&#REF!,""),"}]",""),",","") -> #REF! | O85: 5【稀有】 | P85: 13333 | R85: 稀缺 | T85: 符文 | U85: 粉
A86: 31161 | B86: 1210600,1}] | C86: 311 | D86: =INT(VLOOKUP(J86,$A$7:$D$12,2,0)/COUNTIF($J$21:$J$194,J86)) -> 21 | E86: 2,360}] | G86: =IFERROR(VLOOKUP(D86,O:Q,3,0),"") | I86: 忍者鲨手*1 | J86: 英雄碎片 | K86: 1 | L86: 1420200 | M86: =SUBSTITUTE(SUBSTITUTE(SUBSTITUTE(E92,""&#REF!,""),"}]",""),",","") -> #REF! | O86: 6【宝属性】 | P86: 42857 | R86: 稀缺 | T86: 符文 | U86: 粉 | W86: 洗练定价【独立洗练价格】
A87: 31162 | B87: 1230400,1}] | C87: 311 | D87: =INT(VLOOKUP(J87,$A$7:$D$12,2,0)/COUNTIF($J$21:$J$194,J87)) -> 21 | E87: 2,360}] | G87: =IFERROR(VLOOKUP(D87,O:Q,3,0),"") | I87: 甜心护士*1 | J87: 英雄碎片 | K87: 1 | L87: 1420200 | M87: =SUBSTITUTE(SUBSTITUTE(SUBSTITUTE(E93,""&#REF!,""),"}]",""),",","") -> #REF! | O87: 8【专属】 | P87: 28571 | R87: 稀缺 | T87: 符文 | U87: 粉
A88: 31163 | B88: 1310300,1}] | C88: 311 | D88: =INT(VLOOKUP(J88,$A$7:$D$12,2,0)/COUNTIF($J$21:$J$194,J88)) -> 21 | E88: 2,360}] | G88: =IFERROR(VLOOKUP(D88,O:Q,3,0),"") | I88: 雷震子*1 | J88: 英雄碎片 | K88: 1 | L88: 1420200 | M88: =SUBSTITUTE(SUBSTITUTE(SUBSTITUTE(E94,""&#REF!,""),"}]",""),",","") -> #REF! | O88: 传说英雄随机珍稀符文 | P88: 700 | Q88: 70 | R88: 稀缺 | T88: 符文 | W88: 梦灵试炼（橙卡）
A89: 31164 | B89: 1110100,1}] | C89: 311 | D89: =INT(VLOOKUP(J89,$A$7:$D$12,2,0)/COUNTIF($J$21:$J$194,J89)) -> 21 | E89: 2,360}] | G89: =IFERROR(VLOOKUP(D89,O:Q,3,0),"") | I89: 关羽*1 | J89: 英雄碎片 | K89: 1 | L89: 1420200 | M89: =SUBSTITUTE(SUBSTITUTE(SUBSTITUTE(E95,""&#REF!,""),"}]",""),",","") -> #REF! | O89: 传说英雄随机稀世符文 | P89: 2500 | Q89: 250 | R89: 稀缺 | T89: 符文 | W89: 梦灵试炼（红卡）
A90: 31165 | B90: 1130100,1}] | C90: 311 | D90: =INT(VLOOKUP(J90,$A$7:$D$12,2,0)/COUNTIF($J$21:$J$194,J90)) -> 21 | E90: 2,1200}] | G90: =IFERROR(VLOOKUP(D90,O:Q,3,0),"") | I90: 东方不败*1 | J90: 英雄碎片 | K90: 1 | L90: 1130100 | M90: =SUBSTITUTE(SUBSTITUTE(SUBSTITUTE(E96,""&#REF!,""),"}]",""),",","") -> #REF! | O90: 绝世英雄传说随机专属符文 | P90: 3000 | Q90: 300 | R90: 稀缺 | T90: 符文
A91: 31166 | B91: 1530100,1}] | C91: 311 | D91: =INT(VLOOKUP(J91,$A$7:$D$12,2,0)/COUNTIF($J$21:$J$194,J91)) -> 21 | E91: 2,1200}] | G91: =IFERROR(VLOOKUP(D91,O:Q,3,0),"") | I91: 镭射眼*1 | J91: 英雄碎片 | K91: 1 | L91: 1130100 | M91: =SUBSTITUTE(SUBSTITUTE(SUBSTITUTE(E99,""&#REF!,""),"}]",""),",","") -> #REF! | O91: 绝世英雄神话随机专属符文 | P91: 6000 | Q91: 600 | R91: 稀缺 | T91: 符文
A92: 31167 | B92: 1210300,1}] | C92: 311 | D92: =INT(VLOOKUP(J92,$A$7:$D$12,2,0)/COUNTIF($J$21:$J$194,J92)) -> 21 | E92: 2,1200}] | G92: =IFERROR(VLOOKUP(D92,O:Q,3,0),"") | I92: 亚瑟*1 | J92: 英雄碎片 | K92: 1 | L92: 1130100 | M92: =SUBSTITUTE(SUBSTITUTE(SUBSTITUTE(E100,""&#REF!,""),"}]",""),",","") -> #REF! | N92: 5304000 | O92: 史诗符文 | P92: 1024 | Q92: 102.4 | R92: 受限 | T92: 符文 | U92: 紫 | W92: 6元首冲礼包
A93: 31168 | B93: 1430700,1}] | C93: 311 | D93: =INT(VLOOKUP(J93,$A$7:$D$12,2,0)/COUNTIF($J$21:$J$194,J93)) -> 21 | E93: 2,1200}] | G93: =IFERROR(VLOOKUP(D93,O:Q,2,0),"") | H93: 实际售价（旧 | I93: 蜘蛛女王*1 | J93: 英雄碎片 | K93: 1 | L93: 1130100 | M93: =SUBSTITUTE(SUBSTITUTE(SUBSTITUTE(E101,""&#REF!,""),"}]",""),",","") -> #REF! | N93: 62 | O93: 智械发条 | P93: 150 | Q93: 15 | R93: 受限 | T93: 抽奖道具 | U93: 橙
A94: 31169 | B94: 1140100,1}] | C94: 311 | D94: =INT(VLOOKUP(J94,$A$7:$D$12,2,0)/COUNTIF($J$21:$J$194,J94)) -> 21 | E94: 2,1200}] | H94: server_open_day,2}] | J94: 英雄碎片 | K94: 紫色 | L94: 随机/自选一个价 | M94: =SUBSTITUTE(SUBSTITUTE(SUBSTITUTE(#REF!,""&#REF!,""),"}]",""),",","") -> #REF! | N94: 63 | O94: 精密齿轮 | P94: 1 | Q94: 0.1 | R94: 受限 | T94: 零件 | U94: 紫
A95: 31170 | B95: 1140200,1}] | C95: 311 | D95: =INT(VLOOKUP(J95,$A$7:$D$12,2,0)/COUNTIF($J$21:$J$194,J95)) -> 21 | E95: 2,1200}] | H95: server_open_day,2}] | J95: 英雄碎片 | K95: 橙色 | L95: 随机/自选一个价 | M95: =SUBSTITUTE(SUBSTITUTE(SUBSTITUTE(E102,""&#REF!,""),"}]",""),",","") -> #REF! | N95: 6030001 | O95: 随机史诗零件碎片 | P95: 200 | Q95: 20 | R95: 受限 | T95: 零件 | U95: 紫
A96: 31171 | B96: 1310100,2}] | C96: 311 | D96: =INT(VLOOKUP(J96,$A$7:$D$12,2,0)/COUNTIF($J$21:$J$194,J96)) -> 21 | E96: 2,480}] | J96: 英雄碎片 | K96: 红色 | L96: 随机/自选一个价 | M96: =SUBSTITUTE(SUBSTITUTE(SUBSTITUTE(E103,""&#REF!,""),"}]",""),",","") -> #REF! | N96: 6030002 | O96: 随机传说零件碎片 | P96: 400 | Q96: 40 | R96: 稀缺 | T96: 零件 | U96: 橙
A97: 31172 | D97: 创世梦灵皮肤 | F97: 16000 | G97: 1600 | K97: 粉色 | L97: 1310100 | M97: =SUBSTITUTE(SUBSTITUTE(SUBSTITUTE(E104,""&#REF!,""),"}]",""),",","") -> #REF! | N97: 6030003 | O97: 随机神话零件碎片 | P97: 800 | Q97: 80 | R97: 稀缺 | T97: 零件 | U97: 红
A98: 31173 | M98: =SUBSTITUTE(SUBSTITUTE(SUBSTITUTE(E106,""&#REF!,""),"}]",""),",","") -> #REF! | N98: 6030004 | O98: 随机创世零件碎片 | P98: 1600 | Q98: 160 | R98: 稀缺 | T98: 零件 | U98: 粉
A99: 31174 | B99: 1210400,2}] | C99: 311 | D99: =INT(VLOOKUP(J99,$A$7:$D$12,2,0)/COUNTIF($J$21:$J$194,J99)) -> 21 | E99: 2,480}] | I99: 炽焰巫师*2 | J99: 英雄碎片 | K99: 紫色 | L99: 1310100 | M99: =SUBSTITUTE(SUBSTITUTE(SUBSTITUTE(E107,""&#REF!,""),"}]",""),",","") -> #REF! | N99: 6040001 | O99: 随机史诗零件 | P99: 2000 | Q99: 200 | R99: 受限 | T99: 零件
A100: 31175 | B100: 1230100,2}] | C100: 311 | D100: =INT(VLOOKUP(J100,$A$7:$D$12,2,0)/COUNTIF($J$21:$J$194,J100)) -> 21 | E100: 2,480}] | J100: 英雄碎片 | K100: 橙色 | L100: 1420200 | M100: =SUBSTITUTE(SUBSTITUTE(SUBSTITUTE(E108,""&#REF!,""),"}]",""),",","") -> #REF! | N100: 6040002 | O100: 随机传说零件 | P100: 4000 | Q100: 400 | R100: 稀缺 | T100: 零件
A101: 31176 | B101: 1420200,2}] | C101: 311 | D101: =INT(VLOOKUP(J101,$A$7:$D$12,2,0)/COUNTIF($J$21:$J$194,J101)) -> 21 | E101: 2,720}] | J101: 英雄碎片 | K101: 红色 | L101: 1420200 | M101: =SUBSTITUTE(SUBSTITUTE(SUBSTITUTE(E109,""&#REF!,""),"}]",""),",","") -> #REF! | N101: 6040003 | O101: 随机神话零件 | P101: 8000 | Q101: 800 | R101: 稀缺 | T101: 零件
A102: 31177 | B102: 1210600,2}] | C102: 311 | D102: =INT(VLOOKUP(J102,$A$7:$D$12,2,0)/COUNTIF($J$21:$J$194,J102)) -> 21 | E102: 2,720}] | G102: 250 | J102: 英雄碎片 | K102: 紫色 | L102: 1420200 | M102: =SUBSTITUTE(SUBSTITUTE(SUBSTITUTE(E110,""&#REF!,""),"}]",""),",","") -> #REF! | N102: 6040004 | O102: 随机创世零件 | P102: 16000 | Q102: 1600 | R102: 稀缺 | T102: 零件
A103: 31178 | B103: 1230400,2}] | C103: 311 | D103: =INT(VLOOKUP(J103,$A$7:$D$12,2,0)/COUNTIF($J$21:$J$194,J103)) -> 21 | E103: 2,720}] | G103: 700 | J103: 英雄碎片 | K103: 橙色 | L103: 1420200 | M103: =SUBSTITUTE(SUBSTITUTE(SUBSTITUTE(E111,""&#REF!,""),"}]",""),",","") -> #REF! | N103: 6110030 | O103: 织梦捕星机 | P103: 12000 | Q103: 1200 | R103: 稀缺 | T103: 零件 | U103: 红
...

Sheet 新商店
B2: 设计预期
C3: 前7天小非R日均消耗8000~12000, 7天后日均16000~24000. 中大R日均16000, 7日后日均32000
E5: 1001 | F5: =E5+1000 -> 2001 | G5: =F5+1000 -> 3001 | H5: =G5+1000 -> 4001 | I5: =H5+1000 -> 5001 | J5: =I5+1000 -> 6001 | K5: 7002 | L5: 8001
B6: 天数 | C6: 非R | D6: 大R | E6: =_xlfn.XLOOKUP(E5,$C$30:$C$85,$E$30:$E$85) -> #N/A | F6: =_xlfn.XLOOKUP(F5,$C$30:$C$85,$E$30:$E$85) -> 90 | G6: =_xlfn.XLOOKUP(G5,$C$30:$C$85,$E$30:$E$85) -> 0 | H6: =_xlfn.XLOOKUP(H5,$C$30:$C$85,$E$30:$E$85) -> #N/A | I6: =_xlfn.XLOOKUP(I5,$C$30:$C$85,$E$30:$E$85) -> #N/A | J6: =_xlfn.XLOOKUP(J5,$C$30:$C$85,$E$30:$E$85) -> #N/A | K6: =_xlfn.XLOOKUP(K5,$C$30:$C$85,$E$30:$E$85) -> #N/A | L6: =_xlfn.XLOOKUP(L5,$C$30:$C$85,$E$30:$E$85) -> #N/A
B7: 1 | C7: =SUMIF($B$30:$B$86,$B7,N$30:N$86) -> #N/A | D7: =SUMIF($B$30:$B$86,$B7,O$30:O$86) -> #N/A | E7: 1001 | F7: 2001 | G7: 3001 | H7: 4001 | I7: 5001 | J7: 6001 | K7: 7002 | L7: 8001
B8: 2 | C8: =SUMIF($B$30:$B$86,$B8,N$30:N$86) -> #N/A | D8: =SUMIF($B$30:$B$86,$B8,O$30:O$86) -> #N/A | E8: 1001 | F8: 2001 | G8: 3001 | H8: 4001 | I8: 5002 | J8: 6001 | K8: 7002 | L8: 8001
B9: 3 | C9: =SUMIF($B$30:$B$86,$B9,N$30:N$86) -> #N/A | D9: =SUMIF($B$30:$B$86,$B9,O$30:O$86) -> #N/A | E9: 1001 | F9: 2001 | G9: 3001 | H9: 4001 | I9: 5002 | J9: 6002 | K9: 7002 | L9: 8001
B10: 4 | C10: =SUMIF($B$30:$B$86,$B10,N$30:N$86) -> #N/A | D10: =SUMIF($B$30:$B$86,$B10,O$30:O$86) -> #N/A | E10: 1002 | F10: 2001 | G10: 3001 | H10: 4001 | I10: 5002 | J10: 6002 | K10: 7003 | L10: 8001
B11: 5 | C11: =SUMIF($B$30:$B$86,$B11,N$30:N$86) -> #N/A | D11: =SUMIF($B$30:$B$86,$B11,O$30:O$86) -> #N/A | E11: 1002 | F11: 2001 | G11: 3001 | H11: 4001 | I11: 5002 | J11: 6003 | K11: 7003 | L11: 8001
B12: 6 | C12: =SUMIF($B$30:$B$86,$B12,N$30:N$86) -> #N/A | D12: =SUMIF($B$30:$B$86,$B12,O$30:O$86) -> #N/A | E12: 1002 | F12: 2001 | G12: 3001 | H12: 4001 | I12: 5003 | J12: 6003 | K12: 7003 | L12: 8001
B13: 7 | C13: =SUMIF($B$30:$B$86,$B13,N$30:N$86) -> #N/A | D13: =SUMIF($B$30:$B$86,$B13,O$30:O$86) -> #N/A | E13: 1003 | F13: 2001 | G13: 3001 | H13: 4001 | I13: 5003 | J13: 6003 | K13: 7003 | L13: 8001
C14: =AVERAGE(C7:C12) -> #N/A | D14: =AVERAGE(D7:D12) -> #N/A
E15: 1001 | F15: =E15+1000 -> 2001 | G15: =F15+1000 -> 3001 | H15: =G15+1000 -> 4001 | I15: =H15+1000 -> 5001 | J15: =I15+1000 -> 6001 | K15: 7002 | L15: 8001
B16: 天数 | C16: 非R | D16: 大R | E16: =_xlfn.XLOOKUP(E15,$C$30:$C$85,$E$30:$E$85) -> #N/A | F16: =_xlfn.XLOOKUP(F15,$C$30:$C$85,$E$30:$E$85) -> 90 | G16: =_xlfn.XLOOKUP(G15,$C$30:$C$85,$E$30:$E$85) -> 0 | H16: =_xlfn.XLOOKUP(H15,$C$30:$C$85,$E$30:$E$85) -> #N/A | I16: =_xlfn.XLOOKUP(I15,$C$30:$C$85,$E$30:$E$85) -> #N/A | J16: =_xlfn.XLOOKUP(J15,$C$30:$C$85,$E$30:$E$85) -> #N/A | K16: =_xlfn.XLOOKUP(K15,$C$30:$C$85,$E$30:$E$85) -> #N/A | L16: =_xlfn.XLOOKUP(L15,$C$30:$C$85,$E$30:$E$85) -> #N/A
B17: 1 | E17: 1 | F17: 1 | G17: 0 | H17: 0
B18: 2 | E18: 1 | F18: 0 | G18: 1 | H18: 0
B19: 3 | E19: 0 | F19: 1 | G19: 0 | H19: 0
B20: 4 | E20: 1 | F20: 0 | G20: 0 | H20: 0
B21: 5 | E21: 0 | H21: 0
B22: 6 | E22: 0 | H22: 0
B23: 7 | E23: 1 | H23: 1
H28: 5 | I28: =H28+3 -> 8 | N28: 1 | O28: 2
B29: 组id | C29: 随机库 | D29: id | E29: 内容名 | F29: 随机权重 | G29: 钻石比例 | H29: 小R日均次数 | I29: 大R日均次数 | J29: 最小天数 | K29: 最大天数 | L29: 上限次数 | M29: 目标用户 | N29: 小R | O29: 大R | P29: 小R | Q29: 大R
B30: 1 | C30: =OFFSET($D$6,B30,COUNTIF($B$29:B30,B30)) -> 1001 | D30: 11 | E30: =_xlfn.XLOOKUP(D30,价值表!$D:$D,价值表!$C:$C) | F30: 700 | G30: 0.5 | H30: =$F30/10000*6*H$28*(1-$G30) -> 1.05 | I30: =$F30/10000*6*I$28*(1-$G30) -> 1.68 | J30: 1 | K30: 2 | L30: =IF(OFFSET($D$16,B30,MATCH(E30,$E$16:$L$16,0))="","",OFFSET($D$16,B30,MATCH(E30,$E$16:$L$16,0))) -> #N/A | M30: 非R | N30: {=IF(_xlfn.XLOOKUP($M30,$X$30:$X$34,$Y$30:$Y$34)<=MATCH(N$29,$N$29:$O$29,0),SUMPRODUCT(--($C$91:$C$234=$C30),$G$91:$G$234,$J$91:$J$234)/SUMPRODUCT(--($J$91:$J$234>0),$G$91:$G$234,--($C$91:$C$234=$C30))*MIN(H30,$L30),0)} -> #N/A | O30: {=IF(_xlfn.XLOOKUP($M30,$X$30:$X$34,$Y$30:$Y$34)<=MATCH(O$29,$N$29:$O$29,0),SUMPRODUCT(--($C$91:$C$234=$C30),$G$91:$G$234,$J$91:$J$234)/SUMPRODUCT(--($J$91:$J$234>0),$G$91:$G$234,--($C$91:$C$234=$C30))*MIN(I30,$L30),0)} -> #N/A | P30: {=IF(_xlfn.XLOOKUP($M30,$X$30:$X$34,$Y$30:$Y$34)<=MATCH(N$29,$N$29:$O$29,0),SUMPRODUCT(--($C$91:$C$234=$C30),$G$91:$G$234,$F$91:$F$234,--($J$91:$J$234>0))/SUMPRODUCT(--($J$91:$J$234>0),$G$91:$G$234,--($C$91:$C$234=$C30))*MIN(H30,$L30),0)} -> #N/A | Q30: {=IF(_xlfn.XLOOKUP($M30,$X$30:$X$34,$Y$30:$Y$34)<=MATCH(O$29,$N$29:$O$29,0),SUMPRODUCT(--($C$91:$C$234=$C30),$G$91:$G$234,$F$91:$F$234,--($J$91:$J$234>0))/SUMPRODUCT(--($J$91:$J$234>0),$G$91:$G$234,--($C$91:$C$234=$C30))*MIN(I30,$L30),0)} -> #N/A | U30: 1001 | V30: =_xlfn.XLOOKUP(INT(U30/1000)*1000+1,$C$29:$C$85,$E$29:$E$85) -> #N/A | X30: 非R | Y30: 1
B31: 1 | C31: =OFFSET($D$6,B31,COUNTIF($B$29:B31,B31)) -> 2001 | D31: 9 | E31: =_xlfn.XLOOKUP(D31,价值表!$D:$D,价值表!$C:$C) | F31: 600 | G31: 0.5 | H31: =$F31/10000*6*H$28*(1-$G31) -> 0.9 | I31: =$F31/10000*6*I$28*(1-$G31) -> 1.44 | J31: 1 | K31: 2 | L31: =IF(OFFSET($D$16,B31,MATCH(E31,$E$16:$L$16,0))="","",OFFSET($D$16,B31,MATCH(E31,$E$16:$L$16,0))) -> 1 | M31: 非R | N31: {=IF(_xlfn.XLOOKUP($M31,$X$30:$X$34,$Y$30:$Y$34)<=MATCH(N$29,$N$29:$O$29,0),SUMPRODUCT(--($C$91:$C$234=$C31),$G$91:$G$234,$J$91:$J$234)/SUMPRODUCT(--($J$91:$J$234>0),$G$91:$G$234,--($C$91:$C$234=$C31))*MIN(H31,$L31),0)} -> 1800 | O31: {=IF(_xlfn.XLOOKUP($M31,$X$30:$X$34,$Y$30:$Y$34)<=MATCH(O$29,$N$29:$O$29,0),SUMPRODUCT(--($C$91:$C$234=$C31),$G$91:$G$234,$J$91:$J$234)/SUMPRODUCT(--($J$91:$J$234>0),$G$91:$G$234,--($C$91:$C$234=$C31))*MIN(I31,$L31),0)} -> 2000 | P31: {=IF(_xlfn.XLOOKUP($M31,$X$30:$X$34,$Y$30:$Y$34)<=MATCH(N$29,$N$29:$O$29,0),SUMPRODUCT(--($C$91:$C$234=$C31),$G$91:$G$234,$F$91:$F$234,--($J$91:$J$234>0))/SUMPRODUCT(--($J$91:$J$234>0),$G$91:$G$234,--($C$91:$C$234=$C31))*MIN(H31,$L31),0)} -> 0.9 | Q31: {=IF(_xlfn.XLOOKUP($M31,$X$30:$X$34,$Y$30:$Y$34)<=MATCH(O$29,$N$29:$O$29,0),SUMPRODUCT(--($C$91:$C$234=$C31),$G$91:$G$234,$F$91:$F$234,--($J$91:$J$234>0))/SUMPRODUCT(--($J$91:$J$234>0),$G$91:$G$234,--($C$91:$C$234=$C31))*MIN(I31,$L31),0)} -> 1 | U31: 1002 | V31: =_xlfn.XLOOKUP(INT(U31/1000)*1000+1,$C$29:$C$85,$E$29:$E$85) -> #N/A | X31: 小R | Y31: 1
B32: 1 | C32: =OFFSET($D$6,B32,COUNTIF($B$29:B32,B32)) -> 3001 | D32: 30 | E32: =_xlfn.XLOOKUP(D32,价值表!$D:$D,价值表!$C:$C) | F32: 200 | G32: 0.5 | H32: =$F32/10000*6*H$28*(1-$G32) -> 0.3 | I32: =$F32/10000*6*I$28*(1-$G32) -> 0.48 | J32: 1 | K32: 2 | L32: =IF(OFFSET($D$16,B32,MATCH(E32,$E$16:$L$16,0))="","",OFFSET($D$16,B32,MATCH(E32,$E$16:$L$16,0))) -> 0 | M32: 非R | N32: {=IF(_xlfn.XLOOKUP($M32,$X$30:$X$34,$Y$30:$Y$34)<=MATCH(N$29,$N$29:$O$29,0),SUMPRODUCT(--($C$91:$C$234=$C32),$G$91:$G$234,$J$91:$J$234)/SUMPRODUCT(--($J$91:$J$234>0),$G$91:$G$234,--($C$91:$C$234=$C32))*MIN(H32,$L32),0)} -> 0 | O32: {=IF(_xlfn.XLOOKUP($M32,$X$30:$X$34,$Y$30:$Y$34)<=MATCH(O$29,$N$29:$O$29,0),SUMPRODUCT(--($C$91:$C$234=$C32),$G$91:$G$234,$J$91:$J$234)/SUMPRODUCT(--($J$91:$J$234>0),$G$91:$G$234,--($C$91:$C$234=$C32))*MIN(I32,$L32),0)} -> 0 | P32: {=IF(_xlfn.XLOOKUP($M32,$X$30:$X$34,$Y$30:$Y$34)<=MATCH(N$29,$N$29:$O$29,0),SUMPRODUCT(--($C$91:$C$234=$C32),$G$91:$G$234,$F$91:$F$234,--($J$91:$J$234>0))/SUMPRODUCT(--($J$91:$J$234>0),$G$91:$G$234,--($C$91:$C$234=$C32))*MIN(H32,$L32),0)} -> 0 | Q32: {=IF(_xlfn.XLOOKUP($M32,$X$30:$X$34,$Y$30:$Y$34)<=MATCH(O$29,$N$29:$O$29,0),SUMPRODUCT(--($C$91:$C$234=$C32),$G$91:$G$234,$F$91:$F$234,--($J$91:$J$234>0))/SUMPRODUCT(--($J$91:$J$234>0),$G$91:$G$234,--($C$91:$C$234=$C32))*MIN(I32,$L32),0)} -> 0 | U32: 1003 | V32: =_xlfn.XLOOKUP(INT(U32/1000)*1000+1,$C$29:$C$85,$E$29:$E$85) -> #N/A | X32: 中R | Y32: 1
B33: 1 | C33: =OFFSET($D$6,B33,COUNTIF($B$29:B33,B33)) -> 4001 | D33: 5305001 | E33: =_xlfn.XLOOKUP(D33,价值表!$D:$D,价值表!$C:$C) | F33: 300 | G33: 0.5 | H33: =$F33/10000*6*H$28*(1-$G33) -> 0.45 | I33: =$F33/10000*6*I$28*(1-$G33) -> 0.72 | J33: 1 | K33: 2 | L33: =IF(OFFSET($D$16,B33,MATCH(E33,$E$16:$L$16,0))="","",OFFSET($D$16,B33,MATCH(E33,$E$16:$L$16,0))) -> #N/A | M33: 非R | N33: {=IF(_xlfn.XLOOKUP($M33,$X$30:$X$34,$Y$30:$Y$34)<=MATCH(N$29,$N$29:$O$29,0),SUMPRODUCT(--($C$91:$C$234=$C33),$G$91:$G$234,$J$91:$J$234)/SUMPRODUCT(--($J$91:$J$234>0),$G$91:$G$234,--($C$91:$C$234=$C33))*MIN(H33,$L33),0)} -> #N/A | O33: {=IF(_xlfn.XLOOKUP($M33,$X$30:$X$34,$Y$30:$Y$34)<=MATCH(O$29,$N$29:$O$29,0),SUMPRODUCT(--($C$91:$C$234=$C33),$G$91:$G$234,$J$91:$J$234)/SUMPRODUCT(--($J$91:$J$234>0),$G$91:$G$234,--($C$91:$C$234=$C33))*MIN(I33,$L33),0)} -> #N/A | P33: {=IF(_xlfn.XLOOKUP($M33,$X$30:$X$34,$Y$30:$Y$34)<=MATCH(N$29,$N$29:$O$29,0),SUMPRODUCT(--($C$91:$C$234=$C33),$G$91:$G$234,$F$91:$F$234,--($J$91:$J$234>0))/SUMPRODUCT(--($J$91:$J$234>0),$G$91:$G$234,--($C$91:$C$234=$C33))*MIN(H33,$L33),0)} -> #N/A | Q33: {=IF(_xlfn.XLOOKUP($M33,$X$30:$X$34,$Y$30:$Y$34)<=MATCH(O$29,$N$29:$O$29,0),SUMPRODUCT(--($C$91:$C$234=$C33),$G$91:$G$234,$F$91:$F$234,--($J$91:$J$234>0))/SUMPRODUCT(--($J$91:$J$234>0),$G$91:$G$234,--($C$91:$C$234=$C33))*MIN(I33,$L33),0)} -> #N/A | U33: 2001 | V33: =_xlfn.XLOOKUP(INT(U33/1000)*1000+1,$C$29:$C$85,$E$29:$E$85) -> 90 | X33: 大R | Y33: 2
B34: 1 | C34: =OFFSET($D$6,B34,COUNTIF($B$29:B34,B34)) -> 5001 | D34: 50002 | E34: =_xlfn.XLOOKUP(D34,价值表!$D:$D,价值表!$C:$C) | F34: 2400 | G34: 0.5 | H34: =$F34/10000*6*H$28*(1-$G34) -> 3.6 | I34: =$F34/10000*6*I$28*(1-$G34) -> 5.76 | J34: 1 | K34: 2 | L34: =IF(OFFSET($D$16,B34,MATCH(E34,$E$16:$L$16,0))="","",OFFSET($D$16,B34,MATCH(E34,$E$16:$L$16,0))) -> #N/A | M34: 非R | N34: {=IF(_xlfn.XLOOKUP($M34,$X$30:$X$34,$Y$30:$Y$34)<=MATCH(N$29,$N$29:$O$29,0),SUMPRODUCT(--($C$91:$C$234=$C34),$G$91:$G$234,$J$91:$J$234)/SUMPRODUCT(--($J$91:$J$234>0),$G$91:$G$234,--($C$91:$C$234=$C34))*MIN(H34,$L34),0)} -> #N/A | O34: {=IF(_xlfn.XLOOKUP($M34,$X$30:$X$34,$Y$30:$Y$34)<=MATCH(O$29,$N$29:$O$29,0),SUMPRODUCT(--($C$91:$C$234=$C34),$G$91:$G$234,$J$91:$J$234)/SUMPRODUCT(--($J$91:$J$234>0),$G$91:$G$234,--($C$91:$C$234=$C34))*MIN(I34,$L34),0)} -> #N/A | P34: {=IF(_xlfn.XLOOKUP($M34,$X$30:$X$34,$Y$30:$Y$34)<=MATCH(N$29,$N$29:$O$29,0),SUMPRODUCT(--($C$91:$C$234=$C34),$G$91:$G$234,$F$91:$F$234,--($J$91:$J$234>0))/SUMPRODUCT(--($J$91:$J$234>0),$G$91:$G$234,--($C$91:$C$234=$C34))*MIN(H34,$L34),0)} -> #N/A | Q34: {=IF(_xlfn.XLOOKUP($M34,$X$30:$X$34,$Y$30:$Y$34)<=MATCH(O$29,$N$29:$O$29,0),SUMPRODUCT(--($C$91:$C$234=$C34),$G$91:$G$234,$F$91:$F$234,--($J$91:$J$234>0))/SUMPRODUCT(--($J$91:$J$234>0),$G$91:$G$234,--($C$91:$C$234=$C34))*MIN(I34,$L34),0)} -> #N/A | U34: 3001 | V34: =_xlfn.XLOOKUP(INT(U34/1000)*1000+1,$C$29:$C$85,$E$29:$E$85) -> 0 | X34: 超R | Y34: 3
B35: 1 | C35: =OFFSET($D$6,B35,COUNTIF($B$29:B35,B35)) -> 6001 | D35: 5203001 | E35: =_xlfn.XLOOKUP(D35,价值表!$D:$D,价值表!$C:$C) | F35: 600 | G35: 0.5 | H35: =$F35/10000*6*H$28*(1-$G35) -> 0.9 | I35: =$F35/10000*6*I$28*(1-$G35) -> 1.44 | J35: 1 | K35: 2 | L35: =IF(OFFSET($D$16,B35,MATCH(E35,$E$16:$L$16,0))="","",OFFSET($D$16,B35,MATCH(E35,$E$16:$L$16,0))) -> #N/A | M35: 大R | N35: {=IF(_xlfn.XLOOKUP($M35,$X$30:$X$34,$Y$30:$Y$34)<=MATCH(N$29,$N$29:$O$29,0),SUMPRODUCT(--($C$91:$C$234=$C35),$G$91:$G$234,$J$91:$J$234)/SUMPRODUCT(--($J$91:$J$234>0),$G$91:$G$234,--($C$91:$C$234=$C35))*MIN(H35,$L35),0)} -> 0 | O35: {=IF(_xlfn.XLOOKUP($M35,$X$30:$X$34,$Y$30:$Y$34)<=MATCH(O$29,$N$29:$O$29,0),SUMPRODUCT(--($C$91:$C$234=$C35),$G$91:$G$234,$J$91:$J$234)/SUMPRODUCT(--($J$91:$J$234>0),$G$91:$G$234,--($C$91:$C$234=$C35))*MIN(I35,$L35),0)} -> #N/A | P35: {=IF(_xlfn.XLOOKUP($M35,$X$30:$X$34,$Y$30:$Y$34)<=MATCH(N$29,$N$29:$O$29,0),SUMPRODUCT(--($C$91:$C$234=$C35),$G$91:$G$234,$F$91:$F$234,--($J$91:$J$234>0))/SUMPRODUCT(--($J$91:$J$234>0),$G$91:$G$234,--($C$91:$C$234=$C35))*MIN(H35,$L35),0)} -> 0 | Q35: {=IF(_xlfn.XLOOKUP($M35,$X$30:$X$34,$Y$30:$Y$34)<=MATCH(O$29,$N$29:$O$29,0),SUMPRODUCT(--($C$91:$C$234=$C35),$G$91:$G$234,$F$91:$F$234,--($J$91:$J$234>0))/SUMPRODUCT(--($J$91:$J$234>0),$G$91:$G$234,--($C$91:$C$234=$C35))*MIN(I35,$L35),0)} -> #N/A | U35: 4001 | V35: =_xlfn.XLOOKUP(INT(U35/1000)*1000+1,$C$29:$C$85,$E$29:$E$85) -> #N/A
B36: 1 | C36: =OFFSET($D$6,B36,COUNTIF($B$29:B36,B36)) -> 7002 | D36: 5103001 | E36: =_xlfn.XLOOKUP(D36,价值表!$D:$D,价值表!$C:$C) | F36: 2000 | G36: 0.5 | H36: =$F36/10000*6*H$28*(1-$G36) -> 3 | I36: =$F36/10000*6*I$28*(1-$G36) -> 4.8 | J36: 1 | K36: 2 | L36: =IF(OFFSET($D$16,B36,MATCH(E36,$E$16:$L$16,0))="","",OFFSET($D$16,B36,MATCH(E36,$E$16:$L$16,0))) -> #N/A | M36: 超R | N36: {=IF(_xlfn.XLOOKUP($M36,$X$30:$X$34,$Y$30:$Y$34)<=MATCH(N$29,$N$29:$O$29,0),SUMPRODUCT(--($C$91:$C$234=$C36),$G$91:$G$234,$J$91:$J$234)/SUMPRODUCT(--($J$91:$J$234>0),$G$91:$G$234,--($C$91:$C$234=$C36))*MIN(H36,$L36),0)} -> 0 | O36: {=IF(_xlfn.XLOOKUP($M36,$X$30:$X$34,$Y$30:$Y$34)<=MATCH(O$29,$N$29:$O$29,0),SUMPRODUCT(--($C$91:$C$234=$C36),$G$91:$G$234,$J$91:$J$234)/SUMPRODUCT(--($J$91:$J$234>0),$G$91:$G$234,--($C$91:$C$234=$C36))*MIN(I36,$L36),0)} -> 0 | P36: {=IF(_xlfn.XLOOKUP($M36,$X$30:$X$34,$Y$30:$Y$34)<=MATCH(N$29,$N$29:$O$29,0),SUMPRODUCT(--($C$91:$C$234=$C36),$G$91:$G$234,$F$91:$F$234,--($J$91:$J$234>0))/SUMPRODUCT(--($J$91:$J$234>0),$G$91:$G$234,--($C$91:$C$234=$C36))*MIN(H36,$L36),0)} -> 0 | Q36: {=IF(_xlfn.XLOOKUP($M36,$X$30:$X$34,$Y$30:$Y$34)<=MATCH(O$29,$N$29:$O$29,0),SUMPRODUCT(--($C$91:$C$234=$C36),$G$91:$G$234,$F$91:$F$234,--($J$91:$J$234>0))/SUMPRODUCT(--($J$91:$J$234>0),$G$91:$G$234,--($C$91:$C$234=$C36))*MIN(I36,$L36),0)} -> 0 | U36: 5001 | V36: =_xlfn.XLOOKUP(INT(U36/1000)*1000+1,$C$29:$C$85,$E$29:$E$85) -> #N/A
B37: 1 | C37: =OFFSET($D$6,B37,COUNTIF($B$29:B37,B37)) -> 8001 | D37: 1310100 | E37: =_xlfn.XLOOKUP(D37,价值表!$D:$D,价值表!$C:$C) | F37: 3200 | G37: 0.5 | H37: =$F37/10000*6*H$28*(1-$G37) -> 4.8 | I37: =$F37/10000*6*I$28*(1-$G37) -> 7.68 | J37: 1 | K37: 2 | L37: =IF(OFFSET($D$16,B37,MATCH(E37,$E$16:$L$16,0))="","",OFFSET($D$16,B37,MATCH(E37,$E$16:$L$16,0))) -> #N/A | M37: 超R | N37: {=IF(_xlfn.XLOOKUP($M37,$X$30:$X$34,$Y$30:$Y$34)<=MATCH(N$29,$N$29:$O$29,0),SUMPRODUCT(--($C$91:$C$234=$C37),$G$91:$G$234,$J$91:$J$234)/SUMPRODUCT(--($J$91:$J$234>0),$G$91:$G$234,--($C$91:$C$234=$C37))*MIN(H37,$L37),0)} -> 0 | O37: {=IF(_xlfn.XLOOKUP($M37,$X$30:$X$34,$Y$30:$Y$34)<=MATCH(O$29,$N$29:$O$29,0),SUMPRODUCT(--($C$91:$C$234=$C37),$G$91:$G$234,$J$91:$J$234)/SUMPRODUCT(--($J$91:$J$234>0),$G$91:$G$234,--($C$91:$C$234=$C37))*MIN(I37,$L37),0)} -> 0 | P37: {=IF(_xlfn.XLOOKUP($M37,$X$30:$X$34,$Y$30:$Y$34)<=MATCH(N$29,$N$29:$O$29,0),SUMPRODUCT(--($C$91:$C$234=$C37),$G$91:$G$234,$F$91:$F$234,--($J$91:$J$234>0))/SUMPRODUCT(--($J$91:$J$234>0),$G$91:$G$234,--($C$91:$C$234=$C37))*MIN(H37,$L37),0)} -> 0 | Q37: {=IF(_xlfn.XLOOKUP($M37,$X$30:$X$34,$Y$30:$Y$34)<=MATCH(O$29,$N$29:$O$29,0),SUMPRODUCT(--($C$91:$C$234=$C37),$G$91:$G$234,$F$91:$F$234,--($J$91:$J$234>0))/SUMPRODUCT(--($J$91:$J$234>0),$G$91:$G$234,--($C$91:$C$234=$C37))*MIN(I37,$L37),0)} -> 0 | U37: 5002 | V37: =_xlfn.XLOOKUP(INT(U37/1000)*1000+1,$C$29:$C$85,$E$29:$E$85) -> #N/A
B38: =B30+1 -> 2 | C38: =OFFSET($D$6,B38,COUNTIF($B$29:B38,B38)) -> 1001 | D38: 11 | E38: =_xlfn.XLOOKUP(D38,价值表!$D:$D,价值表!$C:$C) | F38: 700 | G38: 0.5 | H38: =$F38/10000*6*H$28*(1-$G38) -> 1.05 | I38: =$F38/10000*6*I$28*(1-$G38) -> 1.68 | J38: 1 | K38: 2 | L38: =IF(OFFSET($D$16,B38,MATCH(E38,$E$16:$L$16,0))="","",OFFSET($D$16,B38,MATCH(E38,$E$16:$L$16,0))) -> #N/A | M38: 非R | N38: {=IF(_xlfn.XLOOKUP($M38,$X$30:$X$34,$Y$30:$Y$34)<=MATCH(N$29,$N$29:$O$29,0),SUMPRODUCT(--($C$91:$C$234=$C38),$G$91:$G$234,$J$91:$J$234)/SUMPRODUCT(--($J$91:$J$234>0),$G$91:$G$234,--($C$91:$C$234=$C38))*MIN(H38,$L38),0)} -> #N/A | O38: {=IF(_xlfn.XLOOKUP($M38,$X$30:$X$34,$Y$30:$Y$34)<=MATCH(O$29,$N$29:$O$29,0),SUMPRODUCT(--($C$91:$C$234=$C38),$G$91:$G$234,$J$91:$J$234)/SUMPRODUCT(--($J$91:$J$234>0),$G$91:$G$234,--($C$91:$C$234=$C38))*MIN(I38,$L38),0)} -> #N/A | P38: {=IF(_xlfn.XLOOKUP($M38,$X$30:$X$34,$Y$30:$Y$34)<=MATCH(N$29,$N$29:$O$29,0),SUMPRODUCT(--($C$91:$C$234=$C38),$G$91:$G$234,$F$91:$F$234,--($J$91:$J$234>0))/SUMPRODUCT(--($J$91:$J$234>0),$G$91:$G$234,--($C$91:$C$234=$C38))*MIN(H38,$L38),0)} -> #N/A | Q38: {=IF(_xlfn.XLOOKUP($M38,$X$30:$X$34,$Y$30:$Y$34)<=MATCH(O$29,$N$29:$O$29,0),SUMPRODUCT(--($C$91:$C$234=$C38),$G$91:$G$234,$F$91:$F$234,--($J$91:$J$234>0))/SUMPRODUCT(--($J$91:$J$234>0),$G$91:$G$234,--($C$91:$C$234=$C38))*MIN(I38,$L38),0)} -> #N/A | U38: 5003 | V38: =_xlfn.XLOOKUP(INT(U38/1000)*1000+1,$C$29:$C$85,$E$29:$E$85) -> #N/A
B39: =B31+1 -> 2 | C39: =OFFSET($D$6,B39,COUNTIF($B$29:B39,B39)) -> 2001 | D39: 9 | E39: =_xlfn.XLOOKUP(D39,价值表!$D:$D,价值表!$C:$C) | F39: 600 | G39: 0.5 | H39: =$F39/10000*6*H$28*(1-$G39) -> 0.9 | I39: =$F39/10000*6*I$28*(1-$G39) -> 1.44 | J39: 1 | K39: 2 | L39: =IF(OFFSET($D$16,B39,MATCH(E39,$E$16:$L$16,0))="","",OFFSET($D$16,B39,MATCH(E39,$E$16:$L$16,0))) -> 0 | M39: 非R | N39: {=IF(_xlfn.XLOOKUP($M39,$X$30:$X$34,$Y$30:$Y$34)<=MATCH(N$29,$N$29:$O$29,0),SUMPRODUCT(--($C$91:$C$234=$C39),$G$91:$G$234,$J$91:$J$234)/SUMPRODUCT(--($J$91:$J$234>0),$G$91:$G$234,--($C$91:$C$234=$C39))*MIN(H39,$L39),0)} -> 0 | O39: {=IF(_xlfn.XLOOKUP($M39,$X$30:$X$34,$Y$30:$Y$34)<=MATCH(O$29,$N$29:$O$29,0),SUMPRODUCT(--($C$91:$C$234=$C39),$G$91:$G$234,$J$91:$J$234)/SUMPRODUCT(--($J$91:$J$234>0),$G$91:$G$234,--($C$91:$C$234=$C39))*MIN(I39,$L39),0)} -> 0 | P39: {=IF(_xlfn.XLOOKUP($M39,$X$30:$X$34,$Y$30:$Y$34)<=MATCH(N$29,$N$29:$O$29,0),SUMPRODUCT(--($C$91:$C$234=$C39),$G$91:$G$234,$F$91:$F$234,--($J$91:$J$234>0))/SUMPRODUCT(--($J$91:$J$234>0),$G$91:$G$234,--($C$91:$C$234=$C39))*MIN(H39,$L39),0)} -> 0 | Q39: {=IF(_xlfn.XLOOKUP($M39,$X$30:$X$34,$Y$30:$Y$34)<=MATCH(O$29,$N$29:$O$29,0),SUMPRODUCT(--($C$91:$C$234=$C39),$G$91:$G$234,$F$91:$F$234,--($J$91:$J$234>0))/SUMPRODUCT(--($J$91:$J$234>0),$G$91:$G$234,--($C$91:$C$234=$C39))*MIN(I39,$L39),0)} -> 0 | U39: 6001 | V39: =_xlfn.XLOOKUP(INT(U39/1000)*1000+1,$C$29:$C$85,$E$29:$E$85) -> #N/A
B40: =B32+1 -> 2 | C40: =OFFSET($D$6,B40,COUNTIF($B$29:B40,B40)) -> 3001 | D40: 30 | E40: =_xlfn.XLOOKUP(D40,价值表!$D:$D,价值表!$C:$C) | F40: 200 | G40: 0.5 | H40: =$F40/10000*6*H$28*(1-$G40) -> 0.3 | I40: =$F40/10000*6*I$28*(1-$G40) -> 0.48 | J40: 1 | K40: 2 | L40: =IF(OFFSET($D$16,B40,MATCH(E40,$E$16:$L$16,0))="","",OFFSET($D$16,B40,MATCH(E40,$E$16:$L$16,0))) -> 1 | M40: 非R | N40: {=IF(_xlfn.XLOOKUP($M40,$X$30:$X$34,$Y$30:$Y$34)<=MATCH(N$29,$N$29:$O$29,0),SUMPRODUCT(--($C$91:$C$234=$C40),$G$91:$G$234,$J$91:$J$234)/SUMPRODUCT(--($J$91:$J$234>0),$G$91:$G$234,--($C$91:$C$234=$C40))*MIN(H40,$L40),0)} -> 3360 | O40: {=IF(_xlfn.XLOOKUP($M40,$X$30:$X$34,$Y$30:$Y$34)<=MATCH(O$29,$N$29:$O$29,0),SUMPRODUCT(--($C$91:$C$234=$C40),$G$91:$G$234,$J$91:$J$234)/SUMPRODUCT(--($J$91:$J$234>0),$G$91:$G$234,--($C$91:$C$234=$C40))*MIN(I40,$L40),0)} -> 5376 | P40: {=IF(_xlfn.XLOOKUP($M40,$X$30:$X$34,$Y$30:$Y$34)<=MATCH(N$29,$N$29:$O$29,0),SUMPRODUCT(--($C$91:$C$234=$C40),$G$91:$G$234,$F$91:$F$234,--($J$91:$J$234>0))/SUMPRODUCT(--($J$91:$J$234>0),$G$91:$G$234,--($C$91:$C$234=$C40))*MIN(H40,$L40),0)} -> 0.3 | Q40: {=IF(_xlfn.XLOOKUP($M40,$X$30:$X$34,$Y$30:$Y$34)<=MATCH(O$29,$N$29:$O$29,0),SUMPRODUCT(--($C$91:$C$234=$C40),$G$91:$G$234,$F$91:$F$234,--($J$91:$J$234>0))/SUMPRODUCT(--($J$91:$J$234>0),$G$91:$G$234,--($C$91:$C$234=$C40))*MIN(I40,$L40),0)} -> 0.48 | U40: 6002 | V40: =_xlfn.XLOOKUP(INT(U40/1000)*1000+1,$C$29:$C$85,$E$29:$E$85) -> #N/A
B41: =B33+1 -> 2 | C41: =OFFSET($D$6,B41,COUNTIF($B$29:B41,B41)) -> 4001 | D41: 5305001 | E41: =_xlfn.XLOOKUP(D41,价值表!$D:$D,价值表!$C:$C) | F41: 300 | G41: 0.5 | H41: =$F41/10000*6*H$28*(1-$G41) -> 0.45 | I41: =$F41/10000*6*I$28*(1-$G41) -> 0.72 | J41: 1 | K41: 2 | L41: =IF(OFFSET($D$16,B41,MATCH(E41,$E$16:$L$16,0))="","",OFFSET($D$16,B41,MATCH(E41,$E$16:$L$16,0))) -> #N/A | M41: 非R | N41: {=IF(_xlfn.XLOOKUP($M41,$X$30:$X$34,$Y$30:$Y$34)<=MATCH(N$29,$N$29:$O$29,0),SUMPRODUCT(--($C$91:$C$234=$C41),$G$91:$G$234,$J$91:$J$234)/SUMPRODUCT(--($J$91:$J$234>0),$G$91:$G$234,--($C$91:$C$234=$C41))*MIN(H41,$L41),0)} -> #N/A | O41: {=IF(_xlfn.XLOOKUP($M41,$X$30:$X$34,$Y$30:$Y$34)<=MATCH(O$29,$N$29:$O$29,0),SUMPRODUCT(--($C$91:$C$234=$C41),$G$91:$G$234,$J$91:$J$234)/SUMPRODUCT(--($J$91:$J$234>0),$G$91:$G$234,--($C$91:$C$234=$C41))*MIN(I41,$L41),0)} -> #N/A | P41: {=IF(_xlfn.XLOOKUP($M41,$X$30:$X$34,$Y$30:$Y$34)<=MATCH(N$29,$N$29:$O$29,0),SUMPRODUCT(--($C$91:$C$234=$C41),$G$91:$G$234,$F$91:$F$234,--($J$91:$J$234>0))/SUMPRODUCT(--($J$91:$J$234>0),$G$91:$G$234,--($C$91:$C$234=$C41))*MIN(H41,$L41),0)} -> #N/A | Q41: {=IF(_xlfn.XLOOKUP($M41,$X$30:$X$34,$Y$30:$Y$34)<=MATCH(O$29,$N$29:$O$29,0),SUMPRODUCT(--($C$91:$C$234=$C41),$G$91:$G$234,$F$91:$F$234,--($J$91:$J$234>0))/SUMPRODUCT(--($J$91:$J$234>0),$G$91:$G$234,--($C$91:$C$234=$C41))*MIN(I41,$L41),0)} -> #N/A | U41: 6003 | V41: =_xlfn.XLOOKUP(INT(U41/1000)*1000+1,$C$29:$C$85,$E$29:$E$85) -> #N/A
B42: =B34+1 -> 2 | C42: =OFFSET($D$6,B42,COUNTIF($B$29:B42,B42)) -> 5002 | D42: 50002 | E42: =_xlfn.XLOOKUP(D42,价值表!$D:$D,价值表!$C:$C) | F42: 2400 | G42: 0.5 | H42: =$F42/10000*6*H$28*(1-$G42) -> 3.6 | I42: =$F42/10000*6*I$28*(1-$G42) -> 5.76 | J42: 1 | K42: 2 | L42: =IF(OFFSET($D$16,B42,MATCH(E42,$E$16:$L$16,0))="","",OFFSET($D$16,B42,MATCH(E42,$E$16:$L$16,0))) -> #N/A | M42: 非R | N42: {=IF(_xlfn.XLOOKUP($M42,$X$30:$X$34,$Y$30:$Y$34)<=MATCH(N$29,$N$29:$O$29,0),SUMPRODUCT(--($C$91:$C$234=$C42),$G$91:$G$234,$J$91:$J$234)/SUMPRODUCT(--($J$91:$J$234>0),$G$91:$G$234,--($C$91:$C$234=$C42))*MIN(H42,$L42),0)} -> #N/A | O42: {=IF(_xlfn.XLOOKUP($M42,$X$30:$X$34,$Y$30:$Y$34)<=MATCH(O$29,$N$29:$O$29,0),SUMPRODUCT(--($C$91:$C$234=$C42),$G$91:$G$234,$J$91:$J$234)/SUMPRODUCT(--($J$91:$J$234>0),$G$91:$G$234,--($C$91:$C$234=$C42))*MIN(I42,$L42),0)} -> #N/A | P42: {=IF(_xlfn.XLOOKUP($M42,$X$30:$X$34,$Y$30:$Y$34)<=MATCH(N$29,$N$29:$O$29,0),SUMPRODUCT(--($C$91:$C$234=$C42),$G$91:$G$234,$F$91:$F$234,--($J$91:$J$234>0))/SUMPRODUCT(--($J$91:$J$234>0),$G$91:$G$234,--($C$91:$C$234=$C42))*MIN(H42,$L42),0)} -> #N/A | Q42: {=IF(_xlfn.XLOOKUP($M42,$X$30:$X$34,$Y$30:$Y$34)<=MATCH(O$29,$N$29:$O$29,0),SUMPRODUCT(--($C$91:$C$234=$C42),$G$91:$G$234,$F$91:$F$234,--($J$91:$J$234>0))/SUMPRODUCT(--($J$91:$J$234>0),$G$91:$G$234,--($C$91:$C$234=$C42))*MIN(I42,$L42),0)} -> #N/A | U42: 7001 | V42: =_xlfn.XLOOKUP(INT(U42/1000)*1000+2,$C$29:$C$85,$E$29:$E$85) -> #N/A
B43: =B35+1 -> 2 | C43: =OFFSET($D$6,B43,COUNTIF($B$29:B43,B43)) -> 6001 | D43: 5203001 | E43: =_xlfn.XLOOKUP(D43,价值表!$D:$D,价值表!$C:$C) | F43: 600 | G43: 0.5 | H43: =$F43/10000*6*H$28*(1-$G43) -> 0.9 | I43: =$F43/10000*6*I$28*(1-$G43) -> 1.44 | J43: 1 | K43: 2 | L43: =IF(OFFSET($D$16,B43,MATCH(E43,$E$16:$L$16,0))="","",OFFSET($D$16,B43,MATCH(E43,$E$16:$L$16,0))) -> #N/A | M43: 大R | N43: {=IF(_xlfn.XLOOKUP($M43,$X$30:$X$34,$Y$30:$Y$34)<=MATCH(N$29,$N$29:$O$29,0),SUMPRODUCT(--($C$91:$C$234=$C43),$G$91:$G$234,$J$91:$J$234)/SUMPRODUCT(--($J$91:$J$234>0),$G$91:$G$234,--($C$91:$C$234=$C43))*MIN(H43,$L43),0)} -> 0 | O43: {=IF(_xlfn.XLOOKUP($M43,$X$30:$X$34,$Y$30:$Y$34)<=MATCH(O$29,$N$29:$O$29,0),SUMPRODUCT(--($C$91:$C$234=$C43),$G$91:$G$234,$J$91:$J$234)/SUMPRODUCT(--($J$91:$J$234>0),$G$91:$G$234,--($C$91:$C$234=$C43))*MIN(I43,$L43),0)} -> #N/A | P43: {=IF(_xlfn.XLOOKUP($M43,$X$30:$X$34,$Y$30:$Y$34)<=MATCH(N$29,$N$29:$O$29,0),SUMPRODUCT(--($C$91:$C$234=$C43),$G$91:$G$234,$F$91:$F$234,--($J$91:$J$234>0))/SUMPRODUCT(--($J$91:$J$234>0),$G$91:$G$234,--($C$91:$C$234=$C43))*MIN(H43,$L43),0)} -> 0 | Q43: {=IF(_xlfn.XLOOKUP($M43,$X$30:$X$34,$Y$30:$Y$34)<=MATCH(O$29,$N$29:$O$29,0),SUMPRODUCT(--($C$91:$C$234=$C43),$G$91:$G$234,$F$91:$F$234,--($J$91:$J$234>0))/SUMPRODUCT(--($J$91:$J$234>0),$G$91:$G$234,--($C$91:$C$234=$C43))*MIN(I43,$L43),0)} -> #N/A | U43: 7002 | V43: =_xlfn.XLOOKUP(INT(U43/1000)*1000+2,$C$29:$C$85,$E$29:$E$85) -> #N/A
B44: =B36+1 -> 2 | C44: =OFFSET($D$6,B44,COUNTIF($B$29:B44,B44)) -> 7002 | D44: 5103001 | E44: =_xlfn.XLOOKUP(D44,价值表!$D:$D,价值表!$C:$C) | F44: 2000 | G44: 0.5 | H44: =$F44/10000*6*H$28*(1-$G44) -> 3 | I44: =$F44/10000*6*I$28*(1-$G44) -> 4.8 | J44: 1 | K44: 2 | L44: =IF(OFFSET($D$16,B44,MATCH(E44,$E$16:$L$16,0))="","",OFFSET($D$16,B44,MATCH(E44,$E$16:$L$16,0))) -> #N/A | M44: 超R | N44: {=IF(_xlfn.XLOOKUP($M44,$X$30:$X$34,$Y$30:$Y$34)<=MATCH(N$29,$N$29:$O$29,0),SUMPRODUCT(--($C$91:$C$234=$C44),$G$91:$G$234,$J$91:$J$234)/SUMPRODUCT(--($J$91:$J$234>0),$G$91:$G$234,--($C$91:$C$234=$C44))*MIN(H44,$L44),0)} -> 0 | O44: {=IF(_xlfn.XLOOKUP($M44,$X$30:$X$34,$Y$30:$Y$34)<=MATCH(O$29,$N$29:$O$29,0),SUMPRODUCT(--($C$91:$C$234=$C44),$G$91:$G$234,$J$91:$J$234)/SUMPRODUCT(--($J$91:$J$234>0),$G$91:$G$234,--($C$91:$C$234=$C44))*MIN(I44,$L44),0)} -> 0 | P44: {=IF(_xlfn.XLOOKUP($M44,$X$30:$X$34,$Y$30:$Y$34)<=MATCH(N$29,$N$29:$O$29,0),SUMPRODUCT(--($C$91:$C$234=$C44),$G$91:$G$234,$F$91:$F$234,--($J$91:$J$234>0))/SUMPRODUCT(--($J$91:$J$234>0),$G$91:$G$234,--($C$91:$C$234=$C44))*MIN(H44,$L44),0)} -> 0 | Q44: {=IF(_xlfn.XLOOKUP($M44,$X$30:$X$34,$Y$30:$Y$34)<=MATCH(O$29,$N$29:$O$29,0),SUMPRODUCT(--($C$91:$C$234=$C44),$G$91:$G$234,$F$91:$F$234,--($J$91:$J$234>0))/SUMPRODUCT(--($J$91:$J$234>0),$G$91:$G$234,--($C$91:$C$234=$C44))*MIN(I44,$L44),0)} -> 0 | U44: 7003 | V44: =_xlfn.XLOOKUP(INT(U44/1000)*1000+2,$C$29:$C$85,$E$29:$E$85) -> #N/A
B45: =B37+1 -> 2 | C45: =OFFSET($D$6,B45,COUNTIF($B$29:B45,B45)) -> 8001 | D45: 1310100 | E45: =_xlfn.XLOOKUP(D45,价值表!$D:$D,价值表!$C:$C) | F45: 3200 | G45: 0.5 | H45: =$F45/10000*6*H$28*(1-$G45) -> 4.8 | I45: =$F45/10000*6*I$28*(1-$G45) -> 7.68 | J45: 1 | K45: 2 | L45: =IF(OFFSET($D$16,B45,MATCH(E45,$E$16:$L$16,0))="","",OFFSET($D$16,B45,MATCH(E45,$E$16:$L$16,0))) -> #N/A | M45: 超R | N45: {=IF(_xlfn.XLOOKUP($M45,$X$30:$X$34,$Y$30:$Y$34)<=MATCH(N$29,$N$29:$O$29,0),SUMPRODUCT(--($C$91:$C$234=$C45),$G$91:$G$234,$J$91:$J$234)/SUMPRODUCT(--($J$91:$J$234>0),$G$91:$G$234,--($C$91:$C$234=$C45))*MIN(H45,$L45),0)} -> 0 | O45: {=IF(_xlfn.XLOOKUP($M45,$X$30:$X$34,$Y$30:$Y$34)<=MATCH(O$29,$N$29:$O$29,0),SUMPRODUCT(--($C$91:$C$234=$C45),$G$91:$G$234,$J$91:$J$234)/SUMPRODUCT(--($J$91:$J$234>0),$G$91:$G$234,--($C$91:$C$234=$C45))*MIN(I45,$L45),0)} -> 0 | P45: {=IF(_xlfn.XLOOKUP($M45,$X$30:$X$34,$Y$30:$Y$34)<=MATCH(N$29,$N$29:$O$29,0),SUMPRODUCT(--($C$91:$C$234=$C45),$G$91:$G$234,$F$91:$F$234,--($J$91:$J$234>0))/SUMPRODUCT(--($J$91:$J$234>0),$G$91:$G$234,--($C$91:$C$234=$C45))*MIN(H45,$L45),0)} -> 0 | Q45: {=IF(_xlfn.XLOOKUP($M45,$X$30:$X$34,$Y$30:$Y$34)<=MATCH(O$29,$N$29:$O$29,0),SUMPRODUCT(--($C$91:$C$234=$C45),$G$91:$G$234,$F$91:$F$234,--($J$91:$J$234>0))/SUMPRODUCT(--($J$91:$J$234>0),$G$91:$G$234,--($C$91:$C$234=$C45))*MIN(I45,$L45),0)} -> 0 | U45: 8001 | V45: =_xlfn.XLOOKUP(INT(U45/1000)*1000+1,$C$29:$C$85,$E$29:$E$85) -> #N/A
B46: =B38+1 -> 3 | C46: =OFFSET($D$6,B46,COUNTIF($B$29:B46,B46)) -> 1001 | D46: 11 | E46: =_xlfn.XLOOKUP(D46,价值表!$D:$D,价值表!$C:$C) | F46: 700 | G46: 0.5 | H46: =$F46/10000*6*H$28*(1-$G46) -> 1.05 | I46: =$F46/10000*6*I$28*(1-$G46) -> 1.68 | J46: 1 | K46: 2 | L46: =IF(OFFSET($D$16,B46,MATCH(E46,$E$16:$L$16,0))="","",OFFSET($D$16,B46,MATCH(E46,$E$16:$L$16,0))) -> #N/A | M46: 非R | N46: {=IF(_xlfn.XLOOKUP($M46,$X$30:$X$34,$Y$30:$Y$34)<=MATCH(N$29,$N$29:$O$29,0),SUMPRODUCT(--($C$91:$C$234=$C46),$G$91:$G$234,$J$91:$J$234)/SUMPRODUCT(--($J$91:$J$234>0),$G$91:$G$234,--($C$91:$C$234=$C46))*MIN(H46,$L46),0)} -> #N/A | O46: {=IF(_xlfn.XLOOKUP($M46,$X$30:$X$34,$Y$30:$Y$34)<=MATCH(O$29,$N$29:$O$29,0),SUMPRODUCT(--($C$91:$C$234=$C46),$G$91:$G$234,$J$91:$J$234)/SUMPRODUCT(--($J$91:$J$234>0),$G$91:$G$234,--($C$91:$C$234=$C46))*MIN(I46,$L46),0)} -> #N/A | P46: {=IF(_xlfn.XLOOKUP($M46,$X$30:$X$34,$Y$30:$Y$34)<=MATCH(N$29,$N$29:$O$29,0),SUMPRODUCT(--($C$91:$C$234=$C46),$G$91:$G$234,$F$91:$F$234,--($J$91:$J$234>0))/SUMPRODUCT(--($J$91:$J$234>0),$G$91:$G$234,--($C$91:$C$234=$C46))*MIN(H46,$L46),0)} -> #N/A | Q46: {=IF(_xlfn.XLOOKUP($M46,$X$30:$X$34,$Y$30:$Y$34)<=MATCH(O$29,$N$29:$O$29,0),SUMPRODUCT(--($C$91:$C$234=$C46),$G$91:$G$234,$F$91:$F$234,--($J$91:$J$234>0))/SUMPRODUCT(--($J$91:$J$234>0),$G$91:$G$234,--($C$91:$C$234=$C46))*MIN(I46,$L46),0)} -> #N/A
B47: =B39+1 -> 3 | C47: =OFFSET($D$6,B47,COUNTIF($B$29:B47,B47)) -> 2001 | D47: 9 | E47: =_xlfn.XLOOKUP(D47,价值表!$D:$D,价值表!$C:$C) | F47: 600 | G47: 0.5 | H47: =$F47/10000*6*H$28*(1-$G47) -> 0.9 | I47: =$F47/10000*6*I$28*(1-$G47) -> 1.44 | J47: 1 | K47: 2 | L47: =IF(OFFSET($D$16,B47,MATCH(E47,$E$16:$L$16,0))="","",OFFSET($D$16,B47,MATCH(E47,$E$16:$L$16,0))) -> 1 | M47: 非R | N47: {=IF(_xlfn.XLOOKUP($M47,$X$30:$X$34,$Y$30:$Y$34)<=MATCH(N$29,$N$29:$O$29,0),SUMPRODUCT(--($C$91:$C$234=$C47),$G$91:$G$234,$J$91:$J$234)/SUMPRODUCT(--($J$91:$J$234>0),$G$91:$G$234,--($C$91:$C$234=$C47))*MIN(H47,$L47),0)} -> 1800 | O47: {=IF(_xlfn.XLOOKUP($M47,$X$30:$X$34,$Y$30:$Y$34)<=MATCH(O$29,$N$29:$O$29,0),SUMPRODUCT(--($C$91:$C$234=$C47),$G$91:$G$234,$J$91:$J$234)/SUMPRODUCT(--($J$91:$J$234>0),$G$91:$G$234,--($C$91:$C$234=$C47))*MIN(I47,$L47),0)} -> 2000 | P47: {=IF(_xlfn.XLOOKUP($M47,$X$30:$X$34,$Y$30:$Y$34)<=MATCH(N$29,$N$29:$O$29,0),SUMPRODUCT(--($C$91:$C$234=$C47),$G$91:$G$234,$F$91:$F$234,--($J$91:$J$234>0))/SUMPRODUCT(--($J$91:$J$234>0),$G$91:$G$234,--($C$91:$C$234=$C47))*MIN(H47,$L47),0)} -> 0.9 | Q47: {=IF(_xlfn.XLOOKUP($M47,$X$30:$X$34,$Y$30:$Y$34)<=MATCH(O$29,$N$29:$O$29,0),SUMPRODUCT(--($C$91:$C$234=$C47),$G$91:$G$234,$F$91:$F$234,--($J$91:$J$234>0))/SUMPRODUCT(--($J$91:$J$234>0),$G$91:$G$234,--($C$91:$C$234=$C47))*MIN(I47,$L47),0)} -> 1
B48: =B40+1 -> 3 | C48: =OFFSET($D$6,B48,COUNTIF($B$29:B48,B48)) -> 3001 | D48: 30 | E48: =_xlfn.XLOOKUP(D48,价值表!$D:$D,价值表!$C:$C) | F48: 200 | G48: 0.5 | H48: =$F48/10000*6*H$28*(1-$G48) -> 0.3 | I48: =$F48/10000*6*I$28*(1-$G48) -> 0.48 | J48: 1 | K48: 2 | L48: =IF(OFFSET($D$16,B48,MATCH(E48,$E$16:$L$16,0))="","",OFFSET($D$16,B48,MATCH(E48,$E$16:$L$16,0))) -> 0 | M48: 非R | N48: {=IF(_xlfn.XLOOKUP($M48,$X$30:$X$34,$Y$30:$Y$34)<=MATCH(N$29,$N$29:$O$29,0),SUMPRODUCT(--($C$91:$C$234=$C48),$G$91:$G$234,$J$91:$J$234)/SUMPRODUCT(--($J$91:$J$234>0),$G$91:$G$234,--($C$91:$C$234=$C48))*MIN(H48,$L48),0)} -> 0 | O48: {=IF(_xlfn.XLOOKUP($M48,$X$30:$X$34,$Y$30:$Y$34)<=MATCH(O$29,$N$29:$O$29,0),SUMPRODUCT(--($C$91:$C$234=$C48),$G$91:$G$234,$J$91:$J$234)/SUMPRODUCT(--($J$91:$J$234>0),$G$91:$G$234,--($C$91:$C$234=$C48))*MIN(I48,$L48),0)} -> 0 | P48: {=IF(_xlfn.XLOOKUP($M48,$X$30:$X$34,$Y$30:$Y$34)<=MATCH(N$29,$N$29:$O$29,0),SUMPRODUCT(--($C$91:$C$234=$C48),$G$91:$G$234,$F$91:$F$234,--($J$91:$J$234>0))/SUMPRODUCT(--($J$91:$J$234>0),$G$91:$G$234,--($C$91:$C$234=$C48))*MIN(H48,$L48),0)} -> 0 | Q48: {=IF(_xlfn.XLOOKUP($M48,$X$30:$X$34,$Y$30:$Y$34)<=MATCH(O$29,$N$29:$O$29,0),SUMPRODUCT(--($C$91:$C$234=$C48),$G$91:$G$234,$F$91:$F$234,--($J$91:$J$234>0))/SUMPRODUCT(--($J$91:$J$234>0),$G$91:$G$234,--($C$91:$C$234=$C48))*MIN(I48,$L48),0)} -> 0
B49: =B41+1 -> 3 | C49: =OFFSET($D$6,B49,COUNTIF($B$29:B49,B49)) -> 4001 | D49: 5305001 | E49: =_xlfn.XLOOKUP(D49,价值表!$D:$D,价值表!$C:$C) | F49: 300 | G49: 0.5 | H49: =$F49/10000*6*H$28*(1-$G49) -> 0.45 | I49: =$F49/10000*6*I$28*(1-$G49) -> 0.72 | J49: 1 | K49: 2 | L49: =IF(OFFSET($D$16,B49,MATCH(E49,$E$16:$L$16,0))="","",OFFSET($D$16,B49,MATCH(E49,$E$16:$L$16,0))) -> #N/A | M49: 非R | N49: {=IF(_xlfn.XLOOKUP($M49,$X$30:$X$34,$Y$30:$Y$34)<=MATCH(N$29,$N$29:$O$29,0),SUMPRODUCT(--($C$91:$C$234=$C49),$G$91:$G$234,$J$91:$J$234)/SUMPRODUCT(--($J$91:$J$234>0),$G$91:$G$234,--($C$91:$C$234=$C49))*MIN(H49,$L49),0)} -> #N/A | O49: {=IF(_xlfn.XLOOKUP($M49,$X$30:$X$34,$Y$30:$Y$34)<=MATCH(O$29,$N$29:$O$29,0),SUMPRODUCT(--($C$91:$C$234=$C49),$G$91:$G$234,$J$91:$J$234)/SUMPRODUCT(--($J$91:$J$234>0),$G$91:$G$234,--($C$91:$C$234=$C49))*MIN(I49,$L49),0)} -> #N/A | P49: {=IF(_xlfn.XLOOKUP($M49,$X$30:$X$34,$Y$30:$Y$34)<=MATCH(N$29,$N$29:$O$29,0),SUMPRODUCT(--($C$91:$C$234=$C49),$G$91:$G$234,$F$91:$F$234,--($J$91:$J$234>0))/SUMPRODUCT(--($J$91:$J$234>0),$G$91:$G$234,--($C$91:$C$234=$C49))*MIN(H49,$L49),0)} -> #N/A | Q49: {=IF(_xlfn.XLOOKUP($M49,$X$30:$X$34,$Y$30:$Y$34)<=MATCH(O$29,$N$29:$O$29,0),SUMPRODUCT(--($C$91:$C$234=$C49),$G$91:$G$234,$F$91:$F$234,--($J$91:$J$234>0))/SUMPRODUCT(--($J$91:$J$234>0),$G$91:$G$234,--($C$91:$C$234=$C49))*MIN(I49,$L49),0)} -> #N/A
B50: =B42+1 -> 3 | C50: =OFFSET($D$6,B50,COUNTIF($B$29:B50,B50)) -> 5002 | D50: 50002 | E50: =_xlfn.XLOOKUP(D50,价值表!$D:$D,价值表!$C:$C) | F50: 2400 | G50: 0.5 | H50: =$F50/10000*6*H$28*(1-$G50) -> 3.6 | I50: =$F50/10000*6*I$28*(1-$G50) -> 5.76 | J50: 1 | K50: 2 | L50: =IF(OFFSET($D$16,B50,MATCH(E50,$E$16:$L$16,0))="","",OFFSET($D$16,B50,MATCH(E50,$E$16:$L$16,0))) -> #N/A | M50: 非R | N50: {=IF(_xlfn.XLOOKUP($M50,$X$30:$X$34,$Y$30:$Y$34)<=MATCH(N$29,$N$29:$O$29,0),SUMPRODUCT(--($C$91:$C$234=$C50),$G$91:$G$234,$J$91:$J$234)/SUMPRODUCT(--($J$91:$J$234>0),$G$91:$G$234,--($C$91:$C$234=$C50))*MIN(H50,$L50),0)} -> #N/A | O50: {=IF(_xlfn.XLOOKUP($M50,$X$30:$X$34,$Y$30:$Y$34)<=MATCH(O$29,$N$29:$O$29,0),SUMPRODUCT(--($C$91:$C$234=$C50),$G$91:$G$234,$J$91:$J$234)/SUMPRODUCT(--($J$91:$J$234>0),$G$91:$G$234,--($C$91:$C$234=$C50))*MIN(I50,$L50),0)} -> #N/A | P50: {=IF(_xlfn.XLOOKUP($M50,$X$30:$X$34,$Y$30:$Y$34)<=MATCH(N$29,$N$29:$O$29,0),SUMPRODUCT(--($C$91:$C$234=$C50),$G$91:$G$234,$F$91:$F$234,--($J$91:$J$234>0))/SUMPRODUCT(--($J$91:$J$234>0),$G$91:$G$234,--($C$91:$C$234=$C50))*MIN(H50,$L50),0)} -> #N/A | Q50: {=IF(_xlfn.XLOOKUP($M50,$X$30:$X$34,$Y$30:$Y$34)<=MATCH(O$29,$N$29:$O$29,0),SUMPRODUCT(--($C$91:$C$234=$C50),$G$91:$G$234,$F$91:$F$234,--($J$91:$J$234>0))/SUMPRODUCT(--($J$91:$J$234>0),$G$91:$G$234,--($C$91:$C$234=$C50))*MIN(I50,$L50),0)} -> #N/A
B51: =B43+1 -> 3 | C51: =OFFSET($D$6,B51,COUNTIF($B$29:B51,B51)) -> 6002 | D51: 5203001 | E51: =_xlfn.XLOOKUP(D51,价值表!$D:$D,价值表!$C:$C) | F51: 600 | G51: 0.5 | H51: =$F51/10000*6*H$28*(1-$G51) -> 0.9 | I51: =$F51/10000*6*I$28*(1-$G51) -> 1.44 | J51: 1 | K51: 2 | L51: =IF(OFFSET($D$16,B51,MATCH(E51,$E$16:$L$16,0))="","",OFFSET($D$16,B51,MATCH(E51,$E$16:$L$16,0))) -> #N/A | M51: 大R | N51: {=IF(_xlfn.XLOOKUP($M51,$X$30:$X$34,$Y$30:$Y$34)<=MATCH(N$29,$N$29:$O$29,0),SUMPRODUCT(--($C$91:$C$234=$C51),$G$91:$G$234,$J$91:$J$234)/SUMPRODUCT(--($J$91:$J$234>0),$G$91:$G$234,--($C$91:$C$234=$C51))*MIN(H51,$L51),0)} -> 0 | O51: {=IF(_xlfn.XLOOKUP($M51,$X$30:$X$34,$Y$30:$Y$34)<=MATCH(O$29,$N$29:$O$29,0),SUMPRODUCT(--($C$91:$C$234=$C51),$G$91:$G$234,$J$91:$J$234)/SUMPRODUCT(--($J$91:$J$234>0),$G$91:$G$234,--($C$91:$C$234=$C51))*MIN(I51,$L51),0)} -> #N/A | P51: {=IF(_xlfn.XLOOKUP($M51,$X$30:$X$34,$Y$30:$Y$34)<=MATCH(N$29,$N$29:$O$29,0),SUMPRODUCT(--($C$91:$C$234=$C51),$G$91:$G$234,$F$91:$F$234,--($J$91:$J$234>0))/SUMPRODUCT(--($J$91:$J$234>0),$G$91:$G$234,--($C$91:$C$234=$C51))*MIN(H51,$L51),0)} -> 0 | Q51: {=IF(_xlfn.XLOOKUP($M51,$X$30:$X$34,$Y$30:$Y$34)<=MATCH(O$29,$N$29:$O$29,0),SUMPRODUCT(--($C$91:$C$234=$C51),$G$91:$G$234,$F$91:$F$234,--($J$91:$J$234>0))/SUMPRODUCT(--($J$91:$J$234>0),$G$91:$G$234,--($C$91:$C$234=$C51))*MIN(I51,$L51),0)} -> #N/A
B52: =B44+1 -> 3 | C52: =OFFSET($D$6,B52,COUNTIF($B$29:B52,B52)) -> 7002 | D52: 5103001 | E52: =_xlfn.XLOOKUP(D52,价值表!$D:$D,价值表!$C:$C) | F52: 2000 | G52: 0.5 | H52: =$F52/10000*6*H$28*(1-$G52) -> 3 | I52: =$F52/10000*6*I$28*(1-$G52) -> 4.8 | J52: 1 | K52: 2 | L52: =IF(OFFSET($D$16,B52,MATCH(E52,$E$16:$L$16,0))="","",OFFSET($D$16,B52,MATCH(E52,$E$16:$L$16,0))) -> #N/A | M52: 超R | N52: {=IF(_xlfn.XLOOKUP($M52,$X$30:$X$34,$Y$30:$Y$34)<=MATCH(N$29,$N$29:$O$29,0),SUMPRODUCT(--($C$91:$C$234=$C52),$G$91:$G$234,$J$91:$J$234)/SUMPRODUCT(--($J$91:$J$234>0),$G$91:$G$234,--($C$91:$C$234=$C52))*MIN(H52,$L52),0)} -> 0 | O52: {=IF(_xlfn.XLOOKUP($M52,$X$30:$X$34,$Y$30:$Y$34)<=MATCH(O$29,$N$29:$O$29,0),SUMPRODUCT(--($C$91:$C$234=$C52),$G$91:$G$234,$J$91:$J$234)/SUMPRODUCT(--($J$91:$J$234>0),$G$91:$G$234,--($C$91:$C$234=$C52))*MIN(I52,$L52),0)} -> 0 | P52: {=IF(_xlfn.XLOOKUP($M52,$X$30:$X$34,$Y$30:$Y$34)<=MATCH(N$29,$N$29:$O$29,0),SUMPRODUCT(--($C$91:$C$234=$C52),$G$91:$G$234,$F$91:$F$234,--($J$91:$J$234>0))/SUMPRODUCT(--($J$91:$J$234>0),$G$91:$G$234,--($C$91:$C$234=$C52))*MIN(H52,$L52),0)} -> 0 | Q52: {=IF(_xlfn.XLOOKUP($M52,$X$30:$X$34,$Y$30:$Y$34)<=MATCH(O$29,$N$29:$O$29,0),SUMPRODUCT(--($C$91:$C$234=$C52),$G$91:$G$234,$F$91:$F$234,--($J$91:$J$234>0))/SUMPRODUCT(--($J$91:$J$234>0),$G$91:$G$234,--($C$91:$C$234=$C52))*MIN(I52,$L52),0)} -> 0
B53: =B45+1 -> 3 | C53: =OFFSET($D$6,B53,COUNTIF($B$29:B53,B53)) -> 8001 | D53: 1310100 | E53: =_xlfn.XLOOKUP(D53,价值表!$D:$D,价值表!$C:$C) | F53: 3200 | G53: 0.5 | H53: =$F53/10000*6*H$28*(1-$G53) -> 4.8 | I53: =$F53/10000*6*I$28*(1-$G53) -> 7.68 | J53: 1 | K53: 2 | L53: =IF(OFFSET($D$16,B53,MATCH(E53,$E$16:$L$16,0))="","",OFFSET($D$16,B53,MATCH(E53,$E$16:$L$16,0))) -> #N/A | M53: 超R | N53: {=IF(_xlfn.XLOOKUP($M53,$X$30:$X$34,$Y$30:$Y$34)<=MATCH(N$29,$N$29:$O$29,0),SUMPRODUCT(--($C$91:$C$234=$C53),$G$91:$G$234,$J$91:$J$234)/SUMPRODUCT(--($J$91:$J$234>0),$G$91:$G$234,--($C$91:$C$234=$C53))*MIN(H53,$L53),0)} -> 0 | O53: {=IF(_xlfn.XLOOKUP($M53,$X$30:$X$34,$Y$30:$Y$34)<=MATCH(O$29,$N$29:$O$29,0),SUMPRODUCT(--($C$91:$C$234=$C53),$G$91:$G$234,$J$91:$J$234)/SUMPRODUCT(--($J$91:$J$234>0),$G$91:$G$234,--($C$91:$C$234=$C53))*MIN(I53,$L53),0)} -> 0 | P53: {=IF(_xlfn.XLOOKUP($M53,$X$30:$X$34,$Y$30:$Y$34)<=MATCH(N$29,$N$29:$O$29,0),SUMPRODUCT(--($C$91:$C$234=$C53),$G$91:$G$234,$F$91:$F$234,--($J$91:$J$234>0))/SUMPRODUCT(--($J$91:$J$234>0),$G$91:$G$234,--($C$91:$C$234=$C53))*MIN(H53,$L53),0)} -> 0 | Q53: {=IF(_xlfn.XLOOKUP($M53,$X$30:$X$34,$Y$30:$Y$34)<=MATCH(O$29,$N$29:$O$29,0),SUMPRODUCT(--($C$91:$C$234=$C53),$G$91:$G$234,$F$91:$F$234,--($J$91:$J$234>0))/SUMPRODUCT(--($J$91:$J$234>0),$G$91:$G$234,--($C$91:$C$234=$C53))*MIN(I53,$L53),0)} -> 0
B54: =B46+1 -> 4 | C54: =OFFSET($D$6,B54,COUNTIF($B$29:B54,B54)) -> 1002 | D54: 11 | E54: =_xlfn.XLOOKUP(D54,价值表!$D:$D,价值表!$C:$C) | F54: 700 | G54: 0.5 | H54: =$F54/10000*6*H$28*(1-$G54) -> 1.05 | I54: =$F54/10000*6*I$28*(1-$G54) -> 1.68 | J54: 1 | K54: 2 | L54: =IF(OFFSET($D$16,B54,MATCH(E54,$E$16:$L$16,0))="","",OFFSET($D$16,B54,MATCH(E54,$E$16:$L$16,0))) -> #N/A | M54: 非R | N54: {=IF(_xlfn.XLOOKUP($M54,$X$30:$X$34,$Y$30:$Y$34)<=MATCH(N$29,$N$29:$O$29,0),SUMPRODUCT(--($C$91:$C$234=$C54),$G$91:$G$234,$J$91:$J$234)/SUMPRODUCT(--($J$91:$J$234>0),$G$91:$G$234,--($C$91:$C$234=$C54))*MIN(H54,$L54),0)} -> #N/A | O54: {=IF(_xlfn.XLOOKUP($M54,$X$30:$X$34,$Y$30:$Y$34)<=MATCH(O$29,$N$29:$O$29,0),SUMPRODUCT(--($C$91:$C$234=$C54),$G$91:$G$234,$J$91:$J$234)/SUMPRODUCT(--($J$91:$J$234>0),$G$91:$G$234,--($C$91:$C$234=$C54))*MIN(I54,$L54),0)} -> #N/A | P54: {=IF(_xlfn.XLOOKUP($M54,$X$30:$X$34,$Y$30:$Y$34)<=MATCH(N$29,$N$29:$O$29,0),SUMPRODUCT(--($C$91:$C$234=$C54),$G$91:$G$234,$F$91:$F$234,--($J$91:$J$234>0))/SUMPRODUCT(--($J$91:$J$234>0),$G$91:$G$234,--($C$91:$C$234=$C54))*MIN(H54,$L54),0)} -> #N/A | Q54: {=IF(_xlfn.XLOOKUP($M54,$X$30:$X$34,$Y$30:$Y$34)<=MATCH(O$29,$N$29:$O$29,0),SUMPRODUCT(--($C$91:$C$234=$C54),$G$91:$G$234,$F$91:$F$234,--($J$91:$J$234>0))/SUMPRODUCT(--($J$91:$J$234>0),$G$91:$G$234,--($C$91:$C$234=$C54))*MIN(I54,$L54),0)} -> #N/A
B55: =B47+1 -> 4 | C55: =OFFSET($D$6,B55,COUNTIF($B$29:B55,B55)) -> 2001 | D55: 9 | E55: =_xlfn.XLOOKUP(D55,价值表!$D:$D,价值表!$C:$C) | F55: 600 | G55: 0.5 | H55: =$F55/10000*6*H$28*(1-$G55) -> 0.9 | I55: =$F55/10000*6*I$28*(1-$G55) -> 1.44 | J55: 1 | K55: 2 | L55: =IF(OFFSET($D$16,B55,MATCH(E55,$E$16:$L$16,0))="","",OFFSET($D$16,B55,MATCH(E55,$E$16:$L$16,0))) -> 0 | M55: 非R | N55: {=IF(_xlfn.XLOOKUP($M55,$X$30:$X$34,$Y$30:$Y$34)<=MATCH(N$29,$N$29:$O$29,0),SUMPRODUCT(--($C$91:$C$234=$C55),$G$91:$G$234,$J$91:$J$234)/SUMPRODUCT(--($J$91:$J$234>0),$G$91:$G$234,--($C$91:$C$234=$C55))*MIN(H55,$L55),0)} -> 0 | O55: {=IF(_xlfn.XLOOKUP($M55,$X$30:$X$34,$Y$30:$Y$34)<=MATCH(O$29,$N$29:$O$29,0),SUMPRODUCT(--($C$91:$C$234=$C55),$G$91:$G$234,$J$91:$J$234)/SUMPRODUCT(--($J$91:$J$234>0),$G$91:$G$234,--($C$91:$C$234=$C55))*MIN(I55,$L55),0)} -> 0 | P55: {=IF(_xlfn.XLOOKUP($M55,$X$30:$X$34,$Y$30:$Y$34)<=MATCH(N$29,$N$29:$O$29,0),SUMPRODUCT(--($C$91:$C$234=$C55),$G$91:$G$234,$F$91:$F$234,--($J$91:$J$234>0))/SUMPRODUCT(--($J$91:$J$234>0),$G$91:$G$234,--($C$91:$C$234=$C55))*MIN(H55,$L55),0)} -> 0 | Q55: {=IF(_xlfn.XLOOKUP($M55,$X$30:$X$34,$Y$30:$Y$34)<=MATCH(O$29,$N$29:$O$29,0),SUMPRODUCT(--($C$91:$C$234=$C55),$G$91:$G$234,$F$91:$F$234,--($J$91:$J$234>0))/SUMPRODUCT(--($J$91:$J$234>0),$G$91:$G$234,--($C$91:$C$234=$C55))*MIN(I55,$L55),0)} -> 0
B56: =B48+1 -> 4 | C56: =OFFSET($D$6,B56,COUNTIF($B$29:B56,B56)) -> 3001 | D56: 30 | E56: =_xlfn.XLOOKUP(D56,价值表!$D:$D,价值表!$C:$C) | F56: 200 | G56: 0.5 | H56: =$F56/10000*6*H$28*(1-$G56) -> 0.3 | I56: =$F56/10000*6*I$28*(1-$G56) -> 0.48 | J56: 1 | K56: 2 | L56: =IF(OFFSET($D$16,B56,MATCH(E56,$E$16:$L$16,0))="","",OFFSET($D$16,B56,MATCH(E56,$E$16:$L$16,0))) -> 0 | M56: 非R | N56: {=IF(_xlfn.XLOOKUP($M56,$X$30:$X$34,$Y$30:$Y$34)<=MATCH(N$29,$N$29:$O$29,0),SUMPRODUCT(--($C$91:$C$234=$C56),$G$91:$G$234,$J$91:$J$234)/SUMPRODUCT(--($J$91:$J$234>0),$G$91:$G$234,--($C$91:$C$234=$C56))*MIN(H56,$L56),0)} -> 0 | O56: {=IF(_xlfn.XLOOKUP($M56,$X$30:$X$34,$Y$30:$Y$34)<=MATCH(O$29,$N$29:$O$29,0),SUMPRODUCT(--($C$91:$C$234=$C56),$G$91:$G$234,$J$91:$J$234)/SUMPRODUCT(--($J$91:$J$234>0),$G$91:$G$234,--($C$91:$C$234=$C56))*MIN(I56,$L56),0)} -> 0 | P56: {=IF(_xlfn.XLOOKUP($M56,$X$30:$X$34,$Y$30:$Y$34)<=MATCH(N$29,$N$29:$O$29,0),SUMPRODUCT(--($C$91:$C$234=$C56),$G$91:$G$234,$F$91:$F$234,--($J$91:$J$234>0))/SUMPRODUCT(--($J$91:$J$234>0),$G$91:$G$234,--($C$91:$C$234=$C56))*MIN(H56,$L56),0)} -> 0 | Q56: {=IF(_xlfn.XLOOKUP($M56,$X$30:$X$34,$Y$30:$Y$34)<=MATCH(O$29,$N$29:$O$29,0),SUMPRODUCT(--($C$91:$C$234=$C56),$G$91:$G$234,$F$91:$F$234,--($J$91:$J$234>0))/SUMPRODUCT(--($J$91:$J$234>0),$G$91:$G$234,--($C$91:$C$234=$C56))*MIN(I56,$L56),0)} -> 0
B57: =B49+1 -> 4 | C57: =OFFSET($D$6,B57,COUNTIF($B$29:B57,B57)) -> 4001 | D57: 5305001 | E57: =_xlfn.XLOOKUP(D57,价值表!$D:$D,价值表!$C:$C) | F57: 300 | G57: 0.5 | H57: =$F57/10000*6*H$28*(1-$G57) -> 0.45 | I57: =$F57/10000*6*I$28*(1-$G57) -> 0.72 | J57: 1 | K57: 2 | L57: =IF(OFFSET($D$16,B57,MATCH(E57,$E$16:$L$16,0))="","",OFFSET($D$16,B57,MATCH(E57,$E$16:$L$16,0))) -> #N/A | M57: 非R | N57: {=IF(_xlfn.XLOOKUP($M57,$X$30:$X$34,$Y$30:$Y$34)<=MATCH(N$29,$N$29:$O$29,0),SUMPRODUCT(--($C$91:$C$234=$C57),$G$91:$G$234,$J$91:$J$234)/SUMPRODUCT(--($J$91:$J$234>0),$G$91:$G$234,--($C$91:$C$234=$C57))*MIN(H57,$L57),0)} -> #N/A | O57: {=IF(_xlfn.XLOOKUP($M57,$X$30:$X$34,$Y$30:$Y$34)<=MATCH(O$29,$N$29:$O$29,0),SUMPRODUCT(--($C$91:$C$234=$C57),$G$91:$G$234,$J$91:$J$234)/SUMPRODUCT(--($J$91:$J$234>0),$G$91:$G$234,--($C$91:$C$234=$C57))*MIN(I57,$L57),0)} -> #N/A | P57: {=IF(_xlfn.XLOOKUP($M57,$X$30:$X$34,$Y$30:$Y$34)<=MATCH(N$29,$N$29:$O$29,0),SUMPRODUCT(--($C$91:$C$234=$C57),$G$91:$G$234,$F$91:$F$234,--($J$91:$J$234>0))/SUMPRODUCT(--($J$91:$J$234>0),$G$91:$G$234,--($C$91:$C$234=$C57))*MIN(H57,$L57),0)} -> #N/A | Q57: {=IF(_xlfn.XLOOKUP($M57,$X$30:$X$34,$Y$30:$Y$34)<=MATCH(O$29,$N$29:$O$29,0),SUMPRODUCT(--($C$91:$C$234=$C57),$G$91:$G$234,$F$91:$F$234,--($J$91:$J$234>0))/SUMPRODUCT(--($J$91:$J$234>0),$G$91:$G$234,--($C$91:$C$234=$C57))*MIN(I57,$L57),0)} -> #N/A
... B85: =B77+1 -> 7 | C85: =OFFSET($D$6,B85,COUNTIF($B$29:B85,B85)) -> 8001 | D85: 1310100 | E85: =_xlfn.XLOOKUP(D85,价值表!$D:$D,价值表!$C:$C) | F85: 3200 | G85: 0.5 | H85: =$F85/10000*6*H$28*(1-$G85) -> 4.8 | I85: =$F85/10000*6*I$28*(1-$G85) -> 7.68 | J85: 1 | K85: 2 | L85: =IF(OFFSET($D$16,B85,MATCH(E85,$E$16:$L$16,0))="","",OFFSET($D$16,B85,MATCH(E85,$E$16:$L$16,0))) -> #N/A | M85: 超R | N85: {=IF(_xlfn.XLOOKUP($M85,$X$30:$X$34,$Y$30:$Y$34)<=MATCH(N$29,$N$29:$O$29,0),SUMPRODUCT(--($C$91:$C$234=$C85),$G$91:$G$234,$J$91:$J$234)/SUMPRODUCT(--($J$91:$J$234>0),$G$91:$G$234,--($C$91:$C$234=$C85))*MIN(H85,$L85),0)} -> 0 | O85: {=IF(_xlfn.XLOOKUP($M85,$X$30:$X$34,$Y$30:$Y$34)<=MATCH(O$29,$N$29:$O$29,0),SUMPRODUCT(--($C$91:$C$234=$C85),$G$91:$G$234,$J$91:$J$234)/SUMPRODUCT(--($J$91:$J$234>0),$G$91:$G$234,--($C$91:$C$234=$C85))*MIN(I85,$L85),0)} -> 0 | P85: {=IF(_xlfn.XLOOKUP($M85,$X$30:$X$34,$Y$30:$Y$34)<=MATCH(N$29,$N$29:$O$29,0),SUMPRODUCT(--($C$91:$C$234=$C85),$G$91:$G$234,$F$91:$F$234,--($J$91:$J$234>0))/SUMPRODUCT(--($J$91:$J$234>0),$G$91:$G$234,--($C$91:$C$234=$C85))*MIN(H85,$L85),0)} -> 0 | Q85: {=IF(_xlfn.XLOOKUP($M85,$X$30:$X$34,$Y$30:$Y$34)<=MATCH(O$29,$N$29:$O$29,0),SUMPRODUCT(--($C$91:$C$234=$C85),$G$91:$G$234,$F$91:$F$234,--($J$91:$J$234>0))/SUMPRODUCT(--($J$91:$J$234>0),$G$91:$G$234,--($C$91:$C$234=$C85))*MIN(I85,$L85),0)} -> 0
J89: 0.05 | K89: 1
D90: 物品 | E90: 道具名 | F90: 数量 | G90: 修正权重 | H90: 标准权重 | I90: 价值 | J90: 金币 | K90: 钻石 | L90: 性价比
C91: 1001 | D91: =_xlfn.XLOOKUP(INT(C91/1000)*1000+1,$C$30:$C$69,$D$30:$D$69) -> 11 | E91: 梦境招募券 | F91: 5 | G91: =H91*2*_xlfn.XLOOKUP(C91,$C$30:$C$85,$G$30:$G$85) -> 5000 | H91: 5000 | I91: =F91*_xlfn.XLOOKUP(D91,价值表!F:F,价值表!I:I) -> #N/A | J91: 6000 | L91: {=I91/SUMPRODUCT(J91:K91,J$89:K$89)} -> #N/A | M91: ="[{"&D91&","&F91&"}]" -> [{11,5}] | N91: =IF(J91>0,"[{2,"&J91&"}]","[{1,"&K91&"}]") -> [{2,6000}]
C92: 1001 | D92: 11 | E92: 梦境招募券 | F92: 5 | G92: =H92*2*_xlfn.XLOOKUP(C92,$C$30:$C$85,$G$30:$G$85) -> 5000 | H92: 5000 | I92: =F92*_xlfn.XLOOKUP(D92,价值表!F:F,价值表!I:I) -> #N/A | K92: 120 | L92: {=I92/SUMPRODUCT(J92:K92,J$89:K$89)} -> #N/A | M92: ="[{"&D92&","&F92&"}]" -> [{11,5}] | N92: =IF(J92>0,"[{2,"&J92&"}]","[{1,"&K92&"}]") -> [{1,120}]
C93: 1002 | D93: 11 | E93: 梦境招募券 | F93: 5 | G93: =H93*2*_xlfn.XLOOKUP(C93,$C$30:$C$85,$G$30:$G$85) -> 3500 | H93: 3500 | I93: =F93*_xlfn.XLOOKUP(D93,价值表!F:F,价值表!I:I) -> #N/A | J93: 6000 | L93: {=I93/SUMPRODUCT(J93:K93,J$89:K$89)} -> #N/A | M93: ="[{"&D93&","&F93&"}]" -> [{11,5}] | N93: =IF(J93>0,"[{2,"&J93&"}]","[{1,"&K93&"}]") -> [{2,6000}]
C94: 1002 | D94: 11 | E94: 梦境招募券 | F94: 5 | G94: =H94*2*_xlfn.XLOOKUP(C94,$C$30:$C$85,$G$30:$G$85) -> 3500 | H94: 3500 | I94: =F94*_xlfn.XLOOKUP(D94,价值表!F:F,价值表!I:I) -> #N/A | K94: 120 | L94: {=I94/SUMPRODUCT(J94:K94,J$89:K$89)} -> #N/A | M94: ="[{"&D94&","&F94&"}]" -> [{11,5}] | N94: =IF(J94>0,"[{2,"&J94&"}]","[{1,"&K94&"}]") -> [{1,120}]
C95: 1002 | D95: 11 | E95: 梦境招募券 | F95: 10 | G95: =H95*2*_xlfn.XLOOKUP(C95,$C$30:$C$85,$G$30:$G$85) -> 1500 | H95: 1500 | I95: =F95*_xlfn.XLOOKUP(D95,价值表!F:F,价值表!I:I) -> #N/A | J95: 12000 | L95: {=I95/SUMPRODUCT(J95:K95,J$89:K$89)} -> #N/A | M95: ="[{"&D95&","&F95&"}]" -> [{11,10}] | N95: =IF(J95>0,"[{2,"&J95&"}]","[{1,"&K95&"}]") -> [{2,12000}]
C96: 1002 | D96: 11 | E96: 梦境招募券 | F96: 10 | G96: =H96*2*_xlfn.XLOOKUP(C96,$C$30:$C$85,$G$30:$G$85) -> 1500 | H96: 1500 | I96: =F96*_xlfn.XLOOKUP(D96,价值表!F:F,价值表!I:I) -> #N/A | K96: 240 | L96: {=I96/SUMPRODUCT(J96:K96,J$89:K$89)} -> #N/A | M96: ="[{"&D96&","&F96&"}]" -> [{11,10}] | N96: =IF(J96>0,"[{2,"&J96&"}]","[{1,"&K96&"}]") -> [{1,240}]
C97: 1003 | D97: 11 | E97: 梦境招募券 | F97: 5 | G97: =H97*2*_xlfn.XLOOKUP(C97,$C$30:$C$85,$G$30:$G$85) -> 600 | H97: 600 | I97: =F97*_xlfn.XLOOKUP(D97,价值表!F:F,价值表!I:I) -> #N/A | J97: 6000 | L97: {=I97/SUMPRODUCT(J97:K97,J$89:K$89)} -> #N/A | M97: ="[{"&D97&","&F97&"}]" -> [{11,5}] | N97: =IF(J97>0,"[{2,"&J97&"}]","[{1,"&K97&"}]") -> [{2,6000}]
C98: 1003 | D98: 11 | E98: 梦境招募券 | F98: 5 | G98: =H98*2*_xlfn.XLOOKUP(C98,$C$30:$C$85,$G$30:$G$85) -> 600 | H98: 600 | I98: =F98*_xlfn.XLOOKUP(D98,价值表!F:F,价值表!I:I) -> #N/A | K98: 120 | L98: {=I98/SUMPRODUCT(J98:K98,J$89:K$89)} -> #N/A | M98: ="[{"&D98&","&F98&"}]" -> [{11,5}] | N98: =IF(J98>0,"[{2,"&J98&"}]","[{1,"&K98&"}]") -> [{1,120}]
C99: 1003 | D99: 11 | E99: 梦境招募券 | F99: 10 | G99: =H99*2*_xlfn.XLOOKUP(C99,$C$30:$C$85,$G$30:$G$85) -> 400 | H99: 400 | I99: =F99*_xlfn.XLOOKUP(D99,价值表!F:F,价值表!I:I) -> #N/A | J99: 12000 | L99: {=I99/SUMPRODUCT(J99:K99,J$89:K$89)} -> #N/A | M99: ="[{"&D99&","&F99&"}]" -> [{11,10}] | N99: =IF(J99>0,"[{2,"&J99&"}]","[{1,"&K99&"}]") -> [{2,12000}]
C100: 1003 | D100: 11 | E100: 梦境招募券 | F100: 10 | G100: =H100*2*_xlfn.XLOOKUP(C100,$C$30:$C$85,$G$30:$G$85) -> 400 | H100: 400 | I100: =F100*_xlfn.XLOOKUP(D100,价值表!F:F,价值表!I:I) -> #N/A | K100: 240 | L100: {=I100/SUMPRODUCT(J100:K100,J$89:K$89)} -> #N/A | M100: ="[{"&D100&","&F100&"}]" -> [{11,10}] | N100: =IF(J100>0,"[{2,"&J100&"}]","[{1,"&K100&"}]") -> [{1,240}]
C101: 1003 | D101: 11 | E101: 梦境招募券 | F101: 20 | G101: =H101*2*_xlfn.XLOOKUP(C101,$C$30:$C$85,$G$30:$G$85) -> 200 | H101: 200 | I101: =F101*_xlfn.XLOOKUP(D101,价值表!F:F,价值表!I:I) -> #N/A | J101: 24000 | L101: {=I101/SUMPRODUCT(J101:K101,J$89:K$89)} -> #N/A | M101: ="[{"&D101&","&F101&"}]" -> [{11,20}] | N101: =IF(J101>0,"[{2,"&J101&"}]","[{1,"&K101&"}]") -> [{2,24000}]
C102: 1003 | D102: 11 | E102: 梦境招募券 | F102: 20 | G102: =H102*2*_xlfn.XLOOKUP(C102,$C$30:$C$85,$G$30:$G$85) -> 200 | H102: 200 | I102: =F102*_xlfn.XLOOKUP(D102,价值表!F:F,价值表!I:I) -> #N/A | K102: 480 | L102: {=I102/SUMPRODUCT(J102:K102,J$89:K$89)} -> #N/A | M102: ="[{"&D102&","&F102&"}]" -> [{11,20}] | N102: =IF(J102>0,"[{2,"&J102&"}]","[{1,"&K102&"}]") -> [{1,480}]
C103: 2001 | D103: =_xlfn.XLOOKUP(C103,$C$30:$C$69,$D$30:$D$69) -> 9 | E103: 初愿摇杆 | F103: 1 | G103: =H103*2*_xlfn.XLOOKUP(C103,$C$30:$C$85,$G$30:$G$85) -> 1000 | H103: 1000 | I103: =F103*_xlfn.XLOOKUP(D103,价值表!F:F,价值表!I:I) -> 0 | J103: 2000 | L103: {=I103/SUMPRODUCT(J103:K103,J$89:K$89)} -> 0 | M103: ="[{"&D103&","&F103&"}]" -> [{9,1}] | N103: =IF(J103>0,"[{2,"&J103&"}]","[{1,"&K103&"}]") -> [{2,2000}]
C104: 2001 | D104: =_xlfn.XLOOKUP(C104,$C$30:$C$69,$D$30:$D$69) -> 9 | E104: 初愿摇杆 | F104: 1 | G104: =H104*2*_xlfn.XLOOKUP(C104,$C$30:$C$85,$G$30:$G$85) -> 1000 | H104: 1000 | I104: =F104*_xlfn.XLOOKUP(D104,价值表!F:F,价值表!I:I) -> 0 | K104: 35 | L104: {=I104/SUMPRODUCT(J104:K104,J$89:K$89)} -> 0 | M104: ="[{"&D104&","&F104&"}]" -> [{9,1}] | N104: =IF(J104>0,"[{2,"&J104&"}]","[{1,"&K104&"}]") -> [{1,35}]
C105: 3001 | D105: =_xlfn.XLOOKUP(C105,$C$30:$C$69,$D$30:$D$69) -> 30 | E105: 秘藏摇杆 | F105: 1 | G105: =H105*2*_xlfn.XLOOKUP(C105,$C$30:$C$85,$G$30:$G$85) -> 1000 | H105: 1000 | I105: =F105*_xlfn.XLOOKUP(D105,价值表!F:F,价值表!I:I) -> 0 | J105: 11200 | L105: {=I105/SUMPRODUCT(J105:K105,J$89:K$89)} -> 0 | M105: ="[{"&D105&","&F105&"}]" -> [{30,1}] | N105: =IF(J105>0,"[{2,"&J105&"}]","[{1,"&K105&"}]") -> [{2,11200}]
C106: 3001 | D106: =_xlfn.XLOOKUP(C106,$C$30:$C$69,$D$30:$D$69) -> 30 | E106: 秘藏摇杆 | F106: 1 | G106: =H106*2*_xlfn.XLOOKUP(C106,$C$30:$C$85,$G$30:$G$85) -> 1000 | H106: 1000 | I106: =F106*_xlfn.XLOOKUP(D106,价值表!F:F,价值表!I:I) -> 0 | K106: 224 | L106: {=I106/SUMPRODUCT(J106:K106,J$89:K$89)} -> 0 | M106: ="[{"&D106&","&F106&"}]" -> [{30,1}] | N106: =IF(J106>0,"[{2,"&J106&"}]","[{1,"&K106&"}]") -> [{1,224}]
C107: 4001 | D107: 5305001 | E107: 幻梦晶核 | F107: 1 | G107: =H107*2*_xlfn.XLOOKUP(C107,$C$30:$C$85,$G$30:$G$85) -> 1000 | H107: 1000 | I107: =F107*_xlfn.XLOOKUP(D107,价值表!F:F,价值表!I:I) -> #N/A | J107: 6000 | L107: {=I107/SUMPRODUCT(J107:K107,J$89:K$89)} -> #N/A | M107: ="[{"&D107&","&F107&"}]" -> [{5305001,1}] | N107: =IF(J107>0,"[{2,"&J107&"}]","[{1,"&K107&"}]") -> [{2,6000}]
C108: 4001 | D108: 5305001 | E108: 幻梦晶核 | F108: 1 | G108: =H108*2*_xlfn.XLOOKUP(C108,$C$30:$C$85,$G$30:$G$85) -> 1000 | H108: 1000 | I108: =F108*_xlfn.XLOOKUP(D108,价值表!F:F,价值表!I:I) -> #N/A | K108: 48 | L108: {=I108/SUMPRODUCT(J108:K108,J$89:K$89)} -> #N/A | M108: ="[{"&D108&","&F108&"}]" -> [{5305001,1}] | N108: =IF(J108>0,"[{2,"&J108&"}]","[{1,"&K108&"}]") -> [{1,48}]
C109: 5001 | D109: 50003 | E109: 头盔图纸 | F109: 10 | G109: =H109*2*_xlfn.XLOOKUP(C109,$C$30:$C$85,$G$30:$G$85) -> 6000 | H109: 6000 | I109: =F109*_xlfn.XLOOKUP(50002,价值表!F:F,价值表!I:I) -> #N/A | J109: 1000 | L109: {=I109/SUMPRODUCT(J109:K109,J$89:K$89)} -> #N/A | M109: ="[{"&D109&","&F109&"}]" -> [{50003,10}] | N109: =IF(J109>0,"[{2,"&J109&"}]","[{1,"&K109&"}]") -> [{2,1000}]
C110: 5001 | D110: =D109+1 -> 50004 | E110: 衣服图纸 | F110: 10 | G110: =H110*2*_xlfn.XLOOKUP(C110,$C$30:$C$85,$G$30:$G$85) -> 6000 | H110: 6000 | I110: =F110*_xlfn.XLOOKUP(50002,价值表!F:F,价值表!I:I) -> #N/A | J110: 1000 | L110: {=I110/SUMPRODUCT(J110:K110,J$89:K$89)} -> #N/A | M110: ="[{"&D110&","&F110&"}]" -> [{50004,10}] | N110: =IF(J110>0,"[{2,"&J110&"}]","[{1,"&K110&"}]") -> [{2,1000}]
C111: 5001 | D111: =D110+1 -> 50005 | E111: 护臂图纸 | F111: 10 | G111: =H111*2*_xlfn.XLOOKUP(C111,$C$30:$C$85,$G$30:$G$85) -> 6000 | H111: 6000 | I111: =F111*_xlfn.XLOOKUP(50002,价值表!F:F,价值表!I:I) -> #N/A | J111: 1000 | L111: {=I111/SUMPRODUCT(J111:K111,J$89:K$89)} -> #N/A | M111: ="[{"&D111&","&F111&"}]" -> [{50005,10}] | N111: =IF(J111>0,"[{2,"&J111&"}]","[{1,"&K111&"}]") -> [{2,1000}]
C112: 5001 | D112: =D111+1 -> 50006 | E112: 裤子图纸 | F112: 10 | G112: =H112*2*_xlfn.XLOOKUP(C112,$C$30:$C$85,$G$30:$G$85) -> 6000 | H112: 6000 | I112: =F112*_xlfn.XLOOKUP(50002,价值表!F:F,价值表!I:I) -> #N/A | J112: 1000 | L112: {=I112/SUMPRODUCT(J112:K112,J$89:K$89)} -> #N/A | M112: ="[{"&D112&","&F112&"}]" -> [{50006,10}] | N112: =IF(J112>0,"[{2,"&J112&"}]","[{1,"&K112&"}]") -> [{2,1000}]
C113: 5001 | D113: =D112+1 -> 50007 | E113: 鞋子图纸 | F113: 10 | G113: =H113*2*_xlfn.XLOOKUP(C113,$C$30:$C$85,$G$30:$G$85) -> 6000 | H113: 6000 | I113: =F113*_xlfn.XLOOKUP(50002,价值表!F:F,价值表!I:I) -> #N/A | J113: 1000 | L113: {=I113/SUMPRODUCT(J113:K113,J$89:K$89)} -> #N/A | M113: ="[{"&D113&","&F113&"}]" -> [{50007,10}] | N113: =IF(J113>0,"[{2,"&J113&"}]","[{1,"&K113&"}]") -> [{2,1000}]
C114: 5001 | D114: =D113+1 -> 50008 | E114: 手套图纸 | F114: 10 | G114: =H114*2*_xlfn.XLOOKUP(C114,$C$30:$C$85,$G$30:$G$85) -> 6000 | H114: 6000 | I114: =F114*_xlfn.XLOOKUP(50002,价值表!F:F,价值表!I:I) -> #N/A | J114: 1000 | L114: {=I114/SUMPRODUCT(J114:K114,J$89:K$89)} -> #N/A | M114: ="[{"&D114&","&F114&"}]" -> [{50008,10}] | N114: =IF(J114>0,"[{2,"&J114&"}]","[{1,"&K114&"}]") -> [{2,1000}]
C115: 5001 | D115: =D109 -> 50003 | E115: 头盔图纸 | F115: 10 | G115: =H115*2*_xlfn.XLOOKUP(C115,$C$30:$C$85,$G$30:$G$85) -> 6000 | H115: 6000 | I115: =F115*_xlfn.XLOOKUP(50002,价值表!F:F,价值表!I:I) -> #N/A | K115: 25 | L115: {=I115/SUMPRODUCT(J115:K115,J$89:K$89)} -> #N/A | M115: ="[{"&D115&","&F115&"}]" -> [{50003,10}] | N115: =IF(J115>0,"[{2,"&J115&"}]","[{1,"&K115&"}]") -> [{1,25}]
C116: 5001 | D116: =D110 -> 50004 | E116: 衣服图纸 | F116: 10 | G116: =H116*2*_xlfn.XLOOKUP(C116,$C$30:$C$85,$G$30:$G$85) -> 6000 | H116: 6000 | I116: =F116*_xlfn.XLOOKUP(50002,价值表!F:F,价值表!I:I) -> #N/A | K116: 25 | L116: {=I116/SUMPRODUCT(J116:K116,J$89:K$89)} -> #N/A | M116: ="[{"&D116&","&F116&"}]" -> [{50004,10}] | N116: =IF(J116>0,"[{2,"&J116&"}]","[{1,"&K116&"}]") -> [{1,25}]
C117: 5001 | D117: =D111 -> 50005 | E117: 护臂图纸 | F117: 10 | G117: =H117*2*_xlfn.XLOOKUP(C117,$C$30:$C$85,$G$30:$G$85) -> 6000 | H117: 6000 | I117: =F117*_xlfn.XLOOKUP(50002,价值表!F:F,价值表!I:I) -> #N/A | K117: 25 | L117: {=I117/SUMPRODUCT(J117:K117,J$89:K$89)} -> #N/A | M117: ="[{"&D117&","&F117&"}]" -> [{50005,10}] | N117: =IF(J117>0,"[{2,"&J117&"}]","[{1,"&K117&"}]") -> [{1,25}]
C118: 5001 | D118: =D112 -> 50006 | E118: 裤子图纸 | F118: 10 | G118: =H118*2*_xlfn.XLOOKUP(C118,$C$30:$C$85,$G$30:$G$85) -> 6000 | H118: 6000 | I118: =F118*_xlfn.XLOOKUP(50002,价值表!F:F,价值表!I:I) -> #N/A | K118: 25 | L118: {=I118/SUMPRODUCT(J118:K118,J$89:K$89)} -> #N/A | M118: ="[{"&D118&","&F118&"}]" -> [{50006,10}] | N118: =IF(J118>0,"[{2,"&J118&"}]","[{1,"&K118&"}]") -> [{1,25}]
C119: 5001 | D119: =D113 -> 50007 | E119: 鞋子图纸 | F119: 10 | G119: =H119*2*_xlfn.XLOOKUP(C119,$C$30:$C$85,$G$30:$G$85) -> 6000 | H119: 6000 | I119: =F119*_xlfn.XLOOKUP(50002,价值表!F:F,价值表!I:I) -> #N/A | K119: 25 | L119: {=I119/SUMPRODUCT(J119:K119,J$89:K$89)} -> #N/A | M119: ="[{"&D119&","&F119&"}]" -> [{50007,10}] | N119: =IF(J119>0,"[{2,"&J119&"}]","[{1,"&K119&"}]") -> [{1,25}]
C120: 5001 | D120: =D114 -> 50008 | E120: 手套图纸 | F120: 10 | G120: =H120*2*_xlfn.XLOOKUP(C120,$C$30:$C$85,$G$30:$G$85) -> 6000 | H120: 6000 | I120: =F120*_xlfn.XLOOKUP(50002,价值表!F:F,价值表!I:I) -> #N/A | K120: 25 | L120: {=I120/SUMPRODUCT(J120:K120,J$89:K$89)} -> #N/A | M120: ="[{"&D120&","&F120&"}]" -> [{50008,10}] | N120: =IF(J120>0,"[{2,"&J120&"}]","[{1,"&K120&"}]") -> [{1,25}]
C121: 5002 | D121: 50003 | E121: 头盔图纸 | F121: 10 | G121: =H121*2*_xlfn.XLOOKUP(C121,$C$30:$C$85,$G$30:$G$85) -> 8000 | H121: 8000 | I121: =F121*_xlfn.XLOOKUP(50002,价值表!F:F,价值表!I:I) -> #N/A | J121: 1000 | L121: {=I121/SUMPRODUCT(J121:K121,J$89:K$89)} -> #N/A | M121: ="[{"&D121&","&F121&"}]" -> [{50003,10}] | N121: =IF(J121>0,"[{2,"&J121&"}]","[{1,"&K121&"}]") -> [{2,1000}]
C122: 5002 | D122: 50003 | E122: 头盔图纸 | F122: 20 | G122: =H122*2*_xlfn.XLOOKUP(C122,$C$30:$C$85,$G$30:$G$85) -> 4000 | H122: 4000 | I122: =F122*_xlfn.XLOOKUP(50002,价值表!F:F,价值表!I:I) -> #N/A | J122: 2000 | L122: {=I122/SUMPRODUCT(J122:K122,J$89:K$89)} -> #N/A | M122: ="[{"&D122&","&F122&"}]" -> [{50003,20}] | N122: =IF(J122>0,"[{2,"&J122&"}]","[{1,"&K122&"}]") -> [{2,2000}]
C123: 5002 | D123: =D121+1 -> 50004 | E123: 衣服图纸 | F123: =F121 -> 10 | G123: =H123*2*_xlfn.XLOOKUP(C123,$C$30:$C$85,$G$30:$G$85) -> 8000 | H123: 8000 | I123: =F123*_xlfn.XLOOKUP(50002,价值表!F:F,价值表!I:I) -> #N/A | K123: 25 | L123: {=I123/SUMPRODUCT(J123:K123,J$89:K$89)} -> #N/A | M123: ="[{"&D123&","&F123&"}]" -> [{50004,10}] | N123: =IF(J123>0,"[{2,"&J123&"}]","[{1,"&K123&"}]") -> [{1,25}]
C124: 5002 | D124: =D122+1 -> 50004 | E124: 衣服图纸 | F124: =F122 -> 20 | G124: =H124*2*_xlfn.XLOOKUP(C124,$C$30:$C$85,$G$30:$G$85) -> 4000 | H124: 4000 | I124: =F124*_xlfn.XLOOKUP(50002,价值表!F:F,价值表!I:I) -> #N/A | K124: 50 | L124: {=I124/SUMPRODUCT(J124:K124,J$89:K$89)} -> #N/A | M124: ="[{"&D124&","&F124&"}]" -> [{50004,20}] | N124: =IF(J124>0,"[{2,"&J124&"}]","[{1,"&K124&"}]") -> [{1,50}]
C125: 5002 | D125: =D123+1 -> 50005 | E125: 护臂图纸 | F125: =F123 -> 10 | G125: =H125*2*_xlfn.XLOOKUP(C125,$C$30:$C$85,$G$30:$G$85) -> 8000 | H125: 8000 | I125: =F125*_xlfn.XLOOKUP(50002,价值表!F:F,价值表!I:I) -> #N/A | J125: =J121 -> 1000 | K125: =K121 -> 0 | L125: {=I125/SUMPRODUCT(J125:K125,J$89:K$89)} -> #N/A | M125: ="[{"&D125&","&F125&"}]" -> [{50005,10}] | N125: =IF(J125>0,"[{2,"&J125&"}]","[{1,"&K125&"}]") -> [{2,1000}]
C126: 5002 | D126: =D124+1 -> 50005 | E126: 护臂图纸 | F126: =F124 -> 20 | G126: =H126*2*_xlfn.XLOOKUP(C126,$C$30:$C$85,$G$30:$G$85) -> 4000 | H126: 4000 | I126: =F126*_xlfn.XLOOKUP(50002,价值表!F:F,价值表!I:I) -> #N/A | J126: =J122 -> 2000 | K126: =K122 -> 0 | L126: {=I126/SUMPRODUCT(J126:K126,J$89:K$89)} -> #N/A | M126: ="[{"&D126&","&F126&"}]" -> [{50005,20}] | N126: =IF(J126>0,"[{2,"&J126&"}]","[{1,"&K126&"}]") -> [{2,2000}]
C127: 5002 | D127: =D125+1 -> 50006 | E127: 裤子图纸 | F127: =F125 -> 10 | G127: =H127*2*_xlfn.XLOOKUP(C127,$C$30:$C$85,$G$30:$G$85) -> 8000 | H127: 8000 | I127: =F127*_xlfn.XLOOKUP(50002,价值表!F:F,价值表!I:I) -> #N/A | J127: =J123 -> 0 | K127: =K123 -> 25 | L127: {=I127/SUMPRODUCT(J127:K127,J$89:K$89)} -> #N/A | M127: ="[{"&D127&","&F127&"}]" -> [{50006,10}] | N127: =IF(J127>0,"[{2,"&J127&"}]","[{1,"&K127&"}]") -> [{1,25}]
C128: 5002 | D128: =D126+1 -> 50006 | E128: 裤子图纸 | F128: =F126 -> 20 | G128: =H128*2*_xlfn.XLOOKUP(C128,$C$30:$C$85,$G$30:$G$85) -> 4000 | H128: 4000 | I128: =F128*_xlfn.XLOOKUP(50002,价值表!F:F,价值表!I:I) -> #N/A | J128: =J124 -> 0 | K128: =K124 -> 50 | L128: {=I128/SUMPRODUCT(J128:K128,J$89:K$89)} -> #N/A | M128: ="[{"&D128&","&F128&"}]" -> [{50006,20}] | N128: =IF(J128>0,"[{2,"&J128&"}]","[{1,"&K128&"}]") -> [{1,50}]
C129: 5002 | D129: =D127+1 -> 50007 | E129: 鞋子图纸 | F129: =F127 -> 10 | G129: =H129*2*_xlfn.XLOOKUP(C129,$C$30:$C$85,$G$30:$G$85) -> 8000 | H129: 8000 | I129: =F129*_xlfn.XLOOKUP(50002,价值表!F:F,价值表!I:I) -> #N/A | J129: =J125 -> 1000 | K129: =K125 -> 0 | L129: {=I129/SUMPRODUCT(J129:K129,J$89:K$89)} -> #N/A | M129: ="[{"&D129&","&F129&"}]" -> [{50007,10}] | N129: =IF(J129>0,"[{2,"&J129&"}]","[{1,"&K129&"}]") -> [{2,1000}]
C130: 5002 | D130: =D128+1 -> 50007 | E130: 鞋子图纸 | F130: =F128 -> 20 | G130: =H130*2*_xlfn.XLOOKUP(C130,$C$30:$C$85,$G$30:$G$85) -> 4000 | H130: 4000 | I130: =F130*_xlfn.XLOOKUP(50002,价值表!F:F,价值表!I:I) -> #N/A | J130: =J126 -> 2000 | K130: =K126 -> 0 | L130: {=I130/SUMPRODUCT(J130:K130,J$89:K$89)} -> #N/A | M130: ="[{"&D130&","&F130&"}]" -> [{50007,20}] | N130: =IF(J130>0,"[{2,"&J130&"}]","[{1,"&K130&"}]") -> [{2,2000}]
C131: 5002 | D131: =D129+1 -> 50008 | E131: 手套图纸 | F131: =F129 -> 10 | G131: =H131*2*_xlfn.XLOOKUP(C131,$C$30:$C$85,$G$30:$G$85) -> 8000 | H131: 8000 | I131: =F131*_xlfn.XLOOKUP(50002,价值表!F:F,价值表!I:I) -> #N/A | J131: =J127 -> 0 | K131: =K127 -> 25 | L131: {=I131/SUMPRODUCT(J131:K131,J$89:K$89)} -> #N/A | M131: ="[{"&D131&","&F131&"}]" -> [{50008,10}] | N131: =IF(J131>0,"[{2,"&J131&"}]","[{1,"&K131&"}]") -> [{1,25}]
C132: 5002 | D132: =D130+1 -> 50008 | E132: 手套图纸 | F132: =F130 -> 20 | G132: =H132*2*_xlfn.XLOOKUP(C132,$C$30:$C$85,$G$30:$G$85) -> 4000 | H132: 4000 | I132: =F132*_xlfn.XLOOKUP(50002,价值表!F:F,价值表!I:I) -> #N/A | J132: =J128 -> 0 | K132: =K128 -> 50 | L132: {=I132/SUMPRODUCT(J132:K132,J$89:K$89)} -> #N/A | M132: ="[{"&D132&","&F132&"}]" -> [{50008,20}] | N132: =IF(J132>0,"[{2,"&J132&"}]","[{1,"&K132&"}]") -> [{1,50}]
C133: 5002 | D133: =D121 -> 50003 | E133: 头盔图纸 | F133: =F131 -> 10 | G133: =H133*2*_xlfn.XLOOKUP(C133,$C$30:$C$85,$G$30:$G$85) -> 8000 | H133: 8000 | I133: =F133*_xlfn.XLOOKUP(50002,价值表!F:F,价值表!I:I) -> #N/A | J133: =J129 -> 1000 | K133: =K129 -> 0 | L133: {=I133/SUMPRODUCT(J133:K133,J$89:K$89)} -> #N/A | M133: ="[{"&D133&","&F133&"}]" -> [{50003,10}] | N133: =IF(J133>0,"[{2,"&J133&"}]","[{1,"&K133&"}]") -> [{2,1000}]
C134: 5002 | D134: =D122 -> 50003 | E134: 头盔图纸 | F134: =F132 -> 20 | G134: =H134*2*_xlfn.XLOOKUP(C134,$C$30:$C$85,$G$30:$G$85) -> 4000 | H134: 4000 | I134: =F134*_xlfn.XLOOKUP(50002,价值表!F:F,价值表!I:I) -> #N/A | J134: =J130 -> 2000 | K134: =K130 -> 0 | L134: {=I134/SUMPRODUCT(J134:K134,J$89:K$89)} -> #N/A | M134: ="[{"&D134&","&F134&"}]" -> [{50003,20}] | N134: =IF(J134>0,"[{2,"&J134&"}]","[{1,"&K134&"}]") -> [{2,2000}]
C135: 5002 | D135: =D123 -> 50004 | E135: 衣服图纸 | F135: =F133 -> 10 | G135: =H135*2*_xlfn.XLOOKUP(C135,$C$30:$C$85,$G$30:$G$85) -> 8000 | H135: 8000 | I135: =F135*_xlfn.XLOOKUP(50002,价值表!F:F,价值表!I:I) -> #N/A | J135: =J131 -> 0 | K135: =K131 -> 25 | L135: {=I135/SUMPRODUCT(J135:K135,J$89:K$89)} -> #N/A | M135: ="[{"&D135&","&F135&"}]" -> [{50004,10}] | N135: =IF(J135>0,"[{2,"&J135&"}]","[{1,"&K135&"}]") -> [{1,25}]
C136: 5002 | D136: =D124 -> 50004 | E136: 衣服图纸 | F136: =F134 -> 20 | G136: =H136*2*_xlfn.XLOOKUP(C136,$C$30:$C$85,$G$30:$G$85) -> 4000 | H136: 4000 | I136: =F136*_xlfn.XLOOKUP(50002,价值表!F:F,价值表!I:I) -> #N/A | J136: =J132 -> 0 | K136: =K132 -> 50 | L136: {=I136/SUMPRODUCT(J136:K136,J$89:K$89)} -> #N/A | M136: ="[{"&D136&","&F136&"}]" -> [{50004,20}] | N136: =IF(J136>0,"[{2,"&J136&"}]","[{1,"&K136&"}]") -> [{1,50}]
...

Sheet 首充
C2: 首充挡位 | D2: 首充类型 | E2: 道具 | F2: 数量 | G2: 价值 | H2: 总价值(钻石) | I2: 价格 | J2: 性价比
C3: 6 | D3: 首充 | E3: 总和 | J3: =SUM(H3:H14)/I4 -> 124.4
E4: 传说武器皮肤 | F4: 1 | G4: =_xlfn.XLOOKUP(E4,价值表!C:C,价值表!F:F)*F4 -> 4000 | H4: =SUM(G4:G6) -> 5324 | I4: 60 | J4: =H4/I4 -> 88.733333
E5: 梦境招募器 | F5: 10 | G5: =_xlfn.XLOOKUP(E5,价值表!C:C,价值表!F:F)*F5 -> 300
E6: 史诗符文 | F6: 1 | G6: =_xlfn.XLOOKUP(E6,价值表!C:C,价值表!F:F)*F6 -> 1024
E7: 当天特权体验卡 | F7: 1 | G7: 0
E9: 梦境招募器 | F9: 20 | G9: =_xlfn.XLOOKUP(E9,价值表!C:C,价值表!F:F)*F9 -> 600 | H9: =SUM(G9:G11) -> 1100 | I9: 60 | J9: =H9/I9 -> 18.333333
E10: 能量特饮 | F10: 500 | G10: =_xlfn.XLOOKUP(E10,价值表!C:C,价值表!F:F)*F10 -> 500
E12: 传说梦灵 | F12: 1 | G12: =_xlfn.XLOOKUP(E12,价值表!C:C,价值表!F:F)*F12 -> 240 | H12: =SUM(G12:G14) -> 1040 | I12: 60 | J12: =H12/I12 -> 17.333333
E13: 能量特饮 | F13: 800 | G13: =_xlfn.XLOOKUP(E13,价值表!C:C,价值表!F:F)*F13 -> 800
C16: 列1 | D16: 累充 | E16: 道具 | F16: 数量 | G16: 价值 | H16: 总价值(钻石) | I16: 价格 | J16: 性价比
C17: 30 | D17: 累充 | E17: 总和 | J17: =SUM(H17:H28)/I18 -> 11.386667 | L17: =IF(K17="","","{"&K17&","&F17&"}")
D18: 随机 | E18: 史诗梦灵皮肤 | F18: 1 | G18: =_xlfn.XLOOKUP(E18,价值表!C:C,价值表!F:F)*F18 -> 1500 | H18: =SUM(G18:G20) -> 2010 | I18: 300 | J18: =H18/I18 -> 6.7
E19: 装备图纸 | F19: 120 | G19: =_xlfn.XLOOKUP(E19,价值表!C:C,价值表!F:F)*F19 -> 360
E20: 金币 | F20: 3000 | G20: =_xlfn.XLOOKUP(E20,价值表!C:C,价值表!F:F)*F20 -> 150
D23: 第二天 | E23: 星之初愿 | F23: 5 | G23: =_xlfn.XLOOKUP(E23,价值表!C:C,价值表!F:F)*F23 -> 250 | H23: =SUM(G23:G25) -> 610 | I23: 300 | J23: =H23/I23 -> 2.0333333
E24: 装备图纸 | F24: 120 | G24: =_xlfn.XLOOKUP(E24,价值表!C:C,价值表!F:F)*F24 -> 360
D26: 第三天 | E26: 转运石 | F26: 1200 | G26: =_xlfn.XLOOKUP(E26,价值表!C:C,价值表!F:F)*F26 -> 396 | H26: =SUM(G26:G28) -> 796 | I26: 300 | J26: =H26/I26 -> 2.6533333
E27: 超能特饮 | F27: 200 | G27: =_xlfn.XLOOKUP(E27,价值表!C:C,价值表!F:F)*F27 -> 400
O29: 第二天开启
C30: 首充挡位 | D30: 累充 | E30: 道具 | F30: 数量 | G30: 价值 | H30: 总价值(钻石) | I30: 价格 | J30: 性价比 | N30: 首充挡位 | O30: 累充 | P30: 道具 | Q30: 数量 | R30: 价值 | S30: 总价值(钻石) | T30: 价格 | U30: 性价比 | V30: 列1
C31: 98 | D31: 累充 | E31: 总和 | J31: =SUM(H31:H42)/I32 -> 7.8163265 | N31: 128 | O31: 直充 | P31: 总和 | U31: =SUM(S31:S42)/T32 -> 5.9191919
D32: 玉如意 | E32: 传说武器皮肤 | F32: 1 | G32: =_xlfn.XLOOKUP(E32,价值表!$C:$C,价值表!$F:$F)*F32 -> 4000 | H32: =SUM(G32:G34) -> 4790 | I32: 980 | J32: =H32/I32 -> 4.8877551 | O32: 随机 | P32: 传说梦灵皮肤 | Q32: 1 | R32: =_xlfn.XLOOKUP(P32,价值表!$C:$C,价值表!$F:$F)*Q32 -> 4000 | S32: =SUM(R32:R35) -> 6280 | T32: 1980 | U32: =S32/T32 -> 3.1717172 | V32: 100008
E33: 装备图纸 | F33: 180 | G33: =_xlfn.XLOOKUP(E33,价值表!C:C,价值表!F:F)*F33 -> 540 | P33: 钻石 | Q33: 980 | R33: =_xlfn.XLOOKUP(P33,价值表!$C:$C,价值表!$F:$F)*Q33 -> 980 | V33: =_xlfn.XLOOKUP(P33,价值表!$C:$C,价值表!$D:$D) -> 1
E34: 金币 | F34: 5000 | G34: =_xlfn.XLOOKUP(E34,价值表!C:C,价值表!F:F)*F34 -> 250 | P34: 装备图纸 | Q34: 300 | R34: =_xlfn.XLOOKUP(P34,价值表!$C:$C,价值表!$F:$F)*Q34 -> 900 | V34: =_xlfn.XLOOKUP(P34,价值表!$C:$C,价值表!$D:$D) -> 50002
P35: 金币 | Q35: 8000 | R35: =_xlfn.XLOOKUP(P35,价值表!$C:$C,价值表!$F:$F)*Q35 -> 400 | V35: =_xlfn.XLOOKUP(P35,价值表!$C:$C,价值表!$D:$D) -> 2
D37: 第二天 | E37: 星辉秘契 | F37: 2 | G37: =_xlfn.XLOOKUP(E37,价值表!C:C,价值表!F:F)*F37 -> 560 | H37: =SUM(G37:G39) -> 1280 | I37: 980 | J37: =H37/I37 -> 1.3061224 | O37: 第二天 | P37: 梦境招募器 | Q37: 20 | R37: =_xlfn.XLOOKUP(P37,价值表!$C:$C,价值表!$F:$F)*Q37 -> 600 | S37: =SUM(R37:R39) -> 1200 | T37: 1980 | U37: =S37/T37 -> 0.60606061 | V37: =_xlfn.XLOOKUP(P37,价值表!$C:$C,价值表!$D:$D) -> 11
E38: 装备图纸 | F38: 240 | G38: =_xlfn.XLOOKUP(E38,价值表!C:C,价值表!F:F)*F38 -> 720 | P38: 超能特饮 | Q38: 300 | R38: =_xlfn.XLOOKUP(P38,价值表!$C:$C,价值表!$F:$F)*Q38 -> 600 | V38: =_xlfn.XLOOKUP(P38,价值表!$C:$C,价值表!$D:$D) -> 5104001
D40: 第三天 | E40: 转运石 | F40: 3000 | G40: =_xlfn.XLOOKUP(E40,价值表!C:C,价值表!F:F)*F40 -> 990 | H40: =SUM(G40:G42) -> 1590 | I40: 980 | J40: =H40/I40 -> 1.622449 | O40: 第三天 | P40: 星辉秘契 | Q40: 10 | R40: =_xlfn.XLOOKUP(P40,价值表!$C:$C,价值表!$F:$F)*Q40 -> 2800 | S40: =SUM(R40:R42) -> 4240 | T40: 1980 | U40: =S40/T40 -> 2.1414141 | V40: =_xlfn.XLOOKUP(P40,价值表!$C:$C,价值表!$D:$D) -> 30
E41: 超能特饮 | F41: 300 | G41: =_xlfn.XLOOKUP(E41,价值表!C:C,价值表!F:F)*F41 -> 600 | P41: 幻梦晶核 | Q41: 24 | R41: =_xlfn.XLOOKUP(P41,价值表!$C:$C,价值表!$F:$F)*Q41 -> 1440 | V41: =_xlfn.XLOOKUP(P41,价值表!$C:$C,价值表!$D:$D) -> 5305001

Sheet 日月周礼包
B2: 总产出
B3: ID | C3: 每日 | D3: 每周 | E3: 每月
B4: 体力 | C4: {=SUMPRODUCT(--($B$20:$B$62<999+MATCH(C$3,$C$3:$E$3,0)*1000),--($O$20:$O$62=$B4),$K$20:$K$62,$G$20:$G$62)/_xlfn.XLOOKUP($B4,价值表!$C:$C,价值表!$F:$F)} -> 70 | D4: {=SUMPRODUCT(--($B$20:$B$62<999+MATCH(D$3,$C$3:$E$3,0)*1000),--($O$20:$O$62=$B4),$K$20:$K$62,$G$20:$G$62)/_xlfn.XLOOKUP($B4,价值表!$C:$C,价值表!$F:$F)} -> 370 | E4: {=SUMPRODUCT(--($B$20:$B$62<999+MATCH(E$3,$C$3:$E$3,0)*1000),--($O$20:$O$62=$B4),$K$20:$K$62,$G$20:$G$62)/_xlfn.XLOOKUP($B4,价值表!$C:$C,价值表!$F:$F)} -> 370
B5: 金币 | C5: {=SUMPRODUCT(--($B$20:$B$62<999+MATCH(C$3,$C$3:$E$3,0)*1000),--($O$20:$O$62=$B5),$K$20:$K$62,$G$20:$G$62)/_xlfn.XLOOKUP($B5,价值表!$C:$C,价值表!$F:$F)} -> 10000 | D5: {=SUMPRODUCT(--($B$20:$B$62<999+MATCH(D$3,$C$3:$E$3,0)*1000),--($O$20:$O$62=$B5),$K$20:$K$62,$G$20:$G$62)/_xlfn.XLOOKUP($B5,价值表!$C:$C,价值表!$F:$F)} -> 20000 | E5: {=SUMPRODUCT(--($B$20:$B$62<999+MATCH(E$3,$C$3:$E$3,0)*1000),--($O$20:$O$62=$B5),$K$20:$K$62,$G$20:$G$62)/_xlfn.XLOOKUP($B5,价值表!$C:$C,价值表!$F:$F)} -> 20000
B6: 梦境招募器 | C6: {=SUMPRODUCT(--($B$20:$B$62<999+MATCH(C$3,$C$3:$E$3,0)*1000),--($O$20:$O$62=$B6),$K$20:$K$62,$G$20:$G$62)/_xlfn.XLOOKUP($B6,价值表!$C:$C,价值表!$F:$F)} -> 40 | D6: {=SUMPRODUCT(--($B$20:$B$62<999+MATCH(D$3,$C$3:$E$3,0)*1000),--($O$20:$O$62=$B6),$K$20:$K$62,$G$20:$G$62)/_xlfn.XLOOKUP($B6,价值表!$C:$C,价值表!$F:$F)} -> 490 | E6: {=SUMPRODUCT(--($B$20:$B$62<999+MATCH(E$3,$C$3:$E$3,0)*1000),--($O$20:$O$62=$B6),$K$20:$K$62,$G$20:$G$62)/_xlfn.XLOOKUP($B6,价值表!$C:$C,价值表!$F:$F)} -> 990 | H6: 日周月礼包这边核心道具的标准价值
B7: 能量特饮 | C7: {=SUMPRODUCT(--($B$20:$B$62<999+MATCH(C$3,$C$3:$E$3,0)*1000),--($O$20:$O$62=$B7),$K$20:$K$62,$G$20:$G$62)/_xlfn.XLOOKUP($B7,价值表!$C:$C,价值表!$F:$F)} -> 1200 | D7: {=SUMPRODUCT(--($B$20:$B$62<999+MATCH(D$3,$C$3:$E$3,0)*1000),--($O$20:$O$62=$B7),$K$20:$K$62,$G$20:$G$62)/_xlfn.XLOOKUP($B7,价值表!$C:$C,价值表!$F:$F)} -> 1200 | E7: {=SUMPRODUCT(--($B$20:$B$62<999+MATCH(E$3,$C$3:$E$3,0)*1000),--($O$20:$O$62=$B7),$K$20:$K$62,$G$20:$G$62)/_xlfn.XLOOKUP($B7,价值表!$C:$C,价值表!$F:$F)} -> 1200
B8: 超能特饮 | C8: {=SUMPRODUCT(--($B$20:$B$62<999+MATCH(C$3,$C$3:$E$3,0)*1000),--($O$20:$O$62=$B8),$K$20:$K$62,$G$20:$G$62)/_xlfn.XLOOKUP($B8,价值表!$C:$C,价值表!$F:$F)} -> 600 | D8: {=SUMPRODUCT(--($B$20:$B$62<999+MATCH(D$3,$C$3:$E$3,0)*1000),--($O$20:$O$62=$B8),$K$20:$K$62,$G$20:$G$62)/_xlfn.XLOOKUP($B8,价值表!$C:$C,价值表!$F:$F)} -> 4600 | E8: {=SUMPRODUCT(--($B$20:$B$62<999+MATCH(E$3,$C$3:$E$3,0)*1000),--($O$20:$O$62=$B8),$K$20:$K$62,$G$20:$G$62)/_xlfn.XLOOKUP($B8,价值表!$C:$C,价值表!$F:$F)} -> 14600 | H8: 周商店里面 | I8: 价值（钻 | J8: 折扣
B9: 装备图纸 | C9: {=SUMPRODUCT(--($B$20:$B$62<999+MATCH(C$3,$C$3:$E$3,0)*1000),--($O$20:$O$62=$B9),$K$20:$K$62,$G$20:$G$62)/_xlfn.XLOOKUP($B9,价值表!$C:$C,价值表!$F:$F)} -> 300 | D9: {=SUMPRODUCT(--($B$20:$B$62<999+MATCH(D$3,$C$3:$E$3,0)*1000),--($O$20:$O$62=$B9),$K$20:$K$62,$G$20:$G$62)/_xlfn.XLOOKUP($B9,价值表!$C:$C,价值表!$F:$F)} -> 900 | E9: {=SUMPRODUCT(--($B$20:$B$62<999+MATCH(E$3,$C$3:$E$3,0)*1000),--($O$20:$O$62=$B9),$K$20:$K$62,$G$20:$G$62)/_xlfn.XLOOKUP($B9,价值表!$C:$C,价值表!$F:$F)} -> 2100 | H9: 招募卷 | I9: =1050/50 -> 21 | J9: 7折礼包
B10: 星辉秘契 | C10: {=SUMPRODUCT(--($B$20:$B$62<999+MATCH(C$3,$C$3:$E$3,0)*1000),--($O$20:$O$62=$B10),$K$20:$K$62,$G$20:$G$62)/_xlfn.XLOOKUP($B10,价值表!$C:$C,价值表!$F:$F)} -> 21 | D10: {=SUMPRODUCT(--($B$20:$B$62<999+MATCH(D$3,$C$3:$E$3,0)*1000),--($O$20:$O$62=$B10),$K$20:$K$62,$G$20:$G$62)/_xlfn.XLOOKUP($B10,价值表!$C:$C,价值表!$F:$F)} -> 171 | E10: {=SUMPRODUCT(--($B$20:$B$62<999+MATCH(E$3,$C$3:$E$3,0)*1000),--($O$20:$O$62=$B10),$K$20:$K$62,$G$20:$G$62)/_xlfn.XLOOKUP($B10,价值表!$C:$C,价值表!$F:$F)} -> 321 | H10: 招募卷 | I10: =1800/100 -> 18 | J10: 6折礼包
B11: 符引结晶 | C11: {=SUMPRODUCT(--($B$20:$B$62<999+MATCH(C$3,$C$3:$E$3,0)*1000),--($O$20:$O$62=$B11),$K$20:$K$62,$G$20:$G$62)/_xlfn.XLOOKUP($B11,价值表!$C:$C,价值表!$F:$F)} -> 100 | D11: {=SUMPRODUCT(--($B$20:$B$62<999+MATCH(D$3,$C$3:$E$3,0)*1000),--($O$20:$O$62=$B11),$K$20:$K$62,$G$20:$G$62)/_xlfn.XLOOKUP($B11,价值表!$C:$C,价值表!$F:$F)} -> 400 | E11: {=SUMPRODUCT(--($B$20:$B$62<999+MATCH(E$3,$C$3:$E$3,0)*1000),--($O$20:$O$62=$B11),$K$20:$K$62,$G$20:$G$62)/_xlfn.XLOOKUP($B11,价值表!$C:$C,价值表!$F:$F)} -> 400 | H11: 体力 | I11: =96/60 -> 1.6 | J11: 8折
B12: 织梦微尘 | C12: {=SUMPRODUCT(--($B$20:$B$62<999+MATCH(C$3,$C$3:$E$3,0)*1000),--($O$20:$O$62=$B12),$K$20:$K$62,$G$20:$G$62)/_xlfn.XLOOKUP($B12,价值表!$C:$C,价值表!$F:$F)} -> 300 | D12: {=SUMPRODUCT(--($B$20:$B$62<999+MATCH(D$3,$C$3:$E$3,0)*1000),--($O$20:$O$62=$B12),$K$20:$K$62,$G$20:$G$62)/_xlfn.XLOOKUP($B12,价值表!$C:$C,价值表!$F:$F)} -> 900 | E12: {=SUMPRODUCT(--($B$20:$B$62<999+MATCH(E$3,$C$3:$E$3,0)*1000),--($O$20:$O$62=$B12),$K$20:$K$62,$G$20:$G$62)/_xlfn.XLOOKUP($B12,价值表!$C:$C,价值表!$F:$F)} -> 900 | H12: 星辉秘契 | I12: =840/5 -> 168 | J12: 6折
B13: 锻造晶石 | C13: {=SUMPRODUCT(--($B$20:$B$62<999+MATCH(C$3,$C$3:$E$3,0)*1000),--($O$20:$O$62=$B13),$K$20:$K$62,$G$20:$G$62)/_xlfn.XLOOKUP($B13,价值表!$C:$C,价值表!$F:$F)} -> 2500 | D13: {=SUMPRODUCT(--($B$20:$B$62<999+MATCH(D$3,$C$3:$E$3,0)*1000),--($O$20:$O$62=$B13),$K$20:$K$62,$G$20:$G$62)/_xlfn.XLOOKUP($B13,价值表!$C:$C,价值表!$F:$F)} -> 2500 | E13: {=SUMPRODUCT(--($B$20:$B$62<999+MATCH(E$3,$C$3:$E$3,0)*1000),--($O$20:$O$62=$B13),$K$20:$K$62,$G$20:$G$62)/_xlfn.XLOOKUP($B13,价值表!$C:$C,价值表!$F:$F)} -> 2500 | H13: 幻梦晶核 | I13: =216/6 -> 36 | J13: 6折
B14: 幻梦晶核 | C14: {=SUMPRODUCT(--($B$20:$B$62<999+MATCH(C$3,$C$3:$E$3,0)*1000),--($O$20:$O$62=$B14),$K$20:$K$62,$G$20:$G$62)/_xlfn.XLOOKUP($B14,价值表!$C:$C,价值表!$F:$F)} -> 12 | D14: {=SUMPRODUCT(--($B$20:$B$62<999+MATCH(D$3,$C$3:$E$3,0)*1000),--($O$20:$O$62=$B14),$K$20:$K$62,$G$20:$G$62)/_xlfn.XLOOKUP($B14,价值表!$C:$C,价值表!$F:$F)} -> 36 | E14: {=SUMPRODUCT(--($B$20:$B$62<999+MATCH(E$3,$C$3:$E$3,0)*1000),--($O$20:$O$62=$B14),$K$20:$K$62,$G$20:$G$62)/_xlfn.XLOOKUP($B14,价值表!$C:$C,价值表!$F:$F)} -> 256
B15: 转运石 | C15: {=SUMPRODUCT(--($B$20:$B$62<999+MATCH(C$3,$C$3:$E$3,0)*1000),--($O$20:$O$62=$B15),$K$20:$K$62,$G$20:$G$62)/_xlfn.XLOOKUP($B15,价值表!$C:$C,价值表!$F:$F)} -> 3000 | D15: {=SUMPRODUCT(--($B$20:$B$62<999+MATCH(D$3,$C$3:$E$3,0)*1000),--($O$20:$O$62=$B15),$K$20:$K$62,$G$20:$G$62)/_xlfn.XLOOKUP($B15,价值表!$C:$C,价值表!$F:$F)} -> 12000 | E15: {=SUMPRODUCT(--($B$20:$B$62<999+MATCH(E$3,$C$3:$E$3,0)*1000),--($O$20:$O$62=$B15),$K$20:$K$62,$G$20:$G$62)/_xlfn.XLOOKUP($B15,价值表!$C:$C,价值表!$F:$F)} -> 72000
B16: 加速沙漏 | C16: {=SUMPRODUCT(--($B$20:$B$62<999+MATCH(C$3,$C$3:$E$3,0)*1000),--($O$20:$O$62=$B16),$K$20:$K$62,$G$20:$G$62)/_xlfn.XLOOKUP($B16,价值表!$C:$C,价值表!$F:$F)} -> 0 | D16: {=SUMPRODUCT(--($B$20:$B$62<999+MATCH(D$3,$C$3:$E$3,0)*1000),--($O$20:$O$62=$B16),$K$20:$K$62,$G$20:$G$62)/_xlfn.XLOOKUP($B16,价值表!$C:$C,价值表!$F:$F)} -> 240 | E16: {=SUMPRODUCT(--($B$20:$B$62<999+MATCH(E$3,$C$3:$E$3,0)*1000),--($O$20:$O$62=$B16),$K$20:$K$62,$G$20:$G$62)/_xlfn.XLOOKUP($B16,价值表!$C:$C,价值表!$F:$F)} -> 240
B17: 传说符文 | C17: {=SUMPRODUCT(--($B$20:$B$62<999+MATCH(C$3,$C$3:$E$3,0)*1000),--($O$20:$O$62=$B17),$K$20:$K$62,$G$20:$G$62)/_xlfn.XLOOKUP($B17,价值表!$C:$C,价值表!$F:$F)} -> 0 | D17: {=SUMPRODUCT(--($B$20:$B$62<999+MATCH(D$3,$C$3:$E$3,0)*1000),--($O$20:$O$62=$B17),$K$20:$K$62,$G$20:$G$62)/_xlfn.XLOOKUP($B17,价值表!$C:$C,价值表!$F:$F)} -> 0 | E17: {=SUMPRODUCT(--($B$20:$B$62<999+MATCH(E$3,$C$3:$E$3,0)*1000),--($O$20:$O$62=$B17),$K$20:$K$62,$G$20:$G$62)/_xlfn.XLOOKUP($B17,价值表!$C:$C,价值表!$F:$F)} -> 1
B18: 神话符文 | C18: {=SUMPRODUCT(--($B$20:$B$62<999+MATCH(C$3,$C$3:$E$3,0)*1000),--($O$20:$O$62=$B18),$K$20:$K$62,$G$20:$G$62)/_xlfn.XLOOKUP($B18,价值表!$C:$C,价值表!$F:$F)} -> 0 | D18: {=SUMPRODUCT(--($B$20:$B$62<999+MATCH(D$3,$C$3:$E$3,0)*1000),--($O$20:$O$62=$B18),$K$20:$K$62,$G$20:$G$62)/_xlfn.XLOOKUP($B18,价值表!$C:$C,价值表!$F:$F)} -> 0 | E18: {=SUMPRODUCT(--($B$20:$B$62<999+MATCH(E$3,$C$3:$E$3,0)*1000),--($O$20:$O$62=$B18),$K$20:$K$62,$G$20:$G$62)/_xlfn.XLOOKUP($B18,价值表!$C:$C,价值表!$F:$F)} -> 1
B20: ID | C20: 开服时间节点 | D20: 商品名称 | E20: 奖励 | F20: 价格 | G20: 购买次数 | H20: 折扣 | I20: 物品ID | J20: 价值 | K20: 总价值 | L20: 性价比 | M20: 折扣配置 | N20: 标准折扣 | O20: 道具
B21: 1001 | C21: 2 | D21: 免费体力 | E21: [{13,10}] | G21: 1 | I21: =IF(B21="","",SUBSTITUTE(LEFT(E21,FIND(",",E21)-1),"","")) -> [{13 | J21: =_xlfn.XLOOKUP(--SUBSTITUTE(LEFT(E21,FIND(",",E21)-1),"[{",""),价值表!D:D,价值表!F:F) -> 2 | K21: =J21*SUBSTITUTE(SUBSTITUTE(E21,""&I21&",",""),"}]","") -> 20 | L21: =SUBSTITUTE(SUBSTITUTE(F21,"1,",""),"}]","") | N21: =_xlfn.XLOOKUP(--SUBSTITUTE(I21,"[{",""),价值表!D:D,价值表!J:J) -> 7 | O21: =IFERROR(_xlfn.XLOOKUP(IF(E21="","",--SUBSTITUTE(LEFT(E21,FIND(",",E21)-1),"[{","")),价值表!D:D,价值表!C:C),"") -> 体力
B22: 1002 | C22: 2 | D22: 体力 | E22: [{13,60}] | F22: [{1,96}] | G22: 1 | H22: 8折 | I22: =IF(B22="","",SUBSTITUTE(LEFT(E22,FIND(",",E22)-1),"","")) -> [{13 | J22: =_xlfn.XLOOKUP(--SUBSTITUTE(LEFT(E22,FIND(",",E22)-1),"[{",""),价值表!D:D,价值表!F:F) -> 2 | K22: =J22*SUBSTITUTE(SUBSTITUTE(E22,""&I22&",",""),"}]","") -> 120 | L22: =K22/SUBSTITUTE(SUBSTITUTE(SUBSTITUTE(F22,"1,",""),"}]",""),"[{","") -> 1.25 | M22: =ROUND(1/L22*10,0)&"折" -> 8折 | N22: =_xlfn.XLOOKUP(--SUBSTITUTE(I22,"[{",""),价值表!D:D,价值表!J:J) -> 7 | O22: =IFERROR(_xlfn.XLOOKUP(IF(E22="","",--SUBSTITUTE(LEFT(E22,FIND(",",E22)-1),"[{","")),价值表!D:D,价值表!C:C),"") -> 体力
B23: 1003 | C23: 2 | D23: 金币 | E23: [{2,5000}] | F23: [{1,125}] | G23: 2 | H23: 5折 | I23: =IF(B23="","",SUBSTITUTE(LEFT(E23,FIND(",",E23)-1),"","")) -> [{2 | J23: =_xlfn.XLOOKUP(--SUBSTITUTE(LEFT(E23,FIND(",",E23)-1),"[{",""),价值表!D:D,价值表!F:F) -> 0.05 | K23: =J23*SUBSTITUTE(SUBSTITUTE(E23,""&I23&",",""),"}]","") -> 250 | L23: =K23/SUBSTITUTE(SUBSTITUTE(SUBSTITUTE(F23,"1,",""),"}]",""),"[{","") -> 2 | M23: =ROUND(1/L23*10,0)&"折" -> 5折 | N23: =_xlfn.XLOOKUP(--SUBSTITUTE(I23,"[{",""),价值表!D:D,价值表!J:J) -> 5 | O23: =IFERROR(_xlfn.XLOOKUP(IF(E23="","",--SUBSTITUTE(LEFT(E23,FIND(",",E23)-1),"[{","")),价值表!D:D,价值表!C:C),"") -> 金币
B24: 1004 | C24: 2 | D24: 招募器 | E24: [{11,20}] | F24: [{1,480}] | G24: 2 | H24: 8折 | I24: =IF(B24="","",SUBSTITUTE(LEFT(E24,FIND(",",E24)-1),"","")) -> [{11 | J24: =_xlfn.XLOOKUP(--SUBSTITUTE(LEFT(E24,FIND(",",E24)-1),"[{",""),价值表!D:D,价值表!F:F) -> 30 | K24: =J24*SUBSTITUTE(SUBSTITUTE(E24,""&I24&",",""),"}]","") -> 600 | L24: =K24/SUBSTITUTE(SUBSTITUTE(SUBSTITUTE(F24,"1,",""),"}]",""),"[{","") -> 1.25 | M24: =ROUND(1/L24*10,0)&"折" -> 8折 | N24: =_xlfn.XLOOKUP(--SUBSTITUTE(I24,"[{",""),价值表!D:D,价值表!J:J) -> 6 | O24: =IFERROR(_xlfn.XLOOKUP(IF(E24="","",--SUBSTITUTE(LEFT(E24,FIND(",",E24)-1),"[{","")),价值表!D:D,价值表!C:C),"") -> 梦境招募器
B25: 1005 | C25: 2 | D25: 能量特饮 | E25: [{5103002,400}] | F25: [{1,200}] | G25: 3 | H25: 5折 | I25: =IF(B25="","",SUBSTITUTE(LEFT(E25,FIND(",",E25)-1),"","")) -> [{5103001 | J25: =_xlfn.XLOOKUP(--SUBSTITUTE(LEFT(E25,FIND(",",E25)-1),"[{",""),价值表!D:D,价值表!F:F) -> 1 | K25: =J25*SUBSTITUTE(SUBSTITUTE(E25,""&I25&",",""),"}]","") -> 400 | L25: =K25/SUBSTITUTE(SUBSTITUTE(SUBSTITUTE(F25,"1,",""),"}]",""),"[{","") -> 2 | M25: =ROUND(1/L25*10,0)&"折" -> 5折 | N25: =_xlfn.XLOOKUP(--SUBSTITUTE(I25,"[{",""),价值表!D:D,价值表!J:J) -> 5 | O25: =IFERROR(_xlfn.XLOOKUP(IF(E25="","",--SUBSTITUTE(LEFT(E25,FIND(",",E25)-1),"[{","")),价值表!D:D,价值表!C:C),"") -> 能量特饮
B26: 1006 | C26: 2 | D26: 能量特饮 | E26: [{5104001,200}] | F26: [{1,200}] | G26: 3 | H26: 5折 | I26: =IF(B26="","",SUBSTITUTE(LEFT(E26,FIND(",",E26)-1),"","")) -> [{5104001 | J26: =_xlfn.XLOOKUP(--SUBSTITUTE(LEFT(E26,FIND(",",E26)-1),"[{",""),价值表!D:D,价值表!F:F) -> 2 | K26: =J26*SUBSTITUTE(SUBSTITUTE(E26,""&I26&",",""),"}]","") -> 400 | L26: =K26/SUBSTITUTE(SUBSTITUTE(SUBSTITUTE(F26,"1,",""),"}]",""),"[{","") -> 2 | M26: =ROUND(1/L26*10,0)&"折" -> 5折 | N26: =_xlfn.XLOOKUP(--SUBSTITUTE(I26,"[{",""),价值表!D:D,价值表!J:J) -> 0 | O26: =IFERROR(_xlfn.XLOOKUP(IF(E26="","",--SUBSTITUTE(LEFT(E26,FIND(",",E26)-1),"[{","")),价值表!D:D,价值表!C:C),"") -> 超能特饮
B27: 1007 | C27: 2 | D27: 装备图纸 | E27: [{50002,100}] | F27: [{1,240}] | G27: 3 | H27: 8折 | I27: =IF(B27="","",SUBSTITUTE(LEFT(E27,FIND(",",E27)-1),"","")) -> [{50002 | J27: =_xlfn.XLOOKUP(--SUBSTITUTE(LEFT(E27,FIND(",",E27)-1),"[{",""),价值表!D:D,价值表!F:F) -> 3 | K27: =J27*SUBSTITUTE(SUBSTITUTE(E27,""&I27&",",""),"}]","") -> 300 | L27: =K27/SUBSTITUTE(SUBSTITUTE(SUBSTITUTE(F27,"1,",""),"}]",""),"[{","") -> 1.25 | M27: =ROUND(1/L27*10,0)&"折" -> 8折 | N27: =_xlfn.XLOOKUP(--SUBSTITUTE(I27,"[{",""),价值表!D:D,价值表!J:J) -> 6 | O27: =IFERROR(_xlfn.XLOOKUP(IF(E27="","",--SUBSTITUTE(LEFT(E27,FIND(",",E27)-1),"[{","")),价值表!D:D,价值表!C:C),"") -> 装备图纸
B28: 1008 | C28: 2 | D28: 星辉秘契 | E28: [{30,2}] | F28: [{1,392}] | G28: 3 | H28: 7折 | I28: =IF(B28="","",SUBSTITUTE(LEFT(E28,FIND(",",E28)-1),"","")) -> [{30 | J28: =_xlfn.XLOOKUP(--SUBSTITUTE(LEFT(E28,FIND(",",E28)-1),"[{",""),价值表!D:D,价值表!F:F) -> 280 | K28: =J28*SUBSTITUTE(SUBSTITUTE(E28,""&I28&",",""),"}]","") -> 560 | L28: =K28/SUBSTITUTE(SUBSTITUTE(SUBSTITUTE(F28,"1,",""),"}]",""),"[{","") -> 1.4285714 | M28: =ROUND(1/L28*10,0)&"折" -> 7折 | N28: =_xlfn.XLOOKUP(--SUBSTITUTE(I28,"[{",""),价值表!D:D,价值表!J:J) -> 5 | O28: =IFERROR(_xlfn.XLOOKUP(IF(E28="","",--SUBSTITUTE(LEFT(E28,FIND(",",E28)-1),"[{","")),价值表!D:D,价值表!C:C),"") -> 星辉秘契
B29: 1009 | C29: 2 | D29: 星辉秘契 | E29: [{30,5}] | F29: [{1,840}] | G29: 3 | H29: 6折 | I29: =IF(B29="","",SUBSTITUTE(LEFT(E29,FIND(",",E29)-1),"","")) -> [{30 | J29: =_xlfn.XLOOKUP(--SUBSTITUTE(LEFT(E29,FIND(",",E29)-1),"[{",""),价值表!D:D,价值表!F:F) -> 280 | K29: =J29*SUBSTITUTE(SUBSTITUTE(E29,""&I29&",",""),"}]","") -> 1400 | L29: =K29/SUBSTITUTE(SUBSTITUTE(SUBSTITUTE(F29,"1,",""),"}]",""),"[{","") -> 1.6666667 | M29: =ROUND(1/L29*10,0)&"折" -> 6折 | N29: =_xlfn.XLOOKUP(--SUBSTITUTE(I29,"[{",""),价值表!D:D,价值表!J:J) -> 5 | O29: =IFERROR(_xlfn.XLOOKUP(IF(E29="","",--SUBSTITUTE(LEFT(E29,FIND(",",E29)-1),"[{","")),价值表!D:D,价值表!C:C),"") -> 星辉秘契
B30: 1010 | C30: 2 | D30: 符引结晶 | E30: [{5303001,50}] | F30: [{1,225}] | G30: 2 | H30: 9折 | I30: =IF(B30="","",SUBSTITUTE(LEFT(E30,FIND(",",E30)-1),"","")) -> [{5303001 | J30: =_xlfn.XLOOKUP(--SUBSTITUTE(LEFT(E30,FIND(",",E30)-1),"[{",""),价值表!D:D,价值表!F:F) -> 5 | K30: =J30*SUBSTITUTE(SUBSTITUTE(E30,""&I30&",",""),"}]","") -> 250 | L30: =K30/SUBSTITUTE(SUBSTITUTE(SUBSTITUTE(F30,"1,",""),"}]",""),"[{","") -> 1.1111111 | M30: =ROUND(1/L30*10,0)&"折" -> 9折 | N30: =_xlfn.XLOOKUP(--SUBSTITUTE(I30,"[{",""),价值表!D:D,价值表!J:J) -> 8 | O30: =IFERROR(_xlfn.XLOOKUP(IF(E30="","",--SUBSTITUTE(LEFT(E30,FIND(",",E30)-1),"[{","")),价值表!D:D,价值表!C:C),"") -> 符引结晶
B31: 1011 | C31: 2 | D31: 织梦微尘 | E31: [{5203001,50}] | F31: [{1,210}] | G31: 3 | H31: 7折 | I31: =IF(B31="","",SUBSTITUTE(LEFT(E31,FIND(",",E31)-1),"","")) -> [{5203001 | J31: =_xlfn.XLOOKUP(--SUBSTITUTE(LEFT(E31,FIND(",",E31)-1),"[{",""),价值表!D:D,价值表!F:F) -> 3 | K31: =J31*SUBSTITUTE(SUBSTITUTE(E31,""&I31&",",""),"}]","") -> 300 | L31: =K31/SUBSTITUTE(SUBSTITUTE(SUBSTITUTE(F31,"1,",""),"}]",""),"[{","") -> 1.4285714 | M31: =ROUND(1/L31*10,0)&"折" -> 7折 | N31: =_xlfn.XLOOKUP(--SUBSTITUTE(I31,"[{",""),价值表!D:D,价值表!J:J) -> 6 | O31: =IFERROR(_xlfn.XLOOKUP(IF(E31="","",--SUBSTITUTE(LEFT(E31,FIND(",",E31)-1),"[{","")),价值表!D:D,价值表!C:C),"") -> 织梦微尘
B32: 1012 | C32: 2 | D32: 锻造晶石 | E32: [{50001,500}] | F32: [{1,300}] | G32: 5 | H32: 6折 | I32: =IF(B32="","",SUBSTITUTE(LEFT(E32,FIND(",",E32)-1),"","")) -> [{50001 | J32: =_xlfn.XLOOKUP(--SUBSTITUTE(LEFT(E32,FIND(",",E32)-1),"[{",""),价值表!D:D,价值表!F:F) -> 0.1 | K32: =J32*SUBSTITUTE(SUBSTITUTE(E32,""&I32&",",""),"}]","") -> 50 | L32: =K32/SUBSTITUTE(SUBSTITUTE(SUBSTITUTE(F32,"1,",""),"}]",""),"[{","") -> 0.16666667 | M32: =ROUND(1/L32*10,0)&"折" -> 60折 | N32: =_xlfn.XLOOKUP(--SUBSTITUTE(I32,"[{",""),价值表!D:D,价值表!J:J) -> 5 | O32: =IFERROR(_xlfn.XLOOKUP(IF(E32="","",--SUBSTITUTE(LEFT(E32,FIND(",",E32)-1),"[{","")),价值表!D:D,价值表!C:C),"") -> 锻造晶石
B33: 1013 | C33: 2 | D33: 幻梦晶核 | E33: [{5305001,6}] | F33: [{1,216}] | G33: 2 | H33: 6折 | I33: =IF(B33="","",SUBSTITUTE(LEFT(E33,FIND(",",E33)-1),"","")) -> [{5305001 | J33: =_xlfn.XLOOKUP(--SUBSTITUTE(LEFT(E33,FIND(",",E33)-1),"[{",""),价值表!D:D,价值表!F:F) -> 60 | K33: =J33*SUBSTITUTE(SUBSTITUTE(E33,""&I33&",",""),"}]","") -> 360 | L33: =K33/SUBSTITUTE(SUBSTITUTE(SUBSTITUTE(F33,"1,",""),"}]",""),"[{","") -> 1.6666667 | M33: =ROUND(1/L33*10,0)&"折" -> 6折 | N33: =_xlfn.XLOOKUP(--SUBSTITUTE(I33,"[{",""),价值表!D:D,价值表!J:J) -> 5 | O33: =IFERROR(_xlfn.XLOOKUP(IF(E33="","",--SUBSTITUTE(LEFT(E33,FIND(",",E33)-1),"[{","")),价值表!D:D,价值表!C:C),"") -> 幻梦晶核
B34: 1014 | C34: 2 | D34: 转运石 | E34: [{5523001,1000}] | F34: [{1,198}] | G34: 3 | H34: 6折 | I34: =IF(B34="","",SUBSTITUTE(LEFT(E34,FIND(",",E34)-1),"","")) -> [{5523001 | J34: =_xlfn.XLOOKUP(--SUBSTITUTE(LEFT(E34,FIND(",",E34)-1),"[{",""),价值表!D:D,价值表!F:F) -> 0.33 | K34: =J34*SUBSTITUTE(SUBSTITUTE(E34,""&I34&",",""),"}]","") -> 330 | L34: =K34/SUBSTITUTE(SUBSTITUTE(SUBSTITUTE(F34,"1,",""),"}]",""),"[{","") -> 1.6666667 | M34: =ROUND(1/L34*10,0)&"折" -> 6折 | N34: =_xlfn.XLOOKUP(--SUBSTITUTE(I34,"[{",""),价值表!D:D,价值表!J:J) -> 5 | O34: =IFERROR(_xlfn.XLOOKUP(IF(E34="","",--SUBSTITUTE(LEFT(E34,FIND(",",E34)-1),"[{","")),价值表!D:D,价值表!C:C),"") -> 转运石
B35: 1015 | C35: 2 | D35: 智械发条 | E35: [{62,3}] | F35: [{1,225}] | G35: 5 | H35: 5折 | I35: =IF(B35="","",SUBSTITUTE(LEFT(E35,FIND(",",E35)-1),"","")) | J35: =价值表!F114 | K35: =J35*SUBSTITUTE(SUBSTITUTE(E35,""&I35&",",""),"}]","") | L35: =K35/SUBSTITUTE(SUBSTITUTE(SUBSTITUTE(F35,"1,",""),"}]",""),"[{","") | M35: =ROUND(1/L35*10,0)&"折" | N35: =_xlfn.XLOOKUP(--SUBSTITUTE(I35,"[{",""),价值表!D:D,价值表!J:J) | O35: =IFERROR(_xlfn.XLOOKUP(IF(E35="","",--SUBSTITUTE(LEFT(E35,FIND(",",E35)-1),"[{","")),价值表!D:D,价值表!C:C),"")
B37: 2001 | C37: 2 | D37: 体力 | E37: [{13,60}] | F37: [{1,84}] | G37: 5 | H37: 7折 | I37: =IF(B37="","",SUBSTITUTE(LEFT(E37,FIND(",",E37)-1),"","")) -> [{2 | J37: =_xlfn.XLOOKUP(--SUBSTITUTE(LEFT(E37,FIND(",",E37)-1),"[{",""),价值表!D:D,价值表!F:F) -> 0.05 | K37: 500 | L37: 2.5 | M37: 4折 | N37: =_xlfn.XLOOKUP(--SUBSTITUTE(I37,"[{",""),价值表!D:D,价值表!J:J) -> 5 | O37: =IFERROR(_xlfn.XLOOKUP(IF(E37="","",--SUBSTITUTE(LEFT(E37,FIND(",",E37)-1),"[{","")),价值表!D:D,价值表!C:C),"") -> 金币
B38: 2002 | C38: 2 | D38: 金币 | E38: [{2,10000}] | F38: [{1,200}] | G38: 1 | H38: 4折 | I38: =IF(B38="","",SUBSTITUTE(LEFT(E38,FIND(",",E38)-1),"","")) -> [{11 | J38: =_xlfn.XLOOKUP(--SUBSTITUTE(LEFT(E38,FIND(",",E38)-1),"[{",""),价值表!D:D,价值表!F:F) -> 30 | K38: 1500 | L38: 1.4285714 | M38: 7折 | N38: =_xlfn.XLOOKUP(--SUBSTITUTE(I38,"[{",""),价值表!D:D,价值表!J:J) -> 6 | O38: =IFERROR(_xlfn.XLOOKUP(IF(E38="","",--SUBSTITUTE(LEFT(E38,FIND(",",E38)-1),"[{","")),价值表!D:D,价值表!C:C),"") -> 梦境招募器
B39: 2003 | C39: 2 | D39: 招募器 | E39: [{11,50}] | F39: [{1,1050}] | G39: 3 | H39: 7折 | I39: =IF(B39="","",SUBSTITUTE(LEFT(E39,FIND(",",E39)-1),"","")) -> [{11 | J39: =_xlfn.XLOOKUP(--SUBSTITUTE(LEFT(E39,FIND(",",E39)-1),"[{",""),价值表!D:D,价值表!F:F) -> 30 | K39: 3000 | L39: 1.6666667 | M39: 6折 | N39: =_xlfn.XLOOKUP(--SUBSTITUTE(I39,"[{",""),价值表!D:D,价值表!J:J) -> 6 | O39: =IFERROR(_xlfn.XLOOKUP(IF(E39="","",--SUBSTITUTE(LEFT(E39,FIND(",",E39)-1),"[{","")),价值表!D:D,价值表!C:C),"") -> 梦境招募器
B40: 2004 | C40: 2 | D40: 招募器 | E40: [{11,100}] | F40: [{1,1800}] | G40: 3 | H40: 6折 | I40: =IF(B40="","",SUBSTITUTE(LEFT(E40,FIND(",",E40)-1),"","")) -> [{5104001 | J40: =_xlfn.XLOOKUP(--SUBSTITUTE(LEFT(E40,FIND(",",E40)-1),"[{",""),价值表!D:D,价值表!F:F) -> 2 | K40: 800 | L40: 2.5 | M40: 4折 | N40: =_xlfn.XLOOKUP(--SUBSTITUTE(I40,"[{",""),价值表!D:D,价值表!J:J) -> 0 | O40: =IFERROR(_xlfn.XLOOKUP(IF(E40="","",--SUBSTITUTE(LEFT(E40,FIND(",",E40)-1),"[{","")),价值表!D:D,价值表!C:C),"") -> 超能特饮
B41: 2005 | C41: 2 | D41: 能量特饮 | E41: [{5104001,400}] | F41: [{1,320}] | G41: 10 | H41: 7折 | I41: =IF(B41="","",SUBSTITUTE(LEFT(E41,FIND(",",E41)-1),"","")) -> [{50002 | J41: =_xlfn.XLOOKUP(--SUBSTITUTE(LEFT(E41,FIND(",",E41)-1),"[{",""),价值表!D:D,价值表!F:F) -> 3 | K41: 600 | L41: 1.6666667 | M41: 6折 | N41: =_xlfn.XLOOKUP(--SUBSTITUTE(I41,"[{",""),价值表!D:D,价值表!J:J) -> 6 | O41: =IFERROR(_xlfn.XLOOKUP(IF(E41="","",--SUBSTITUTE(LEFT(E41,FIND(",",E41)-1),"[{","")),价值表!D:D,价值表!C:C),"") -> 装备图纸
B42: 2006 | C42: 2 | D42: 装备图纸 | E42: [{50002,200}] | F42: [{1,360}] | G42: 3 | H42: 6折 | I42: =IF(B42="","",SUBSTITUTE(LEFT(E42,FIND(",",E42)-1),"","")) -> [{30 | J42: =_xlfn.XLOOKUP(--SUBSTITUTE(LEFT(E42,FIND(",",E42)-1),"[{",""),价值表!D:D,价值表!F:F) -> 280 | K42: 2800 | L42: 2 | M42: 5折 | N42: =_xlfn.XLOOKUP(--SUBSTITUTE(I42,"[{",""),价值表!D:D,价值表!J:J) -> 5 | O42: =IFERROR(_xlfn.XLOOKUP(IF(E42="","",--SUBSTITUTE(LEFT(E42,FIND(",",E42)-1),"[{","")),价值表!D:D,价值表!C:C),"") -> 星辉秘契
B43: 2007 | C43: 2 | D43: 星辉秘契 | E43: [{30,10}] | F43: [{1,1400}] | G43: 5 | H43: 5折 | I43: =IF(B43="","",SUBSTITUTE(LEFT(E43,FIND(",",E43)-1),"","")) -> [{30 | J43: =_xlfn.XLOOKUP(--SUBSTITUTE(LEFT(E43,FIND(",",E43)-1),"[{",""),价值表!D:D,价值表!F:F) -> 280 | K43: 5600 | L43: 2.5 | M43: 4折 | N43: =_xlfn.XLOOKUP(--SUBSTITUTE(I43,"[{",""),价值表!D:D,价值表!J:J) -> 5 | O43: =IFERROR(_xlfn.XLOOKUP(IF(E43="","",--SUBSTITUTE(LEFT(E43,FIND(",",E43)-1),"[{","")),价值表!D:D,价值表!C:C),"") -> 星辉秘契
B44: 2008 | C44: 2 | D44: 星辉秘契 | E44: [{30,20}] | F44: [{1,2240}] | G44: 5 | H44: 4折 | I44: =IF(B44="","",SUBSTITUTE(LEFT(E44,FIND(",",E44)-1),"","")) -> [{5303001 | J44: =_xlfn.XLOOKUP(--SUBSTITUTE(LEFT(E44,FIND(",",E44)-1),"[{",""),价值表!D:D,价值表!F:F) -> 5 | K44: 500 | L44: 1.25 | M44: 8折 | N44: =_xlfn.XLOOKUP(--SUBSTITUTE(I44,"[{",""),价值表!D:D,价值表!J:J) -> 8 | O44: =IFERROR(_xlfn.XLOOKUP(IF(E44="","",--SUBSTITUTE(LEFT(E44,FIND(",",E44)-1),"[{","")),价值表!D:D,价值表!C:C),"") -> 符引结晶
B45: 2009 | C45: 2 | D45: 符引结晶 | E45: [{5303001,100}] | F45: [{1,400}] | G45: 3 | H45: 8折 | I45: =IF(B45="","",SUBSTITUTE(LEFT(E45,FIND(",",E45)-1),"","")) -> [{5305001 | J45: =_xlfn.XLOOKUP(--SUBSTITUTE(LEFT(E45,FIND(",",E45)-1),"[{",""),价值表!D:D,价值表!F:F) -> 60 | K45: 720 | L45: 2 | M45: =ROUND(1/L45*10,0)&"折" -> 5折 | N45: =_xlfn.XLOOKUP(--SUBSTITUTE(I45,"[{",""),价值表!D:D,价值表!J:J) -> 5 | O45: =IFERROR(_xlfn.XLOOKUP(IF(E45="","",--SUBSTITUTE(LEFT(E45,FIND(",",E45)-1),"[{","")),价值表!D:D,价值表!C:C),"") -> 幻梦晶核
B46: 2010 | C46: 2 | D46: 幻梦晶核 | E46: [{5305001,12}] | F46: [{1,360}] | G46: 2 | H46: 5折 | I46: =IF(B46="","",SUBSTITUTE(LEFT(E46,FIND(",",E46)-1),"","")) -> [{5203001 | J46: =_xlfn.XLOOKUP(--SUBSTITUTE(LEFT(E46,FIND(",",E46)-1),"[{",""),价值表!D:D,价值表!F:F) -> 3 | K46: 600 | L46: 1.6666667 | M46: =ROUND(1/L46*10,0)&"折" -> 6折 | N46: =_xlfn.XLOOKUP(--SUBSTITUTE(I46,"[{",""),价值表!D:D,价值表!J:J) -> 6 | O46: =IFERROR(_xlfn.XLOOKUP(IF(E46="","",--SUBSTITUTE(LEFT(E46,FIND(",",E46)-1),"[{","")),价值表!D:D,价值表!C:C),"") -> 织梦微尘
B47: 2011 | C47: 2 | D47: 织梦微尘 | E47: [{5203001,200}] | F47: [{1,360}] | G47: 3 | H47: 6折 | I47: =IF(B47="","",SUBSTITUTE(LEFT(E47,FIND(",",E47)-1),"","")) -> [{5204001 | J47: =_xlfn.XLOOKUP(--SUBSTITUTE(LEFT(E47,FIND(",",E47)-1),"[{",""),价值表!D:D,价值表!F:F) -> 5 | K47: 120 | L47: =K47/SUBSTITUTE(SUBSTITUTE(SUBSTITUTE(F47,"1,",""),"}]",""),"[{","") -> 0.6 | M47: =ROUND(1/L47*10,0)&"折" -> 17折 | N47: =_xlfn.XLOOKUP(--SUBSTITUTE(I47,"[{",""),价值表!D:D,价值表!J:J) -> 0 | O47: =IFERROR(_xlfn.XLOOKUP(IF(E47="","",--SUBSTITUTE(LEFT(E47,FIND(",",E47)-1),"[{","")),价值表!D:D,价值表!C:C),"") -> 加速沙漏
B48: 2012 | C48: 2 | D48: 加速沙漏 | E48: [{5204001,24}] | F48: [{1,200}] | G48: 10 | H48: 8折 | I48: =IF(B48="","",SUBSTITUTE(LEFT(E48,FIND(",",E48)-1),"","")) -> [{100009 | J48: =_xlfn.XLOOKUP(--SUBSTITUTE(LEFT(E48,FIND(",",E48)-1),"[{",""),价值表!D:D,价值表!F:F) | K48: 3000 | L48: =K48/SUBSTITUTE(SUBSTITUTE(SUBSTITUTE(F48,"1,",""),"}]",""),"[{","") -> 3.0612245 | M48: =ROUND(1/L48*10,0)&"折" -> 3折 | N48: =_xlfn.XLOOKUP(--SUBSTITUTE(I48,"[{",""),价值表!D:D,价值表!J:J) | O48: =IFERROR(_xlfn.XLOOKUP(IF(E48="","",--SUBSTITUTE(LEFT(E48,FIND(",",E48)-1),"[{","")),价值表!D:D,价值表!C:C),"")
B49: 2013 | C49: 2 | D49: 梦境衣橱盒 | E49: [{100009,1}] | F49: [{1,980}] | G49: 3 | H49: 1折 | I49: =IF(B49="","",SUBSTITUTE(LEFT(E49,FIND(",",E49)-1),"","")) -> [{5523001 | J49: =价值表!F95 | K49: 990 | L49: =K49/SUBSTITUTE(SUBSTITUTE(SUBSTITUTE(F49,"1,",""),"}]",""),"[{","") -> 1.98 | M49: =ROUND(1/L49*10,0)&"折" -> 5折 | N49: =_xlfn.XLOOKUP(--SUBSTITUTE(I49,"[{",""),价值表!D:D,价值表!J:J) -> 5 | O49: =IFERROR(_xlfn.XLOOKUP(IF(E49="","",--SUBSTITUTE(LEFT(E49,FIND(",",E49)-1),"[{","")),价值表!D:D,价值表!C:C),"") -> 转运石
B50: 2014 | C50: 2 | D50: 转运石 | E50: [{5523001,3000}] | F50: [{1,500}] | G50: 4 | H50: 5折 | I50: =IF(B50="","",SUBSTITUTE(LEFT(E50,FIND(",",E50)-1),"","")) | J50: =_xlfn.XLOOKUP(--SUBSTITUTE(LEFT(E50,FIND(",",E50)-1),"[{",""),价值表!D:D,价值表!F:F) | K50: =J50*SUBSTITUTE(SUBSTITUTE(E50,""&I50&",",""),"}]","") | L50: =K50/SUBSTITUTE(SUBSTITUTE(SUBSTITUTE(F50,"1,",""),"}]",""),"[{","") | M50: =ROUND(1/L50*10,0)&"折" | N50: =_xlfn.XLOOKUP(--SUBSTITUTE(I50,"[{",""),价值表!D:D,价值表!J:J) | O50: =IFERROR(_xlfn.XLOOKUP(IF(E50="","",--SUBSTITUTE(LEFT(E50,FIND(",",E50)-1),"[{","")),价值表!D:D,价值表!C:C),"")
B51: 2015 | C51: 2 | D51: 智械发条 | E51: [{62,10}] | F51: [{1,600}] | G51: 3 | H51: 4折 | I51: =IF(B51="","",SUBSTITUTE(LEFT(E51,FIND(",",E51)-1),"","")) -> [{11 | J51: =价值表!F114 | K51: =J51*SUBSTITUTE(SUBSTITUTE(E51,""&I51&",",""),"}]","") -> 1500 | L51: =K51/SUBSTITUTE(SUBSTITUTE(SUBSTITUTE(F51,"1,",""),"}]",""),"[{","") -> 2 | M51: =ROUND(1/L51*10,0)&"折" -> 5折 | N51: =_xlfn.XLOOKUP(--SUBSTITUTE(I51,"[{",""),价值表!D:D,价值表!J:J) -> 6 | O51: =IFERROR(_xlfn.XLOOKUP(IF(E51="","",--SUBSTITUTE(LEFT(E51,FIND(",",E51)-1),"[{","")),价值表!D:D,价值表!C:C),"") -> 梦境招募器
B52: 2016 | C52: 2 | D52: 随机史诗藏品 | E52: [{6220021,1}] | F52: [{1,1400}] | G52: 3 | H52: 6折 | I52: =IF(B52="","",SUBSTITUTE(LEFT(E52,FIND(",",E52)-1),"","")) -> [{11 | J52: =价值表!F181 | K52: =J52*SUBSTITUTE(SUBSTITUTE(E52,""&I52&",",""),"}]","") -> 6000 | L52: =K52/SUBSTITUTE(SUBSTITUTE(SUBSTITUTE(F52,"1,",""),"}]",""),"[{","") -> 1.8181818 | M52: =ROUND(1/L52*10,0)&"折" -> 6折 | N52: =_xlfn.XLOOKUP(--SUBSTITUTE(I52,"[{",""),价值表!D:D,价值表!J:J) -> 6 | O52: =IFERROR(_xlfn.XLOOKUP(IF(E52="","",--SUBSTITUTE(LEFT(E52,FIND(",",E52)-1),"[{","")),价值表!D:D,价值表!C:C),"") -> 梦境招募器
B53: 2017 | C53: 2 | D53: 万象自选宝盒Ⅰ | E53: [{100143,1}] | F53: [{1,3000}] | G53: 1 | H53: 5折 | I53: =IF(B53="","",SUBSTITUTE(LEFT(E53,FIND(",",E53)-1),"","")) -> [{5104001 | J53: =价值表!F105 | K53: =J53*SUBSTITUTE(SUBSTITUTE(E53,""&I53&",",""),"}]","") -> 2000 | L53: =K53/SUBSTITUTE(SUBSTITUTE(SUBSTITUTE(F53,"1,",""),"}]",""),"[{","") -> 3.3333333 | M53: =ROUND(1/L53*10,0)&"折" -> 3折 | N53: =_xlfn.XLOOKUP(--SUBSTITUTE(I53,"[{",""),价值表!D:D,价值表!J:J) -> 0 | O53: =IFERROR(_xlfn.XLOOKUP(IF(E53="","",--SUBSTITUTE(LEFT(E53,FIND(",",E53)-1),"[{","")),价值表!D:D,价值表!C:C),"") -> 超能特饮
B55: 3001 | C55: 2 | D55: 招募器 | E55: [{11,50}] | F55: [{1,750}] | G55: 2 | H55: 5折 | I55: =IF(B55="","",SUBSTITUTE(LEFT(E55,FIND(",",E55)-1),"","")) -> [{5305001 | J55: =_xlfn.XLOOKUP(--SUBSTITUTE(LEFT(E55,FIND(",",E55)-1),"[{",""),价值表!D:D,价值表!F:F) -> 60 | K55: =J55*SUBSTITUTE(SUBSTITUTE(E55,""&I55&",",""),"}]","") -> 1800 | L55: =K55/SUBSTITUTE(SUBSTITUTE(SUBSTITUTE(F55,"1,",""),"}]",""),"[{","") -> 2 | M55: =ROUND(1/L55*10,0)&"折" -> 5折 | N55: =_xlfn.XLOOKUP(--SUBSTITUTE(I55,"[{",""),价值表!D:D,价值表!J:J) -> 5 | O55: =IFERROR(_xlfn.XLOOKUP(IF(E55="","",--SUBSTITUTE(LEFT(E55,FIND(",",E55)-1),"[{","")),价值表!D:D,价值表!C:C),"") -> 幻梦晶核
B56: 3002 | C56: 2 | D56: 招募器 | E56: [{11,200}] | F56: [{1,3300}] | G56: 2 | H56: 6折 | I56: =IF(B56="","",SUBSTITUTE(LEFT(E56,FIND(",",E56)-1),"","")) -> [{5305001 | J56: =_xlfn.XLOOKUP(--SUBSTITUTE(LEFT(E56,FIND(",",E56)-1),"[{",""),价值表!D:D,价值表!F:F) -> 60 | K56: =J56*SUBSTITUTE(SUBSTITUTE(E56,""&I56&",",""),"}]","") -> 7800 | L56: =K56/SUBSTITUTE(SUBSTITUTE(SUBSTITUTE(F56,"1,",""),"}]",""),"[{","") -> 2.5 | M56: =ROUND(1/L56*10,0)&"折" -> 4折 | N56: =_xlfn.XLOOKUP(--SUBSTITUTE(I56,"[{",""),价值表!D:D,价值表!J:J) -> 5 | O56: =IFERROR(_xlfn.XLOOKUP(IF(E56="","",--SUBSTITUTE(LEFT(E56,FIND(",",E56)-1),"[{","")),价值表!D:D,价值表!C:C),"") -> 幻梦晶核
B57: 3003 | C57: 2 | D57: 能量特饮 | E57: [{5104001,1000}] | F57: [{1,600}] | G57: 10 | H57: 3折 | I57: =IF(B57="","",SUBSTITUTE(LEFT(E57,FIND(",",E57)-1),"","")) -> [{100008 | J57: =_xlfn.XLOOKUP(--SUBSTITUTE(LEFT(E57,FIND(",",E57)-1),"[{",""),价值表!D:D,价值表!F:F) | K57: =J57*SUBSTITUTE(SUBSTITUTE(E57,""&I57&",",""),"}]","") -> 5000 | L57: =K57/SUBSTITUTE(SUBSTITUTE(SUBSTITUTE(F57,"1,",""),"}]",""),"[{","") -> 1.5243902 | M57: =ROUND(1/L57*10,0)&"折" -> 7折 | N57: =_xlfn.XLOOKUP(--SUBSTITUTE(I57,"[{",""),价值表!D:D,价值表!J:J) | O57: =IFERROR(_xlfn.XLOOKUP(IF(E57="","",--SUBSTITUTE(LEFT(E57,FIND(",",E57)-1),"[{","")),价值表!D:D,价值表!C:C),"")
B58: 3004 | C58: 2 | D58: 装备图纸 | E58: [{50002,400}] | F58: [{1,600}] | G58: 3 | H58: 5折 | I58: =IF(B58="","",SUBSTITUTE(LEFT(E58,FIND(",",E58)-1),"","")) -> [{30 | J58: =_xlfn.XLOOKUP(--SUBSTITUTE(LEFT(E58,FIND(",",E58)-1),"[{",""),价值表!D:D,价值表!F:F) -> 280 | K58: =J58*SUBSTITUTE(SUBSTITUTE(E58,""&I58&",",""),"}]","") -> 2800 | L58: =K58/SUBSTITUTE(SUBSTITUTE(SUBSTITUTE(F58,"1,",""),"}]",""),"[{","") -> 3.3333333 | M58: =ROUND(1/L58*10,0)&"折" -> 3折 | N58: =_xlfn.XLOOKUP(--SUBSTITUTE(I58,"[{",""),价值表!D:D,价值表!J:J) -> 5 | O58: =IFERROR(_xlfn.XLOOKUP(IF(E58="","",--SUBSTITUTE(LEFT(E58,FIND(",",E58)-1),"[{","")),价值表!D:D,价值表!C:C),"") -> 星辉秘契
B59: 3005 | C59: 2 | D59: 幻梦晶核 | E59: [{5305001,30}] | F59: [{1,900}] | G59: 3 | H59: 5折 | I59: =IF(B59="","",SUBSTITUTE(LEFT(E59,FIND(",",E59)-1),"","")) -> [{30 | J59: =_xlfn.XLOOKUP(--SUBSTITUTE(LEFT(E59,FIND(",",E59)-1),"[{",""),价值表!D:D,价值表!F:F) -> 280 | K59: =J59*SUBSTITUTE(SUBSTITUTE(E59,""&I59&",",""),"}]","") -> 11200 | L59: =K59/SUBSTITUTE(SUBSTITUTE(SUBSTITUTE(F59,"1,",""),"}]",""),"[{","") -> 2.5 | M59: =ROUND(1/L59*10,0)&"折" -> 4折 | N59: =_xlfn.XLOOKUP(--SUBSTITUTE(I59,"[{",""),价值表!D:D,价值表!J:J) -> 5 | O59: =IFERROR(_xlfn.XLOOKUP(IF(E59="","",--SUBSTITUTE(LEFT(E59,FIND(",",E59)-1),"[{","")),价值表!D:D,价值表!C:C),"") -> 星辉秘契
B60: 3006 | C60: 2 | D60: 幻梦晶核 | E60: [{5305001,130}] | F60: [{1,3120}] | G60: 1 | H60: 4折 | I60: =IF(B60="","",SUBSTITUTE(LEFT(E60,FIND(",",E60)-1),"","")) -> [{5305000 | J60: =_xlfn.XLOOKUP(--SUBSTITUTE(LEFT(E60,FIND(",",E60)-1),"[{",""),价值表!D:D,价值表!F:F) -> 4096 | K60: =J60*SUBSTITUTE(SUBSTITUTE(E60,""&I60&",",""),"}]","") -> 4096 | L60: =K60/SUBSTITUTE(SUBSTITUTE(SUBSTITUTE(F60,"1,",""),"}]",""),"[{","") -> 2.9681159 | M60: =ROUND(1/L60*10,0)&"折" -> 3折 | N60: =_xlfn.XLOOKUP(--SUBSTITUTE(I60,"[{",""),价值表!D:D,价值表!J:J) -> 0 | O60: =IFERROR(_xlfn.XLOOKUP(IF(E60="","",--SUBSTITUTE(LEFT(E60,FIND(",",E60)-1),"[{","")),价值表!D:D,价值表!C:C),"") -> 传说符文
B61: 3007 | C61: 2 | D61: 绮梦衣橱盒 | E61: [{100008,1}] | F61: [{1,3280}] | G61: 2 | H61: 4折 | I61: =IF(B61="","",SUBSTITUTE(LEFT(E61,FIND(",",E61)-1),"","")) -> [{5306000 | J61: =价值表!F96 | K61: =J61*SUBSTITUTE(SUBSTITUTE(E61,""&I61&",",""),"}]","") -> 16384 | L61: =K61/SUBSTITUTE(SUBSTITUTE(SUBSTITUTE(F61,"1,",""),"}]",""),"[{","") -> 2.5283951 | M61: =ROUND(1/L61*10,0)&"折" -> 4折 | N61: =_xlfn.XLOOKUP(--SUBSTITUTE(I61,"[{",""),价值表!D:D,价值表!J:J) -> 0 | O61: =IFERROR(_xlfn.XLOOKUP(IF(E61="","",--SUBSTITUTE(LEFT(E61,FIND(",",E61)-1),"[{","")),价值表!D:D,价值表!C:C),"") -> 神话符文
B62: 3008 | C62: 2 | D62: 星辉秘契 | E62: [{30,10}] | F62: [{1,840}] | G62: 3 | H62: 3折 | I62: =IF(B62="","",SUBSTITUTE(LEFT(E62,FIND(",",E62)-1),"","")) -> [{5523001 | J62: =_xlfn.XLOOKUP(--SUBSTITUTE(LEFT(E62,FIND(",",E62)-1),"[{",""),价值表!D:D,价值表!F:F) -> 0.33 | K62: =J62*SUBSTITUTE(SUBSTITUTE(E62,""&I62&",",""),"}]","") -> 3300 | L62: =K62/SUBSTITUTE(SUBSTITUTE(SUBSTITUTE(F62,"1,",""),"}]",""),"[{","") -> 2.5 | M62: =ROUND(1/L62*10,0)&"折" -> 4折 | N62: =_xlfn.XLOOKUP(--SUBSTITUTE(I62,"[{",""),价值表!D:D,价值表!J:J) -> 5 | O62: =IFERROR(_xlfn.XLOOKUP(IF(E62="","",--SUBSTITUTE(LEFT(E62,FIND(",",E62)-1),"[{","")),价值表!D:D,价值表!C:C),"") -> 转运石
B63: 3009 | C63: 2 | D63: 星辉秘契 | E63: [{30,40}] | F63: [{1,4480}] | G63: 3 | H63: 4折 | I63: =IF(B63="","",SUBSTITUTE(LEFT(E63,FIND(",",E63)-1),"","")) | J63: =_xlfn.XLOOKUP(--SUBSTITUTE(LEFT(E63,FIND(",",E63)-1),"[{",""),价值表!D:D,价值表!F:F) | K63: =J63*SUBSTITUTE(SUBSTITUTE(E63,""&I63&",",""),"}]","") | L63: =K63/SUBSTITUTE(SUBSTITUTE(SUBSTITUTE(F63,"1,",""),"}]",""),"[{","") | M63: =ROUND(1/L63*10,0)&"折" | N63: =_xlfn.XLOOKUP(--SUBSTITUTE(I63,"[{",""),价值表!D:D,价值表!J:J) | O63: =IFERROR(_xlfn.XLOOKUP(IF(E63="","",--SUBSTITUTE(LEFT(E63,FIND(",",E63)-1),"[{","")),价值表!D:D,价值表!C:C),"")
B64: 3010 | C64: 2 | D64: 传说符文 | E64: [{5305000,1}] | F64: [{1,1380}] | G64: 1 | H64: 1折 | I64: =IF(B64="","",SUBSTITUTE(LEFT(E64,FIND(",",E64)-1),"","")) | J64: =_xlfn.XLOOKUP(--SUBSTITUTE(LEFT(E64,FIND(",",E64)-1),"[{",""),价值表!D:D,价值表!F:F) | K64: =J64*SUBSTITUTE(SUBSTITUTE(E64,""&I64&",",""),"}]","") | L64: =K64/SUBSTITUTE(SUBSTITUTE(SUBSTITUTE(F64,"1,",""),"}]",""),"[{","") | M64: =ROUND(1/L64*10,0)&"折" | N64: =_xlfn.XLOOKUP(--SUBSTITUTE(I64,"[{",""),价值表!D:D,价值表!J:J) | O64: =IFERROR(_xlfn.XLOOKUP(IF(E64="","",--SUBSTITUTE(LEFT(E64,FIND(",",E64)-1),"[{","")),价值表!D:D,价值表!C:C),"")
B65: 3011 | C65: 2 | D65: 神话符文 | E65: [{5306000,1}] | F65: [{1,6480}] | G65: 1 | H65: 1折 | I65: =IF(B65="","",SUBSTITUTE(LEFT(E65,FIND(",",E65)-1),"","")) | J65: =_xlfn.XLOOKUP(--SUBSTITUTE(LEFT(E65,FIND(",",E65)-1),"[{",""),价值表!D:D,价值表!F:F) | K65: =J65*SUBSTITUTE(SUBSTITUTE(E65,""&I65&",",""),"}]","") | L65: =K65/SUBSTITUTE(SUBSTITUTE(SUBSTITUTE(F65,"1,",""),"}]",""),"[{","") | M65: =ROUND(1/L65*10,0)&"折" | N65: =_xlfn.XLOOKUP(--SUBSTITUTE(I65,"[{",""),价值表!D:D,价值表!J:J) | O65: =IFERROR(_xlfn.XLOOKUP(IF(E65="","",--SUBSTITUTE(LEFT(E65,FIND(",",E65)-1),"[{","")),价值表!D:D,价值表!C:C),"")
B66: 3012 | C66: 2 | D66: 转运石 | E66: [{5523001,10000}] | F66: [{1,1320}] | G66: 6 | H66: 4折 | I66: =IF(B66="","",SUBSTITUTE(LEFT(E66,FIND(",",E66)-1),"","")) | J66: =_xlfn.XLOOKUP(--SUBSTITUTE(LEFT(E66,FIND(",",E66)-1),"[{",""),价值表!D:D,价值表!F:F) | K66: =J66*SUBSTITUTE(SUBSTITUTE(E66,""&I66&",",""),"}]","") | L66: =K66/SUBSTITUTE(SUBSTITUTE(SUBSTITUTE(F66,"1,",""),"}]",""),"[{","") | M66: =ROUND(1/L66*10,0)&"折" | N66: =_xlfn.XLOOKUP(--SUBSTITUTE(I66,"[{",""),价值表!D:D,价值表!J:J) | O66: =IFERROR(_xlfn.XLOOKUP(IF(E66="","",--SUBSTITUTE(LEFT(E66,FIND(",",E66)-1),"[{","")),价值表!D:D,价值表!C:C),"")
B67: 3013 | C67: 2 | D67: 智械发条 | E67: [{62,10}] | F67: [{1,450}] | G67: 3 | H67: 3折 | I67: =IF(B67="","",SUBSTITUTE(LEFT(E67,FIND(",",E67)-1),"","")) | J67: =价值表!F114 | K67: =J67*SUBSTITUTE(SUBSTITUTE(E67,""&I67&",",""),"}]","") | L67: =K67/SUBSTITUTE(SUBSTITUTE(SUBSTITUTE(F67,"1,",""),"}]",""),"[{","") | M67: =ROUND(1/L67*10,0)&"折" | N67: =_xlfn.XLOOKUP(--SUBSTITUTE(I67,"[{",""),价值表!D:D,价值表!J:J) | O67: =IFERROR(_xlfn.XLOOKUP(IF(E67="","",--SUBSTITUTE(LEFT(E67,FIND(",",E67)-1),"[{","")),价值表!D:D,价值表!C:C),"")
B68: 3014 | C68: 2 | D68: 智械发条 | E68: [{62,20}] | F68: [{1,1200}] | G68: 2 | H68: 4折 | I68: =IF(B68="","",SUBSTITUTE(LEFT(E68,FIND(",",E68)-1),"","")) | J68: =价值表!F114 | K68: =J68*SUBSTITUTE(SUBSTITUTE(E68,""&I68&",",""),"}]","") | L68: =K68/SUBSTITUTE(SUBSTITUTE(SUBSTITUTE(F68,"1,",""),"}]",""),"[{","") | M68: =ROUND(1/L68*10,0)&"折" | N68: =_xlfn.XLOOKUP(--SUBSTITUTE(I68,"[{",""),价值表!D:D,价值表!J:J) | O68: =IFERROR(_xlfn.XLOOKUP(IF(E68="","",--SUBSTITUTE(LEFT(E68,FIND(",",E68)-1),"[{","")),价值表!D:D,价值表!C:C),"")
B69: 3015 | C69: 2 | D69: 怦怦时刻 | E69: [{6200012,1}] | F69: [{1,2400}] | G69: 3 | H69: 5折 | I69: =IF(B69="","",SUBSTITUTE(LEFT(E69,FIND(",",E69)-1),"","")) | J69: =价值表!F149 | K69: =J69*SUBSTITUTE(SUBSTITUTE(E69,""&I69&",",""),"}]","") | L69: =K69/SUBSTITUTE(SUBSTITUTE(SUBSTITUTE(F69,"1,",""),"}]",""),"[{","") | M69: =ROUND(1/L69*10,0)&"折" | N69: =_xlfn.XLOOKUP(--SUBSTITUTE(I69,"[{",""),价值表!D:D,价值表!J:J) | O69: =IFERROR(_xlfn.XLOOKUP(IF(E69="","",--SUBSTITUTE(LEFT(E69,FIND(",",E69)-1),"[{","")),价值表!D:D,价值表!C:C),"")

Sheet 大小月卡
C1: 设计思路
D2: 1 | E2: 前期先不开放永久卡
D3: 2 | E3: 双月卡区分权限：特权卡+扫荡卡，且双卡都能每日领取资源
D4: 3 | E4: 有月度双卡共鸣效果，进一步给出钩子
D7: 道具 | E7: 数量 | F7: 付费性价比
D8: 钻石 | E8: =J18*30+J21*30+180+300 -> 5280 | F8: =E8/48/10 -> 11
D9: 招募券 | E9: =J19*30+E27 -> 80 | F9: =E9/48/10 -> 0.16666667
D10: 体力 | E10: =J22*30 -> 300 | F10: =E10/48/10 -> 0.625
C15: 月卡特权
D17: 月卡类型 | E17: 特权 | F17: 购买即得 | G17: 每日福利 | H17: 购买价格/人民币 | I17: 每日奖励 | J17: 数量 | K17: 价值 | L17: 性价比
D18: 特权月卡 | E18: 跳过所有广告 | F18: 180钻石 | G18: 60钻石+2梦境招募器 | H18: 18 | I18: 钻石 | J18: 60 | K18: =_xlfn.XLOOKUP(I18,价值表!C:C,价值表!F:F)*J18*30 -> 1800 | L18: =(180+SUM($K$18:$K$20))/180 -> 21
E19: 体力上限+20 | I19: 梦境招募器 | J19: 2 | K19: =_xlfn.XLOOKUP(I19,价值表!C:C,价值表!F:F)*J19*30 -> 1800
E20: 商店刷新次数+3 | K20: =_xlfn.XLOOKUP(I20,价值表!C:C,价值表!F:F)*J20*30 -> 0
D21: 福利月卡 | E21: 快速扫荡不限次数 | F21: 300钻石 | G21: 100钻石+10体力 | H21: 30 | I21: 钻石 | J21: 100 | K21: =_xlfn.XLOOKUP(I21,价值表!C:C,价值表!F:F)*J21*30 -> 3000 | L21: =(300+SUM($K$21:$K$23))/300 -> 13
E22: 主线3倍速（未通关关卡可用） | I22: 体力 | J22: 10 | K22: =_xlfn.XLOOKUP(I22,价值表!C:C,价值表!F:F)*J22*30 -> 600
E23: 挂机时间+4小时，收益+30% | K23: =_xlfn.XLOOKUP(I23,价值表!C:C,价值表!F:F)*J23*30 -> 0
D26: 双卡共鸣 | E26: 数量
D27: 梦境招募器 | E27: 20
D28: 星辉秘契 | E28: 2
D29: 梦境股东 | E29: 1

Sheet 每周周卡
B2: 道具 | C2: 数量 | D2: 付费性价比
B3: 钻石 | C3: =SUM(G7:G13)+7*价值表!F112 | D3: =C3/12/10
B6: 方案id | C6: 登录天 | D6: 免费奖励 | E6: 免费数量 | F6: 付费奖励 | G6: 付费数量 | H6: 免费奖励2 | I6: 付费奖励2 | J6: 总价值 | K6: 累计性价比
B7: 180005 | C7: 1 | D7: 装备图纸 | E7: 10 | F7: 钻石 | G7: 300 | H7: ="[{"&_xlfn.XLOOKUP(D7,价值表!$C:$C,价值表!$D:$D)&","&E7&"}]" -> [{50002,10}] | I7: ="[{1,"&G7&"},{9800301,1}]" | J7: =_xlfn.XLOOKUP(D7,价值表!C:C,价值表!F:F)*E7+_xlfn.XLOOKUP(F7,价值表!C:C,价值表!F:F)*G7+价值表!F112 | K7: =SUM($J$7:J7)/120 -> 2.75
B8: 180005 | C8: 2 | D8: 能量特饮 | E8: 50 | F8: 钻石 | G8: 100 | H8: ="[{"&_xlfn.XLOOKUP(D8,价值表!$C:$C,价值表!$D:$D)&","&E8&"}]" -> [{5103001,50}] | I8: ="[{1,"&G8&"},{9800301,1}]" | J8: =_xlfn.XLOOKUP(D8,价值表!C:C,价值表!F:F)*E8+_xlfn.XLOOKUP(F8,价值表!C:C,价值表!F:F)*G8+价值表!F112 | K8: =SUM($J$7:J8)/120 -> 4
B9: 180005 | C9: 3 | D9: 星之初愿 | E9: 1 | F9: 钻石 | G9: 100 | H9: ="[{"&_xlfn.XLOOKUP(D9,价值表!$C:$C,价值表!$D:$D)&","&E9&"}]" -> [{9,1}] | I9: ="[{1,"&G9&"},{9800301,1}]" | J9: =_xlfn.XLOOKUP(D9,价值表!C:C,价值表!F:F)*E9+_xlfn.XLOOKUP(F9,价值表!C:C,价值表!F:F)*G9+价值表!F112 | K9: =SUM($J$7:J9)/120 -> 5.25
B10: 180005 | C10: 4 | D10: 装备图纸 | E10: 10 | F10: 钻石 | G10: 100 | H10: ="[{"&_xlfn.XLOOKUP(D10,价值表!$C:$C,价值表!$D:$D)&","&E10&"}]" -> [{50002,10}] | I10: ="[{1,"&G10&"},{9800301,1}]" | J10: =_xlfn.XLOOKUP(D10,价值表!C:C,价值表!F:F)*E10+_xlfn.XLOOKUP(F10,价值表!C:C,价值表!F:F)*G10+价值表!F112 | K10: =SUM($J$7:J10)/120 -> 6.3333333
B11: 180005 | C11: 5 | D11: 能量特饮 | E11: 50 | F11: 钻石 | G11: 100 | H11: ="[{"&_xlfn.XLOOKUP(D11,价值表!$C:$C,价值表!$D:$D)&","&E11&"}]" -> [{5103001,50}] | I11: ="[{1,"&G11&"},{9800301,1}]" | J11: =_xlfn.XLOOKUP(D11,价值表!C:C,价值表!F:F)*E11+_xlfn.XLOOKUP(F11,价值表!C:C,价值表!F:F)*G11+价值表!F112 | K11: =SUM($J$7:J11)/120 -> 7.5833333
B12: 180005 | C12: 6 | D12: 星之初愿 | E12: 1 | F12: 钻石 | G12: 100 | H12: ="[{"&_xlfn.XLOOKUP(D12,价值表!$C:$C,价值表!$D:$D)&","&E12&"}]" -> [{9,1}] | I12: ="[{1,"&G12&"},{9800301,1}]" | J12: =_xlfn.XLOOKUP(D12,价值表!C:C,价值表!F:F)*E12+_xlfn.XLOOKUP(F12,价值表!C:C,价值表!F:F)*G12+价值表!F112 | K12: =SUM($J$7:J12)/120 -> 8.8333333
B13: 180005 | C13: 7 | D13: 梦境招募器 | E13: 5 | F13: 钻石 | G13: 100 | H13: ="[{"&_xlfn.XLOOKUP(D13,价值表!$C:$C,价值表!$D:$D)&","&E13&"}]" -> [{11,5}] | I13: ="[{1,"&G13&"},{9800301,1}]" | J13: =_xlfn.XLOOKUP(D13,价值表!C:C,价值表!F:F)*E13+_xlfn.XLOOKUP(F13,价值表!C:C,价值表!F:F)*G13+价值表!F112 | K13: =SUM($J$7:J13)/120 -> 10.916667

Sheet 体力战令
B5: 道具 | C5: 数量 | D5: 活动性价比 | E5: 活动占比
B6: 梦境招募器 | C6: {=SUMPRODUCT(--($M$16:$M$65=$B6),$N$16:$N$65)+SUMPRODUCT(--($G$16:$G$65=$B6),$H$16:$H$65)+SUMPRODUCT(--($B$16:$B$65=$B6),$C$16:$C$65)} -> 300 | D6: =_xlfn.XLOOKUP(B6,价值表!C:C,价值表!F:F)*C6/(25+68)/10 | E6: =C6*2/3000 -> 0.2
B7: 星辉秘契 | C7: {=SUMPRODUCT(--($M$16:$M$65=$B7),$N$16:$N$65)+SUMPRODUCT(--($G$16:$G$65=$B7),$H$16:$H$65)+SUMPRODUCT(--($B$16:$B$65=$B7),$C$16:$C$65)} -> 57 | D7: =_xlfn.XLOOKUP(B7,价值表!C:C,价值表!F:F)*C7/(25+68)/10 | E7: =C7*2/226 -> 0.50442478
B8: 星之初愿 | C8: {=SUMPRODUCT(--($M$16:$M$65=$B8),$N$16:$N$65)+SUMPRODUCT(--($G$16:$G$65=$B8),$H$16:$H$65)+SUMPRODUCT(--($B$16:$B$65=$B8),$C$16:$C$65)} -> 6 | D8: =_xlfn.XLOOKUP(B8,价值表!C:C,价值表!F:F)*C8/(25+68)/10
B9: 咩菲特的雕像 | C9: {=SUMPRODUCT(--($M$16:$M$65=$B9),$N$16:$N$65)+SUMPRODUCT(--($G$16:$G$65=$B9),$H$16:$H$65)+SUMPRODUCT(--($B$16:$B$65=$B9),$C$16:$C$65)} -> 23 | D9: =_xlfn.XLOOKUP(B9,价值表!C:C,价值表!F:F)*C9/(25+68)/10
B10: 能量特饮 | C10: {=SUMPRODUCT(--($M$16:$M$65=$B10),$N$16:$N$65)+SUMPRODUCT(--($G$16:$G$65=$B10),$H$16:$H$65)+SUMPRODUCT(--($B$16:$B$65=$B10),$C$16:$C$65)} -> 950 | D10: =_xlfn.XLOOKUP(B10,价值表!C:C,价值表!F:F)*C10/(25+68)/10
B11: 金币 | C11: {=SUMPRODUCT(--($M$16:$M$65=$B11),$N$16:$N$65)+SUMPRODUCT(--($G$16:$G$65=$B11),$H$16:$H$65)+SUMPRODUCT(--($B$16:$B$65=$B11),$C$16:$C$65)} -> 3000 | D11: =_xlfn.XLOOKUP(B11,价值表!C:C,价值表!F:F)*C11/(25+68)/10
D12: 总性价比
D13: =SUM(D6,D7,D8,D9,D10,D11) -> 28.177083
B14: 免费档 | G14: 25元档 | M14: 68元档
B15: 基金1 | G15: 基金1 | M15: 基金2
B16: 道具 | C16: 数量 | D16: 配置 | E16: 道具1价值 | G16: 道具 | H16: 数量 | I16: 配置 | J16: 道具1价值 | K16: 累计性价比 | M16: 道具 | N16: 数量 | O16: 配置 | P16: 道具1价值 | Q16: 累计性价比
B17: 星之初愿 | C17: 1 | D17: ="[{"&_xlfn.XLOOKUP(B17,价值表!$C:$C,价值表!$D:$D)&","&C17&"}]" -> [{9,1}] | E17: =_xlfn.XLOOKUP(B17,价值表!$C:$C,价值表!$F:$F)*C17 -> 50 | G17: 钻石 | H17: 300 | I17: ="[{"&_xlfn.XLOOKUP(G17,价值表!$C:$C,价值表!$D:$D)&","&H17&"}]" -> [{1,300}] | J17: =_xlfn.XLOOKUP(G17,价值表!$C:$C,价值表!$F:$F)*H17 -> 300 | K17: =SUM($J$17:J17)/250 | M17: 钻石 | N17: 680 | O17: ="[{"&_xlfn.XLOOKUP(M17,价值表!$C:$C,价值表!$D:$D)&","&N17&"}]" -> [{1,680}] | P17: =_xlfn.XLOOKUP(M17,价值表!$C:$C,价值表!$F:$F)*N17 -> 680 | Q17: =SUM($J$17:P17)/680 -> 2.4427521
B18: 咩菲特的雕像 | C18: 1 | D18: ="[{"&_xlfn.XLOOKUP(B18,价值表!$C:$C,价值表!$D:$D)&","&C18&"}]" -> [{5800004,1}] | E18: =_xlfn.XLOOKUP(B18,价值表!$C:$C,价值表!$F:$F)*C18 -> 30 | G18: 梦境招募器 | H18: 5 | I18: ="[{"&_xlfn.XLOOKUP(G18,价值表!$C:$C,价值表!$D:$D)&","&H18&"}]" -> [{11,5}] | J18: =_xlfn.XLOOKUP(G18,价值表!$C:$C,价值表!$F:$F)*H18 -> 150 | K18: =SUM($J$17:J18)/250 | M18: 星辉秘契 | N18: 1 | O18: ="[{"&_xlfn.XLOOKUP(M18,价值表!$C:$C,价值表!$D:$D)&","&N18&"}]" -> [{30,1}] | P18: =_xlfn.XLOOKUP(M18,价值表!$C:$C,价值表!$F:$F)*N18 -> 280 | Q18: =SUM($J$17:P18)/680 -> 3.0789391
B19: 能量特饮 | C19: 50 | D19: ="[{"&_xlfn.XLOOKUP(B19,价值表!$C:$C,价值表!$D:$D)&","&C19&"}]" -> [{5103001,50}] | E19: =_xlfn.XLOOKUP(B19,价值表!$C:$C,价值表!$F:$F)*C19 -> 50 | G19: 梦境招募器 | H19: 5 | I19: ="[{"&_xlfn.XLOOKUP(G19,价值表!$C:$C,价值表!$D:$D)&","&H19&"}]" -> [{11,5}] | J19: =_xlfn.XLOOKUP(G19,价值表!$C:$C,价值表!$F:$F)*H19 -> 150 | K19: =SUM($J$17:J19)/250 | M19: 星辉秘契 | N19: 1 | O19: ="[{"&_xlfn.XLOOKUP(M19,价值表!$C:$C,价值表!$D:$D)&","&N19&"}]" -> [{30,1}] | P19: =_xlfn.XLOOKUP(M19,价值表!$C:$C,价值表!$F:$F)*N19 -> 280 | Q19: =SUM($J$17:P19)/680 -> 3.7159139
B20: 咩菲特的雕像 | C20: 1 | D20: ="[{"&_xlfn.XLOOKUP(B20,价值表!$C:$C,价值表!$D:$D)&","&C20&"}]" -> [{5800004,1}] | E20: =_xlfn.XLOOKUP(B20,价值表!$C:$C,价值表!$F:$F)*C20 -> 30 | G20: 梦境招募器 | H20: 5 | I20: ="[{"&_xlfn.XLOOKUP(G20,价值表!$C:$C,价值表!$D:$D)&","&H20&"}]" -> [{11,5}] | J20: =_xlfn.XLOOKUP(G20,价值表!$C:$C,价值表!$F:$F)*H20 -> 150 | K20: =SUM($J$17:J20)/250 | M20: 星辉秘契 | N20: 1 | O20: ="[{"&_xlfn.XLOOKUP(M20,价值表!$C:$C,价值表!$D:$D)&","&N20&"}]" -> [{30,1}] | P20: =_xlfn.XLOOKUP(M20,价值表!$C:$C,价值表!$F:$F)*N20 -> 280 | Q20: =SUM($J$17:P20)/680 -> 4.3536765
B21: 金币 | C21: 500 | D21: ="[{"&_xlfn.XLOOKUP(B21,价值表!$C:$C,价值表!$D:$D)&","&C21&"}]" -> [{2,500}] | E21: =_xlfn.XLOOKUP(B21,价值表!$C:$C,价值表!$F:$F)*C21 -> 25 | G21: 梦境招募器 | H21: 10 | I21: ="[{"&_xlfn.XLOOKUP(G21,价值表!$C:$C,价值表!$D:$D)&","&H21&"}]" -> [{11,10}] | J21: =_xlfn.XLOOKUP(G21,价值表!$C:$C,价值表!$F:$F)*H21 -> 300 | K21: =SUM($J$17:J21)/250 | M21: 星辉秘契 | N21: 2 | O21: ="[{"&_xlfn.XLOOKUP(M21,价值表!$C:$C,价值表!$D:$D)&","&N21&"}]" -> [{30,2}] | P21: =_xlfn.XLOOKUP(M21,价值表!$C:$C,价值表!$F:$F)*N21 -> 560 | Q21: =SUM($J$17:P21)/680 -> 5.6268382
B22: 咩菲特的雕像 | C22: 1 | D22: ="[{"&_xlfn.XLOOKUP(B22,价值表!$C:$C,价值表!$D:$D)&","&C22&"}]" -> [{5800004,1}] | E22: =_xlfn.XLOOKUP(B22,价值表!$C:$C,价值表!$F:$F)*C22 -> 30 | G22: 梦境招募器 | H22: 5 | I22: ="[{"&_xlfn.XLOOKUP(G22,价值表!$C:$C,价值表!$D:$D)&","&H22&"}]" -> [{11,5}] | J22: =_xlfn.XLOOKUP(G22,价值表!$C:$C,价值表!$F:$F)*H22 -> 150 | K22: =SUM($J$17:J22)/250 | M22: 星辉秘契 | N22: 1 | O22: ="[{"&_xlfn.XLOOKUP(M22,价值表!$C:$C,价值表!$D:$D)&","&N22&"}]" -> [{30,1}] | P22: =_xlfn.XLOOKUP(M22,价值表!$C:$C,价值表!$F:$F)*N22 -> 280 | Q22: =SUM($J$17:P22)/680 -> 6.2669643
B23: 能量特饮 | C23: 100 | D23: ="[{"&_xlfn.XLOOKUP(B23,价值表!$C:$C,价值表!$D:$D)&","&C23&"}]" -> [{5103001,100}] | E23: =_xlfn.XLOOKUP(B23,价值表!$C:$C,价值表!$F:$F)*C23 -> 100 | G23: 梦境招募器 | H23: 5 | I23: ="[{"&_xlfn.XLOOKUP(G23,价值表!$C:$C,价值表!$D:$D)&","&H23&"}]" -> [{11,5}] | J23: =_xlfn.XLOOKUP(G23,价值表!$C:$C,价值表!$F:$F)*H23 -> 150 | K23: =SUM($J$17:J23)/250 | M23: 星辉秘契 | N23: 1 | O23: ="[{"&_xlfn.XLOOKUP(M23,价值表!$C:$C,价值表!$D:$D)&","&N23&"}]" -> [{30,1}] | P23: =_xlfn.XLOOKUP(M23,价值表!$C:$C,价值表!$F:$F)*N23 -> 280 | Q23: =SUM($J$17:P23)/680 -> 6.9078782
B24: 咩菲特的雕像 | C24: 1 | D24: ="[{"&_xlfn.XLOOKUP(B24,价值表!$C:$C,价值表!$D:$D)&","&C24&"}]" -> [{5800004,1}] | E24: =_xlfn.XLOOKUP(B24,价值表!$C:$C,价值表!$F:$F)*C24 -> 30 | G24: 梦境招募器 | H24: 5 | I24: ="[{"&_xlfn.XLOOKUP(G24,价值表!$C:$C,价值表!$D:$D)&","&H24&"}]" -> [{11,5}] | J24: =_xlfn.XLOOKUP(G24,价值表!$C:$C,价值表!$F:$F)*H24 -> 150 | K24: =SUM($J$17:J24)/250 | M24: 星辉秘契 | N24: 1 | O24: ="[{"&_xlfn.XLOOKUP(M24,价值表!$C:$C,价值表!$D:$D)&","&N24&"}]" -> [{30,1}] | P24: =_xlfn.XLOOKUP(M24,价值表!$C:$C,价值表!$F:$F)*N24 -> 280 | Q24: =SUM($J$17:P24)/680 -> 7.5495798
B25: 星之初愿 | C25: 1 | D25: ="[{"&_xlfn.XLOOKUP(B25,价值表!$C:$C,价值表!$D:$D)&","&C25&"}]" -> [{9,1}] | E25: =_xlfn.XLOOKUP(B25,价值表!$C:$C,价值表!$F:$F)*C25 -> 50 | G25: 梦境招募器 | H25: 5 | I25: ="[{"&_xlfn.XLOOKUP(G25,价值表!$C:$C,价值表!$D:$D)&","&H25&"}]" -> [{11,5}] | J25: =_xlfn.XLOOKUP(G25,价值表!$C:$C,价值表!$F:$F)*H25 -> 150 | K25: =SUM($J$17:J25)/250 | M25: 星辉秘契 | N25: 1 | O25: ="[{"&_xlfn.XLOOKUP(M25,价值表!$C:$C,价值表!$D:$D)&","&N25&"}]" -> [{30,1}] | P25: =_xlfn.XLOOKUP(M25,价值表!$C:$C,价值表!$F:$F)*N25 -> 280 | Q25: =SUM($J$17:P25)/680 -> 8.1920693
B26: 梦境招募器 | C26: 5 | D26: ="[{"&_xlfn.XLOOKUP(B26,价值表!$C:$C,价值表!$D:$D)&","&C26&"}]" -> [{11,5}] | E26: =_xlfn.XLOOKUP(B26,价值表!$C:$C,价值表!$F:$F)*C26 -> 150 | G26: 梦境招募器 | H26: 10 | I26: ="[{"&_xlfn.XLOOKUP(G26,价值表!$C:$C,价值表!$D:$D)&","&H26&"}]" -> [{11,10}] | J26: =_xlfn.XLOOKUP(G26,价值表!$C:$C,价值表!$F:$F)*H26 -> 300 | K26: =SUM($J$17:J26)/250 | M26: 星辉秘契 | N26: 2 | O26: ="[{"&_xlfn.XLOOKUP(M26,价值表!$C:$C,价值表!$D:$D)&","&N26&"}]" -> [{30,2}] | P26: =_xlfn.XLOOKUP(M26,价值表!$C:$C,价值表!$F:$F)*N26 -> 560 | Q26: =SUM($J$17:P26)/680 -> 9.469958
B27: 咩菲特的雕像 | C27: 1 | D27: ="[{"&_xlfn.XLOOKUP(B27,价值表!$C:$C,价值表!$D:$D)&","&C27&"}]" -> [{5800004,1}] | E27: =_xlfn.XLOOKUP(B27,价值表!$C:$C,价值表!$F:$F)*C27 -> 30 | G27: 梦境招募器 | H27: 5 | I27: ="[{"&_xlfn.XLOOKUP(G27,价值表!$C:$C,价值表!$D:$D)&","&H27&"}]" -> [{11,5}] | J27: =_xlfn.XLOOKUP(G27,价值表!$C:$C,价值表!$F:$F)*H27 -> 150 | K27: =SUM($J$17:J27)/250 | M27: 星辉秘契 | N27: 1 | O27: ="[{"&_xlfn.XLOOKUP(M27,价值表!$C:$C,价值表!$D:$D)&","&N27&"}]" -> [{30,1}] | P27: =_xlfn.XLOOKUP(M27,价值表!$C:$C,价值表!$F:$F)*N27 -> 280 | Q27: =SUM($J$17:P27)/680 -> 10.114811
B28: 能量特饮 | C28: 50 | D28: ="[{"&_xlfn.XLOOKUP(B28,价值表!$C:$C,价值表!$D:$D)&","&C28&"}]" -> [{5103001,50}] | E28: =_xlfn.XLOOKUP(B28,价值表!$C:$C,价值表!$F:$F)*C28 -> 50 | G28: 梦境招募器 | H28: 5 | I28: ="[{"&_xlfn.XLOOKUP(G28,价值表!$C:$C,价值表!$D:$D)&","&H28&"}]" -> [{11,5}] | J28: =_xlfn.XLOOKUP(G28,价值表!$C:$C,价值表!$F:$F)*H28 -> 150 | K28: =SUM($J$17:J28)/250 | M28: 星辉秘契 | N28: 1 | O28: ="[{"&_xlfn.XLOOKUP(M28,价值表!$C:$C,价值表!$D:$D)&","&N28&"}]" -> [{30,1}] | P28: =_xlfn.XLOOKUP(M28,价值表!$C:$C,价值表!$F:$F)*N28 -> 280 | Q28: =SUM($J$17:P28)/680 -> 10.760452
... B66: 星辉秘契 | C66: 2 | D66: ="[{"&_xlfn.XLOOKUP(B66,价值表!$C:$C,价值表!$D:$D)&","&C66&"}]" -> [{30,2}] | E66: =_xlfn.XLOOKUP(B66,价值表!$C:$C,价值表!$F:$F)*C66 -> 560 | G66: 梦境招募器 | H66: 10 | I66: ="[{"&_xlfn.XLOOKUP(G66,价值表!$C:$C,价值表!$D:$D)&","&H66&"}]" -> [{11,10}] | J66: =_xlfn.XLOOKUP(G66,价值表!$C:$C,价值表!$F:$F)*H66 -> 300 | K66: =SUM($J$17:J66)/250 | M66: 星辉秘契 | N66: 2 | O66: ="[{"&_xlfn.XLOOKUP(M66,价值表!$C:$C,价值表!$D:$D)&","&N66&"}]" -> [{30,2}] | P66: =_xlfn.XLOOKUP(M66,价值表!$C:$C,价值表!$F:$F)*N66 -> 560 | Q66: =SUM($J$17:P66)/680 -> 41.065756
B67: 总产出 | E67: =SUM(E17:E66) -> 3100 | J67: =SUM(J17:J66) -> 9150 | P67: =SUM(P17:P66) -> 17200

Sheet 钻石基金
C2: 道具 | D2: 数量 | E2: 活动性价比 | F2: 活动占比
C3: 钻石 | D3: =SUM(H12:H31) -> 10455 | E3: =_xlfn.XLOOKUP(C3,价值表!C:C,价值表!F:F)*D3/98/10 -> 10.668367
H8: 售价 | I8: 返利比 | P8: 售价 | Q8: 返利比 | U8: 钻石基金Ⅲ（type 205） | Z8: 售价 | AA8: 返利比
H9: 98 | I9: =I32/H9/10 -> 10.668367 | P9: 98 | Q9: =Q32/10/P9 -> 12.169388 | R9: =Q9/I9 -> 1.1406982 | Z9: 98 | AA9: =AA32/Z9/10
D10: 基础奖励 | G10: 高级奖励 | L10: 基础奖励 | O10: 高级奖励 | S10: =S32/I32 -> 1.0909613 | U10: 基础奖励 | Y10: 高级奖励
C11: 章节 | D11: 物品类型 | E11: 数量 | F11: 价值 | G11: 物品类型2 | H11: 数量2 | I11: 价值2 | K11: 章节 | L11: 物品类型 | M11: 数量 | N11: 价值 | O11: 物品类型2 | P11: 数量2 | Q11: 价值2 | S11: 蔚蓝参考 | U11: 章节 | V11: 物品类型 | W11: 数量 | X11: 价值 | Y11: 物品类型2 | Z11: 数量2 | AA11: 价值2
C12: 5 | D12: 金币 | E12: 500 | F12: =_xlfn.XLOOKUP(D12,价值表!$C:$C,价值表!$F:$F)*E12 -> 25 | G12: 钻石 | H12: 980 | I12: =_xlfn.XLOOKUP(G12,价值表!$C:$C,价值表!$F:$F)*H12 -> 980 | K12: 105 | L12: 金币 | M12: 700 | N12: =_xlfn.XLOOKUP(L12,价值表!$C:$C,价值表!$F:$F)*M12 -> 35 | O12: 钻石 | P12: 1080 | Q12: =_xlfn.XLOOKUP(O12,价值表!$C:$C,价值表!$F:$F)*P12 -> 1080 | S12: 980 | U12: 205 | V12: 金币 | W12: 800 | X12: =_xlfn.XLOOKUP(V12,价值表!$C:$C,价值表!$F:$F)*W12 | Y12: 钻石 | Z12: 1200 | AA12: =_xlfn.XLOOKUP(Y12,价值表!$C:$C,价值表!$F:$F)*Z12
C13: 10 | D13: 金币 | E13: 500 | F13: =_xlfn.XLOOKUP(D13,价值表!$C:$C,价值表!$F:$F)*E13 -> 25 | G13: 钻石 | H13: 150 | I13: =_xlfn.XLOOKUP(G13,价值表!$C:$C,价值表!$F:$F)*H13 -> 150 | K13: 110 | L13: 金币 | M13: 700 | N13: =_xlfn.XLOOKUP(L13,价值表!$C:$C,价值表!$F:$F)*M13 -> 35 | O13: 钻石 | P13: 160 | Q13: =_xlfn.XLOOKUP(O13,价值表!$C:$C,价值表!$F:$F)*P13 -> 160 | S13: 160 | U13: 210 | V13: 金币 | W13: 800 | X13: =_xlfn.XLOOKUP(V13,价值表!$C:$C,价值表!$F:$F)*W13 | Y13: 钻石 | Z13: 180 | AA13: =_xlfn.XLOOKUP(Y13,价值表!$C:$C,价值表!$F:$F)*Z13
C14: 15 | D14: 金币 | E14: 500 | F14: =_xlfn.XLOOKUP(D14,价值表!$C:$C,价值表!$F:$F)*E14 -> 25 | G14: 钻石 | H14: 150 | I14: =_xlfn.XLOOKUP(G14,价值表!$C:$C,价值表!$F:$F)*H14 -> 150 | K14: 115 | L14: 金币 | M14: 700 | N14: =_xlfn.XLOOKUP(L14,价值表!$C:$C,价值表!$F:$F)*M14 -> 35 | O14: 钻石 | P14: 160 | Q14: =_xlfn.XLOOKUP(O14,价值表!$C:$C,价值表!$F:$F)*P14 -> 160 | S14: 160 | U14: 215 | V14: 金币 | W14: 800 | X14: =_xlfn.XLOOKUP(V14,价值表!$C:$C,价值表!$F:$F)*W14 | Y14: 钻石 | Z14: 180 | AA14: =_xlfn.XLOOKUP(Y14,价值表!$C:$C,价值表!$F:$F)*Z14
C15: 20 | D15: 金币 | E15: 500 | F15: =_xlfn.XLOOKUP(D15,价值表!$C:$C,价值表!$F:$F)*E15 -> 25 | G15: 钻石 | H15: 150 | I15: =_xlfn.XLOOKUP(G15,价值表!$C:$C,价值表!$F:$F)*H15 -> 150 | K15: 120 | L15: 金币 | M15: 700 | N15: =_xlfn.XLOOKUP(L15,价值表!$C:$C,价值表!$F:$F)*M15 -> 35 | O15: 钻石 | P15: 160 | Q15: =_xlfn.XLOOKUP(O15,价值表!$C:$C,价值表!$F:$F)*P15 -> 160 | S15: 160 | U15: 220 | V15: 金币 | W15: 800 | X15: =_xlfn.XLOOKUP(V15,价值表!$C:$C,价值表!$F:$F)*W15 | Y15: 钻石 | Z15: 180 | AA15: =_xlfn.XLOOKUP(Y15,价值表!$C:$C,价值表!$F:$F)*Z15
C16: 25 | D16: 钻石 | E16: 50 | F16: =_xlfn.XLOOKUP(D16,价值表!$C:$C,价值表!$F:$F)*E16 -> 50 | G16: 钻石 | H16: 1080 | I16: =_xlfn.XLOOKUP(G16,价值表!$C:$C,价值表!$F:$F)*H16 -> 1080 | K16: 125 | L16: 钻石 | M16: 70 | N16: =_xlfn.XLOOKUP(L16,价值表!$C:$C,价值表!$F:$F)*M16 -> 70 | O16: 钻石 | P16: 1280 | Q16: =_xlfn.XLOOKUP(O16,价值表!$C:$C,价值表!$F:$F)*P16 -> 1280 | S16: 1280 | U16: 225 | V16: 钻石 | W16: 80 | X16: =_xlfn.XLOOKUP(V16,价值表!$C:$C,价值表!$F:$F)*W16 | Y16: 钻石 | Z16: 1400 | AA16: =_xlfn.XLOOKUP(Y16,价值表!$C:$C,价值表!$F:$F)*Z16
C17: 30 | D17: 金币 | E17: 1000 | F17: =_xlfn.XLOOKUP(D17,价值表!$C:$C,价值表!$F:$F)*E17 -> 50 | G17: 钻石 | H17: 200 | I17: =_xlfn.XLOOKUP(G17,价值表!$C:$C,价值表!$F:$F)*H17 -> 200 | K17: 130 | L17: 金币 | M17: 1200 | N17: =_xlfn.XLOOKUP(L17,价值表!$C:$C,价值表!$F:$F)*M17 -> 60 | O17: 钻石 | P17: 220 | Q17: =_xlfn.XLOOKUP(O17,价值表!$C:$C,价值表!$F:$F)*P17 -> 220 | S17: 210 | U17: 230 | V17: 金币 | W17: 1300 | X17: =_xlfn.XLOOKUP(V17,价值表!$C:$C,价值表!$F:$F)*W17 | Y17: 钻石 | Z17: 250 | AA17: =_xlfn.XLOOKUP(Y17,价值表!$C:$C,价值表!$F:$F)*Z17
C18: 35 | D18: 金币 | E18: 1000 | F18: =_xlfn.XLOOKUP(D18,价值表!$C:$C,价值表!$F:$F)*E18 -> 50 | G18: 钻石 | H18: 200 | I18: =_xlfn.XLOOKUP(G18,价值表!$C:$C,价值表!$F:$F)*H18 -> 200 | K18: 135 | L18: 金币 | M18: 1200 | N18: =_xlfn.XLOOKUP(L18,价值表!$C:$C,价值表!$F:$F)*M18 -> 60 | O18: 钻石 | P18: 220 | Q18: =_xlfn.XLOOKUP(O18,价值表!$C:$C,价值表!$F:$F)*P18 -> 220 | S18: 210 | U18: 235 | V18: 金币 | W18: 1300 | X18: =_xlfn.XLOOKUP(V18,价值表!$C:$C,价值表!$F:$F)*W18 | Y18: 钻石 | Z18: 250 | AA18: =_xlfn.XLOOKUP(Y18,价值表!$C:$C,价值表!$F:$F)*Z18
C19: 40 | D19: 金币 | E19: 1000 | F19: =_xlfn.XLOOKUP(D19,价值表!$C:$C,价值表!$F:$F)*E19 -> 50 | G19: 钻石 | H19: 200 | I19: =_xlfn.XLOOKUP(G19,价值表!$C:$C,价值表!$F:$F)*H19 -> 200 | K19: 140 | L19: 金币 | M19: 1200 | N19: =_xlfn.XLOOKUP(L19,价值表!$C:$C,价值表!$F:$F)*M19 -> 60 | O19: 钻石 | P19: 220 | Q19: =_xlfn.XLOOKUP(O19,价值表!$C:$C,价值表!$F:$F)*P19 -> 220 | S19: 210 | U19: 240 | V19: 金币 | W19: 1300 | X19: =_xlfn.XLOOKUP(V19,价值表!$C:$C,价值表!$F:$F)*W19 | Y19: 钻石 | Z19: 250 | AA19: =_xlfn.XLOOKUP(Y19,价值表!$C:$C,价值表!$F:$F)*Z19
C20: 45 | D20: 金币 | E20: 1000 | F20: =_xlfn.XLOOKUP(D20,价值表!$C:$C,价值表!$F:$F)*E20 -> 50 | G20: 钻石 | H20: 200 | I20: =_xlfn.XLOOKUP(G20,价值表!$C:$C,价值表!$F:$F)*H20 -> 200 | K20: 145 | L20: 金币 | M20: 1200 | N20: =_xlfn.XLOOKUP(L20,价值表!$C:$C,价值表!$F:$F)*M20 -> 60 | O20: 钻石 | P20: 220 | Q20: =_xlfn.XLOOKUP(O20,价值表!$C:$C,价值表!$F:$F)*P20 -> 220 | S20: 210 | U20: 245 | V20: 金币 | W20: 1300 | X20: =_xlfn.XLOOKUP(V20,价值表!$C:$C,价值表!$F:$F)*W20 | Y20: 钻石 | Z20: 250 | AA20: =_xlfn.XLOOKUP(Y20,价值表!$C:$C,价值表!$F:$F)*Z20
C21: 50 | D21: 钻石 | E21: 100 | F21: =_xlfn.XLOOKUP(D21,价值表!$C:$C,价值表!$F:$F)*E21 -> 100 | G21: 钻石 | H21: 1280 | I21: =_xlfn.XLOOKUP(G21,价值表!$C:$C,价值表!$F:$F)*H21 -> 1280 | K21: 150 | L21: 钻石 | M21: 120 | N21: =_xlfn.XLOOKUP(L21,价值表!$C:$C,价值表!$F:$F)*M21 -> 120 | O21: 钻石 | P21: 1580 | Q21: =_xlfn.XLOOKUP(O21,价值表!$C:$C,价值表!$F:$F)*P21 -> 1580 | S21: 1480 | U21: 250 | V21: 钻石 | W21: 130 | X21: =_xlfn.XLOOKUP(V21,价值表!$C:$C,价值表!$F:$F)*W21 | Y21: 钻石 | Z21: 1688 | AA21: =_xlfn.XLOOKUP(Y21,价值表!$C:$C,价值表!$F:$F)*Z21
C22: 55 | D22: 金币 | E22: 1500 | F22: =_xlfn.XLOOKUP(D22,价值表!$C:$C,价值表!$F:$F)*E22 -> 75 | G22: 钻石 | H22: 240 | I22: =_xlfn.XLOOKUP(G22,价值表!$C:$C,价值表!$F:$F)*H22 -> 240 | K22: 155 | L22: 金币 | M22: 1700 | N22: =_xlfn.XLOOKUP(L22,价值表!$C:$C,价值表!$F:$F)*M22 -> 85 | O22: 钻石 | P22: 260 | Q22: =_xlfn.XLOOKUP(O22,价值表!$C:$C,价值表!$F:$F)*P22 -> 260 | S22: 250 | U22: 255 | V22: 金币 | W22: 1800 | X22: =_xlfn.XLOOKUP(V22,价值表!$C:$C,价值表!$F:$F)*W22 | Y22: 钻石 | Z22: 280 | AA22: =_xlfn.XLOOKUP(Y22,价值表!$C:$C,价值表!$F:$F)*Z22
C23: 60 | D23: 金币 | E23: 1500 | F23: =_xlfn.XLOOKUP(D23,价值表!$C:$C,价值表!$F:$F)*E23 -> 75 | G23: 钻石 | H23: 240 | I23: =_xlfn.XLOOKUP(G23,价值表!$C:$C,价值表!$F:$F)*H23 -> 240 | K23: 160 | L23: 金币 | M23: 1700 | N23: =_xlfn.XLOOKUP(L23,价值表!$C:$C,价值表!$F:$F)*M23 -> 85 | O23: 钻石 | P23: 260 | Q23: =_xlfn.XLOOKUP(O23,价值表!$C:$C,价值表!$F:$F)*P23 -> 260 | S23: 250 | U23: 260 | V23: 金币 | W23: 1800 | X23: =_xlfn.XLOOKUP(V23,价值表!$C:$C,价值表!$F:$F)*W23 | Y23: 钻石 | Z23: 280 | AA23: =_xlfn.XLOOKUP(Y23,价值表!$C:$C,价值表!$F:$F)*Z23
... C31: 100 | D31: 钻石 | E31: 200 | F31: =_xlfn.XLOOKUP(D31,价值表!$C:$C,价值表!$F:$F)*E31 -> 200 | G31: 钻石 | H31: 2025 | I31: =_xlfn.XLOOKUP(G31,价值表!$C:$C,价值表!$F:$F)*H31 -> 2025 | K31: 200 | L31: 钻石 | M31: 220 | N31: =_xlfn.XLOOKUP(L31,价值表!$C:$C,价值表!$F:$F)*M31 -> 220 | O31: 钻石 | P31: 2326 | Q31: =_xlfn.XLOOKUP(O31,价值表!$C:$C,价值表!$F:$F)*P31 -> 2326 | S31: 2226 | U31: 300 | V31: 钻石 | W31: 250 | X31: =_xlfn.XLOOKUP(V31,价值表!$C:$C,价值表!$F:$F)*W31 | Y31: 钻石 | Z31: 2600 | AA31: =_xlfn.XLOOKUP(Y31,价值表!$C:$C,价值表!$F:$F)*Z31
I32: =SUM(I12:I31) -> 10455 | Q32: =SUM(Q12:Q31) -> 11926 | S32: =SUM(S12:S31) -> 11406 | AA32: =SUM(AA12:AA31)
C39: 关卡条件 | D39: 预期抽数 | E39: 钻石 | F39: 抽卡进度 | H39: 主线章节 | I39: 已通关玩家数 | J39: 首通时对应累抽数 | M39: 首通时对应基因进度 | P39: 首通时对应主角等级
C40: 4 | D40: =_xlfn.XLOOKUP(C40,$H$41:$H$117,$K$41:$K$117) -> 30 | E40: 980 | F40: =OFFSET(#REF!,D40,0) -> #REF! | J40: 中位数 | K40: 前25分位 | L40: 极值 | M40: 中位数 | N40: 前25分位 | O40: 极值 | P40: 中位数 | Q40: 前25分位 | R40: 极值
C41: 8 | D41: =_xlfn.XLOOKUP(C41,$H$41:$H$117,$K$41:$K$117) -> 123 | E41: 240 | F41: =OFFSET(#REF!,D41,0) -> #REF! | H41: 1 | I41: 7263 | J41: 0 | K41: 0 | L41: 0 | M41: 0 | N41: 0 | O41: 0 | P41: 1 | Q41: 1 | R41: 4
C42: 12 | D42: =_xlfn.XLOOKUP(C42,$H$41:$H$117,$K$41:$K$117) -> 270 | E42: 240 | F42: =OFFSET(#REF!,D42,0) -> #REF! | H42: 2 | I42: 6556 | J42: 0 | K42: 0 | L42: 0 | M42: 0 | N42: 0 | O42: 0 | P42: 2 | Q42: 2 | R42: 4
C43: 16 | D43: =_xlfn.XLOOKUP(C43,$H$41:$H$117,$K$41:$K$117) -> 491 | E43: 240 | F43: =OFFSET(#REF!,D43,0) -> #REF! | H43: 3 | I43: 6020 | J43: 10 | K43: 10 | L43: 50 | M43: 0 | N43: 0 | O43: 0 | P43: 3 | Q43: 4 | R43: 6
C44: 20 | D44: =_xlfn.XLOOKUP(C44,$H$41:$H$117,$K$41:$K$117) -> 650 | E44: 240 | F44: =OFFSET(#REF!,D44,0) -> #REF! | H44: 4 | I44: 5350 | J44: 20 | K44: 30 | L44: 90 | M44: 0 | N44: 0 | O44: 0 | P44: 4 | Q44: 4 | R44: 8
C45: 24 | D45: =_xlfn.XLOOKUP(C45,$H$41:$H$117,$K$41:$K$117) -> 794 | E45: 1280 | F45: =OFFSET(#REF!,D45,0) -> #REF! | H45: 5 | I45: 4721 | J45: 31 | K45: 40 | L45: 230 | M45: 0 | N45: 0 | O45: 0 | P45: 5 | Q45: 6 | R45: 12
C46: 28 | D46: =_xlfn.XLOOKUP(C46,$H$41:$H$117,$K$41:$K$117) -> 957 | E46: 280 | F46: =OFFSET(#REF!,D46,0) -> #REF! | H46: 6 | I46: 4405 | J46: 60 | K46: 80 | L46: 230 | M46: 0 | N46: 0 | O46: 0 | P46: 6 | Q46: 7 | R46: 15
C47: 32 | D47: =_xlfn.XLOOKUP(C47,$H$41:$H$117,$K$41:$K$117) -> 1140 | E47: 280 | F47: =OFFSET(#REF!,D47,0) -> #REF! | H47: 7 | I47: 4123 | J47: 80 | K47: 100 | L47: 380 | M47: 0 | N47: 0 | O47: 1 | P47: 7 | Q47: 8 | R47: 16
C48: 36 | D48: =_xlfn.XLOOKUP(C48,$H$41:$H$117,$K$41:$K$117) -> 1356 | E48: 280 | F48: =OFFSET(#REF!,D48,0) -> #REF! | H48: 8 | I48: 3918 | J48: 100 | K48: 123 | L48: 380 | M48: 1 | N48: 1 | O48: 2 | P48: 7 | Q48: 8 | R48: 22
C49: 40 | D49: =_xlfn.XLOOKUP(C49,$H$41:$H$117,$K$41:$K$117) -> 1540 | E49: 280 | F49: =OFFSET(#REF!,D49,0) -> #REF! | H49: 9 | I49: 3698 | J49: 130 | K49: 160 | L49: 583 | M49: 1 | N49: 2 | O49: 2 | P49: 8 | Q49: 9 | R49: 23
C50: 44 | D50: =_xlfn.XLOOKUP(C50,$H$41:$H$117,$K$41:$K$117) -> 1790 | E50: 280 | F50: =OFFSET(#REF!,D50,0) -> #REF! | H50: 10 | I50: 3551 | J50: 160 | K50: 190 | L50: 583 | M50: 2 | N50: 2 | O50: 2 | P50: 9 | Q50: 10 | R50: 23
C51: 48 | D51: =_xlfn.XLOOKUP(C51,$H$41:$H$117,$K$41:$K$117) -> 2139 | E51: 1380 | F51: =OFFSET(#REF!,D51,0) -> #REF! | H51: 11 | I51: 3338 | J51: 200 | K51: 240 | L51: 1530 | M51: 2 | N51: 2 | O51: 3 | P51: 10 | Q51: 11 | R51: 25
C52: 52 | D52: =_xlfn.XLOOKUP(C52,$H$41:$H$117,$K$41:$K$117) -> 2503 | E52: 320 | F52: =OFFSET(#REF!,D52,0) -> #REF! | H52: 12 | I52: 3261 | J52: 220 | K52: 270 | L52: 1560 | M52: 2 | N52: 2 | O52: 3 | P52: 10 | Q52: 11 | R52: 25
... C64: 100 | D64: =_xlfn.XLOOKUP(C64,$H$41:$H$117,$K$41:$K$117) -> #N/A | E64: 2025 | F64: =OFFSET(#REF!,D64,0) -> #REF! | H64: 24 | I64: 2042 | J64: 700 | K64: 794 | L64: 2048 | M64: 4 | N64: 4 | O64: 5 | P64: 17 | Q64: 18 | R64: 29
H65: 25 | I65: 1951 | J65: 753 | K65: 840 | L65: 2288 | M65: 4 | N65: 5 | O65: 5 | P65: 18 | Q65: 19 | R65: 30
H66: 26 | I66: 1885 | J66: 780 | K66: 877 | L66: 2988 | M66: 4 | N66: 5 | O66: 6 | P66: 18 | Q66: 19 | R66: 30
H67: 27 | I67: 1833 | J67: 808 | K67: 920 | L67: 3257 | M67: 5 | N67: 5 | O67: 6 | P67: 19 | Q67: 20 | R67: 30
H68: 28 | I68: 1772 | J68: 840 | K68: 957 | L68: 3257 | M68: 5 | N68: 5 | O68: 6 | P68: 19 | Q68: 20 | R68: 30
H69: 29 | I69: 1675 | J69: 870 | K69: 998 | L69: 3327 | M69: 5 | N69: 5 | O69: 6 | P69: 19 | Q69: 21 | R69: 31
H70: 30 | I70: 1589 | J70: 925 | K70: 1059 | L70: 3467 | M70: 5 | N70: 5 | O70: 6 | P70: 20 | Q70: 21 | R70: 33
H71: 31 | I71: 1486 | J71: 964 | K71: 1094 | L71: 3467 | M71: 5 | N71: 6 | O71: 7 | P71: 21 | Q71: 22 | R71: 33
H72: 32 | I72: 1329 | J72: 1035 | K72: 1140 | L72: 3547 | M72: 5 | N72: 6 | O72: 7 | P72: 21 | Q72: 23 | R72: 33
H73: 33 | I73: 1244 | J73: 1074 | K73: 1194 | L73: 2880 | M73: 6 | N73: 6 | O73: 7 | P73: 22 | Q73: 23 | R73: 32
H74: 34 | I74: 1140 | J74: 1140 | K74: 1258 | L74: 2890 | M74: 6 | N74: 6 | O74: 7 | P74: 23 | Q74: 24 | R74: 33
H75: 35 | I75: 972 | J75: 1240 | K75: 1332 | L75: 2900 | M75: 6 | N75: 7 | O75: 7 | P75: 24 | Q75: 25 | R75: 34
H76: 36 | I76: 911 | J76: 1260 | K76: 1356 | L76: 2900 | M76: 7 | N76: 7 | O76: 8 | P76: 24 | Q76: 26 | R76: 34
... H117: 77 | I117: 1 | J117: 6000 | K117: 6000 | L117: 6000 | M117: 13 | N117: 13 | O117: 13 | P117: 44 | Q117: 44 | R117: 44

Sheet 每日特惠
B2: 道具 | C2: 数量 | D2: 活动性价比 | E2: 活动占比
B3: 心梦宝石 | C3: {=SUMPRODUCT(--($D$12:$D$25=B3),$E$12:$E$25)} -> 24 | D3: =_xlfn.XLOOKUP(B3,价值表!C:C,价值表!F:F)*C3/25/10 -> 0.96
B4: 装备图纸 | C4: {=SUMPRODUCT(--($D$12:$D$25=B4),$E$12:$E$25)} -> 10 | D4: =_xlfn.XLOOKUP(B4,价值表!C:C,价值表!F:F)*C4/25/10 -> 0.12
B5: 体力 | C5: {=SUMPRODUCT(--($D$12:$D$25=B5),$E$12:$E$25)} -> 50 | D5: =_xlfn.XLOOKUP(B5,价值表!C:C,价值表!F:F)*C5/25/10 -> 0.4
B6: 梦境招募器 | C6: {=SUMPRODUCT(--($D$12:$D$25=B6),$E$12:$E$25)} -> 15 | D6: =_xlfn.XLOOKUP(B6,价值表!C:C,价值表!F:F)*C6/25/10 -> 1.8
B7: 每日特惠宝箱 | C7: {=SUMPRODUCT(--($D$12:$D$25=B7),$E$12:$E$25)} -> 6 | D7: =_xlfn.XLOOKUP(B7,价值表!C:C,价值表!F:F)*C7/25/10 -> 0.96
B8: 星辉秘契 | C8: {=SUMPRODUCT(--($D$12:$D$25=B8),$E$12:$E$25)} -> 2 | D8: =_xlfn.XLOOKUP(B8,价值表!C:C,价值表!F:F)*C8/25/10 -> 2.24
B11: 礼包内容 | C11: 道具ID | D11: 道具名 | E11: 数量 | F11: 价值 | G11: 价格 | H11: 性价比
B12: 免费礼包 | C12: 44 | D12: =_xlfn.XLOOKUP(C12,价值表!D:D,价值表!C:C) -> 心梦宝石 | E12: 1 | F12: =_xlfn.XLOOKUP(C12,价值表!D:D,价值表!F:F)*E12 -> 10
C13: 50002 | D13: =_xlfn.XLOOKUP(C13,价值表!D:D,价值表!C:C) -> 装备图纸 | E13: 10 | F13: =_xlfn.XLOOKUP(C13,价值表!D:D,价值表!F:F)*E13 -> 30
B14: 1元礼包 | C14: 44 | D14: =_xlfn.XLOOKUP(C14,价值表!D:D,价值表!C:C) -> 心梦宝石 | E14: 2 | F14: =_xlfn.XLOOKUP(C14,价值表!D:D,价值表!F:F)*E14 -> 20 | G14: 10 | H14: =SUM(F14:F17)/G14 -> 23
C15: 13 | D15: =_xlfn.XLOOKUP(C15,价值表!D:D,价值表!C:C) -> 体力 | E15: 10 | F15: =_xlfn.XLOOKUP(C15,价值表!D:D,价值表!F:F)*E15 -> 20
C16: 11 | D16: =_xlfn.XLOOKUP(C16,价值表!D:D,价值表!C:C) -> 梦境招募器 | E16: 5 | F16: =_xlfn.XLOOKUP(C16,价值表!D:D,价值表!F:F)*E16 -> 150
C17: 20038 | D17: =_xlfn.XLOOKUP(C17,价值表!D:D,价值表!C:C) -> 每日特惠宝箱 | E17: 1 | F17: =_xlfn.XLOOKUP(C17,价值表!D:D,价值表!F:F)*E17 -> 40
B18: 6元礼包 | C18: 44 | D18: =_xlfn.XLOOKUP(C18,价值表!D:D,价值表!C:C) -> 心梦宝石 | E18: 6 | F18: =_xlfn.XLOOKUP(C18,价值表!D:D,价值表!F:F)*E18 -> 60 | G18: 60 | H18: =SUM(F18:F21)/G18 -> 7.8333333
C19: 13 | D19: =_xlfn.XLOOKUP(C19,价值表!D:D,价值表!C:C) -> 体力 | E19: 15 | F19: =_xlfn.XLOOKUP(C19,价值表!D:D,价值表!F:F)*E19 -> 30
C20: 11 | D20: =_xlfn.XLOOKUP(C20,价值表!D:D,价值表!C:C) -> 梦境招募器 | E20: 15 | F20: =_xlfn.XLOOKUP(C20,价值表!D:D,价值表!F:F)*E20 -> 300
C21: 20038 | D21: =_xlfn.XLOOKUP(C21,价值表!D:D,价值表!C:C) -> 每日特惠宝箱 | E21: 2 | F21: =_xlfn.XLOOKUP(C21,价值表!D:D,价值表!F:F)*E21 -> 80
B22: 18元礼包 | C22: 44 | D22: =_xlfn.XLOOKUP(C22,价值表!D:D,价值表!C:C) -> 心梦宝石 | E22: 15 | F22: =_xlfn.XLOOKUP(C22,价值表!D:D,价值表!F:F)*E22 -> 150 | G22: 180 | H22: =SUM(F22:F25)/G22 -> 4.8888889
C23: 13 | D23: =_xlfn.XLOOKUP(C23,价值表!D:D,价值表!C:C) -> 体力 | E23: 25 | F23: =_xlfn.XLOOKUP(C23,价值表!D:D,价值表!F:F)*E23 -> 50
C24: 30 | D24: =_xlfn.XLOOKUP(C24,价值表!D:D,价值表!C:C) -> 星辉秘契 | E24: 2 | F24: =_xlfn.XLOOKUP(C24,价值表!D:D,价值表!F:F)*E24 -> 560
C25: 20038 | D25: =_xlfn.XLOOKUP(C25,价值表!D:D,价值表!C:C) -> 每日特惠宝箱 | E25: 3 | F25: =_xlfn.XLOOKUP(C25,价值表!D:D,价值表!F:F)*E25 -> 120

Sheet 章节礼包
B2: 道具 | C2: 数量
B3: 能量特饮 | C3: {=SUMPRODUCT(OFFSET($I$13:$I$22,0,MATCH(B3,$B$3:$B$9,0)))} -> 6000
B4: 幻梦晶核 | C4: {=SUMPRODUCT(OFFSET($I$13:$I$22,0,MATCH(B4,$B$3:$B$9,0)))} -> 42
B5: 装备图纸 | C5: {=SUMPRODUCT(OFFSET($I$13:$I$22,0,MATCH(B5,$B$3:$B$9,0)))} -> 3890
B6: 梦境招募器 | C6: {=SUMPRODUCT(OFFSET($I$13:$I$22,0,MATCH(B6,$B$3:$B$9,0)))} -> 260
B7: 星辉秘契 | C7: {=SUMPRODUCT(OFFSET($I$13:$I$22,0,MATCH(B7,$B$3:$B$9,0)))} -> 20
B8: 传说符文 | C8: {=SUMPRODUCT(OFFSET($I$13:$I$22,0,MATCH(B8,$B$3:$B$9,0)))} -> 3
B9: 神话符文 | C9: {=SUMPRODUCT(OFFSET($I$13:$I$22,0,MATCH(B9,$B$3:$B$9,0)))} -> 1
J12: =_xlfn.XLOOKUP(J13,价值表!$C:$C,价值表!$F:$F) -> 1 | K12: =_xlfn.XLOOKUP(K13,价值表!$C:$C,价值表!$F:$F) -> 60 | L12: =_xlfn.XLOOKUP(L13,价值表!$C:$C,价值表!$F:$F) -> 3 | M12: =_xlfn.XLOOKUP(M13,价值表!$C:$C,价值表!$F:$F) -> 30 | N12: =_xlfn.XLOOKUP(N13,价值表!$C:$C,价值表!$F:$F) -> 280 | O12: =_xlfn.XLOOKUP(O13,价值表!$C:$C,价值表!$F:$F) -> 4096 | P12: =_xlfn.XLOOKUP(P13,价值表!$C:$C,价值表!$F:$F) -> 16384 | Q12: 性价比
B13: 礼包id | C13: 礼包类型 | D13: 购买消耗 | E13: 描述 | F13: 超值数值 | G13: 触发条件 | H13: 奖励列表 | J13: 能量特饮 | K13: 幻梦晶核 | L13: 装备图纸 | M13: 梦境招募器 | N13: 星辉秘契 | O13: 传说符文 | P13: 神话符文
B14: 1001 | C14: 钻石 | D14: [{1,680}] | E14: 第5章礼包 | F14: 400 | G14: 4 | H14: [{11,30},{5104001,400},{50026,120}] | I14: 680 | J14: 400 | L14: 120 | M14: 30 | Q14: {=SUMPRODUCT(J14:P14,$J$12:$P$12)/I14} -> 2.4411765
B15: 1002 | C15: 钻石 | D15: [{1,980}] | E15: 第8章礼包 | F15: 400 | G15: 7 | H15: [{100009,1},{5104001,600},{50026,200}] | I15: 980 | J15: 600 | L15: 200 | Q15: {=(SUMPRODUCT(J15:P15,$J$12:$P$12)+980)/I15} -> 2.2244898
B16: 1003 | C16: 钻石 | D16: [{1,980}] | E16: 第10章礼包 | F16: 400 | G16: 9 | H16: [{11,50},{5104001,800},{50026,240}] | I16: 980 | J16: 800 | L16: 240 | M16: 50 | Q16: {=SUMPRODUCT(J16:P16,$J$12:$P$12)/I16} -> 3.0816327
B17: 1004 | C17: 钻石 | D17: [{1,1280}] | E17: 第15章礼包 | F17: 400 | G17: 14 | H17: [{11,80},{5104001,1000},{50026,280}] | I17: 1280 | J17: 1000 | L17: 280 | M17: 80 | Q17: {=SUMPRODUCT(J17:P17,$J$12:$P$12)/I17} -> 3.3125
B18: 1005 | C18: 钻石 | D18: [{1,1680}] | E18: 第20章礼包 | F18: 400 | G18: 19 | H18: [{11,100},{5104001,1200},{50026,350}] | I18: 1680 | J18: 1200 | L18: 350 | M18: 100 | Q18: {=SUMPRODUCT(J18:P18,$J$12:$P$12)/I18} -> 3.125
B19: 1006 | C19: 钻石 | D19: [{1,1800}] | E19: 第24章礼包 | F19: 400 | G19: 23 | H19: [{30,20},{5305001,6},{50026,400}] | I19: 1800 | K19: 6 | L19: 400 | N19: 20 | Q19: {=SUMPRODUCT(J19:P19,$J$12:$P$12)/I19} -> 3.9777778
B20: 1007 | C20: 钻石 | D20: [{1,1980}] | E20: 第28章礼包 | F20: 300 | G20: 27 | H20: [{5305000,1},{5305001,12},{50026,500}] | I20: 1980 | K20: 12 | L20: 500 | O20: 1 | Q20: {=SUMPRODUCT(J20:P20,$J$12:$P$12)/I20} -> 3.189899
B21: 1008 | C21: 钻石 | D21: [{1,3280}] | E21: 第32章礼包 | F21: 300 | G21: 31 | H21: [{5305000,2},{5305001,24},{50026,600}] | I21: 3280 | K21: 24 | L21: 600 | O21: 2 | Q21: {=SUMPRODUCT(J21:P21,$J$12:$P$12)/I21} -> 3.4853659
B22: 1009 | C22: 钻石 | D22: [{1,6480}] | E22: 第36章礼包 | F22: 300 | G22: 35 | H22: [{5306000,1},{5104001,2000},{50026,1200}] | I22: 6480 | J22: 2000 | L22: 1200 | P22: 1 | Q22: {=SUMPRODUCT(J22:P22,$J$12:$P$12)/I22} -> 3.3925926

Sheet 红卡皮肤转盘
D3: 抽卡道具 | E3: 祈福石
D4: 祈福石价值 | E4: 120 | F4: 钻石 | O4: 自选传说梦灵皮肤
D5: 单抽价值 | E5: 246.12782 | Q5: 20~22天 | R5: 主角时装
D6: 单抽返利比 | E6: 1.26 | R6: 主角武器
D7: 单轮抽奖时，X抽有对应的消耗数值。第1抽消耗1个抽卡道具，第3抽消耗2个抽卡道具 | L7: 自选宝箱 | P7: 100042 | Q7: 试炼宝箱
L8: 物品 | M8: 数量 | N8: 价值 | Q8: 物品 | R8: 数量 | S8: 价值 | T8: 权重 | U8: 前N次必不出
C9: 层数 | D9: 物品 | E9: 数量 | F9: 价值 | G9: 权重 | H9: 前N次必不出 | K9: 5600109 | L9: 神话梦灵碎片 | M9: 60 | N9: 2880 | Q9: 随机神话梦灵皮肤 | R9: 1 | S9: 8000 | T9: 300 | V9: 30
C10: 第一层 | D10: 试炼宝箱 | E10: 1 | F10: 7142.8571 | G10: 20 | H10: 7 | K10: 100018 | L10: 自选传说梦灵皮肤 | M10: 1 | N10: 4000 | Q10: 随机神话梦灵皮肤 | R10: 1 | S10: 8000 | T10: 30 | Y10: 随机神话梦灵皮肤 | Z10: 4 | AA10: 32000
B11: （后羿、诸葛、海拉） | C11: 第二层 | D11: 随机神话梦灵 | E11: 1 | F11: 480 | G11: 80 | K11: 5305001 | L11: 幻梦晶核 | M11: 60 | N11: 3600 | Q11: 随机神话梦灵皮肤 | R11: 1 | S11: 8000 | T11: 30 | Y11: 自选宝箱 | Z11: 1 | AA11: 4000
D12: 梦境招募器 | E12: 15 | F12: 450 | G12: 120 | K12: 11 | L12: 梦境招募器 | M12: 100 | N12: 3000 | Q12: 随机神话梦灵皮肤 | R12: 1 | S12: 8000 | T12: 30 | Y12: 自选传说秘宝皮肤 | Z12: 1 | AA12: 4000
C13: 第三层 | D13: 幻梦晶核 | E13: 6 | F13: 360 | G13: 160 | K13: 5505009 | L13: 玉如意 | M13: 1 | N13: 4000 | Q13: 自选宝箱 | R13: 1 | S13: 4000 | T13: 400 | Y13: 自选神话梦灵皮肤 | Z13: 1 | AA13: 8000
D14: 星之初愿 | E14: 5 | F14: 250 | G14: 170 | P14: 自选 | Q14: 自选传说秘宝皮肤 | R14: 1 | S14: 6000 | T14: 200 | Y14: 神话梦灵 | Z14: 7 | AA14: 3360
D15: 体力 | E15: 60 | F15: 120 | G15: 290 | P15: 自选 | Q15: 自选神话梦灵皮肤 | R15: 1 | S15: 8000 | T15: 10 | U15: 4 | Y15: 梦境招募器 | Z15: 105 | AA15: 3150
C16: 第四层 | D16: 超能特饮 | E16: 100 | F16: 200 | G16: 290 | L16: 神话梦灵碎片 | M16: 权重一样 | Q16: 神话梦灵 | R16: 7 | S16: 7142.8571 | T16: 1000 | Y16: 幻梦晶核 | Z16: 42 | AA16: 2520
D17: 装备图纸 | E17: 50 | F17: 150 | G17: 290 | M17: 后羿 | Q17: 梦境招募器 | R17: 105 | Y17: 星之初愿 | Z17: 35 | AA17: 1750
D18: 转运石 | E18: 300 | F18: 100 | G18: 290 | M18: 诸葛 | Q18: 幻梦晶核 | R18: 42 | Y18: 体力 | Z18: 420 | AA18: 840
D19: 金币 | E19: 2000 | F19: 100 | G19: 290 | M19: 海拉 | Q19: 星之初愿 | R19: 35 | Y19: 超能特饮 | Z19: 700 | AA19: 1400
E20: 单轮总价值 | F20: 9352.8571 | G20: 2000 | Q20: 体力 | R20: 420 | Y20: 装备图纸 | Z20: 350 | AA20: 1050
E21: 单抽价值 | F21: 246.12782 | Q21: 超能特饮 | R21: 700 | Y21: 转运石 | Z21: 2100 | AA21: 700
B22: 注意 | C22: 保底内容：第四抽必定获得第二层奖励 | Q22: 装备图纸 | R22: 350 | Y22: 金币 | Z22: 14000 | AA22: 700
C23: 如果在1-3抽已经获得第二层奖励，则该判断该保底已经生效过，第四抽不生效 | Q23: 转运石 | R23: 2100
Q24: 金币 | R24: 14000 | AA24: 63470 | AB24: 52080
C25: 商店数值 | AB25: 1.218702
B28: 任务数值
C29: 仅统计活动期 | D29: 任务汇总 | E29: 10
C30: 刷新频率 | D30: 任务类型 | E30: 数量 | F30: 奖励内容 | G30: 奖励数量 | H30: 奖励价值 | L30: 红卡皮肤抽奖-划断
B31: 日常 | C31: 每日刷新 | D31: 每日登录游戏 | F31: 祈福石 | G31: 1 | H31: 120 | I31: 3 | L31: 1、开服天数≥20天的，开服时间为0318-0321，自然日：4.9-4.11开启
B32: 核心循环 | C32: 一次性 | D32: 竞技场挑战次数 | E32: 5 | F32: 祈福石 | G32: 1 | H32: 120 | L32: 2、开服天数＜20天的，开始时间在0322及以后的，开服20-22天开启
C33: 一次性 | D33: 竞技场挑战次数 | E33: 10 | F33: 祈福石 | G33: 1 | H33: 120
C34: 一次性 | D34: 竞技场挑战次数 | E34: 15 | F34: 祈福石 | G34: 1 | H34: 120
B35: 当期消耗 | C35: 一次性 | D35: 秘宝等级达到 | E35: 3 | F35: 祈福石 | G35: 1 | H35: 120
B36: 核心循环 | C36: 一次性 | D36: 合作本挑战 | E36: 5 | F36: 祈福石 | G36: 1 | H36: 120
C37: 一次性 | D37: 合作本挑战 | E37: 10 | F37: 祈福石 | G37: 1 | H37: 120
C38: 一次性 | D38: 合作本挑战 | E38: 15 | F38: 祈福石 | G38: 1 | H38: 120
B41: 商店数值
C42: 礼包名称 | D42: 价格（人民币） | E42: 限购次数 | F42: 物品类型 | G42: 数量 | H42: 价值 | I42: 物品类型 | J42: 数量 | K42: 价值 | L42: 总价值 | M42: 返利比
B43: 6 | C43: 12元礼包 | D43: 12 | E43: 3 | F43: 钻石 | G43: 120 | H43: 120 | I43: 祈福石 | J43: 5 | K43: 600 | L43: 720 | M43: 6 | N43: 0.17
B44: 10.5 | C44: 30元礼包 | D44: 30 | E44: 5 | F44: 钻石 | G44: 300 | H44: 300 | I44: 祈福石 | J44: 8 | K44: 960 | L44: 1260 | M44: 4.2 | N44: 0.24
B45: 23.166667 | C45: 98元礼包 | D45: 98 | E45: 5 | F45: 钻石 | G45: 980 | H45: 980 | I45: 祈福石 | J45: 15 | K45: 1800 | L45: 2780 | M45: 2.84 | N45: 0.35
J46: 130
F47: 186.33333 | J47: 676
C50: 随机传说梦灵皮肤 | D50: 自选传说秘宝皮肤 | E50: 自选传说梦灵皮肤 | F50: 随机神话梦灵皮肤 | G50: 随机神话梦灵皮肤 | H50: 随机神话梦灵皮肤 | I50: 随机神话梦灵皮肤
B51: 单轮第X抽 | C51: 第1轮 | D51: 第2轮 | E51: 第3轮 | F51: 第4轮 | G51: 第5轮 | H51: 第6轮 | I51: 第7轮
B52: 1 | C52: 1 | D52: 2 | E52: 3 | F52: 4 | G52: 5 | H52: 6 | I52: 7
B53: 2 | C53: 2 | D53: 3 | E53: 3 | F53: 4 | G53: 5 | H53: 6 | I53: 7
B54: 3 | C54: 2 | D54: 3 | E54: 4 | F54: 5 | G54: 6 | H54: 7 | I54: 8
B55: 4 | C55: 3 | D55: 4 | E55: 4 | F55: 5 | G55: 6 | H55: 7 | I55: 8
B56: 5 | C56: 3 | D56: 4 | E56: 5 | F56: 6 | G56: 7 | H56: 8 | I56: 8
B57: 6 | C57: 4 | D57: 5 | E57: 5 | F57: 6 | G57: 7 | H57: 8 | I57: 9
B58: 7 | C58: 5 | D58: 5 | E58: 6 | F58: 7 | G58: 8 | H58: 9 | I58: 9
B59: 8 | C59: 5 | D59: 6 | E59: 7 | F59: 8 | G59: 8 | H59: 9 | I59: 10
B60: 9 | C60: 6 | D60: 7 | E60: 8 | F60: 8 | G60: 9 | H60: 9 | I60: 10
B61: 10 | C61: 7 | D61: 7 | E61: 9 | F61: 9 | G61: 9 | H61: 9 | I61: 10
C62: 38 | D62: 46 | E62: 54 | F62: 62 | G62: 70 | H62: 78 | I62: 86 | J62: 434
C63: 4560 | D63: 5520 | E63: 6480 | F63: 7440 | G63: 8400 | H63: 9360 | I63: 10320
C64: 2.05 | D64: 1.69 | E64: 1.44 | F64: 1.26 | G64: 1.11 | H64: 1 | I64: 0.91
C68: 476

Sheet 1每日商店
B2: 设计预期
B3: 金币 | C3: 前7天小非R日均消耗8000~12000, 7天后日均16000~24000. 中大R日均16000, 7日后日均32000
E5: 1001 | F5: =E5+1000 -> 2001 | G5: =F5+1000 -> 3001 | H5: =G5+1000 -> 4001 | I5: =H5+1000 -> 5001 | J5: =I5+1000 -> 6001 | K5: 7002 | L5: 8001
B6: 天数 | C6: 非R | D6: 大R | E6: =_xlfn.XLOOKUP(E5,$C$30:$C$85,$E$30:$E$85) -> 梦境招募器 | F6: =_xlfn.XLOOKUP(F5,$C$30:$C$85,$E$30:$E$85) -> 星之初愿 | G6: =_xlfn.XLOOKUP(G5,$C$30:$C$85,$E$30:$E$85) -> 星辉秘契 | H6: =_xlfn.XLOOKUP(H5,$C$30:$C$85,$E$30:$E$85) -> 幻梦晶核 | I6: =_xlfn.XLOOKUP(I5,$C$30:$C$85,$E$30:$E$85) -> 装备图纸 | J6: =_xlfn.XLOOKUP(J5,$C$30:$C$85,$E$30:$E$85) -> 织梦微尘 | K6: =_xlfn.XLOOKUP(K5,$C$30:$C$85,$E$30:$E$85) -> 能量特饮 | L6: =_xlfn.XLOOKUP(L5,$C$30:$C$85,$E$30:$E$85) -> 稀有梦灵
B7: 1 | C7: =SUMIF($B$30:$B$86,$B7,N$30:N$86) -> 11400 | D7: =SUMIF($B$30:$B$86,$B7,O$30:O$86) -> 16640 | E7: 1001 | F7: 2001 | G7: 3001 | H7: 4001 | I7: 5001 | J7: 6001 | K7: 7002 | L7: 8001
B8: 2 | C8: =SUMIF($B$30:$B$86,$B8,N$30:N$86) -> 14160 | D8: =SUMIF($B$30:$B$86,$B8,O$30:O$86) -> 21936 | E8: 1001 | F8: 2001 | G8: 3001 | H8: 4001 | I8: 5002 | J8: 6001 | K8: 7002 | L8: 8001
B9: 3 | C9: =SUMIF($B$30:$B$86,$B9,N$30:N$86) -> 6600 | D9: =SUMIF($B$30:$B$86,$B9,O$30:O$86) -> 13520 | E9: 1001 | F9: 2001 | G9: 3001 | H9: 4001 | I9: 5002 | J9: 6002 | K9: 7002 | L9: 8001
B10: 4 | C10: =SUMIF($B$30:$B$86,$B10,N$30:N$86) -> 12600 | D10: =SUMIF($B$30:$B$86,$B10,O$30:O$86) -> 19320 | E10: 1002 | F10: 2001 | G10: 3001 | H10: 4001 | I10: 5002 | J10: 6002 | K10: 7003 | L10: 8001
B11: 5 | C11: =SUMIF($B$30:$B$86,$B11,N$30:N$86) -> 9960 | D11: =SUMIF($B$30:$B$86,$B11,O$30:O$86) -> 21696 | E11: 1002 | F11: 2001 | G11: 3001 | H11: 4001 | I11: 5002 | J11: 6003 | K11: 7003 | L11: 8001
B12: 6 | C12: =SUMIF($B$30:$B$86,$B12,N$30:N$86) -> 12360 | D12: =SUMIF($B$30:$B$86,$B12,O$30:O$86) -> 25536 | E12: 1002 | F12: 2001 | G12: 3001 | H12: 4001 | I12: 5003 | J12: 6003 | K12: 7003 | L12: 8001
B13: 7 | C13: =SUMIF($B$30:$B$86,$B13,N$30:N$86) -> 26060 | D13: =SUMIF($B$30:$B$86,$B13,O$30:O$86) -> 40856 | E13: 1003 | F13: 2001 | G13: 3001 | H13: 4001 | I13: 5003 | J13: 6003 | K13: 7003 | L13: 8001
C14: =AVERAGE(C7:C12) -> 11180 | D14: =AVERAGE(D7:D12) -> 19774.667
E15: 1001 | F15: =E15+1000 -> 2001 | G15: =F15+1000 -> 3001 | H15: =G15+1000 -> 4001 | I15: =H15+1000 -> 5001 | J15: =I15+1000 -> 6001 | K15: 7002 | L15: 8001
B16: 天数 | C16: 非R | D16: 大R | E16: =_xlfn.XLOOKUP(E15,$C$30:$C$85,$E$30:$E$85) -> 梦境招募器 | F16: =_xlfn.XLOOKUP(F15,$C$30:$C$85,$E$30:$E$85) -> 星之初愿 | G16: =_xlfn.XLOOKUP(G15,$C$30:$C$85,$E$30:$E$85) -> 星辉秘契 | H16: =_xlfn.XLOOKUP(H15,$C$30:$C$85,$E$30:$E$85) -> 幻梦晶核 | I16: =_xlfn.XLOOKUP(I15,$C$30:$C$85,$E$30:$E$85) -> 装备图纸 | J16: =_xlfn.XLOOKUP(J15,$C$30:$C$85,$E$30:$E$85) -> 织梦微尘 | K16: =_xlfn.XLOOKUP(K15,$C$30:$C$85,$E$30:$E$85) -> 能量特饮 | L16: =_xlfn.XLOOKUP(L15,$C$30:$C$85,$E$30:$E$85) -> 稀有梦灵
B17: 1 | E17: 1 | F17: 1 | G17: 0 | H17: 0
B18: 2 | E18: 1 | F18: 0 | G18: 1 | H18: 0
B19: 3 | E19: 0 | F19: 1 | G19: 0 | H19: 0
B20: 4 | E20: 1 | F20: 0 | G20: 0 | H20: 0
B21: 5 | E21: 0 | H21: 0
B22: 6 | E22: 0 | H22: 0
B23: 7 | E23: 1 | H23: 1
H28: 5 | I28: =H28+3 -> 8 | N28: 1 | O28: 2
B29: 组id | C29: 随机库 | D29: id | E29: 内容名 | F29: 随机权重 | G29: 钻石比例 | H29: 小R日均次数 | I29: 大R日均次数 | J29: 最小天数 | K29: 最大天数 | L29: 上限次数 | M29: 目标用户 | N29: 小R | O29: 大R | P29: 小R | Q29: 大R
B30: 1 | C30: =OFFSET($D$6,B30,COUNTIF($B$29:B30,B30)) -> 1001 | D30: 11 | E30: =_xlfn.XLOOKUP(D30,价值表!D:D,价值表!C:C) -> 梦境招募器 | F30: 700 | G30: 0.5 | H30: =$F30/10000*6*H$28*(1-$G30) -> 1.05 | I30: =$F30/10000*6*I$28*(1-$G30) -> 1.68 | J30: 1 | K30: 2 | L30: =IF(OFFSET($D$16,B30,MATCH(E30,$E$16:$L$16,0))="","",OFFSET($D$16,B30,MATCH(E30,$E$16:$L$16,0))) -> 1 | M30: 非R | N30: {=IF(_xlfn.XLOOKUP($M30,$X$30:$X$34,$Y$30:$Y$34)<=MATCH(N$29,$N$29:$O$29,0),SUMPRODUCT(--($C$91:$C$234=$C30),$G$91:$G$234,$J$91:$J$234)/SUMPRODUCT(--($J$91:$J$234>0),$G$91:$G$234,--($C$91:$C$234=$C30))*MIN(H30,$L30),0)} -> 6000 | O30: {=IF(_xlfn.XLOOKUP($M30,$X$30:$X$34,$Y$30:$Y$34)<=MATCH(O$29,$N$29:$O$29,0),SUMPRODUCT(--($C$91:$C$234=$C30),$G$91:$G$234,$J$91:$J$234)/SUMPRODUCT(--($J$91:$J$234>0),$G$91:$G$234,--($C$91:$C$234=$C30))*MIN(I30,$L30),0)} -> 6000 | P30: {=IF(_xlfn.XLOOKUP($M30,$X$30:$X$34,$Y$30:$Y$34)<=MATCH(N$29,$N$29:$O$29,0),SUMPRODUCT(--($C$91:$C$234=$C30),$G$91:$G$234,$F$91:$F$234,--($J$91:$J$234>0))/SUMPRODUCT(--($J$91:$J$234>0),$G$91:$G$234,--($C$91:$C$234=$C30))*MIN(H30,$L30),0)} -> 5 | Q30: {=IF(_xlfn.XLOOKUP($M30,$X$30:$X$34,$Y$30:$Y$34)<=MATCH(O$29,$N$29:$O$29,0),SUMPRODUCT(--($C$91:$C$234=$C30),$G$91:$G$234,$F$91:$F$234,--($J$91:$J$234>0))/SUMPRODUCT(--($J$91:$J$234>0),$G$91:$G$234,--($C$91:$C$234=$C30))*MIN(I30,$L30),0)} -> 5 | U30: 1001 | V30: =_xlfn.XLOOKUP(INT(U30/1000)*1000+1,$C$29:$C$85,$E$29:$E$85) -> 梦境招募器 | X30: 非R | Y30: 1
B31: 1 | C31: =OFFSET($D$6,B31,COUNTIF($B$29:B31,B31)) -> 2001 | D31: 9 | E31: =_xlfn.XLOOKUP(D31,价值表!D:D,价值表!C:C) -> 星之初愿 | F31: 600 | G31: 0.5 | H31: =$F31/10000*6*H$28*(1-$G31) -> 0.9 | I31: =$F31/10000*6*I$28*(1-$G31) -> 1.44 | J31: 1 | K31: 2 | L31: =IF(OFFSET($D$16,B31,MATCH(E31,$E$16:$L$16,0))="","",OFFSET($D$16,B31,MATCH(E31,$E$16:$L$16,0))) -> 1 | M31: 非R | N31: {=IF(_xlfn.XLOOKUP($M31,$X$30:$X$34,$Y$30:$Y$34)<=MATCH(N$29,$N$29:$O$29,0),SUMPRODUCT(--($C$91:$C$234=$C31),$G$91:$G$234,$J$91:$J$234)/SUMPRODUCT(--($J$91:$J$234>0),$G$91:$G$234,--($C$91:$C$234=$C31))*MIN(H31,$L31),0)} -> 1800 | O31: {=IF(_xlfn.XLOOKUP($M31,$X$30:$X$34,$Y$30:$Y$34)<=MATCH(O$29,$N$29:$O$29,0),SUMPRODUCT(--($C$91:$C$234=$C31),$G$91:$G$234,$J$91:$J$234)/SUMPRODUCT(--($J$91:$J$234>0),$G$91:$G$234,--($C$91:$C$234=$C31))*MIN(I31,$L31),0)} -> 2000 | P31: {=IF(_xlfn.XLOOKUP($M31,$X$30:$X$34,$Y$30:$Y$34)<=MATCH(N$29,$N$29:$O$29,0),SUMPRODUCT(--($C$91:$C$234=$C31),$G$91:$G$234,$F$91:$F$234,--($J$91:$J$234>0))/SUMPRODUCT(--($J$91:$J$234>0),$G$91:$G$234,--($C$91:$C$234=$C31))*MIN(H31,$L31),0)} -> 0.9 | Q31: {=IF(_xlfn.XLOOKUP($M31,$X$30:$X$34,$Y$30:$Y$34)<=MATCH(O$29,$N$29:$O$29,0),SUMPRODUCT(--($C$91:$C$234=$C31),$G$91:$G$234,$F$91:$F$234,--($J$91:$J$234>0))/SUMPRODUCT(--($J$91:$J$234>0),$G$91:$G$234,--($C$91:$C$234=$C31))*MIN(I31,$L31),0)} -> 1 | U31: 1002 | V31: =_xlfn.XLOOKUP(INT(U31/1000)*1000+1,$C$29:$C$85,$E$29:$E$85) -> 梦境招募器 | X31: 小R | Y31: 1
B32: 1 | C32: =OFFSET($D$6,B32,COUNTIF($B$29:B32,B32)) -> 3001 | D32: 30 | E32: =_xlfn.XLOOKUP(D32,价值表!D:D,价值表!C:C) -> 星辉秘契 | F32: 200 | G32: 0.5 | H32: =$F32/10000*6*H$28*(1-$G32) -> 0.3 | I32: =$F32/10000*6*I$28*(1-$G32) -> 0.48 | J32: 1 | K32: 2 | L32: =IF(OFFSET($D$16,B32,MATCH(E32,$E$16:$L$16,0))="","",OFFSET($D$16,B32,MATCH(E32,$E$16:$L$16,0))) -> 0 | M32: 非R | N32: {=IF(_xlfn.XLOOKUP($M32,$X$30:$X$34,$Y$30:$Y$34)<=MATCH(N$29,$N$29:$O$29,0),SUMPRODUCT(--($C$91:$C$234=$C32),$G$91:$G$234,$J$91:$J$234)/SUMPRODUCT(--($J$91:$J$234>0),$G$91:$G$234,--($C$91:$C$234=$C32))*MIN(H32,$L32),0)} -> 0 | O32: {=IF(_xlfn.XLOOKUP($M32,$X$30:$X$34,$Y$30:$Y$34)<=MATCH(O$29,$N$29:$O$29,0),SUMPRODUCT(--($C$91:$C$234=$C32),$G$91:$G$234,$J$91:$J$234)/SUMPRODUCT(--($J$91:$J$234>0),$G$91:$G$234,--($C$91:$C$234=$C32))*MIN(I32,$L32),0)} -> 0 | P32: {=IF(_xlfn.XLOOKUP($M32,$X$30:$X$34,$Y$30:$Y$34)<=MATCH(N$29,$N$29:$O$29,0),SUMPRODUCT(--($C$91:$C$234=$C32),$G$91:$G$234,$F$91:$F$234,--($J$91:$J$234>0))/SUMPRODUCT(--($J$91:$J$234>0),$G$91:$G$234,--($C$91:$C$234=$C32))*MIN(H32,$L32),0)} -> 0 | Q32: {=IF(_xlfn.XLOOKUP($M32,$X$30:$X$34,$Y$30:$Y$34)<=MATCH(O$29,$N$29:$O$29,0),SUMPRODUCT(--($C$91:$C$234=$C32),$G$91:$G$234,$F$91:$F$234,--($J$91:$J$234>0))/SUMPRODUCT(--($J$91:$J$234>0),$G$91:$G$234,--($C$91:$C$234=$C32))*MIN(I32,$L32),0)} -> 0 | U32: 1003 | V32: =_xlfn.XLOOKUP(INT(U32/1000)*1000+1,$C$29:$C$85,$E$29:$E$85) -> 梦境招募器 | X32: 中R | Y32: 1
B33: 1 | C33: =OFFSET($D$6,B33,COUNTIF($B$29:B33,B33)) -> 4001 | D33: 5305001 | E33: =_xlfn.XLOOKUP(D33,价值表!D:D,价值表!C:C) -> 幻梦晶核 | F33: 300 | G33: 0.5 | H33: =$F33/10000*6*H$28*(1-$G33) -> 0.45 | I33: =$F33/10000*6*I$28*(1-$G33) -> 0.72 | J33: 1 | K33: 2 | L33: =IF(OFFSET($D$16,B33,MATCH(E33,$E$16:$L$16,0))="","",OFFSET($D$16,B33,MATCH(E33,$E$16:$L$16,0))) -> 0 | M33: 非R | N33: {=IF(_xlfn.XLOOKUP($M33,$X$30:$X$34,$Y$30:$Y$34)<=MATCH(N$29,$N$29:$O$29,0),SUMPRODUCT(--($C$91:$C$234=$C33),$G$91:$G$234,$J$91:$J$234)/SUMPRODUCT(--($J$91:$J$234>0),$G$91:$G$234,--($C$91:$C$234=$C33))*MIN(H33,$L33),0)} -> 0 | O33: {=IF(_xlfn.XLOOKUP($M33,$X$30:$X$34,$Y$30:$Y$34)<=MATCH(O$29,$N$29:$O$29,0),SUMPRODUCT(--($C$91:$C$234=$C33),$G$91:$G$234,$J$91:$J$234)/SUMPRODUCT(--($J$91:$J$234>0),$G$91:$G$234,--($C$91:$C$234=$C33))*MIN(I33,$L33),0)} -> 0 | P33: {=IF(_xlfn.XLOOKUP($M33,$X$30:$X$34,$Y$30:$Y$34)<=MATCH(N$29,$N$29:$O$29,0),SUMPRODUCT(--($C$91:$C$234=$C33),$G$91:$G$234,$F$91:$F$234,--($J$91:$J$234>0))/SUMPRODUCT(--($J$91:$J$234>0),$G$91:$G$234,--($C$91:$C$234=$C33))*MIN(H33,$L33),0)} -> 0 | Q33: {=IF(_xlfn.XLOOKUP($M33,$X$30:$X$34,$Y$30:$Y$34)<=MATCH(O$29,$N$29:$O$29,0),SUMPRODUCT(--($C$91:$C$234=$C33),$G$91:$G$234,$F$91:$F$234,--($J$91:$J$234>0))/SUMPRODUCT(--($J$91:$J$234>0),$G$91:$G$234,--($C$91:$C$234=$C33))*MIN(I33,$L33),0)} -> 0 | U33: 2001 | V33: =_xlfn.XLOOKUP(INT(U33/1000)*1000+1,$C$29:$C$85,$E$29:$E$85) -> 星之初愿 | X33: 大R | Y33: 2
B34: 1 | C34: =OFFSET($D$6,B34,COUNTIF($B$29:B34,B34)) -> 5001 | D34: 50002 | E34: =_xlfn.XLOOKUP(D34,价值表!D:D,价值表!C:C) -> 装备图纸 | F34: 2400 | G34: 0.5 | H34: =$F34/10000*6*H$28*(1-$G34) -> 3.6 | I34: =$F34/10000*6*I$28*(1-$G34) -> 5.76 | J34: 1 | K34: 2 | L34: =IF(OFFSET($D$16,B34,MATCH(E34,$E$16:$L$16,0))="","",OFFSET($D$16,B34,MATCH(E34,$E$16:$L$16,0))) | M34: 非R | N34: {=IF(_xlfn.XLOOKUP($M34,$X$30:$X$34,$Y$30:$Y$34)<=MATCH(N$29,$N$29:$O$29,0),SUMPRODUCT(--($C$91:$C$234=$C34),$G$91:$G$234,$J$91:$J$234)/SUMPRODUCT(--($J$91:$J$234>0),$G$91:$G$234,--($C$91:$C$234=$C34))*MIN(H34,$L34),0)} -> 3600 | O34: {=IF(_xlfn.XLOOKUP($M34,$X$30:$X$34,$Y$30:$Y$34)<=MATCH(O$29,$N$29:$O$29,0),SUMPRODUCT(--($C$91:$C$234=$C34),$G$91:$G$234,$J$91:$J$234)/SUMPRODUCT(--($J$91:$J$234>0),$G$91:$G$234,--($C$91:$C$234=$C34))*MIN(I34,$L34),0)} -> 5760 | P34: {=IF(_xlfn.XLOOKUP($M34,$X$30:$X$34,$Y$30:$Y$34)<=MATCH(N$29,$N$29:$O$29,0),SUMPRODUCT(--($C$91:$C$234=$C34),$G$91:$G$234,$F$91:$F$234,--($J$91:$J$234>0))/SUMPRODUCT(--($J$91:$J$234>0),$G$91:$G$234,--($C$91:$C$234=$C34))*MIN(H34,$L34),0)} -> 36 | Q34: {=IF(_xlfn.XLOOKUP($M34,$X$30:$X$34,$Y$30:$Y$34)<=MATCH(O$29,$N$29:$O$29,0),SUMPRODUCT(--($C$91:$C$234=$C34),$G$91:$G$234,$F$91:$F$234,--($J$91:$J$234>0))/SUMPRODUCT(--($J$91:$J$234>0),$G$91:$G$234,--($C$91:$C$234=$C34))*MIN(I34,$L34),0)} -> 57.6 | U34: 3001 | V34: =_xlfn.XLOOKUP(INT(U34/1000)*1000+1,$C$29:$C$85,$E$29:$E$85) -> 星辉秘契 | X34: 超R | Y34: 3
B35: 1 | C35: =OFFSET($D$6,B35,COUNTIF($B$29:B35,B35)) -> 6001 | D35: 5203001 | E35: =_xlfn.XLOOKUP(D35,价值表!D:D,价值表!C:C) -> 织梦微尘 | F35: 600 | G35: 0.5 | H35: =$F35/10000*6*H$28*(1-$G35) -> 0.9 | I35: =$F35/10000*6*I$28*(1-$G35) -> 1.44 | J35: 1 | K35: 2 | L35: =IF(OFFSET($D$16,B35,MATCH(E35,$E$16:$L$16,0))="","",OFFSET($D$16,B35,MATCH(E35,$E$16:$L$16,0))) | M35: 大R | N35: {=IF(_xlfn.XLOOKUP($M35,$X$30:$X$34,$Y$30:$Y$34)<=MATCH(N$29,$N$29:$O$29,0),SUMPRODUCT(--($C$91:$C$234=$C35),$G$91:$G$234,$J$91:$J$234)/SUMPRODUCT(--($J$91:$J$234>0),$G$91:$G$234,--($C$91:$C$234=$C35))*MIN(H35,$L35),0)} -> 0 | O35: {=IF(_xlfn.XLOOKUP($M35,$X$30:$X$34,$Y$30:$Y$34)<=MATCH(O$29,$N$29:$O$29,0),SUMPRODUCT(--($C$91:$C$234=$C35),$G$91:$G$234,$J$91:$J$234)/SUMPRODUCT(--($J$91:$J$234>0),$G$91:$G$234,--($C$91:$C$234=$C35))*MIN(I35,$L35),0)} -> 2880 | P35: {=IF(_xlfn.XLOOKUP($M35,$X$30:$X$34,$Y$30:$Y$34)<=MATCH(N$29,$N$29:$O$29,0),SUMPRODUCT(--($C$91:$C$234=$C35),$G$91:$G$234,$F$91:$F$234,--($J$91:$J$234>0))/SUMPRODUCT(--($J$91:$J$234>0),$G$91:$G$234,--($C$91:$C$234=$C35))*MIN(H35,$L35),0)} -> 0 | Q35: {=IF(_xlfn.XLOOKUP($M35,$X$30:$X$34,$Y$30:$Y$34)<=MATCH(O$29,$N$29:$O$29,0),SUMPRODUCT(--($C$91:$C$234=$C35),$G$91:$G$234,$F$91:$F$234,--($J$91:$J$234>0))/SUMPRODUCT(--($J$91:$J$234>0),$G$91:$G$234,--($C$91:$C$234=$C35))*MIN(I35,$L35),0)} -> 14.4 | U35: 4001 | V35: =_xlfn.XLOOKUP(INT(U35/1000)*1000+1,$C$29:$C$85,$E$29:$E$85) -> 幻梦晶核
B36: 1 | C36: =OFFSET($D$6,B36,COUNTIF($B$29:B36,B36)) -> 7002 | D36: 5103001 | E36: =_xlfn.XLOOKUP(D36,价值表!D:D,价值表!C:C) -> 能量特饮 | F36: 2000 | G36: 0.5 | H36: =$F36/10000*6*H$28*(1-$G36) -> 3 | I36: =$F36/10000*6*I$28*(1-$G36) -> 4.8 | J36: 1 | K36: 2 | L36: =IF(OFFSET($D$16,B36,MATCH(E36,$E$16:$L$16,0))="","",OFFSET($D$16,B36,MATCH(E36,$E$16:$L$16,0))) | M36: 超R | N36: {=IF(_xlfn.XLOOKUP($M36,$X$30:$X$34,$Y$30:$Y$34)<=MATCH(N$29,$N$29:$O$29,0),SUMPRODUCT(--($C$91:$C$234=$C36),$G$91:$G$234,$J$91:$J$234)/SUMPRODUCT(--($J$91:$J$234>0),$G$91:$G$234,--($C$91:$C$234=$C36))*MIN(H36,$L36),0)} -> 0 | O36: {=IF(_xlfn.XLOOKUP($M36,$X$30:$X$34,$Y$30:$Y$34)<=MATCH(O$29,$N$29:$O$29,0),SUMPRODUCT(--($C$91:$C$234=$C36),$G$91:$G$234,$J$91:$J$234)/SUMPRODUCT(--($J$91:$J$234>0),$G$91:$G$234,--($C$91:$C$234=$C36))*MIN(I36,$L36),0)} -> 0 | P36: {=IF(_xlfn.XLOOKUP($M36,$X$30:$X$34,$Y$30:$Y$34)<=MATCH(N$29,$N$29:$O$29,0),SUMPRODUCT(--($C$91:$C$234=$C36),$G$91:$G$234,$F$91:$F$234,--($J$91:$J$234>0))/SUMPRODUCT(--($J$91:$J$234>0),$G$91:$G$234,--($C$91:$C$234=$C36))*MIN(H36,$L36),0)} -> 0 | Q36: {=IF(_xlfn.XLOOKUP($M36,$X$30:$X$34,$Y$30:$Y$34)<=MATCH(O$29,$N$29:$O$29,0),SUMPRODUCT(--($C$91:$C$234=$C36),$G$91:$G$234,$F$91:$F$234,--($J$91:$J$234>0))/SUMPRODUCT(--($J$91:$J$234>0),$G$91:$G$234,--($C$91:$C$234=$C36))*MIN(I36,$L36),0)} -> 0 | U36: 5001 | V36: =_xlfn.XLOOKUP(INT(U36/1000)*1000+1,$C$29:$C$85,$E$29:$E$85) -> 装备图纸
B37: 1 | C37: =OFFSET($D$6,B37,COUNTIF($B$29:B37,B37)) -> 8001 | D37: 1310100 | E37: =_xlfn.XLOOKUP(D37,价值表!D:D,价值表!C:C) -> 稀有梦灵 | F37: 3200 | G37: 0.5 | H37: =$F37/10000*6*H$28*(1-$G37) -> 4.8 | I37: =$F37/10000*6*I$28*(1-$G37) -> 7.68 | J37: 1 | K37: 2 | L37: =IF(OFFSET($D$16,B37,MATCH(E37,$E$16:$L$16,0))="","",OFFSET($D$16,B37,MATCH(E37,$E$16:$L$16,0))) | M37: 超R | N37: {=IF(_xlfn.XLOOKUP($M37,$X$30:$X$34,$Y$30:$Y$34)<=MATCH(N$29,$N$29:$O$29,0),SUMPRODUCT(--($C$91:$C$234=$C37),$G$91:$G$234,$J$91:$J$234)/SUMPRODUCT(--($J$91:$J$234>0),$G$91:$G$234,--($C$91:$C$234=$C37))*MIN(H37,$L37),0)} -> 0 | O37: {=IF(_xlfn.XLOOKUP($M37,$X$30:$X$34,$Y$30:$Y$34)<=MATCH(O$29,$N$29:$O$29,0),SUMPRODUCT(--($C$91:$C$234=$C37),$G$91:$G$234,$J$91:$J$234)/SUMPRODUCT(--($J$91:$J$234>0),$G$91:$G$234,--($C$91:$C$234=$C37))*MIN(I37,$L37),0)} -> 0 | P37: {=IF(_xlfn.XLOOKUP($M37,$X$30:$X$34,$Y$30:$Y$34)<=MATCH(N$29,$N$29:$O$29,0),SUMPRODUCT(--($C$91:$C$234=$C37),$G$91:$G$234,$F$91:$F$234,--($J$91:$J$234>0))/SUMPRODUCT(--($J$91:$J$234>0),$G$91:$G$234,--($C$91:$C$234=$C37))*MIN(H37,$L37),0)} -> 0 | Q37: {=IF(_xlfn.XLOOKUP($M37,$X$30:$X$34,$Y$30:$Y$34)<=MATCH(O$29,$N$29:$O$29,0),SUMPRODUCT(--($C$91:$C$234=$C37),$G$91:$G$234,$F$91:$F$234,--($J$91:$J$234>0))/SUMPRODUCT(--($J$91:$J$234>0),$G$91:$G$234,--($C$91:$C$234=$C37))*MIN(I37,$L37),0)} -> 0 | U37: 5002 | V37: =_xlfn.XLOOKUP(INT(U37/1000)*1000+1,$C$29:$C$85,$E$29:$E$85) -> 装备图纸
B38: =B30+1 -> 2 | C38: =OFFSET($D$6,B38,COUNTIF($B$29:B38,B38)) -> 1001 | D38: 11 | E38: =_xlfn.XLOOKUP(D38,价值表!D:D,价值表!C:C) -> 梦境招募器 | F38: 700 | G38: 0.5 | H38: =$F38/10000*6*H$28*(1-$G38) -> 1.05 | I38: =$F38/10000*6*I$28*(1-$G38) -> 1.68 | J38: 1 | K38: 2 | L38: =IF(OFFSET($D$16,B38,MATCH(E38,$E$16:$L$16,0))="","",OFFSET($D$16,B38,MATCH(E38,$E$16:$L$16,0))) -> 1 | M38: 非R | N38: {=IF(_xlfn.XLOOKUP($M38,$X$30:$X$34,$Y$30:$Y$34)<=MATCH(N$29,$N$29:$O$29,0),SUMPRODUCT(--($C$91:$C$234=$C38),$G$91:$G$234,$J$91:$J$234)/SUMPRODUCT(--($J$91:$J$234>0),$G$91:$G$234,--($C$91:$C$234=$C38))*MIN(H38,$L38),0)} -> 6000 | O38: {=IF(_xlfn.XLOOKUP($M38,$X$30:$X$34,$Y$30:$Y$34)<=MATCH(O$29,$N$29:$O$29,0),SUMPRODUCT(--($C$91:$C$234=$C38),$G$91:$G$234,$J$91:$J$234)/SUMPRODUCT(--($J$91:$J$234>0),$G$91:$G$234,--($C$91:$C$234=$C38))*MIN(I38,$L38),0)} -> 6000 | P38: {=IF(_xlfn.XLOOKUP($M38,$X$30:$X$34,$Y$30:$Y$34)<=MATCH(N$29,$N$29:$O$29,0),SUMPRODUCT(--($C$91:$C$234=$C38),$G$91:$G$234,$F$91:$F$234,--($J$91:$J$234>0))/SUMPRODUCT(--($J$91:$J$234>0),$G$91:$G$234,--($C$91:$C$234=$C38))*MIN(H38,$L38),0)} -> 5 | Q38: {=IF(_xlfn.XLOOKUP($M38,$X$30:$X$34,$Y$30:$Y$34)<=MATCH(O$29,$N$29:$O$29,0),SUMPRODUCT(--($C$91:$C$234=$C38),$G$91:$G$234,$F$91:$F$234,--($J$91:$J$234>0))/SUMPRODUCT(--($J$91:$J$234>0),$G$91:$G$234,--($C$91:$C$234=$C38))*MIN(I38,$L38),0)} -> 5 | U38: 5003 | V38: =_xlfn.XLOOKUP(INT(U38/1000)*1000+1,$C$29:$C$85,$E$29:$E$85) -> 装备图纸
B39: =B31+1 -> 2 | C39: =OFFSET($D$6,B39,COUNTIF($B$29:B39,B39)) -> 2001 | D39: 9 | E39: =_xlfn.XLOOKUP(D39,价值表!D:D,价值表!C:C) -> 星之初愿 | F39: 600 | G39: 0.5 | H39: =$F39/10000*6*H$28*(1-$G39) -> 0.9 | I39: =$F39/10000*6*I$28*(1-$G39) -> 1.44 | J39: 1 | K39: 2 | L39: =IF(OFFSET($D$16,B39,MATCH(E39,$E$16:$L$16,0))="","",OFFSET($D$16,B39,MATCH(E39,$E$16:$L$16,0))) -> 0 | M39: 非R | N39: {=IF(_xlfn.XLOOKUP($M39,$X$30:$X$34,$Y$30:$Y$34)<=MATCH(N$29,$N$29:$O$29,0),SUMPRODUCT(--($C$91:$C$234=$C39),$G$91:$G$234,$J$91:$J$234)/SUMPRODUCT(--($J$91:$J$234>0),$G$91:$G$234,--($C$91:$C$234=$C39))*MIN(H39,$L39),0)} -> 0 | O39: {=IF(_xlfn.XLOOKUP($M39,$X$30:$X$34,$Y$30:$Y$34)<=MATCH(O$29,$N$29:$O$29,0),SUMPRODUCT(--($C$91:$C$234=$C39),$G$91:$G$234,$J$91:$J$234)/SUMPRODUCT(--($J$91:$J$234>0),$G$91:$G$234,--($C$91:$C$234=$C39))*MIN(I39,$L39),0)} -> 0 | P39: {=IF(_xlfn.XLOOKUP($M39,$X$30:$X$34,$Y$30:$Y$34)<=MATCH(N$29,$N$29:$O$29,0),SUMPRODUCT(--($C$91:$C$234=$C39),$G$91:$G$234,$F$91:$F$234,--($J$91:$J$234>0))/SUMPRODUCT(--($J$91:$J$234>0),$G$91:$G$234,--($C$91:$C$234=$C39))*MIN(H39,$L39),0)} -> 0 | Q39: {=IF(_xlfn.XLOOKUP($M39,$X$30:$X$34,$Y$30:$Y$34)<=MATCH(O$29,$N$29:$O$29,0),SUMPRODUCT(--($C$91:$C$234=$C39),$G$91:$G$234,$F$91:$F$234,--($J$91:$J$234>0))/SUMPRODUCT(--($J$91:$J$234>0),$G$91:$G$234,--($C$91:$C$234=$C39))*MIN(I39,$L39),0)} -> 0 | U39: 6001 | V39: =_xlfn.XLOOKUP(INT(U39/1000)*1000+1,$C$29:$C$85,$E$29:$E$85) -> 织梦微尘
B40: =B32+1 -> 2 | C40: =OFFSET($D$6,B40,COUNTIF($B$29:B40,B40)) -> 3001 | D40: 30 | E40: =_xlfn.XLOOKUP(D40,价值表!D:D,价值表!C:C) -> 星辉秘契 | F40: 200 | G40: 0.5 | H40: =$F40/10000*6*H$28*(1-$G40) -> 0.3 | I40: =$F40/10000*6*I$28*(1-$G40) -> 0.48 | J40: 1 | K40: 2 | L40: =IF(OFFSET($D$16,B40,MATCH(E40,$E$16:$L$16,0))="","",OFFSET($D$16,B40,MATCH(E40,$E$16:$L$16,0))) -> 1 | M40: 非R | N40: {=IF(_xlfn.XLOOKUP($M40,$X$30:$X$34,$Y$30:$Y$34)<=MATCH(N$29,$N$29:$O$29,0),SUMPRODUCT(--($C$91:$C$234=$C40),$G$91:$G$234,$J$91:$J$234)/SUMPRODUCT(--($J$91:$J$234>0),$G$91:$G$234,--($C$91:$C$234=$C40))*MIN(H40,$L40),0)} -> 3360 | O40: {=IF(_xlfn.XLOOKUP($M40,$X$30:$X$34,$Y$30:$Y$34)<=MATCH(O$29,$N$29:$O$29,0),SUMPRODUCT(--($C$91:$C$234=$C40),$G$91:$G$234,$J$91:$J$234)/SUMPRODUCT(--($J$91:$J$234>0),$G$91:$G$234,--($C$91:$C$234=$C40))*MIN(I40,$L40),0)} -> 5376 | P40: {=IF(_xlfn.XLOOKUP($M40,$X$30:$X$34,$Y$30:$Y$34)<=MATCH(N$29,$N$29:$O$29,0),SUMPRODUCT(--($C$91:$C$234=$C40),$G$91:$G$234,$F$91:$F$234,--($J$91:$J$234>0))/SUMPRODUCT(--($J$91:$J$234>0),$G$91:$G$234,--($C$91:$C$234=$C40))*MIN(H40,$L40),0)} -> 0.3 | Q40: {=IF(_xlfn.XLOOKUP($M40,$X$30:$X$34,$Y$30:$Y$34)<=MATCH(O$29,$N$29:$O$29,0),SUMPRODUCT(--($C$91:$C$234=$C40),$G$91:$G$234,$F$91:$F$234,--($J$91:$J$234>0))/SUMPRODUCT(--($J$91:$J$234>0),$G$91:$G$234,--($C$91:$C$234=$C40))*MIN(I40,$L40),0)} -> 0.48 | U40: 6002 | V40: =_xlfn.XLOOKUP(INT(U40/1000)*1000+1,$C$29:$C$85,$E$29:$E$85) -> 织梦微尘
B41: =B33+1 -> 2 | C41: =OFFSET($D$6,B41,COUNTIF($B$29:B41,B41)) -> 4001 | D41: 5305001 | E41: =_xlfn.XLOOKUP(D41,价值表!D:D,价值表!C:C) -> 幻梦晶核 | F41: 300 | G41: 0.5 | H41: =$F41/10000*6*H$28*(1-$G41) -> 0.45 | I41: =$F41/10000*6*I$28*(1-$G41) -> 0.72 | J41: 1 | K41: 2 | L41: =IF(OFFSET($D$16,B41,MATCH(E41,$E$16:$L$16,0))="","",OFFSET($D$16,B41,MATCH(E41,$E$16:$L$16,0))) -> 0 | M41: 非R | N41: {=IF(_xlfn.XLOOKUP($M41,$X$30:$X$34,$Y$30:$Y$34)<=MATCH(N$29,$N$29:$O$29,0),SUMPRODUCT(--($C$91:$C$234=$C41),$G$91:$G$234,$J$91:$J$234)/SUMPRODUCT(--($J$91:$J$234>0),$G$91:$G$234,--($C$91:$C$234=$C41))*MIN(H41,$L41),0)} -> 0 | O41: {=IF(_xlfn.XLOOKUP($M41,$X$30:$X$34,$Y$30:$Y$34)<=MATCH(O$29,$N$29:$O$29,0),SUMPRODUCT(--($C$91:$C$234=$C41),$G$91:$G$234,$J$91:$J$234)/SUMPRODUCT(--($J$91:$J$234>0),$G$91:$G$234,--($C$91:$C$234=$C41))*MIN(I41,$L41),0)} -> 0 | P41: {=IF(_xlfn.XLOOKUP($M41,$X$30:$X$34,$Y$30:$Y$34)<=MATCH(N$29,$N$29:$O$29,0),SUMPRODUCT(--($C$91:$C$234=$C41),$G$91:$G$234,$F$91:$F$234,--($J$91:$J$234>0))/SUMPRODUCT(--($J$91:$J$234>0),$G$91:$G$234,--($C$91:$C$234=$C41))*MIN(H41,$L41),0)} -> 0 | Q41: {=IF(_xlfn.XLOOKUP($M41,$X$30:$X$34,$Y$30:$Y$34)<=MATCH(O$29,$N$29:$O$29,0),SUMPRODUCT(--($C$91:$C$234=$C41),$G$91:$G$234,$F$91:$F$234,--($J$91:$J$234>0))/SUMPRODUCT(--($J$91:$J$234>0),$G$91:$G$234,--($C$91:$C$234=$C41))*MIN(I41,$L41),0)} -> 0 | U41: 6003 | V41: =_xlfn.XLOOKUP(INT(U41/1000)*1000+1,$C$29:$C$85,$E$29:$E$85) -> 织梦微尘
