Workbook

Sheet 路线图
A1: 时间 | C1: 1 | D1: 2 | E1: 3 | F1: 4 | G1: 5 | H1: 6 | I1: 7 | J1: 8 | K1: 9 | L1: 10 | M1: 11 | N1: 12 | O1: 13 | P1: 14 | Q1: 第3周 | R1: 第4周 | S1: 第5周 | T1: 第6周 | U1: 第7周 | V1: 第8周 | W1: 第9周 | X1: 第10周 | Y1: 第11周 | Z1: 第12周 | AA1: 第13周 | AB1: 第14周 | AC1: 第15周 | AD1: 第16周
A2: 满活跃非r主线 | C2: 10 | D2: 15 | E2: 20 | F2: 25 | G2: 30 | H2: 35 | I2: 40
A3: 满活跃小R主线（四卡党） | C3: 15 | D3: 25 | E3: 35 | F3: 45 | G3: 48 | H3: 50 | I3: 54
A4: 满活跃中R主线（四卡党+活动）1000+，日产200抽 | J4: 57 | K4: 60 | L4: 63 | M4: 66 | N4: 69 | O4: 71 | P4: 73
A5: 满活跃大R主线3000+ | Q5: 80 | R5: 87 | S5: 94 | T5: 101 | U5: 108 | V5: 115 | W5: 122 | X5: 129 | Y5: 136 | Z5: 143 | AA5: 150 | AB5: 157 | AC5: 164 | AD5: 171 | AE5: 178
A6: 养成 梦灵线 | B6: 梦灵 | C6: 2-3紫（5级 | D6: 东方/镭射 | E6: 亚瑟 | F6: 蜘蛛 | G6: 唐小僧 | H6: 神灯 | I6: 关羽 | J6: 后羿/诸葛/我爱沙 | Q6: 海拉/妲己 | R6: 白素贞 | S6: 零日骇客UP (31天） | W6: 雅典娜UP (59天） | AB6: 女娲UP (73天） | AE6: 杨戬UP (102天）
B7: 挂件 解锁条件-主角等级 | C7: 弹幕流/全图流/爆发流 | D7: 能量流 | F7: 召唤流 | H7: 共鸣流 | J7: 赛季挂件 (S0) | W7: 赛季挂件 (S1)
B8: 符文 | C8: 开启
A9: 养成 主角线 | B9: 装备 | C9: 开启 | E9: 红装 | Q9: 粉装 | T9: 彩装 | U9: 彩虹装
B10: 武器 | C10: 开局+1 | E10: 开局+1 | P10: 开局+1 | T10: 开局+1
B11: 秘宝 | H11: 开启
B12: 藏品 | Q12: 藏品系统（15天） （静默开启）
B13: 载具 | R13: 载具系统 （22天）
B14: 宠物 | V14: 宠物系统 （60天）
A15: 玩法 | B15: 荧幕争锋 | C15: 开启
B16: 梦域巡航 | C16: 难度1 | E16: 难度2 | H16: 难度3 | L16: 难度4 | P16: 难度5 | Q16: 难度6/难度7 | R16: 难度8 | S16: 难度9 | T16: 难度10 彩虹关1(藏品) | V16: 彩虹2 | Y16: 彩虹3 | AA16: 彩虹4
B17: 海底捞金 | C17: 开启
B18: 贪吃大作战 | E18: 开启 | Q18: 升级
B19: 梦隙迷廊 | R19: 开启
B20: 宠物玩法 | V20: 开启
B21: 赛季玩法 | X21: S1玩法
A22: 活动 | B22: 赛季循环 （长周期投辅线） | C22: S0赛季-梦境启航（过度赛季） | V22: S1赛季-我有一座恐怖屋（主推射手、法师)
C23: 主投：红梦灵及皮肤、红色符文（好词条） 辅投：橙、紫梦灵及皮肤、符文祝福石 进度：B级冒险家+散件 荣誉：主角氛围特效-白日梦想（S） | V23: 主投：粉梦灵皮肤、红色符文（好词条） 辅投：橙、红梦灵及皮肤、符文祝福石 进度：B级 小鬼当家+散件 荣誉：主角氛围特效-百鬼夜行（S）
B24: 周循环 （循环投养成） | D24: 开服冲刺//根据抽数达成配置奖励，同时玩家首日抽卡次数保留到开服冲刺 | J24: 招募冲刺【根据第7天招募次数达成中位数来设置首档和后续的奖励】 | Q24: 符文冲刺(boss) | R24: 秘宝冲刺 （排行投皮肤） | S24: 招募冲刺 | T24: 符文冲刺(boss) | U24: 秘宝冲刺 | V24: 招募冲刺 （跨服） | W24: 符文冲刺 | X24: 秘宝冲刺 | Y24: 招募冲刺 | Z24: 符文冲刺 | AA24: 秘宝冲刺 | AB24: 招募冲刺
Q25: 悬赏（1档） | T25: 悬赏（2档） | W25: 悬赏（3档） | Z25: 悬赏（4档）
Q26: 红符文、随机橙藏品、指定橙藏品 第三周（符文产品） 第四周（载具产品） 第五周（招募冲刺 | T26: 红符文、载具粉零件 第6周（彩虹关的藏品 | W26: 载具粉零件、红符文、指定橙藏品... | Z26: 载具粉零件、红符文、指定橙藏品...
B27: 限时活动 （短周期投核心线) | G27: 橙卡试炼 | K27: 时装抽奖【星轨探测】聚焦皮肤 | O27: 红卡试炼(13-16天) | S27: 粉卡试炼 | V27: 粉卡试炼 | Y27: 粉卡试炼 | AB27: 粉卡试炼
G28: 橙卡皮肤 专属符文（红卡预告） | K28: 天使套-A （S0） | O28: 红卡皮肤 专属符文 | S28: 粉卡皮肤 专属符文 | V28: 粉卡皮肤 专属符文 | Y28: 粉卡皮 肤专属符文 | AB28: 粉卡皮肤 专属符文
B32: 1.梦灵节奏适当压缩了一点（粉卡阶段采用的蔚蓝上一版本的节奏，因为我们存量不够）
B34: 2.三类活动线的做了调整：
B35: 月活动→赛季：主要做主轴目标和荣誉追求，投放辅线的资源
B36: 周循环活动：做中小R的钻石消耗和付费转化，主要承载中小R的长期目标和小额付费转化，投放养成资源
B37: 限时活动：拉收，短周期，投放核心资源
B38: 一个核心调整思路就是要把一些投放内容隔离到只有限时活动投放
B40: 3.目前盘下来，需要一个大颗粒度的投放内容去支撑上面这个投放结构，目前考虑下来还是藏品比较合适。对应的秘宝的价值要做上去，现在被当成藏品在投放。
B42: 首周：
B43: 1.关卡战力压制
B44: 2.梦灵节点追求
B46: 次周：
B47: 1.符文概率调整
... B57: 1.载具系统

Sheet 活动设计标准
C1: 稀缺度
C3: 稀缺度 | D3: 定义 | E3: 投放约束
C4: 常规 | D4: 存在稳定、重复获取渠道 | E4: 可进入日常、常驻商店和普通礼包
C5: 受限 | D5: 稳定出现，但存在周期或数量限制 | E5: 可进入周循环、战令、限购礼包
C6: 稀缺 | D6: 只在少量运营活动中周期投放 | E6: 控制月度总量，禁止日常大量投放
C7: 限定 | D7: 赛季、联动、首发或特定时间独占 | E7: 限定渠道、限定周期，返场需单独审核
C10: 材料返利比
C12: 直购档位/RMB | D12: 标准返比 | E12: 示例 | H12: 月卡、周卡、基金、战令类，返比>1000%
C13: 6 | D13: 10 | E13: 6元=6高抽+60钻 | H13: 基础资源 | I13: 30元=36小时
C14: 12 | D14: 8 | I14: 68元=72小时
C15: 30 | D15: 6 | E15: 30元=10心愿抽+300钻
C16: 68 | D16: 5 | I16: 基金 | J16: 10
C17: 98 | D17: 4 | I17: 战令 | J17: 15
C18: 128 | D18: 3.5
C19: 198 | D19: 3
C20: 328 | D20: 2.5
C21: 648 | D21: 2
C23: 钻石消耗活动直购礼包返利比
C24: 直购档位/RMB | D24: 标准返比 | E24: 示例
C25: 6 | D25: 10 | J25: 5
C26: 30 | D26: 4 | J26: 5
C27: 98 | D27: 2.5 | J27: 5
C28: 328 | D28: 1.5
C30: 活动返利比
C32: 活动评级 | D32: 标准返比
C33: S | D33: 3
C34: A | D34: 200%-225%
C35: B | D35: 150%-175%

Sheet 优化总内容
A1: 活动分类 | B1: 周期分类 | C1: 活动名字 | D1: 价格 | E1: 活动开始时间 | F1: 活动结束时间 | G1: 转化率 | H1: 优化思路 | I1: 目标用户 | J1: 截图1 | K1: 截图2
A2: 常驻活动 | B2: 终身限购 | C2: 首充 | D2: 6 | E2: 1 | F2: 99999 | G2: 跟用户质量有关 | H2: 1、新增30元（橙卡皮）、68元 直购（橙色角色皮） 2、搭配6元武器，制作一个橙色队长皮肤跟武器搭配，提高转化目标提高首日LTV。 3、128元送橙色皮肤后续玩家会觉得亏，数据上来看购买128元橙色皮肤的流失率会比不买的高了一些。让玩家感觉首充是赚的。而且可以把这个奖励剥离开，不会重复投放。 | I2: 小R/破冰
C3: 钻石战令（Ⅰ、Ⅱ、Ⅲ） | D3: 98 | E3: 1 | F3: 99999 | G3: 0.095 | H3: 首月战令投放68元战令皮，后续期数暂定投放其他限时内容 比如载具、宠物 或者其他 | I3: 中R钻石转化需要提升
B4: 周期活动 | C4: 大/小月卡 | D4: 18、30 | E4: 1 | F4: 30 | G4: 26%/30% | H4: 1、提高特权点 2、双卡激活奖励加一个聊天框带一点属性，提高双卡的标识。 | I4: 中小R核心付费点
C5: 大/小体力战令 | D5: 28、68 | E5: 1 | F5: 14 | G5: 20%/10% | H5: 1、28元体力战令保持，2、68元应该在反比不动太多的情况下投放一些可自选的内容，选择多一些。 | I5: 中小R核心付费点
C6: 周卡 | D6: 12 | E6: 1 | F6: 7 | G6: 0.15 | H6: 1、初始增加金币券 2、开启载具副本后，减负用户 可增加对组队的减负的道具（比如打1次队员可以抵2次的券）。 | I6: 中核心付费点
C7: 每日特惠 | D7: 1、6、18 | E7: 1 | F7: 1 | G7: 3%/1.5%/0.2% | H7: 1、礼包心梦宝石增加2-3档次随机 比如可以在 1元可在1、2、3、5个之间随机 2、梦境奇迹宝箱可以给固定碎片，按照玩家拥有的英雄和卡池等级可选择获取的量。 | I7: 中大R核心付费点
C8: 特惠礼包（日、周、月） | D8: 钻石 | E8: 1 | F8: 30 | H8: 1、根据数据来调整售价策略 2、后续可计划根据购买的量越大越有折扣，这样后续的体感价值可以根据玩家的进度活动进度可以进行贬值也不影响玩家的体感。 | I8: 中大R购买
C9: 连充活动（6、25） | D9: 6、25 | E9: 1 | F9: 7 | G9: 10%/6% | H9: 开启新玩法后会考虑新增新成长点的自选奖励 | I9: 中大R购买
C10: 兑换商店【心梦宝石】 | E10: 1 | F10: 7 | H10: 1、降低钻石的限购次数为1次， 2、若首充增加橙色皮肤可新增到这里当成短期的升星目标 （武器的购买不错） 3、新增新的成长点内容 比如载具、藏品等需要添加 4、会额外增加心梦宝石的产量（核心与付费有关系） 5、核心就每日、冲刺获取，其他地方不投放。
A11: 循环活动 | C11: 招募冲刺 | E11: 7 | H11: 1、根据玩家的资源获取和内容，来评估奖励和消耗的配置是否需要更新。 2、生态影响什么时候加入跨服。 3、如果没跨服则需要根据数据来计算排行榜的保底机制。
C12: 符文冲刺 | E12: 7 | H12: 根据玩家的资源获取和内容，来评估奖励和消耗的配置是否需要更新。
C13: 秘宝冲刺 | E13: 7 | H13: 根据玩家的资源获取和内容，来评估奖励和消耗的配置是否需要更新。
C14: 悬赏活动1 | E14: 10 | H14: 1、规划5层的奖励 前4层基本每层都会又一个玩家热衷度较高的内容 2、第5层是稀有道具是为了提高玩家的付费冲动，核心是神话符文、载具、秘宝、藏品、角色皮肤等 3、如果7天一期的话，类似二游复刻一样提高稀缺性，相似的道具投放时间间隔长一些，规划5层的奖励内容。
C15: 悬赏活动2 | E15: 10
C16: 悬赏活动3【载具】 | E16: 10
C17: 悬赏活动4【载具】 | E17: 10
A18: 限时活动 | B18: 服务器限时 | C18: 招募狂欢（橙卡） | E18: 2 | F18: 7 | H18: 1、首轮的次数降低到400（500就可以抽橙色了，第2天开启这个时候玩家对橙色的追求没那么大了） 2、第2轮开始放随机、固定橙色皮肤
C19: 招募狂欢（红卡） | E19: 8 | F19: 14 | H19: 1、这个时候如果玩家已经开到4级卡池 那么这个奖励无所谓 2、但是如果玩家还未开4级卡池，那么这个给固定卡的感受会更强一些。 3、可仿照招募狂欢后续的活动做一定优化，下期在走纯粹排行
C20: 橙卡试炼 | E20: 5 | F20: 8 | H20: 搭配限时激活礼包
C21: 红卡试炼 | E21: 12 | F21: 15 | H21: 1、增加抽卡额外转盘，提高玩家抽卡转盘（需求需额外开发，待定） 2、周期时间需要规划下，是否间隔太近，让玩家感觉自己橙卡的付费保值性大幅度下滑（蔚蓝放到了19天）
C22: 粉卡试炼（星光炼梦）【转盘2】
C23: 月光炼梦【转盘2】 | E23: 20 | F23: 22 | H23: 核心思路3个 1、钻石购买限制次数 2、提高礼包限制次数 3、抽奖道具活动结束后不使用则回收或者给予一定的资源。付费进行分层，保证普通玩家可以快基本拿到一个保底，如果想拿其他的必须充钱。（目前我们的付费留存和活跃留存远远低于蔚蓝，所以付费分层和服务器生态需要进行优化）
C24: 星轨探测【转盘1】 | E24: 27 | F24: 29
C25: 粉卡限时up
C26: 限时激活礼包
B27: 节日限时 | C27: 大富翁活动
C28: 端午活动
A29: 月度活动 | C29: 首月 | H29: 1、活跃+签到+战令+核心转盘【首月根据玩家进度投放一个主角皮肤，后续则以粉皮为主】+预约奖励 2、是否参考限时活动一样保证一个月的保底策略

Sheet 追求表
B1: 紫 | C1: 东方/镭射 | D1: 亚瑟 | E1: 蜘蛛 | F1: 唐小僧 | G1: 神灯 | H1: 关羽 | I1: 后羿/诸葛/我爱沙 | P1: 海拉/妲己 | W1: 白素贞
A2: 功能新增 | P2: 藏品 | W2: 载具 | AF2: 粉卡
A3: 天数 | B3: 1 | C3: 2 | D3: 3 | E3: 4 | F3: 5 | G3: 6 | H3: 7 | I3: 8 | J3: 9 | K3: 10 | L3: 11 | M3: 12 | N3: 13 | O3: 14 | P3: 15 | Q3: 16 | R3: 17 | S3: 18 | T3: 19 | U3: 20 | V3: 21 | W3: 22 | X3: 23 | Y3: 24 | Z3: 25 | AA3: 26 | AB3: 27 | AC3: 28 | AD3: 29 | AE3: 30 | AF3: 31 | AG3: 32 | AH3: 33 | AI3: 34 | AJ3: 35 | AK3: 36 | AL3: 37 | AM3: 38 | AN3: 39 | AO3: 40 | AP3: 41 | AQ3: 42 | AR3: 43 | AS3: 44 | AT3: 45 | AU3: 46 | AV3: 47 | AW3: 48 | AX3: 49 | AY3: 50 | AZ3: 51 | BA3: 52 | BB3: 53 | BC3: 54 | BD3: 55 | BE3: 56 | BF3: 57 | BG3: 58 | BH3: 59 | BI3: 60
A4: 活动 | B4: 6元首冲
A5: 活动 | B5: 每日特惠(1、6、18) 优化1、6、18元随机宝箱，提高返利
A6: 活动 | B6: 日/周/月礼包
A7: 活动 | B7: 每日充值(25元赠送1个传说祝福石)
A8: 活动 | B8: 大小月卡 18/30
A9: 活动 | B9: 体力战令28/68 | P9: 体力战令28/68（68元增加自选，加一些材料） | AD9: 体力战令28/68（68元增加自选）
A10: 活动 | B10: 周卡（新增金币扫荡） | I10: 周卡（金币扫荡） | P10: 周卡（金币扫荡） | W10: 周卡（（组队双倍）（金币扫荡） | AD10: 周卡（（组队双倍）（金币扫荡） | AK10: 周卡（（组队双倍）（金币扫荡）
A11: 活动 | B11: 钻石战令Ⅰ Ⅱ | W11: 载具战令
A12: 活动 | B12: 七日目标//玩法活跃引导【洗练石引导的问题要不要去掉？改成送个祝福石？】
A13: 活动 | B13: 章节礼包
A14: 活动 | B14: 招募狂欢（3200） | I14: 招募冲刺（红卡魂魄） | P14: 符文冲刺（符文宝石） | W14: 秘宝冲刺（秘宝皮肤） | AD14: 招募冲刺（粉卡魂魄）（藏品） | AK14: 符文冲刺（符文宝石） | AR14: 秘宝冲刺（皮肤+藏品） | AY14: 招募冲刺（粉卡魂魄）（藏品） | BF14: 符文冲刺（符文宝石）
A15: 活动 | F15: 橙卡试炼【皮肤、符文】 | L15: 红卡试炼【符文、皮肤】
A16: 活动 | D16: 礼包
A17: 活动 | P17: 悬赏活动1【符文洗炼藏品】 | W17: 悬赏活动2【组队藏品】 | AD17: 悬赏活动3【招募藏品】 | AK17: 悬赏活动1【周卡迷廊藏品】 | AR17: 悬赏活动2【组队藏品】 | AY17: 悬赏活动3【招募藏品】 | BF17: 悬赏活动1【符文洗炼藏品、符文】
A18: 活动 | B18: 月度活动（红色皮肤、专属符文（限制1个4档）主要是投放皮肤） | AF18: 次月活动（粉卡皮肤）
A19: 限时活动 | I19: 皮肤（天使套）直抽月光炼梦改【5+5】A | P19: 神秘套【月光炼梦】 | AB19: 载具转盘（主投皮肤）星轨探测改（A）
A20: 限时UP | W20: 宇宙套【月光炼梦】 | AF20: 限时up（15天）（骇客） | AU20: 限时up（15天）（雅典娜）
A87: 天数 | B87: 1 | C87: 2 | D87: 3 | E87: 4 | F87: 5 | G87: 6 | H87: 7 | I87: 8 | J87: 9 | K87: 10 | L87: 11 | M87: 12 | N87: 13 | O87: 14 | P87: 15 | Q87: 16 | R87: 17 | S87: 18 | T87: 19 | U87: 20 | V87: 21 | W87: 22 | X87: 23 | Y87: 24 | Z87: 25 | AA87: 26 | AB87: 27 | AC87: 28 | AD87: 29 | AE87: 30 | AF87: 31 | AG87: 32 | AH87: 33 | AI87: 34 | AJ87: 35 | AK87: 36 | AL87: 37 | AM87: 38 | AN87: 39 | AO87: 40 | AP87: 41 | AQ87: 42 | AR87: 43 | AS87: 44 | AT87: 45 | AU87: 46 | AV87: 47 | AW87: 48 | AX87: 49 | AY87: 50 | AZ87: 51 | BA87: 52 | BB87: 53 | BC87: 54 | BD87: 55 | BE87: 56 | BF87: 57 | BG87: 58 | BH87: 59 | BI87: 60
A88: 活动 | B88: 小R
A89: 活动 | B89: 中小R，1元提高付费率，搏一搏，6元和25元搭配连充给予一个长期的目标
A90: 活动 | B90: 日/周/月礼包
A91: 活动 | B91: 每日充值(25元赠送1个传说祝福石) 中 大R的日常付费追求
A92: 活动 | B92: 大小月卡 18/30 全体
A93: 活动 | B93: 体力战令28/68（28元必追，68元后续迭代） | P93: 体力战令28/68（68元增加自选，加一些材料） | AD93: 体力战令28/68（68元增加自选）
A94: 活动 | B94: 周卡（新增金币扫荡）【必追】 | I94: 周卡（金币扫荡） | P94: 周卡（金币扫荡） | W94: 周卡（（组队双倍）（金币扫荡） | AD94: 周卡（（组队双倍）（金币扫荡） | AK94: 周卡（（组队双倍）（金币扫荡）
A95: 活动 | B95: 钻石战令Ⅰ Ⅱ （提高钻石价值后必追） | W95: 载具战令
A96: 活动 | B96: 七日目标//玩法活跃引导
A97: 活动 | B97: 章节礼包
A98: 活动 | C98: 招募狂欢（3000） | I98: 招募冲刺（红卡魂魄） | P98: 符文冲刺（符文宝石） | W98: 秘宝冲刺（皮肤） | AD98: 招募冲刺（粉卡魂魄）（藏品） | AK98: 符文冲刺（符文宝石） | AR98: 秘宝冲刺（皮肤+藏品） | AY98: 招募冲刺（粉卡魂魄）（藏品）
A99: 活动 | F99: 橙卡试炼【皮肤】 | L99: 红卡试炼【符文】
A100: 活动 | E100: 推送
A101: 活动 | P101: 悬赏活动1【符文洗炼藏品、符文】 | W101: 悬赏活动2【月卡藏品、超级洗练石】 | AD101: 悬赏活动3【载具、招募藏品】 | AK101: 悬赏活动1【符文藏品、符文、】 | AR101: 悬赏活动2【增加载具、月卡藏品】 | AY101: 悬赏活动3【招募藏品】
A102: 活动 | B102: 月度活动（红色皮肤、专属符文（限制1个4档）主要是投放皮肤）长线活跃 | AF102: 次月活动（粉卡皮肤）
A103: 限时活动 | I103: 皮肤（天使套）直抽月光炼梦改【5+5】 | AB103: 载具直抽 星轨探测
A104: 限时UP | AF104: 限时up（15天）（骇客） | AU104: 限时up（15天）（雅典娜）
A117: 天数 | B117: 1 | C117: 2~4 | D117: 5~7 | E117: 8 | F117: 9~14 | G117: 15~18 | H117: 19~21 | I117: 22 | J117: 23~24 | K117: 25~27 | L117: 28 | M117: 29~30
A118: 目标定位 | B118: 小R
A119: 目标定位 | B119: 小中R
A120: 目标定位 | B120: 小中R
A121: 目标定位 | B121: 全体玩家
A122: 目标定位 | B122: 全体玩家
A123: 目标定位 | B123: 小中大R
A124: 目标定位 | C124: 小中R | E124: 小中R | G124: 小中R | I124: 小中R
A125: 目标定位 | D125: 中大R | F125: 中大R
A126: 目标定位 | B126: 全体玩家
A127: 目标定位 | H127: 中大R
A128: 目标定位 | H128: 中大R | K128: 小中R
A132: 天数 | B132: 1 | C132: 2~4 | D132: 5~7 | E132: 8 | F132: 9~14 | G132: 15~18 | H132: 19~21 | I132: 22 | J132: 23~24 | K132: 25~27 | L132: 28 | M132: 29~30
B133: 皮肤及养成资源
A134: 产出定位 | B134: 日常资源
A135: 产出定位 | B135: 日常资源
A136: 产出定位 | B136: 日常资源
A137: 产出定位 | B137: 日常资源
A138: 产出定位 | B138: 养成资源
A139: 产出定位 | C139: 养成资源-红卡 | E139: 养成资源-招募券 | G139: 养成资源-高品质图腾 | I139: 养成资源
A140: 产出定位 | D140: 养成资源-红色专属图腾 | F140: 皮肤资源-国王/武器/英雄皮肤
A141: 产出定位 | B141: 日常及养成资源
A142: 产出定位 | H142: 养成资源
A143: 产出定位 | H143: 养成资源-红色专属图腾 | K143: 皮肤资源

Sheet 道具价值表-汇总
A1: 道具id | B1: 道具【梦境】 | C1: 单价（人民币） | D1: 单价（钻石） | E1: 稀有程度 | F1: 特殊运营活动价格（人民币） | G1: 类型 | H1: 品质 | I1: 针对玩家 | J1: 备注 | K1: 计算
A2: 1 | B2: 钻石 | C2: 0.1 | D2: =C2*10 | E2: 常规 | G2: 货币 | H2: 橙 | J2: /
A3: 2 | B3: 金币 | C3: 0.005 | D3: =C3*10 | E3: 常规 | G3: 货币 | H3: 蓝 | J3: /
A4: 9800301 | B4: 金币吸收器 | C4: 5 | D4: 50
A5: 44 | B5: 心梦宝石 | C5: 1.4 | D5: =C5*10 | E5: 受限 | G5: 兑换道具 | H5: 橙 | J5: 每日特惠/循环冲刺活动，兑换商店货币）
A6: 13 | B6: 体力 | C6: 0.2 | D6: =C6*10 | E6: 常规 | G6: 消耗道具 | H6: 紫
A7: 20002 | B7: 梦境奇迹宝箱 | C7: 1 | D7: =C7*10 | E7: 受限 | G7: 消耗道具 | H7: 紫 | J7: 每日特惠礼包
A8: 20038 | B8: 梦境惊喜宝箱 | C8: 8 | D8: 80 | E8: 受限 | J8: 每日特惠礼包
A9: 5600208 | B9: 悬赏线索 | C9: 0.3 | D9: 3 | E9: 受限 | H9: 橙 | J9: 悬赏活动产出的价值
A10: 5203001 | B10: 织梦微尘 | C10: 0.3 | D10: =C10*10 | E10: 受限 | G10: 队长道具 | H10: 蓝 | J10: /
A11: 5103001 | B11: 随机能量特饮 | C11: 0.1 | D11: =C11*10 | E11: 常规 | G11: 梦灵道具 | H11: 蓝 | J11: /
A12: 5104001 | B12: 超能特饮 | C12: 0.2 | D12: =C12*10 | E12: 常规 | G12: 梦灵道具 | H12: 紫 | J12: /
A13: 5600014 | B13: 史诗梦灵碎片 | C13: 1.2 | D13: =C13*10 | E13: 常规 | G13: 梦灵 | H13: 紫 | J13: /
A14: 5600015 | B14: 传说梦灵碎片 | C14: 2.4 | D14: =C14*10 | E14: 受限 | G14: 梦灵 | H14: 橙
B15: 神话梦灵碎片 | C15: 4.8 | D15: =C15*10 | E15: 稀缺 | G15: 梦灵 | H15: 红
B16: 创世梦灵碎片 | C16: 9.6 | D16: =C16*10 | E16: 稀缺 | G16: 梦灵
B17: 自选史诗梦灵碎片 | C17: 1.2 | D17: =C17*10 | E17: 受限 | G17: 梦灵 | J17: /
B18: 自选传说梦灵碎片 | C18: 2.4 | D18: =C18*10 | E18: 受限 | G18: 梦灵
B19: 自选神话梦灵碎片 | C19: 4.8 | D19: =C19*10 | E19: 稀缺 | G19: 梦灵
B20: 自选创世梦灵碎片 | C20: 9.6 | D20: =C20*10 | E20: 稀缺 | G20: 梦灵
B21: 随机史诗梦灵 | C21: 12 | D21: =C21*10 | E21: 受限 | G21: 梦灵 | J21: =D21*0.4
B22: 随机传说梦灵 | C22: 24 | D22: =C22*10 | E22: 受限 | G22: 梦灵 | J22: =D22*0.4
B23: 随机神话梦灵 | C23: 48 | D23: =C23*10 | E23: 稀缺 | G23: 梦灵 | J23: =D23*0.4
B24: 随机创世梦灵 | C24: 96 | D24: =C24*10 | E24: 稀缺 | G24: 梦灵 | J24: =D24*0.4
B25: 自选史诗梦灵 | C25: 12 | D25: =C25*10 | E25: 受限 | G25: 梦灵
B26: 自选传说梦灵 | C26: 24 | D26: =C26*10 | E26: 受限 | G26: 梦灵
B27: 自选神话梦灵 | C27: 48 | D27: =C27*10 | E27: 稀缺 | G27: 梦灵 | J27: /
B28: 自选创世梦灵 | C28: 96 | D28: =C28*10 | E28: 稀缺 | G28: 梦灵
A29: 50002 | B29: 装备图纸 | C29: 0.3 | D29: =C29*10 | E29: 常规 | G29: 装备道具 | H29: 蓝 | J29: /
B30: 固定部位装备图纸 | C30: 0.5 | D30: =C30*10 | E30: 受限 | G30: 装备道具 | J30: /
A31: 50001 | B31: 锻造晶石 | C31: 0.01 | D31: =C31*10 | E31: 常规 | G31: 装备道具 | H31: 蓝 | J31: /
A32: 5303001 | B32: 符引结晶 | C32: 0.5 | D32: =C32*10 | E32: 常规 | G32: 符文 | H32: 蓝 | J32: 200个合成1个，紫色的需要符引结晶
A33: 5305001 | B33: 幻梦晶核 | C33: 6 | D33: =C33*10 | E33: 受限 | G33: 符文 | H33: 橙 | J33: /
A34: 5305010 | B34: 传说祝福石 | C34: 150 | D34: 1500 | E34: 稀缺 | G34: 符文 | H34: 橙
A35: 5305008 | B35: 神话祝福石 | C35: 500 | D35: 5000 | E35: 稀缺 | G35: 符文 | H35: 红
A36: 5305009 | B36: 创世祝福石 | C36: 1600 | D36: 16000 | E36: 稀缺 | G36: 符文 | H36: 粉
A37: 5301000 | B37: 普通符文 | C37: 1.6 | D37: =C37*10 | E37: 常规 | G37: 符文
A38: 5302000 | B38: 优秀符文 | C38: 6.4 | D38: =C38*10 | E38: 常规 | G38: 符文
A39: 5303000 | B39: 稀有符文 | C39: 25.6 | D39: =C39*10 | E39: 常规 | G39: 符文
A40: 5304000 | B40: 史诗符文 | C40: 102.4 | D40: =C40*10 | E40: 受限 | G40: 符文 | J40: 日常获取4折
A41: 5305000 | B41: 传说符文 | C41: 409.6 | D41: =C41*10 | E41: 稀缺 | G41: 符文 | J41: 1638.4 | K41: =D41/2
A42: 5306000 | B42: 神话符文 | C42: 1638.4 | D42: =C42*10 | E42: 稀缺 | G42: 符文 | J42: 6553.6 | K42: =D42/2
A43: 5307000 | B43: 创世符文 | C43: 6553.6 | D43: =C43*10 | E43: 稀缺 | G43: 符文 | J43: 26214.4 | K43: =D43/2
B44: 自选普通符文 | C44: 1.6 | D44: =C44*10 | E44: 受限 | G44: 符文
B45: 自选优秀符文 | C45: 6.4 | D45: =C45*10 | E45: 受限 | G45: 符文
B46: 自选稀有符文 | C46: 25.6 | D46: =C46*10 | E46: 受限 | G46: 符文
B47: 自选史诗符文 | C47: 102.4 | D47: =C47*10 | E47: 受限 | G47: 符文
B48: 自选传说符文 | C48: 409.6 | D48: =C48*10 | E48: 稀缺 | G48: 符文
B49: 自选神话符文 | C49: 1638.4 | D49: =C49*10 | E49: 稀缺 | G49: 符文
B50: 自选创世符文 | C50: 6553.6 | D50: =C50*10 | E50: 稀缺 | G50: 符文 | J50: 0.3
B51: 1【普通】 | D51: 319.48882 | E51: 常规 | G51: 符文 | H51: 紫 | J51: 1
B52: 2【普通】 | D52: 319.48882 | E52: 常规 | G52: 符文 | H52: 紫 | J52: 10
B53: 3【普通】 | D53: 324.72634 | E53: 常规 | G53: 符文 | H53: 紫
B54: 4【专属】 | D54: 1735.5372 | E54: 受限 | G54: 符文 | H54: 紫
B55: 5【稀有】 | E55: 稀缺 | G55: 符文 | H55: 紫
B56: 6【宝属性】 | D56: 29577.465 | E56: 稀缺 | G56: 符文 | H56: 紫 | J56: 洗练定价【获取+洗练价格】80洗一次，200合一个，合2.5一个，主要是暴击率的洗练
B57: 8【专属】 | E57: 受限 | G57: 符文 | H57: 紫
B58: 1【普通】 | D58: 305.08475 | E58: 受限 | G58: 符文 | H58: 橙
B59: 2【普通】 | D59: 305.08475 | E59: 受限 | G59: 符文 | H59: 橙
B60: 3【普通】 | D60: 268.34862 | E60: 受限 | G60: 符文 | H60: 橙
B61: 4【专属】 | D61: 2600 | E61: 稀缺 | G61: 符文 | H61: 橙
B62: 5【稀有】 | D62: 4000 | E62: 稀缺 | G62: 符文 | H62: 橙
B63: 6【宝属性】 | D63: 12857.143 | E63: 稀缺 | G63: 符文 | H63: 橙 | J63: 洗练定价【独立洗练价格】
B64: 8【专属】 | D64: 8571.4286 | E64: 稀缺 | G64: 符文 | H64: 橙
B65: 1【普通】 | D65: 610.16949 | E65: 受限 | G65: 符文 | H65: 红
B66: 2【普通】 | D66: 610.16949 | E66: 受限 | G66: 符文 | H66: 红
B67: 3【普通】 | D67: 536.69725 | E67: 受限 | G67: 符文 | H67: 红
B68: 4【专属】 | D68: 5200 | E68: 稀缺 | G68: 符文 | H68: 红
B69: 5【稀有】 | D69: 8000 | E69: 稀缺 | G69: 符文 | H69: 红
B70: 6【宝属性】 | D70: 25714.286 | E70: 稀缺 | G70: 符文 | H70: 红 | J70: 洗练定价【独立洗练价格】
B71: 8【专属】 | D71: 17142.857 | E71: 稀缺 | G71: 符文 | H71: 红
B72: 1【普通】 | D72: 1016.9492 | E72: 稀缺 | G72: 符文 | H72: 粉
B73: 2【普通】 | D73: 1016.9492 | E73: 稀缺 | G73: 符文 | H73: 粉
B74: 3【普通】 | D74: 894.49541 | E74: 稀缺 | G74: 符文 | H74: 粉
B75: 4【专属】 | D75: 8666.6667 | E75: 稀缺 | G75: 符文 | H75: 粉
B76: 5【稀有】 | D76: 13333.333 | E76: 稀缺 | G76: 符文 | H76: 粉
B77: 6【宝属性】 | D77: 42857.143 | E77: 稀缺 | G77: 符文 | H77: 粉 | J77: 洗练定价【独立洗练价格】
B78: 8【专属】 | D78: 28571.429 | E78: 稀缺 | G78: 符文 | H78: 粉
B79: 传说英雄随机珍稀符文 | C79: 70 | D79: =C79*10 | E79: 稀缺 | G79: 符文 | J79: 梦灵试炼（橙卡） | K79: =D41+D61
B80: 传说英雄随机稀世符文 | C80: 250 | D80: =C80*10 | E80: 稀缺 | G80: 符文 | J80: 梦灵试炼（红卡）
B81: 绝世英雄传说随机专属符文 | C81: 300 | D81: =C81*10 | E81: 稀缺 | G81: 符文
B82: 绝世英雄神话随机专属符文 | C82: 600 | D82: =C82*10 | E82: 稀缺 | G82: 符文
A83: 5304000 | B83: 史诗符文 | C83: 102.4 | D83: =C83*10 | E83: 受限 | G83: 符文 | H83: 紫 | J83: 6元首冲礼包
A84: 62 | B84: 智械发条 | C84: 15 | D84: =C84*10 | E84: 受限 | G84: 抽奖道具 | H84: 橙
A85: 63 | B85: 精密齿轮 | C85: 0.1 | D85: =C85*10 | E85: 受限 | G85: 零件 | H85: 紫
A86: 6030001 | B86: 随机史诗零件碎片 | C86: =C90/10 | D86: =C86*10 | E86: 受限 | G86: 零件 | H86: 紫
A87: 6030002 | B87: 随机传说零件碎片 | C87: =C91/10 | D87: =C87*10 | E87: 稀缺 | G87: 零件 | H87: 橙
A88: 6030003 | B88: 随机神话零件碎片 | C88: =C92/10 | D88: =C88*10 | E88: 稀缺 | G88: 零件 | H88: 红
A89: 6030004 | B89: 随机创世零件碎片 | C89: =C93/10 | D89: =C89*10 | E89: 稀缺 | G89: 零件 | H89: 粉
A90: 6040001 | B90: 随机史诗零件 | C90: 200 | D90: =C90*10 | E90: 受限 | G90: 零件 | K90: =D90/2
A91: 6040002 | B91: 随机传说零件 | C91: 400 | D91: =C91*10 | E91: 稀缺 | G91: 零件 | K91: =D91/2
A92: 6040003 | B92: 随机神话零件 | C92: 800 | D92: =C92*10 | E92: 稀缺 | G92: 零件 | K92: =D92/2
A93: 6040004 | B93: 随机创世零件 | C93: 1600 | D93: =C93*10 | E93: 稀缺 | G93: 零件 | K93: =D93/2
A94: 6110030 | B94: 织梦捕星机 | C94: 1200 | D94: =C94*10 | E94: 稀缺 | G94: 零件 | H94: 红
A95: 5523002 | B95: 转运石 | C95: 0.033 | D95: =C95*10 | E95: 常规 | G95: 秘宝 | H95: 紫 | J95: / | K95: 100112
A96: 100086 | B96: 自选传说秘宝皮肤 | C96: 600 | D96: =C96*10 | E96: 稀缺 | G96: 秘宝
B97: 自选神话秘宝皮肤 | C97: 1200 | D97: =C97*10 | E97: 稀缺 | G97: 秘宝
A98: 11 | B98: 梦境招募器 | C98: 3 | D98: =C98*10 | E98: 常规 | G98: 抽奖道具 | H98: 紫 | J98: /
A99: 35 | B99: 梦愿水晶 | C99: 60 | D99: =C99*10 | E99: 受限 | G99: 抽奖道具 | H99: 橙 | J99: /
A100: 9 | B100: 星之初愿 | C100: 5 | D100: =C100*10 | E100: 常规 | G100: 抽奖道具 | H100: 紫 | J100: /
...

Sheet item
A1: 道具id | B1: 道具名字 | C1: 道具描述
A2: id | B2: name | C2: desc
B5: 货币 | C5: 道具id段：1~10000，基础货币和各种活动代币
A8: 1 | B8: 钻石 | C8: 梦境由认知构成，因此钻石成为了梦境中非常稀有的流通货币，珍贵的钻石总是蕴含着宛若星辰的辉芒
A9: 2 | B9: 金币 | C9: 梦境由认知构成，因此金币便成了梦境中最为通用的货币，没有人能拒绝金光闪闪的东西
A10: 5 | B10: 日活跃度 | C10: 是护卫队每日在梦境中活跃完成任务的象征，达到一定目标即可领取额外奖励
A11: 6 | B11: 周活跃度 | C11: 是护卫队每周在梦境中活跃完成任务的象征，达到一定目标即可领取额外奖励
A12: 7 | B12: 通行证积分 | C12: 消耗1点体力获取1点积分，达到积分可获得相应奖励
A13: 9 | B13: 星之初愿 | C13: 星愿铸成的指引之钥，可用于商店进行符文招募
A14: 10 | B14: 代金券 | C14: 存在于虚幻与现实中的货币，在梦境中能代替现实货币用于购买付费商品
A15: 11 | B15: 梦境招募器 | C15: 梦境中彩虹机器的启动器，可用于商店进行梦灵招募
A16: 12 | B16: 成就点 | C16: 任务中获得的成就点
A17: 13 | B17: 体力 | C17: 梦境护卫队在梦境中的行动都需要消耗体力，如果体力不足，则需要养精蓄锐，择时再战
A18: 14 | B18: 等级经验 | C18: 梦境护卫队的每次行动都会获得等级经验，累积等级经验可以提高梦境护卫队的等级，从而进行更高难度的行动
A19: 15 | B19: 七日挑战活跃点 | C19: 在七日挑战中完成任务后可以获得活跃点，达到指定数量即可领取节点奖励
... A64: 65 | B64: 星铸等级经验 | C64: 获得后可增加星铸之路等级经验
B66: 实物奖励
A67: 1001 | B67: 5万梦想基金 | C67: 次元旅行启动！美团联名消费卡，助你实现双人现世游。
A68: 1002 | B68: 睡衣套装 | C68: 联动定制，软糯亲肤触感。
A69: 1003 | B69: 喜马拉雅月卡 | C69: 喜马拉雅会员权益，海量疗愈声波，带你沉浸式漫游次元。
A70: 1004 | B70: 眼罩周边 | C70: 梦境伴侣，带您沉浸入梦。
A71: 1005 | B71: 助眠枕头 | C71: 跨界补给，让你一秒进入深度梦境。
A72: 1006 | B72: 黄金金钞 | C72: 专属定制黄金金钞，定格梦境高光时刻。
A73: 1007 | B73: 盲盒 | C73: 梦境盲盒，玩转你的梦灵人格！
A74: 1008 | B74: 苹果手机 | C74: 限定实物大奖，梦境限定稀有奖励。
A75: 1009 | B75: 好梦枕头 | C75: 助眠好梦枕头实物奖励，让你一秒进入深度梦境。
A76: 1010 | B76: 睡衣套装 | C76: 联动定制，软糯亲肤触感。
A77: 1011 | B77: 喜马拉雅月卡 | C77: 喜马拉雅会员权益，海量疗愈声波，带你沉浸式漫游次元。
A78: 1012 | B78: 眼罩周边 | C78: 梦境伴侣，带您沉浸入梦。
... A85: 1019 | B85: 黄金金钞 | C85: 专属定制黄金金钞，定格梦境高光时刻。
B89: 梦灵养成道具【正式】 | C89: 道具id段：51+职业【1位】+品质【1位】+排序【3位】
A91: 5103001 | B91: 随机能量特饮 | C91: 职业的能量特饮，可获得随机的职业能量特饮
A92: 5103002 | B92: 随机能量特饮 | C92: 职业的能量特饮，可获得随机的职业能量特饮
A93: 5103003 | B93: 随机能量特饮 | C93: 职业的能量特饮，可获得随机的职业能量特饮
A94: 5104001 | B94: 超能特饮 | C94: 超级能量特饮，对应梦灵特饮不足时，可用超能特饮替代消耗
A95: 5113001 | B95: 战士特饮 | C95: 战士职业的能量特饮，可用于战士梦灵升级
A96: 5123001 | B96: 法师特饮 | C96: 法师职业的能量特饮，可用于法师梦灵升级
A97: 5133001 | B97: 射手特饮 | C97: 射手职业的能量特饮，可用于射手梦灵升级
A98: 5143001 | B98: 辅助特饮 | C98: 辅助职业的能量特饮，可用于辅助梦灵升级
A99: 5153001 | B99: 控制特饮 | C99: 控制职业的能量特饮，可用于控制梦灵升级
A100: 5163001 | B100: 毒系特饮 | C100: 毒系职业的能量特饮，可用于毒系梦灵升级
A101: 5173001 | B101: 召唤特饮 | C101: 召唤职业的能量特饮，可用于召唤梦灵升级
A102: 5182001 | B102: 优秀梦灵通用碎片 | C102: 优秀梦灵升星通用材料,本体碎片不足时,可用通用碎片替代消耗。
... A107: 5187001 | B107: 创世梦灵通用碎片 | C107: 创世梦灵升星通用材料,本体碎片不足时,可用通用碎片替代消耗。
B109: 主角皮肤道具，武器/时装/秘宝【正式】 | C109: 道具id段：55+类型【1位，0=武器， 1=时装 ，2=秘宝】+品质【1位】+排序【3位】
C111: 主角武器↓
A112: 5505001 | B112: 喵喵锤 | C112: 可用于激活或升星【喵喵锤】武器皮肤
A113: 5505002 | B113: 鸭鸭锤 | C113: 可用于激活或升星【鸭鸭锤】武器皮肤
A114: 5505003 | B114: 机械锤 | C114: 可用于激活或升星【机械锤】武器皮肤
A115: 5505004 | B115: 科技锤 | C115: 可用于激活或升星【科技锤】武器皮肤
A116: 5505005 | B116: 鲨鱼锤 | C116: 可用于激活或升星【鲨鱼锤】武器皮肤
A117: 5505006 | B117: 蛋糕锤 | C117: 可用于激活或升星【蛋糕锤】武器皮肤
A118: 5505007 | B118: 小狗锤 | C118: 可用于激活或升星【小狗锤】武器皮肤
A119: 5505008 | B119: 苦尽柑来 | C119: 别人问这柑什么味，你就回他三个字：橘内人
A120: 5505009 | B120: 如意 | C120: 可用于激活或升星【如意】武器皮肤
A121: 5505010 | B121: 奇异权杖 | C121: 可用于激活或升星【奇异权杖】武器皮肤
A122: 5505016 | B122: 开翼未来 | C122: 可用于激活或升星【开翼未来】武器皮肤
A123: 5505014 | B123: 大开眼戒 | C123: 可用于激活或升星【大开眼戒】武器皮肤
... A126: 5506002 | B126: 小狗锤 | C126: 可用于激活或升星【小狗锤】武器皮肤
C129: 主角时装↓
A130: 10150010 | B130: 星航制服 | C130: 可用于激活或升星【星航制服】主角皮肤
A131: 10350010 | B131: 星航头盔 | C131: 可用于激活或升星【星航头盔】主角皮肤
A132: 10150020 | B132: 云仙道袍 | C132: 可用于激活或升星【云仙道袍】主角皮肤
A133: 10350020 | B133: 云仙头饰 | C133: 可用于激活或升星【云仙头饰】主角皮肤
A134: 10150030 | B134: 神秘影袍 | C134: 可用于激活或升星【神秘影袍】主角皮肤
A135: 10350030 | B135: 神秘影帽 | C135: 可用于激活或升星【神秘影帽】主角皮肤
A136: 10140010 | B136: 灰色校园校服 | C136: 可用于激活或升星【灰色校园校服】主角皮肤
A137: 101400101 | B137: 红色校园校服 | C137: 可用于激活或升星【红色校园校服】主角皮肤
A138: 101400102 | B138: 蓝色校园校服 | C138: 可用于激活或升星【蓝色校园校服】主角皮肤
A139: 10340010 | B139: 灰色校园发饰 | C139: 可用于激活或升星【灰色校园发饰】主角皮肤
A140: 103400101 | B140: 红色校园发饰 | C140: 可用于激活或升星【红色校园发饰】主角皮肤
A141: 103400102 | B141: 蓝色校园发饰 | C141: 可用于激活或升星【蓝色校园发饰】主角皮肤
... A261: 10140370 | B261: 咕勇者服饰 | C261: 可用于激活或升星【咕勇者服饰】主角皮肤
C265: 主角秘宝↓
A266: 5523001 | B266: 转运石 | C266: 可用于洗炼秘宝的特殊道具
A267: 5523003 | B267: 欧气补给袋 | C267: 开启后可获得随机数量的转运石
A268: 5523004 | B268: 欧气补给箱 | C268: 开启后可获得随机数量的转运石
A269: 5523005 | B269: 转运石盲盒壹 | C269: 开启后可获得随机数量的转运石
A270: 5523006 | B270: 转运石盲盒贰 | C270: 开启后可获得随机数量的转运石
A271: 5523007 | B271: 转运石盲盒叁 | C271: 开启后可获得随机数量的转运石
A272: 5523008 | B272: 转运石盲盒肆 | C272: 开启后可获得随机数量的转运石
A273: 5523009 | B273: 转运石盲盒伍 | C273: 开启后可获得随机数量的转运石
A274: 5523010 | B274: 转运石盲盒陆 | C274: 开启后可获得随机数量的转运石
A275: 5523011 | B275: 转运石盲盒柒 | C275: 开启后可获得随机数量的转运石
A276: 5523012 | B276: 转运石盲盒捌 | C276: 开启后可获得随机数量的转运石
A277: 5523013 | B277: 转运石盲盒玖 | C277: 开启后可获得随机数量的转运石
... A301: 5526005 | B301: 我爱沙专属 | C301: 可用于激活或升星【我爱沙专属】秘宝皮肤
B303: 遗留物品 | C303: 道具id段：10001~19999，各种物品和展示道具
A305: 10002 | B305: 能量特饮 | C305: 职业的能量特饮，激发潜能，可用于梦灵升级
A306: 10008 | B306: 战士特饮 | C306: 战士职业的能量特饮，激发潜能，可用于战士梦灵升级
A307: 10009 | B307: 法师特饮 | C307: 法师职业的能量特饮，激发潜能，可用于法师梦灵升级
A308: 10010 | B308: 猎手特饮 | C308: 猎手职业的能量特饮，激发潜能，可用于猎手梦灵升级
A309: 10011 | B309: 辅助特饮 | C309: 辅助职业的能量特饮，激发潜能，可用于辅助梦灵升级
A310: 10012 | B310: 毒系特饮 | C310: 毒系职业的能量特饮，激发潜能，可用于毒系梦灵升级
A312: 10001 | B312: 装备强化石 | C312: 可用于强化装备
A313: 10003 | B313: 突破核心 | C313: 梦灵升级和升星提升到一定程度时突破需要用到的材料
A314: 10004 | B314: 基因罐 | C314: 具有特殊力量的序列，可用于在武器研究中解锁技能节点
A315: 10005 | B315: 巅峰突破石 | C315: 蕴含巅峰力量的石头，可帮助梦灵突破巅峰，
A316: 10006 | B316: 重铸石 | C316: 一种罕见的矿石，可用于戒指重铸技能
A317: 10007 | B317: 回溯沙漏 | C317: 可用于11星以上梦灵星级重置
...

Sheet 特惠+充值
A1: 日礼包
H2: 汇总
A3: 免费/广告 | B3: 道具 | C3: 道具id | D3: 数量 | E3: 单价 | F3: 价值 | H3: 体力 | I3: =SUMIF($B$4:$B$30,H3,$D$4:$D$35)
B4: 装备图纸 | C4: {=B4} | D4: 10 | E4: {=B4} | F4: =D4*E4 | H4: 梦境招募器 | I4: =SUMIF($B$4:$B$30,H4,$D$4:$D$35)
B5: 心梦宝石 | C5: {=B5} | D5: 1 | E5: {=B5} | F5: =D5*E5 | H5: 梦境奇迹宝箱 | I5: =SUMIF($B$4:$B$30,H5,$D$4:$D$35)
H6: 心梦宝石 | I6: =SUMIF($B$4:$B$30,H6,$D$4:$D$35) | M6: 价值
J7: 调整前 | L7: 梦境奇迹宝箱 | M7: 40
B8: 超值礼包 | J8: 道具 | K8: 道具id | L8: 道具数量 | M8: 单价 | N8: 权重
A9: 1元 | B9: 道具 | C9: 道具id | D9: 数量 | E9: 单价 | F9: 价值 | G9: =SUM(F10:F13)/10 | J9: 幻梦晶核 | K9: {=J9} | L9: 1 | M9: {=J9} | N9: 250
B10: 体力 | C10: {=B10} | D10: 10 | E10: {=B10} | F10: =D10*E10 | J10: 星辉秘契 | K10: {=J10} | L10: 1 | M10: {=J10} | N10: 250
B11: 梦境招募器 | C11: {=B11} | D11: 5 | E11: {=B11} | F11: =D11*E11 | J11: 梦境招募器 | K11: {=J11} | L11: 5 | M11: {=J11} | N11: 500
B12: 梦境奇迹宝箱 | C12: {=B12} | D12: 1 | E12: 80 | F12: =D12*E12 | J12: 随机能量特饮 | K12: {=J12} | L12: 25 | M12: {=J12} | N12: 2000
B13: 心梦宝石 | C13: {=B13} | D13: 2 | E13: {=B13} | F13: =D13*E13 | J13: 星之初愿 | K13: {=J13} | L13: 1 | M13: {=J13} | N13: 1000
J14: 符引结晶 | K14: {=J14} | L14: 5 | M14: {=J14} | N14: 2000
B15: 优选礼包 | J15: 装备图纸 | K15: {=J15} | L15: 10 | M15: {=J15} | N15: 2000
A16: 6元 | B16: 道具 | C16: 道具id | D16: 数量 | E16: 单价 | F16: 价值 | G16: =SUM(F17:F20)/60 | J16: 金币 | K16: {=J16} | L16: 200 | M16: {=J16} | N16: 2000
B17: 体力 | C17: {=B17} | D17: 15 | E17: {=B17} | F17: =D17*E17
B18: 梦境招募器 | C18: {=B18} | D18: 15 | E18: {=B18} | F18: =D18*E18
B19: 梦境奇迹宝箱 | C19: {=B19} | D19: 2 | E19: 80 | F19: =D19*E19 | M19: 价值
B20: 心梦宝石 | C20: {=B20} | D20: 6 | E20: {=B20} | F20: =D20*E20 | J20: 调整后 | L20: 梦境奇迹宝箱 | M20: 80 | P20: 梦境惊喜宝箱
J21: 道具 | K21: 道具id | L21: 道具数量 | M21: 价格 | N21: 权重 | O21: 概率 | P21: 单价
B22: 尊享礼包 | J22: 梦境招募器 | K22: {=J22} | L22: 66 | M22: {=J22} | N22: 50 | O22: =N22/10000 | P22: =O22*M22*L22
A23: 18元 | B23: 道具 | C23: 道具id | D23: 数量 | E23: 单价 | F23: 价值 | G23: =SUM(F24:F27)/180 | J23: 梦境招募器 | K23: {=J23} | L23: 10 | M23: {=J23} | N23: 290 | O23: =N23/10000 | P23: =O23*M23*L23
B24: 体力 | C24: {=B24} | D24: 25 | E24: {=B24} | F24: =D24*E24 | J24: 梦境招募器 | K24: {=J24} | L24: 5 | M24: {=J24} | N24: 800 | O24: =N24/10000 | P24: =O24*M24*L24
B25: 星辉秘契 | C25: {=B25} | D25: 2 | E25: {=B25} | F25: =D25*E25 | J25: 随机能量特饮 | K25: {=J25} | L25: 50 | M25: {=J25} | N25: 1450 | O25: =N25/10000 | P25: =O25*M25*L25
B26: 梦境奇迹宝箱 | C26: {=B26} | D26: 3 | E26: 80 | F26: =D26*E26 | J26: 星之初愿 | K26: {=J26} | L26: 2 | M26: {=J26} | N26: 1810 | O26: =N26/10000 | P26: =O26*M26*L26
B27: 心梦宝石 | C27: {=B27} | D27: 15 | E27: {=B27} | F27: =D27*E27 | J27: 符引结晶 | K27: {=J27} | L27: 10 | M27: {=J27} | N27: 1500 | O27: =N27/10000 | P27: =O27*M27*L27
J28: 装备图纸 | K28: {=J28} | L28: 20 | M28: {=J28} | N28: 1800 | O28: =N28/10000 | P28: =O28*M28*L28
J29: 金币 | K29: {=J29} | L29: 500 | M29: {=J29} | N29: 2300 | O29: =N29/10000 | P29: =O29*M29*L29
A30: 累充
A32: 仅钻石商店和冲刺礼包计入额度
D34: 赠送
B35: 钻石 | D35: 道具 | E35: id | F35: 数量 | G35: 单价 | H35: 整体价值 | I35: 返利比
A36: 累计充值 | B36: 60 | D36: 体力 | E36: {=D36} | F36: 20 | G36: {=D36} | H36: =G36*F36 | I36: =H36/B36
A37: 累计充值 | B37: 300 | D37: 梦境招募器 | E37: {=D37} | F37: 10 | G37: {=D37} | H37: =G37*F37 | I37: =H37/(B37-B36)
A38: 累计充值 | B38: 600 | D38: 金币 | E38: {=D38} | F38: 3000 | G38: {=D38} | H38: =G38*F38 | I38: =H38/(B38-B37)
A39: 累计充值 | B39: 1280 | D39: 星辉秘契 | E39: {=D39} | F39: 1 | G39: {=D39} | H39: =G39*F39 | I39: =H39/(B39-B38)
A40: 累计充值 | B40: 3280 | D40: 幻梦晶核 | E40: {=D40} | F40: 24 | G40: {=D40} | H40: =G40*F40 | I40: =H40/(B40-B39)
A44: 每日充值
B47: 6元档次 | N47: 25元档次
B48: 天数 | C48: 道具 | D48: id | E48: 数量 | F48: 单价 | G48: 道具 | H48: id | I48: 数量 | J48: 单价 | K48: 价值 | N48: 天数 | O48: 道具 | P48: id | Q48: 数量 | R48: 单价 | S48: 道具 | T48: id | U48: 数量 | V48: 单价 | W48: 价值
B49: 1 | C49: 金币 | D49: {=C49} | E49: 800 | F49: {=C49} | G49: 随机能量特饮 | H49: {=G49} | I49: 50 | J49: {=G49} | K49: =J49*I49+F49*E49 | N49: 1 | O49: 金币吸收器 | P49: 9800301 | Q49: 1 | R49: {=O49} | S49: 随机能量特饮 | T49: {=S49} | U49: 150 | V49: {=S49} | W49: =V49*U49+R49*Q49 | X49: 稿子*1
B50: 2 | C50: 星之初愿 | D50: {=C50} | E50: 1 | F50: {=C50} | G50: 随机能量特饮 | H50: {=G50} | I50: 50 | J50: {=G50} | K50: =J50*I50+F50*E50 | N50: 2 | O50: 星之初愿 | P50: 9 | Q50: 1 | R50: {=O50} | S50: 随机能量特饮 | T50: {=S50} | U50: 150 | V50: {=S50} | W50: =V50*U50+R50*Q50
B51: 3 | C51: 锻造晶石 | D51: {=C51} | E51: 50 | F51: {=C51} | G51: 随机能量特饮 | H51: {=G51} | I51: 50 | J51: {=G51} | K51: =J51*I51+F51*E51 | N51: 3 | O51: 装备图纸 | P51: 50002 | Q51: 50 | R51: {=O51} | S51: 随机能量特饮 | T51: {=S51} | U51: 150 | V51: {=S51} | W51: =V51*U51+R51*Q51
B52: 4 | C52: 织梦微尘 | D52: {=C52} | E52: 25 | F52: {=C52} | G52: 随机能量特饮 | H52: {=G52} | I52: 50 | J52: {=G52} | K52: =J52*I52+F52*E52 | N52: 5 | O52: 金币吸收器 | P52: 9800301 | Q52: 1 | R52: {=O52} | S52: 随机能量特饮 | T52: {=S52} | U52: 150 | V52: {=S52} | W52: =V52*U52+R52*Q52 | X52: 稿子*1
B53: 5 | C53: 金币 | D53: {=C53} | E53: 800 | F53: {=C53} | G53: 随机能量特饮 | H53: {=G53} | I53: 50 | J53: {=G53} | K53: =J53*I53+F53*E53 | N53: 4 | O53: 星之初愿 | P53: 9 | Q53: 1 | R53: {=O53} | S53: 随机能量特饮 | T53: {=S53} | U53: 150 | V53: {=S53} | W53: =V53*U53+R53*Q53
B54: 6 | C54: 金币吸收器 | D54: {=C54} | E54: 1 | F54: {=C54} | G54: 随机能量特饮 | H54: {=G54} | I54: 50 | J54: {=G54} | K54: =J54*I54+F54*E54 | N54: 6 | O54: 装备图纸 | P54: 50002 | Q54: 50 | R54: {=O54} | S54: 随机能量特饮 | T54: {=S54} | U54: 150 | V54: {=S54} | W54: =V54*U54+R54*Q54
B55: 7 | C55: 星之初愿 | D55: {=C55} | E55: 1 | F55: {=C55} | G55: 随机能量特饮 | H55: {=G55} | I55: 50 | J55: {=G55} | K55: =J55*I55+F55*E55 | N55: 5 | O55: 金币吸收器 | P55: 9800301 | Q55: 1 | R55: {=O55} | S55: 随机能量特饮 | T55: {=S55} | U55: 150 | V55: {=S55} | W55: =V55*U55+R55*Q55 | X55: 稿子*2
B57: 天数 | C57: 道具 | D57: id | E57: 数量 | F57: 单价 | G57: 价值 | N57: 天数 | O57: 道具 | P57: id | Q57: 数量 | R57: 价值
B58: 2 | C58: 梦境招募器 | D58: {=C58} | E58: 10 | F58: {=C58} | G58: =F58*E58 | N58: 2 | O58: 梦愿水晶 | P58: {=O58} | Q58: 1 | R58: {=O58}
B59: 4 | C59: 梦愿水晶 | D59: {=C59} | E59: 1 | F59: {=C59} | G59: =F59*E59 | N59: 4 | O59: 星辉秘契 | P59: {=O59} | Q59: 5 | R59: {=O59}
B60: 6 | C60: 幻梦晶核 | D60: {=C60} | E60: 6 | F60: {=C60} | G60: =F60*E60 | N60: 6 | O60: 传说祝福石 | P60: {=O60} | Q60: 1 | R60: {=O60}
A89: 礼包 | B89: 奖励内容 | C89: 道具id | D89: 奖励数量 | E89: 单价 | F89: 价值 | G89: 奖励内容 | H89: 道具id | I89: 奖励数量 | J89: 单价 | K89: 价值 | L89: 奖励内容 | M89: 道具id | N89: 奖励数量 | O89: 单价 | P89: 价值 | Q89: 价值 | R89: 目前价格 | S89: 修改价格 | T89: 暂定价格 | U89: 暂定价格 | V89: 限购
A90: 1 | B90: 梦境招募器 | C90: {=B90} | D90: 25 | E90: {=B90} | F90: =D90*E90 | G90: 星之初愿 | H90: {=G90} | I90: 2 | J90: {=G90} | K90: =I90*J90 | L90: 随机能量特饮 | M90: {=L90} | N90: 88 | O90: {=L90} | P90: =N90*O90 | Q90: =P90+K90+F90 | R90: 388 | S90: =R90/Q90 | T90: =Q90*0.5 | U90: 488 | V90: 1
A91: 2 | B91: 梦境招募器 | C91: {=B91} | D91: 50 | E91: {=B91} | F91: =D91*E91 | G91: 星之初愿 | H91: {=G91} | I91: 4 | J91: {=G91} | K91: =I91*J91 | L91: 随机能量特饮 | M91: {=L91} | N91: 168 | O91: {=L91} | P91: =N91*O91 | Q91: =P91+K91+F91 | R91: 788 | S91: =R91/Q91 | T91: =Q91*0.5 | U91: 938 | V91: 2
A92: 3 | B92: 梦境招募器 | C92: {=B92} | D92: 100 | E92: {=B92} | F92: =D92*E92 | G92: 星辉秘契 | H92: {=G92} | I92: 2 | J92: {=G92} | K92: =I92*J92 | L92: 随机能量特饮 | M92: {=L92} | N92: 288 | O92: {=L92} | P92: =N92*O92 | Q92: =P92+K92+F92 | R92: 1688 | S92: =R92/Q92 | T92: =Q92*0.5 | U92: 1988 | V92: 3

Sheet 首充+三卡
A1: 首充活动 | W1: 8
A3: 价格 | B3: 备注 | C3: 道具 | D3: 道具id | E3: 数量 | F3: 单价 | G3: 价值 | H3: 道具 | I3: 道具id | J3: 数量 | K3: 单价 | L3: 价值 | M3: 道具 | N3: 道具id | O3: 数量 | P3: 单价 | Q3: 价值 | R3: 道具 | S3: 道具id | T3: 数量 | U3: 单价 | V3: 价值
A4: 6 | B4: 直购 | C4: 喵喵锤 | D4: 5505001 | E4: 1 | F4: 4000 | G4: =F4*E4 | H4: 梦境招募器 | I4: 11 | J4: 10 | K4: {=H4} | L4: =K4*J4 | M4: 史诗符文 | N4: 5304000 | O4: 1 | Q4: 256 | R4: 当天特权卡 | S4: 100040 | T4: 1 | V4: 300
C5: 梦境招募器 | D5: 11 | E5: 20 | F5: {=C5} | G5: =F5*E5 | H5: 超能特饮 | I5: 5104001 | J5: 300 | K5: {=H5} | L5: =K5*J5 | V5: =V4+Q4+L4+G4 | W5: =V5/60
C6: 随机传说梦灵 | D6: 5600005 | E6: 1 | F6: {=C6} | G6: =F6*E6 | H6: 超能特饮 | I6: 5104001 | J6: 500 | K6: {=H6} | L6: =K6*J6 | V6: =L5+G5 | W6: =V6/60
V7: =L6+G6 | W7: =V7/60
A8: 30 | B8: 累充 | C8: 镭射 | D8: 1530100 | E8: 1 | F8: 480 | G8: =F8*E8 | H8: 超能特饮 | I8: 5104001 | J8: 300 | K8: {=H8} | L8: =K8*J8 | M8: 金币 | N8: 2 | O8: 3000 | P8: {=M8} | Q8: =P8*O8
C9: 星之初愿 | D9: {=C9} | E9: 5 | F9: {=C9} | G9: =F9*E9 | H9: 装备图纸 | I9: {=H9} | J9: 100 | K9: {=H9} | L9: =K9*J9
C10: 梦境招募器 | D10: {=C10} | E10: 10 | F10: {=C10} | G10: =F10*E10 | H10: 装备图纸 | I10: {=H10} | J10: 150 | K10: {=H10} | L10: =K10*J10
A12: 68 | B12: 累充 | C12: 无心睡眠 | D12: 15301011 | E12: 1 | F12: 4000 | G12: =F12*E12 | H12: 装备图纸 | I12: {=H12} | J12: 100 | K12: {=H12} | L12: =K12*J12 | M12: 金币 | N12: 2 | O12: 5000 | P12: {=M12} | Q12: =P12*O12
C13: 星辉秘契 | D13: {=C13} | E13: 2 | F13: {=C13} | G13: =F13*E13 | H13: 梦境招募器 | I13: {=H13} | J13: 10 | K13: {=H13} | L13: =K13*J13
C14: 星辉秘契 | D14: {=C14} | E14: 3 | F14: {=C14} | G14: =F14*E14 | H14: 梦境招募器 | I14: {=H14} | J14: 20 | K14: {=H14} | L14: =K14*J14
R15: 价值 | S15: 反比
C16: 道具 | D16: 道具id | E16: 数量 | F16: 单价 | G16: 价值 | H16: 道具 | I16: 道具id | J16: 数量 | K16: 单价 | L16: 价值 | M16: 道具 | N16: 道具id | O16: 数量 | P16: 单价 | Q16: 价值
A17: 68 | B17: 单笔 | C17: 镭射 | D17: 1530100 | E17: 1 | F17: 480 | G17: =F17*E17 | H17: 无心睡眠 | I17: 15301011 | J17: 1 | K17: 4000 | L17: =K17*J17 | M17: 超能特饮 | N17: {=M17} | O17: 200 | P17: {=M17} | Q17: =P17*O17 | R17: =Q17+L17+G17 | S17: =R17/A17/10 | T17: =S17+S18+S19
C18: 镭射 | D18: 1530100 | E18: 2 | F18: 480 | G18: =F18*E18 | H18: 装备图纸 | I18: {=H18} | J18: 100 | K18: {=H18} | L18: =K18*J18 | R18: =Q18+L18+G18 | S18: =R18/A17/10
C19: 镭射 | D19: 1530100 | E19: 3 | F19: 480 | G19: =F19*E19 | H19: 装备图纸 | I19: {=H19} | J19: 200 | K19: {=H19} | L19: =K19*J19 | R19: =Q19+L19+G19 | S19: =R19/A17/10
A21: 128 | B21: 单笔 | C21: 紫色勇者服 | D21: 101400302 | E21: 1 | F21: 4000 | G21: =F21*E21 | H21: 紫色勇者发饰 | I21: {=H21} | J21: 1 | K21: 1 | L21: 1000 | M21: 金币 | N21: {=M21} | O21: 3000 | P21: {=M21} | Q21: =P21*O21 | R21: =Q21+L21+G21 | S21: =R21/A21/10 | T21: =S21+S22+S23
C22: 星辉秘契 | D22: {=C22} | E22: 3 | F22: {=C22} | G22: =F22*E22 | H22: 金币 | I22: {=H22} | J22: 4000 | K22: {=H22} | L22: =K22*J22 | R22: =Q22+L22+G22 | S22: =R22/A21/10
C23: 星辉秘契 | D23: {=C23} | E23: 5 | F23: {=C23} | G23: =F23*E23 | H23: 金币 | I23: {=H23} | J23: 5000 | K23: {=H23} | L23: =K23*J23 | R23: =Q23+L23+G23 | S23: =R23/A21/10
A25: 月卡
B27: 新增一些广告点
B28: 特权月卡 | H28: 福利月卡
B30: 道具 | C30: 道具id | D30: 数量 | H30: 道具 | I30: 道具id | J30: 数量
A31: 每日 | B31: 钻石 | C31: 1 | D31: 60 | G31: 每日 | H31: 钻石 | I31: 1 | J31: 100
B32: 梦境招募器 | C32: 11 | D32: 2 | H32: 体力 | I32: 13 | J32: 10
H34: 已通关主线支持2倍速
B35: 特权无限使用 | C35: 无限 | H35: 争锋、捞金、贪吃支持2倍速
B36: 精品商店刷新次数 | C36: 3 | H36: 睡眠时间+4小时，收益+30%
B37: 心愿招募刷新 | C37: 1 | H37: 梦域巡航可领取特权门票+1
A41: 激活 | B41: 双卡奖励 | C41: 道具id | D41: 数量
B42: 梦境招募器 | C42: 11 | D42: 20
B43: 星辉秘契 | C43: 30 | D43: 2
B44: 聊天框 | C44: 1 | D44: 1%暴击
A47: 特权周卡（签到）
C52: 特权
C54: 合作模式可获得双倍奖励
C55: 每天首次协助合作，可获得队长奖励
C56: 梦隙迷廊通关迷廊币+20%
C58: 签到奖励
C59: 免费 | J59: 优化点 | K59: 活跃活动3次组队副本的达成率只有40%多点，也就是很多人是打不满的
C60: 道具 | D60: 道具id | E60: 数量 | F60: 单价 | G60: 价值 | J60: 所以需要增加队员多倍券。金币扫荡券（当日生效）越往后价值越高
B61: 1 | C61: 装备图纸 | D61: 50002 | E61: 10 | J61: 逐步提高周卡的吸引力
B62: 2 | C62: 随机能量特饮 | D62: 5103001 | E62: 50
B63: 3 | C63: 星之初愿 | D63: 9 | E63: 1
B64: 4 | C64: 装备图纸 | D64: 50002 | E64: 10
B65: 5 | C65: 随机能量特饮 | D65: 5103001 | E65: 50
B66: 6 | C66: 星之初愿 | D66: 9 | E66: 1
B67: 7 | C67: 梦境招募器 | D67: 11 | E67: 5
C69: 付费 | I69: 付费 | J69: 第一周投放 | O69: 付费 | P69: 预计第3周投放，新增载具后，释放一些时间
C70: 道具 | D70: 道具id | E70: 数量 | F70: 单价 | G70: 价值 | I70: 道具 | J70: 道具id | K70: 数量 | L70: 单价 | M70: 价值 | O70: 道具 | P70: 道具id | Q70: 数量 | R70: 单价 | S70: 价值
B71: 1 | C71: 钻石 | D71: 1 | E71: 300 | H71: 1 | I71: 金币吸尘器 | J71: 9800301 | K71: 1 | N71: 1 | O71: 组队券 | Q71: 1 | T71: 更新一个紫色藏品
B72: 2 | C72: 钻石 | D72: 1 | E72: 100 | H72: 2 | I72: 金币吸尘器 | J72: 9800301 | K72: 1 | N72: 2 | O72: 组队券 | Q72: 1 | T72: 扫荡一次好友奖励
B73: 3 | C73: 钻石 | D73: 1 | E73: 100 | H73: 3 | I73: 金币吸尘器 | J73: 9800301 | K73: 1 | N73: 3 | O73: 组队券 | Q73: 1
B74: 4 | C74: 钻石 | D74: 1 | E74: 100 | H74: 4 | I74: 金币吸尘器 | J74: 9800301 | K74: 1 | N74: 4 | O74: 组队券 | Q74: 1
B75: 5 | C75: 钻石 | D75: 1 | E75: 100 | H75: 5 | I75: 金币吸尘器 | J75: 9800301 | K75: 1 | N75: 5 | O75: 组队券 | Q75: 1
B76: 6 | C76: 钻石 | D76: 1 | E76: 100 | H76: 6 | I76: 金币吸尘器 | J76: 9800301 | K76: 1 | N76: 6 | O76: 组队券 | Q76: 1
B77: 7 | C77: 钻石 | D77: 1 | E77: 100 | H77: 7 | I77: 金币吸尘器 | J77: 9800301 | K77: 1 | N77: 7 | O77: 组队券 | Q77: 1

Sheet 日周月礼包
A1: 日礼包
B3: 道具 | C3: 道具id | D3: 数量 | E3: 单价 | F3: 价值 | G3: 原价 | H3: 售价 | I3: 限购次数 | J3: 折扣
B4: 体力 | C4: {=B4} | D4: 10 | E4: {=B4} | F4: =E4*D4 | G4: =IFERROR(H4/J4*10,"") | H4: 0 | I4: 1 | J4: 0
A5: 新增 | B5: 体力 | C5: {=B5} | D5: 10 | E5: {=B5} | F5: =E5*D5 | H5: 广告 | I5: 1 | J5: 0
B6: 体力 | C6: {=B6} | D6: 60 | E6: {=B6} | F6: =E6*D6 | G6: =IFERROR(H6/J6*10,"") | H6: 96 | I6: 1 | J6: 8
B7: 金币 | C7: {=B7} | D7: 5000 | E7: {=B7} | F7: =E7*D7 | G7: =IFERROR(H7/J7*10,"") | H7: 125 | I7: 2 | J7: 5
B8: 梦境招募器 | C8: {=B8} | D8: 20 | E8: {=B8} | F8: =E8*D8 | G8: =IFERROR(H8/J8*10,"") | H8: 480 | I8: 2 | J8: 8
B9: 随机能量特饮 | C9: {=B9} | D9: 400 | E9: {=B9} | F9: =E9*D9 | G9: =IFERROR(H9/J9*10,"") | H9: 200 | I9: 3 | J9: 5
B10: 超能特饮 | C10: {=B10} | D10: 200 | E10: {=B10} | F10: =E10*D10 | G10: =IFERROR(H10/J10*10,"") | H10: 200 | I10: 3 | J10: 5
B11: 装备图纸 | C11: {=B11} | D11: 100 | E11: {=B11} | F11: =E11*D11 | G11: =IFERROR(H11/J11*10,"") | H11: 240 | I11: 3 | J11: 8
B12: 星辉秘契 | C12: {=B12} | D12: 2 | E12: {=B12} | F12: =E12*D12 | G12: =IFERROR(H12/J12*10,"") | H12: 392 | I12: 3 | J12: 7
B13: 星辉秘契 | C13: {=B13} | D13: 5 | E13: {=B13} | F13: =E13*D13 | G13: =IFERROR(H13/J13*10,"") | H13: 840 | I13: 3 | J13: 6
B14: 符引结晶 | C14: {=B14} | D14: 50 | E14: {=B14} | F14: =E14*D14 | G14: =IFERROR(H14/J14*10,"") | H14: 225 | I14: 2 | J14: 9
B15: 织梦微尘 | C15: {=B15} | D15: 50 | E15: {=B15} | F15: =E15*D15 | G15: =IFERROR(H15/J15*10,"") | H15: 210 | I15: 3 | J15: 7
B16: 锻造晶石 | C16: {=B16} | D16: 500 | E16: {=B16} | F16: =E16*D16 | G16: =IFERROR(H16/J16*10,"") | H16: 300 | I16: 5 | J16: 6
B17: 幻梦晶核 | C17: {=B17} | D17: 6 | E17: {=B17} | F17: =E17*D17 | G17: =IFERROR(H17/J17*10,"") | H17: 216 | I17: 2 | J17: 6
B18: 转运石 | C18: {=B18} | D18: 1000 | E18: {=B18} | F18: =E18*D18 | G18: =IFERROR(H18/J18*10,"") | H18: 196 | I18: 3 | J18: 6
B19: 智械发条 | C19: {=B19} | D19: 3 | E19: {=B19} | F19: =E19*D19 | G19: =IFERROR(H19/J19*10,"") | H19: 225 | I19: 5 | J19: 5 | K19: 载具开启 | L19: 配置天数开启
A25: 周礼包
B27: 道具 | C27: 道具id | D27: 数量 | E27: 单价 | F27: 价值 | G27: 原价 | H27: 售价 | I27: 限购次数 | J27: 折扣
B28: 体力 | C28: {=B28} | D28: 10 | E28: {=B28} | F28: =E28*D28 | H28: 0
A29: 新增 | B29: 体力 | C29: {=B29} | D29: 10 | E29: {=B29} | F29: =E29*D29 | H29: 广告
B30: 体力 | C30: {=B30} | D30: 60 | E30: {=B30} | F30: =E30*D30 | G30: =IFERROR(H30/J30*10,"") | H30: 84 | I30: 5 | J30: 7
B31: 金币 | C31: {=B31} | D31: 10000 | E31: {=B31} | F31: =E31*D31 | G31: =IFERROR(H31/J31*10,"") | H31: 200 | I31: 1 | J31: 4
B32: 梦境招募器 | C32: {=B32} | D32: 50 | E32: {=B32} | F32: =E32*D32 | G32: =IFERROR(H32/J32*10,"") | H32: 1050 | I32: 3 | J32: 7
B33: 梦境招募器 | C33: {=B33} | D33: 100 | E33: {=B33} | F33: =E33*D33 | G33: =IFERROR(H33/J33*10,"") | H33: 1800 | I33: 3 | J33: 6
B34: 超能特饮 | C34: {=B34} | D34: 400 | E34: {=B34} | F34: =E34*D34 | G34: =IFERROR(H34/J34*10,"") | H34: 320 | I34: 10 | J34: 7
B35: 装备图纸 | C35: {=B35} | D35: 200 | E35: {=B35} | F35: =E35*D35 | G35: =IFERROR(H35/J35*10,"") | H35: 360 | I35: 3 | J35: 6
B36: 星辉秘契 | C36: {=B36} | D36: 10 | E36: {=B36} | F36: =E36*D36 | G36: =IFERROR(H36/J36*10,"") | H36: 1400 | I36: 5 | J36: 5
B37: 星辉秘契 | C37: {=B37} | D37: 20 | E37: {=B37} | F37: =E37*D37 | G37: =IFERROR(H37/J37*10,"") | H37: 2240 | I37: 5 | J37: 4
B38: 符引结晶 | C38: {=B38} | D38: 100 | E38: {=B38} | F38: =E38*D38 | G38: =IFERROR(H38/J38*10,"") | H38: 400 | I38: 3 | J38: 8
B39: 幻梦晶核 | C39: {=B39} | D39: 12 | E39: {=B39} | F39: =E39*D39 | G39: =IFERROR(H39/J39*10,"") | H39: 360 | I39: 2 | J39: 5
B40: 织梦微尘 | C40: {=B40} | D40: 200 | E40: {=B40} | F40: =E40*D40 | G40: =IFERROR(H40/J40*10,"") | H40: 360 | I40: 3 | J40: 6 | P40: 1、符文
B41: 加速沙漏 | C41: {=B41} | D41: 50 | E41: {=B41} | F41: =E41*D41 | G41: =IFERROR(H41/J41*10,"") | H41: 200 | I41: 10 | J41: 8 | L41: 删除投放 | P41: 2、皮肤 | Q41: 周礼包限购 | R41: 跟着玩家节奏走
B42: 梦境衣橱礼包 | C42: {=B42} | D42: 1 | G42: =IFERROR(H42/J42*10,"") | H42: 980 | I42: 3 | J42: 1
B43: 转运石 | C43: {=B43} | D43: 3000 | E43: {=B43} | F43: =E43*D43 | G43: =IFERROR(H43/J43*10,"") | H43: 500 | I43: 4 | J43: 5 | P43: 橙色梦灵
B44: 智械发条 | C44: {=B44} | D44: 10 | E44: {=B44} | F44: =E44*D44 | G44: =IFERROR(H44/J44*10,"") | H44: 600 | I44: 3 | J44: 4 | K44: 22日开启 | L44: 配置天数开启
B45: 精密齿轮 | C45: {=B45} | D45: 300 | E45: {=B45} | F45: =E45*D45 | G45: =H45/J45*10 | H45: 180 | I45: 5 | J45: 6 | K45: 22日开启 | L45: 配置天数开启
B46: 随机史诗藏品 | C46: 6220021 | D46: 1 | E46: 2400 | F46: =E46*D46 | G46: =IFERROR(H46/J46*10,"") | H46: 1400 | I46: 3 | J46: 6 | K46: 15日开启 | L46: 配置天数开启
B47: 万象自选宝盒Ⅰ | C47: {=B47} | D47: 1 | E47: 6000 | F47: =E47*D47 | G47: 6000 | H47: 1800 | I47: 1 | J47: 3 | K47: 15日开启 | L47: 配置天数开启
A49: 月礼包 | D49: 累充300元开启
B51: 道具 | C51: 道具id | D51: 数量 | E51: 单价 | F51: 价值 | G51: 原价 | H51: 售价 | I51: 限购次数 | J51: 折扣
B52: 体力 | C52: {=B52} | D52: 10 | H52: 0
A53: 新增 | B53: 体力 | C53: {=B53} | D53: 10 | H53: 广告
B54: 梦境招募器 | C54: {=B54} | D54: 50 | G54: =IFERROR(H54/J54*10,"") | H54: 750 | I54: 2 | J54: 5
B55: 梦境招募器 | C55: {=B55} | D55: 200 | G55: =IFERROR(H55/J55*10,"") | H55: 3300 | I55: 2 | J55: 6
B56: 超能特饮 | C56: {=B56} | D56: 1000 | G56: =IFERROR(H56/J56*10,"") | H56: 600 | I56: 10 | J56: 3
B57: 装备图纸 | C57: {=B57} | D57: 400 | G57: =IFERROR(H57/J57*10,"") | H57: 600 | I57: 3 | J57: 5
B58: 幻梦晶核 | C58: {=B58} | D58: 30 | G58: =IFERROR(H58/J58*10,"") | H58: 900 | I58: 3 | J58: 5
B59: 幻梦晶核 | C59: {=B59} | D59: 130 | G59: =IFERROR(H59/J59*10,"") | H59: 3120 | I59: 1 | J59: 4
B60: 绮梦衣橱盒Ⅰ | C60: {=B60} | D60: 1 | G60: =IFERROR(H60/J60*10,"") | H60: 3280 | I60: 3 | J60: 4
B61: 星辉秘契 | C61: {=B61} | D61: 10 | G61: =IFERROR(H61/J61*10,"") | H61: 840 | I61: 3 | J61: 3
B62: 星辉秘契 | C62: {=B62} | D62: 40 | G62: =IFERROR(H62/J62*10,"") | H62: 4480 | I62: 3 | J62: 4
B63: 传说符文 | C63: {=B63} | D63: 1 | G63: =IFERROR(H63/J63*10,"") | H63: 1380 | I63: 1 | J63: 1
B64: 神话符文 | C64: {=B64} | D64: 1 | G64: =IFERROR(H64/J64*10,"") | H64: 6480 | I64: 1 | J64: 1
B65: 转运石 | C65: {=B65} | D65: 10000 | G65: =IFERROR(H65/J65*10,"") | H65: 1320 | I65: 6 | J65: 4
B66: 智械发条 | C66: {=B66} | D66: 10 | G66: =IFERROR(H66/J66*10,"") | H66: 450 | I66: 3 | J66: 3 | K66: 载具开启 | L66: 配置天数开启
B67: 智械发条 | C67: {=B67} | D67: 20 | G67: =IFERROR(H67/J67*10,"") | H67: 1200 | I67: 2 | J67: 4 | K67: 载具开启 | L67: 配置天数开启
B68: 精密齿轮 | C68: {=B68} | D68: 1000 | E68: {=B68} | F68: =E68*D68 | G68: =H68/J68*10 | H68: 400 | I68: 5 | J68: 4 | K68: 载具开启 | L68: 配置天数开启
B69: 怦怦时刻 | C69: {=B69} | D69: 4800 | E69: 1 | F69: 4800 | G69: 4800 | H69: 2400 | I69: 3 | J69: 5 | L69: 配置天数开启

Sheet 心梦商店
A1: 商店ID | B1: 格子 | C1: 展示排序 （序号越小越靠前） | D1: 购买次数范围 通过已购买次数来取数据 比如配置了2表示购已买次数大于等于2时取这条 不分段的话不配或者配0 | E1: 开启条件 | F1: 购买条件 | G1: 是否屏蔽 1：不屏蔽 0：屏蔽 用于项目有线上服时又需要删除某个格子 | H1: 商品名称 | I1: 商品 | J1: 购买消耗 不填则无消耗，由广告控制 | K1: 刷新前可购买次数 0-不限购买次数 其余-可购买次数 | L1: 商店刷新类型 0-不刷新 1-日 2-周 3-月 | M1: 客户端 展示结束时间
A2: shop_id | B2: id | C2: order | D2: buy_count_range | E2: condition | F2: buy_cond | G2: is_close | H2: name | I2: reward | J2: need | K2: buy_count | L2: refresh | M2: end_time
C3: 心梦商店
A4: 4 | B4: 1 | C4: 100 | G4: 1 | H4: 金币 | I4: [{2,500}] | J4: [] | K4: 1 | L4: 2
A5: 4 | B5: 2 | C5: 601 | G5: 1 | H5: 随机神话符文 | I5: [{5306000,1}] | J5: [{44,480}] | K5: 1 | L5: 2
A6: 4 | B6: 3 | C6: 765 | E6: [{server_open_day,29}] | G6: 1 | H6: 钻石 | I6: [{1,1688}] | J6: [{44,120}] | K6: 2 | L6: 2
A7: 4 | B7: 4 | C7: 766 | E7: [{server_open_day,15}] | G7: 1 | H7: 钻石 | I7: [{1,888}] | J7: [{44,60}] | K7: 2 | L7: 2
A8: 4 | B8: 5 | C8: 800 | G8: 1 | H8: 幻梦晶核 | I8: [{5305001,50}] | J8: [{44,188}] | K8: 2 | L8: 2
A9: 4 | B9: 6 | C9: 1300 | G9: 1 | H9: 招募器 | I9: [{11,50}] | J9: [{44,60}] | K9: 1 | L9: 2
A10: 4 | B10: 7 | C10: 900 | G10: 1 | H10: 星辉秘契 | I10: [{30,20}] | J10: [{44,150}] | K10: 1 | L10: 2
A11: 4 | B11: 8 | C11: 500 | E11: [{server_open_day,31}] | G11: 1 | H11: 绮梦衣橱礼盒 | I11: [{100119,1}] | J11: [{44,380}] | K11: 2 | L11: 2
A12: 4 | B12: 9 | C12: 600 | G12: 1 | H12: 喵喵锤子 | I12: [{5505001,1}] | J12: [{44,300}] | K12: 5 | L12: 0
A13: 4 | B13: 10 | C13: 700 | G13: 1 | H13: 神话祝福石 | I13: [{5305008,1}] | J13: [{44,350}] | K13: 1 | L13: 2
A14: 4 | B14: 11 | C14: 200 | G14: 1 | H14: 童话造物幻衣 | I14: [{100041,1}] | J14: [{44,1200}] | K14: 5 | L14: 0
A15: 4 | B15: 12 | C15: 300 | G15: 1 | H15: 小狗锤 | I15: [{5506002,1}] | J15: [{44,600}] | K15: 5 | L15: 0
A16: 4 | B16: 13 | C16: 400 | E16: [{server_open_day,31}] | G16: 1 | H16: 繁星衣橱礼盒 | I16: [{100123,1}] | J16: [{44,750}] | K16: 2 | L16: 3
A17: 4 | B17: 14 | C17: 301 | G17: 1 | H17: 小狗锤 | I17: [{5506002,1}] | J17: [{44,600}] | K17: 5 | M17: {{2026,5,29},{23,59,59}}
A18: 4 | B18: 15 | C18: 1100 | E18: [{server_open_day,22},{chapter_pve,60}] | G18: 1 | H18: 智械发条 | I18: [{62,10}] | J18: [{44,100}] | K18: 2 | L18: 2
A19: 4 | B19: 16 | C19: 1200 | E19: [{server_open_day,22},{chapter_pve,60}] | G19: 1 | H19: 精密齿轮 | I19: [{63,1500}] | J19: [{44,100}] | K19: 5 | L19: 2
A20: 4 | B20: 17 | C20: 401 | E20: [{server_open_day,15}] | G20: 1 | H20: 抵达深空 | I20: [{6200016,1}] | J20: [{44,680}] | K20: 1 | L20: 3
A21: 4 | B21: 18 | C21: 601 | E21: [{server_open_day,15}] | G21: 1 | H21: 酣眠的祝福 | I21: [{6200015,1}] | J21: [{44,380}] | K21: 1 | L21: 2

Sheet 招募狂欢
A1: 招募狂欢 | C1: 开服第2-7天开启
B3: 轮次 | C3: 物品类型 | D3: 数量 | E3: 价值 | F3: 物品类型 | G3: 数量 | H3: 价值 | I3: 物品类型 | J3: 数量 | K3: 价值 | L3: 总价值 | M3: 道具id
B4: 第1轮 | C4: 随机传说梦灵 | D4: 1 | E4: {=C4} | F4: 随机紫色专属【紫色】 | G4: 1 | H4: 1024 | I4: 超能特饮 | J4: 300 | K4: 600 | L4: =K4+H4+E4 | M4: 5800012
B5: 第2轮 | C5: 自选传说梦灵 | D5: 1 | E5: {=C5} | F5: 自选紫色专属【紫色】 | G5: 1 | H5: 1024 | I5: 超能特饮 | J5: 500 | K5: 1000 | L5: =K5+H5+E5 | M5: 5800012
B6: 第3轮 | C6: 自选传说梦灵 | D6: 2 | E6: {=C6} | F6: 自选紫色专属【紫色】 | G6: 1 | H6: 1024 | I6: 超能特饮 | J6: 800 | K6: 1600 | L6: =K6+H6+E6 | M6: 5800012 | O6: 3卡用户的引导
B7: 第4轮 | C7: 随机神话梦灵 | D7: 1 | E7: {=C7} | F7: 随机橙色稀有【橙色】 | G7: 1 | H7: 4000 | I7: 超能特饮 | J7: 1000 | K7: 2000 | L7: =K7+H7+E7 | M7: 5600082 | N7: 去掉 | O7: 300+的用户
M8: 星辉秘契
M9: 星辉秘契
B10: 节点数值 | M10: 星辉秘契
M11: 星辉秘契
A12: 一轮 | B12: 节点数值 | C12: 物品类型 | D12: 数量 | E12: 价值 | F12: 物品类型 | G12: 数量 | H12: 价值 | I12: 总价值 | J12: 返利比
B13: 60 | C13: 梦境招募器 | D13: 5 | E13: 150 | F13: 随机能量特饮 | G13: 30 | H13: 30 | I13: 180 | J13: 0.1
B14: 120 | C14: 梦境招募器 | D14: 5 | E14: 150 | F14: 随机能量特饮 | G14: 30 | H14: 30 | I14: 180 | J14: 0.1
B15: 200 | C15: 梦境招募器 | D15: 5 | E15: 150 | F15: 随机能量特饮 | G15: 30 | H15: 30 | I15: 180 | J15: 0.08
B16: 300 | C16: 梦境招募器 | D16: 10 | E16: 300 | F16: 随机能量特饮 | G16: 50 | H16: 50 | I16: 350 | J16: 0.12
B17: 420 | C17: 梦境招募器 | D17: 10 | E17: 300 | F17: 随机能量特饮 | G17: 50 | H17: 50 | I17: 350 | J17: 0.1
B18: 600 | C18: 梦境招募器 | D18: 10 | E18: 300 | F18: 随机能量特饮 | G18: 50 | H18: 50 | I18: 350 | J18: 0.06
D19: 45 | G19: 240 | I19: =SUM(I13:I18) | J19: 0.0883
A21: 二轮 | B21: 节点数值 | C21: 物品类型 | D21: 数量 | E21: 价值 | F21: 物品类型 | G21: 数量 | H21: 价值 | I21: 总价值 | J21: 返利比
B22: 60 | C22: 梦境招募器 | D22: 5 | E22: 150 | F22: 随机能量特饮 | G22: 50 | H22: 50 | I22: 200 | J22: 0.11
B23: 120 | C23: 梦境招募器 | D23: 5 | E23: 150 | F23: 随机能量特饮 | G23: 50 | H23: 50 | I23: 200 | J23: 0.11
B24: 200 | C24: 梦境招募器 | D24: 5 | E24: 150 | F24: 随机能量特饮 | G24: 50 | H24: 50 | I24: 200 | J24: 0.08
B25: 300 | C25: 梦境招募器 | D25: 10 | E25: 300 | F25: 随机能量特饮 | G25: 80 | H25: 80 | I25: 380 | J25: 0.13
B26: 420 | C26: 梦境招募器 | D26: 10 | E26: 300 | F26: 随机能量特饮 | G26: 80 | H26: 80 | I26: 380 | J26: 0.11
B27: 600 | C27: 梦境招募器 | D27: 10 | E27: 300 | F27: 随机能量特饮 | G27: 80 | H27: 80 | I27: 380 | J27: 0.07
A30: 三轮 | B30: 节点数值 | C30: 物品类型 | D30: 数量 | E30: 价值 | F30: 物品类型 | G30: 数量 | H30: 价值 | I30: 总价值 | J30: 返利比
B31: 80 | C31: 梦境招募器 | D31: 5 | E31: 150 | F31: 随机能量特饮 | G31: 80 | H31: 80 | I31: 230 | J31: 0.1
B32: 160 | C32: 梦境招募器 | D32: 5 | E32: 150 | F32: 随机能量特饮 | G32: 80 | H32: 80 | I32: 230 | J32: 0.1
B33: 260 | C33: 梦境招募器 | D33: 5 | E33: 150 | F33: 随机能量特饮 | G33: 80 | H33: 80 | I33: 230 | J33: 0.08
B34: 400 | C34: 梦境招募器 | D34: 10 | E34: 300 | F34: 随机能量特饮 | G34: 100 | H34: 100 | I34: 400 | J34: 0.1
B35: 580 | C35: 梦境招募器 | D35: 10 | E35: 300 | F35: 随机能量特饮 | G35: 100 | H35: 100 | I35: 400 | J35: 0.07
B36: 800 | C36: 梦境招募器 | D36: 10 | E36: 300 | F36: 随机能量特饮 | G36: 100 | H36: 100 | I36: 400 | J36: 0.06
D37: 45 | G37: 540 | I37: =SUM(I31:I36) | J37: 0.0788
A39: 四轮 | B39: 节点数值 | C39: 物品类型 | D39: 数量 | E39: 价值 | F39: 物品类型 | G39: 数量 | H39: 价值 | I39: 总价值 | J39: 返利比
B40: 120 | C40: 梦境招募器 | D40: 5 | E40: 150 | F40: 随机能量特饮 | G40: 100 | H40: 100 | I40: 250 | J40: 0.08
B41: 240 | C41: 梦境招募器 | D41: 5 | E41: 150 | F41: 随机能量特饮 | G41: 100 | H41: 100 | I41: 250 | J41: 0.08
B42: 400 | C42: 梦境招募器 | D42: 5 | E42: 150 | F42: 随机能量特饮 | G42: 100 | H42: 100 | I42: 250 | J42: 0.07
B43: 600 | C43: 梦境招募器 | D43: 10 | E43: 300 | F43: 随机能量特饮 | G43: 120 | H43: 120 | I43: 420 | J43: 0.08
B44: 800 | C44: 梦境招募器 | D44: 10 | E44: 300 | F44: 随机能量特饮 | G44: 120 | H44: 120 | I44: 420 | J44: 0.06
B45: 1200 | C45: 梦境招募器 | D45: 10 | E45: 300 | F45: 随机能量特饮 | G45: 120 | H45: 120 | I45: 420 | J45: 0.05
D46: 45 | G46: 660 | I46: =SUM(I40:I45) | J46: 0.067

Sheet 橙卡试炼活动
A1: 梦灵试炼 | B1: 卡牌品质 | C1: 开服第X天开启 | D1: 活动持续时间（天） | E1: 活动说明 | F1: 规则：
B2: 橙卡 | C2: 5 | D2: 4 | F2: 1、活动期间，可选择传说梦灵作为升级目标，可随时更换;
F3: 2、选中的梦灵达到指定等级后，可解锁对应等级的专属升级礼包;
F4: 3、每个礼包只能获取1次，已购买的专属升级礼包、已领取的免费奖励不会随更换梦灵重置。
A6: 梦灵试炼 | B6: 免费奖励 | F6: 升级专属礼包
A7: 梦灵等级 | B7: 道具 | C7: 单价 | D7: 数量 | E7: 总价值 | F7: 货币 | G7: 对应档位 | H7: 展示折扣 | I7: 道具1 | J7: 单价1 | K7: 数量1 | L7: 价值1 | M7: 道具2 | N7: 单价2 | O7: 数量2 | P7: 价值2 | Q7: 道具3 | R7: 单价3 | S7: 数量3 | T7: 价值3 | U7: 总价值 | V7: 返利
A8: 1 | B8: 梦境招募器 | C8: {=B8} | D8: 5 | E8: =PRODUCT(C8:D8) | F8: 钻石 | G8: 688 | H8: =G8/U8 | I8: 超能特饮 | J8: {=I8} | K8: 50 | L8: =PRODUCT(J8:K8) | M8: 梦境招募器 | N8: {=M8} | O8: 50 | P8: =PRODUCT(N8:O8) | U8: =SUMIF($B$7:$T$7,"价值*",B8:T8) | V8: =U8/(G8) | W8: =G8/H8*10
A9: 5 | B9: 梦境招募器 | C9: {=B9} | D9: 10 | E9: =PRODUCT(C9:D9) | F9: 钻石 | G9: 1688 | H9: =G9/U9 | I9: 自选传说梦灵 | J9: {=I9} | K9: 1 | L9: =PRODUCT(J9:K9) | M9: 梦境招募器 | N9: {=M9} | O9: 100 | P9: =PRODUCT(N9:O9) | Q9: 超能特饮 | R9: {=Q9} | S9: 100 | T9: =PRODUCT(R9:S9) | U9: =SUMIF($B$7:$T$7,"价值*",B9:T9) | V9: =U9/(G9) | W9: =G9/H9*10
A10: 10 | B10: 梦境招募器 | C10: {=B10} | D10: 15 | E10: =PRODUCT(C10:D10) | F10: 钻石 | G10: 2388 | H10: =G10/U10 | I10: 自选传说梦灵 | J10: {=I10} | K10: 2 | L10: =PRODUCT(J10:K10) | M10: 梦境招募器 | N10: {=M10} | O10: 150 | P10: =PRODUCT(N10:O10) | Q10: 传说梦灵随机珍稀符文 | R10: 2000 | S10: 1 | T10: =PRODUCT(R10:S10) | U10: =SUMIF($B$7:$T$7,"价值*",B10:T10) | V10: =U10/(G10) | W10: =G10/H10*10
A11: 12 | B11: 梦愿水晶 | C11: {=B11} | D11: 1 | E11: =PRODUCT(C11:D11) | F11: 钻石 | G11: 2688 | H11: =G11/U11 | I11: 自选传说梦灵 | J11: {=I11} | K11: 2 | L11: =PRODUCT(J11:K11) | M11: 星辉秘契 | N11: {=M11} | O11: 5 | P11: =PRODUCT(N11:O11) | Q11: 传说梦灵随机稀世符文 | R11: 5000 | S11: 1 | T11: =PRODUCT(R11:S11) | U11: =SUMIF($B$7:$T$7,"价值*",B11:T11) | V11: =U11/(G11) | W11: =G11/H11*10
A12: 15 | B12: 随机橙色皮肤 | C12: 4000 | D12: 1 | E12: =PRODUCT(C12:D12) | F12: 钻石 | G12: 3088 | H12: =G12/U12 | I12: 随机神话梦灵 | J12: 5000 | K12: 1 | L12: 5000 | M12: 星辉秘契 | N12: {=M12} | O12: 10 | P12: =PRODUCT(N12:O12) | Q12: 超能特饮 | R12: {=Q12} | S12: 300 | T12: =PRODUCT(R12:S12) | U12: =SUMIF($B$7:$T$7,"价值*",B12:T12) | V12: =U12/(G12) | W12: =G12/H12*10
A13: 17 | B13: 星辉秘契 | C13: {=B13} | D13: 2 | E13: =PRODUCT(C13:D13) | F13: 钻石 | G13: 3288 | H13: =G13/U13 | I13: 幻梦晶核 | J13: {=I13} | K13: 50 | L13: =PRODUCT(J13:K13) | M13: 星辉秘契 | N13: {=M13} | O13: 20 | P13: =PRODUCT(N13:O13) | S13: 1 | T13: =PRODUCT(R13:S13) | U13: =SUMIF($B$7:$T$7,"价值*",B13:T13) | V13: =U13/(G13) | W13: =G13/H13*10
A14: 20 | B14: 星辉秘契 | C14: {=B14} | D14: 3 | E14: =PRODUCT(C14:D14) | F14: 钻石 | G14: 4388 | H14: =G14/U14 | I14: 幻梦晶核 | J14: {=I14} | K14: 80 | L14: =PRODUCT(J14:K14) | M14: 星辉秘契 | N14: {=M14} | O14: 30 | P14: =PRODUCT(N14:O14) | U14: =SUMIF($B$7:$T$7,"价值*",B14:T14) | V14: =U14/(G14) | W14: =G14/H14*10
L18: 100144

Sheet 红卡试炼活动
A1: 梦灵试炼 | B1: 卡牌品质 | C1: 开服第X天开启 | D1: 活动持续时间（天） | E1: 活动说明 | F1: 规则：
B2: 红卡 | C2: 11 | D2: 4 | F2: 1、活动期间，可选择传说梦灵作为升级目标，可随时更换;
F3: 2、选中的梦灵达到指定等级后，可解锁对应等级的专属升级礼包;
F4: 3、每个礼包只能获取1次，已购买的专属升级礼包、已领取的免费奖励不会随更换梦灵重置。
A6: 梦灵试炼 | B6: 免费奖励 | F6: 升级专属礼包
A7: 梦灵等级 | B7: 道具 | C7: 单价 | D7: 数量 | E7: 总价值 | F7: 货币 | G7: 对应档位 | H7: 展示折扣 | I7: 道具1 | J7: 单价1 | K7: 数量1 | L7: 价值1 | M7: 道具2 | N7: 单价2 | O7: 数量2 | P7: 价值2 | Q7: 道具3 | R7: 单价3 | S7: 数量3 | T7: 价值3 | U7: 总价值 | V7: 返利 | W7: 历史
A8: 1 | B8: 梦境招募器 | C8: {=B8} | D8: 5 | E8: =PRODUCT(C8:D8) | F8: 钻石 | G8: 688 | H8: =G8/U8*10 | I8: 超能特饮 | J8: {=I8} | K8: 50 | L8: =PRODUCT(J8:K8) | M8: 梦境招募器 | N8: {=M8} | O8: 50 | P8: =PRODUCT(N8:O8) | U8: =SUMIF($B$7:$T$7,"价值*",B8:T8) | V8: =U8/(G8)
A9: 5 | B9: 梦境招募器 | C9: {=B9} | D9: 10 | E9: =PRODUCT(C9:D9) | F9: 钻石 | G9: 1688 | H9: =G9/U9*10 | I9: 自选神话梦灵 | J9: {=I9} | K9: 1 | L9: =PRODUCT(J9:K9) | M9: 梦境招募器 | N9: {=M9} | O9: 100 | P9: =PRODUCT(N9:O9) | Q9: 超能特饮 | R9: {=Q9} | S9: 100 | T9: =PRODUCT(R9:S9) | U9: =SUMIF($B$7:$T$7,"价值*",B9:T9) | V9: =U9/(G9) | W9: 超能特饮
A10: 8 | B10: 传说祝福石 | C10: {=B10} | D10: 1 | E10: =PRODUCT(C10:D10) | F10: 钻石 | G10: 1988 | H10: =G10/U10*10 | I10: 自选神话梦灵 | J10: {=I10} | K10: 2 | L10: =PRODUCT(J10:K10) | M10: 梦境招募器 | N10: {=M10} | O10: 150 | P10: =PRODUCT(N10:O10) | Q10: 超能特饮 | R10: {=Q10} | S10: 200 | T10: =PRODUCT(R10:S10) | U10: =SUMIF($B$7:$T$7,"价值*",B10:T10) | V10: =U10/(G10) | W10: 超能特饮
A11: 10 | B11: 梦境招募器 | C11: {=B11} | D11: 15 | E11: =PRODUCT(C11:D11) | F11: 钻石 | G11: 3588 | H11: =G11/U11*10 | I11: 自选神话梦灵 | J11: {=I11} | K11: 2 | L11: =PRODUCT(J11:K11) | M11: 梦境招募器 | N11: {=M11} | O11: 200 | P11: =PRODUCT(N11:O11) | Q11: 神话梦灵随机珍稀符文 | R11: 3000 | S11: 1 | T11: =PRODUCT(R11:S11) | U11: =SUMIF($B$7:$T$7,"价值*",B11:T11) | V11: =U11/(G11) | W11: 超能特饮
A12: 12 | B12: 梦愿水晶 | C12: {=B12} | D12: 1 | E12: =PRODUCT(C12:D12) | F12: 钻石 | G12: 3688 | H12: =G12/U12*10 | I12: 自选神话梦灵 | J12: {=I12} | K12: 1 | L12: =PRODUCT(J12:K12) | M12: 星辉秘契 | N12: {=M12} | O12: 5 | P12: =PRODUCT(N12:O12) | Q12: 神话梦灵随机稀世符文 | R12: 6000 | S12: 1 | T12: =PRODUCT(R12:S12) | U12: =SUMIF($B$7:$T$7,"价值*",B12:T12) | V12: =U12/(G12) | W12: 神话梦灵随机珍稀符文
A13: 15 | B13: 星辉秘契 | C13: {=B13} | D13: 2 | E13: =PRODUCT(C13:D13) | F13: 钻石 | G13: 5688 | H13: =G13/U13*10 | I13: 自选神话梦灵 | J13: {=I13} | K13: 2 | L13: =PRODUCT(J13:K13) | M13: 星辉秘契 | N13: {=M13} | O13: 10 | P13: =PRODUCT(N13:O13) | Q13: 自选神话梦灵皮肤 | R13: 8000 | S13: 1 | T13: =PRODUCT(R13:S13) | U13: =SUMIF($B$7:$T$7,"价值*",B13:T13) | V13: =U13/(G13) | W13: 神话梦灵随机稀世符文
A14: 17 | B14: 星辉秘契 | C14: {=B14} | D14: 2 | E14: =PRODUCT(C14:D14) | F14: 钻石 | G14: 5888 | H14: =G14/U14*10 | I14: 幻梦晶核 | J14: {=I14} | K14: 150 | L14: =PRODUCT(J14:K14) | M14: 星辉秘契 | N14: {=M14} | O14: 20 | P14: =PRODUCT(N14:O14) | U14: =SUMIF($B$7:$T$7,"价值*",B14:T14) | V14: =U14/(G14)
A15: 20 | B15: 星辉秘契 | C15: {=B15} | D15: 3 | E15: =PRODUCT(C15:D15) | F15: 钻石 | G15: 7888 | H15: =G15/U15*10 | M15: 星辉秘契 | N15: {=M15} | O15: 30 | P15: =PRODUCT(N15:O15) | Q15: 梦境招募器 | R15: {=Q15} | S15: 300 | T15: =S15*R15 | U15: =SUMIF($B$7:$T$7,"价值*",B15:T15) | V15: =U15/(G15)
Q16: 这个时候还未投放
Q17: 创世祝福石 | R17: 16000 | S17: 1

Sheet 冲刺活动
A1: 招募冲刺
B2: 节点数值 | D2: A_活动轮循任务_activity_round_cycle_data.xml | N2: 轮次数值 | P2: A_活动轮循任务_activity_round_cycle_data.xml
A3: 新节点
B4: 节点数值 | C4: 物品类型 | D4: 数量 | E4: 价值 | F4: 物品类型 | G4: 数量 | H4: 价值 | I4: 总价值 | J4: 返利比 | K4: 新返利比 | N4: 轮次 | O4: 物品类型 | P4: 数量 | Q4: 价值 | R4: 物品类型 | S4: 数量 | T4: 价值 | U4: 物品类型 | V4: 数量 | W4: 价值 | X4: 总价值 | Y4: 原反比 | Z4: 原节点 | AA4: 现节点 | AB4: 现反比
A5: 60 | B5: 60 | C5: 梦境招募器 | D5: 5 | E5: =D5*_xlfn.XLOOKUP(C5,'道具价值表-汇总'!$B:$B,'道具价值表-汇总'!$D:$D,,0,1) | F5: 超能特饮 | G5: 30 | H5: =G5*_xlfn.XLOOKUP(F5,'道具价值表-汇总'!$B:$B,'道具价值表-汇总'!$D:$D,,0,1) | I5: =H5+E5 | J5: 0.18 | K5: =I5/((A5-A4)*30) | N5: 第1轮 | O5: 钻石 | P5: 100 | Q5: =P5*_xlfn.XLOOKUP(O5,'道具价值表-汇总'!$B:$B,'道具价值表-汇总'!$D:$D,,0,1) | R5: 神话梦灵碎片 | S5: 10 | T5: =S5*_xlfn.XLOOKUP(R5,'道具价值表-汇总'!$B:$B,'道具价值表-汇总'!$D:$D,,0,1) | U5: 超能特饮 | V5: 500 | W5: =V5*_xlfn.XLOOKUP(U5,'道具价值表-汇总'!$B:$B,'道具价值表-汇总'!$D:$D,,0,1) | X5: =SUMIF($N$4:$W$4,"价值*",N5:W5) | Y5: 0.098333333 | AA5: 500 | AB5: =X5/(AA5*50)
A6: 120 | B6: 120 | C6: 梦境招募器 | D6: 5 | E6: =D6*_xlfn.XLOOKUP(C6,'道具价值表-汇总'!$B:$B,'道具价值表-汇总'!$D:$D,,0,1) | F6: 超能特饮 | G6: 30 | H6: =G6*_xlfn.XLOOKUP(F6,'道具价值表-汇总'!$B:$B,'道具价值表-汇总'!$D:$D,,0,1) | I6: =H6+E6 | J6: 0.18 | K6: =I6/((A6-A5)*30) | N6: 第2轮 | O6: 钻石 | P6: 150 | Q6: =P6*_xlfn.XLOOKUP(O6,'道具价值表-汇总'!$B:$B,'道具价值表-汇总'!$D:$D,,0,1) | R6: 神话梦灵碎片 | S6: 15 | T6: =S6*_xlfn.XLOOKUP(R6,'道具价值表-汇总'!$B:$B,'道具价值表-汇总'!$D:$D,,0,1) | U6: 超能特饮 | V6: 800 | W6: =V6*_xlfn.XLOOKUP(U6,'道具价值表-汇总'!$B:$B,'道具价值表-汇总'!$D:$D,,0,1) | X6: =SUMIF($N$4:$W$4,"价值*",N6:W6) | Y6: 0.090555556 | AA6: 700 | AB6: =X6/(AA6*50)
A7: 200 | B7: 200 | C7: 梦境招募器 | D7: 5 | E7: =D7*_xlfn.XLOOKUP(C7,'道具价值表-汇总'!$B:$B,'道具价值表-汇总'!$D:$D,,0,1) | F7: 超能特饮 | G7: 30 | H7: =G7*_xlfn.XLOOKUP(F7,'道具价值表-汇总'!$B:$B,'道具价值表-汇总'!$D:$D,,0,1) | I7: =H7+E7 | J7: 0.14 | K7: =I7/((A7-A6)*30) | N7: 第3轮 | O7: 心梦宝石 | P7: 50 | Q7: =P7*_xlfn.XLOOKUP(O7,'道具价值表-汇总'!$B:$B,'道具价值表-汇总'!$D:$D,,0,1) | R7: 神话梦灵碎片 | S7: 20 | T7: =S7*_xlfn.XLOOKUP(R7,'道具价值表-汇总'!$B:$B,'道具价值表-汇总'!$D:$D,,0,1) | U7: 超能特饮 | V7: 1000 | W7: =V7*_xlfn.XLOOKUP(U7,'道具价值表-汇总'!$B:$B,'道具价值表-汇总'!$D:$D,,0,1) | X7: =SUMIF($N$4:$W$4,"价值*",N7:W7) | Y7: 0.13583333 | AA7: 1200 | AB7: =X7/(AA7*50)
A8: 280 | B8: 280 | C8: 梦境招募器 | D8: 10 | E8: =D8*_xlfn.XLOOKUP(C8,'道具价值表-汇总'!$B:$B,'道具价值表-汇总'!$D:$D,,0,1) | F8: 超能特饮 | G8: 50 | H8: =G8*_xlfn.XLOOKUP(F8,'道具价值表-汇总'!$B:$B,'道具价值表-汇总'!$D:$D,,0,1) | I8: =H8+E8 | J8: 0.19 | K8: =I8/((A8-A7)*30) | N8: 第4轮 | O8: 心梦宝石 | P8: 100 | Q8: =P8*_xlfn.XLOOKUP(O8,'道具价值表-汇总'!$B:$B,'道具价值表-汇总'!$D:$D,,0,1) | R8: 神话梦灵碎片 | S8: 30 | T8: =S8*_xlfn.XLOOKUP(R8,'道具价值表-汇总'!$B:$B,'道具价值表-汇总'!$D:$D,,0,1) | U8: 超能特饮 | V8: 1200 | W8: =V8*_xlfn.XLOOKUP(U8,'道具价值表-汇总'!$B:$B,'道具价值表-汇总'!$D:$D,,0,1) | X8: =SUMIF($N$4:$W$4,"价值*",N8:W8) | Y8: 0.115 | AA8: 1600 | AB8: =X8/(AA8*50)
A9: 360 | B9: 360 | C9: 梦境招募器 | D9: 10 | E9: =D9*_xlfn.XLOOKUP(C9,'道具价值表-汇总'!$B:$B,'道具价值表-汇总'!$D:$D,,0,1) | F9: 超能特饮 | G9: 50 | H9: =G9*_xlfn.XLOOKUP(F9,'道具价值表-汇总'!$B:$B,'道具价值表-汇总'!$D:$D,,0,1) | I9: =H9+E9 | J9: 0.17 | K9: =I9/((A9-A8)*30)
A10: 500 | B10: 500 | C10: 梦境招募器 | D10: 10 | E10: =D10*_xlfn.XLOOKUP(C10,'道具价值表-汇总'!$B:$B,'道具价值表-汇总'!$D:$D,,0,1) | F10: 超能特饮 | G10: 50 | H10: =G10*_xlfn.XLOOKUP(F10,'道具价值表-汇总'!$B:$B,'道具价值表-汇总'!$D:$D,,0,1) | I10: =H10+E10 | J10: 0.11 | K10: =I10/((A10-A9)*30)
D11: 270 | G11: 1830 | N11: 任务数值 | P11: A_活动任务_activity_tasks_data.xml
T12: 25
B13: 节点数值 | C13: 物品类型 | D13: 数量 | E13: 价值 | F13: 物品类型 | G13: 数量 | H13: 价值 | I13: 总价值 | J13: 返利比 | K13: 新返利比 | N13: 任务 | O13: 奖励 | P13: 数量 | Q13: 价值
A14: 80 | B14: 80 | C14: 梦境招募器 | D14: 5 | E14: =D14*_xlfn.XLOOKUP(C14,'道具价值表-汇总'!$B:$B,'道具价值表-汇总'!$D:$D,,0,1) | F14: 超能特饮 | G14: 50 | H14: 100 | I14: =H14+E14 | J14: 0.14 | K14: =I14/((A14-A13)*30) | N14: 消耗200体力 | O14: 梦境招募器 | P14: 5 | Q14: 150
A15: 160 | B15: 160 | C15: 梦境招募器 | D15: 5 | E15: =D15*_xlfn.XLOOKUP(C15,'道具价值表-汇总'!$B:$B,'道具价值表-汇总'!$D:$D,,0,1) | F15: 超能特饮 | G15: 50 | H15: 100 | I15: =H15+E15 | J15: 0.14 | K15: =I15/((A15-A14)*30) | N15: 消耗500体力 | O15: 梦境招募器 | P15: 10 | Q15: 300
A16: 260 | B16: 260 | C16: 梦境招募器 | D16: 5 | E16: =D16*_xlfn.XLOOKUP(C16,'道具价值表-汇总'!$B:$B,'道具价值表-汇总'!$D:$D,,0,1) | F16: 超能特饮 | G16: 50 | H16: 100 | I16: =H16+E16 | J16: 0.1 | K16: =I16/((A16-A15)*30) | N16: 消耗1000体力 | O16: 钻石 | P16: 188 | Q16: 188
A17: 380 | B17: 380 | C17: 梦境招募器 | D17: 10 | E17: =D17*_xlfn.XLOOKUP(C17,'道具价值表-汇总'!$B:$B,'道具价值表-汇总'!$D:$D,,0,1) | F17: 超能特饮 | G17: 80 | H17: 160 | I17: =H17+E17 | J17: 0.15 | K17: =I17/((A17-A16)*30) | N17: 参与5次竞技场 | O17: 梦境招募器 | P17: 5 | Q17: 150
A18: 520 | B18: 520 | C18: 梦境招募器 | D18: 10 | E18: =D18*_xlfn.XLOOKUP(C18,'道具价值表-汇总'!$B:$B,'道具价值表-汇总'!$D:$D,,0,1) | F18: 超能特饮 | G18: 80 | H18: 160 | I18: =H18+E18 | J18: 0.11 | K18: =I18/((A18-A17)*30) | N18: 参与10次竞技场 | O18: 梦境招募器 | P18: 10 | Q18: 300
A19: 700 | B19: 700 | C19: 梦境招募器 | D19: 10 | E19: =D19*_xlfn.XLOOKUP(C19,'道具价值表-汇总'!$B:$B,'道具价值表-汇总'!$D:$D,,0,1) | F19: 超能特饮 | G19: 80 | H19: 160 | I19: =H19+E19 | J19: 0.1 | K19: =I19/((A19-A18)*30) | N19: 参与20次竞技场 | O19: 梦愿水晶 | P19: 1 | Q19: 600
D20: 45 | G20: 390 | I20: 2130 | J20: 0.1183
B22: 节点数值 | C22: 物品类型 | D22: 数量 | E22: 价值 | F22: 物品类型 | G22: 数量 | H22: 价值 | I22: 总价值 | J22: 返利比
A23: 120 | B23: 120 | C23: 梦境招募器 | D23: 10 | E23: =D23*_xlfn.XLOOKUP(C23,'道具价值表-汇总'!$B:$B,'道具价值表-汇总'!$D:$D,,0,1) | F23: 超能特饮 | G23: 80 | H23: 160 | I23: =H23+E23 | J23: 0.19 | K23: =I23/((A23-A22)*30)
A24: 240 | B24: 240 | C24: 梦境招募器 | D24: 10 | E24: =D24*_xlfn.XLOOKUP(C24,'道具价值表-汇总'!$B:$B,'道具价值表-汇总'!$D:$D,,0,1) | F24: 超能特饮 | G24: 80 | H24: 160 | I24: =H24+E24 | J24: 0.19 | K24: =I24/((A24-A23)*30)
A25: 360 | B25: 360 | C25: 梦境招募器 | D25: 10 | E25: =D25*_xlfn.XLOOKUP(C25,'道具价值表-汇总'!$B:$B,'道具价值表-汇总'!$D:$D,,0,1) | F25: 超能特饮 | G25: 80 | H25: 160 | I25: =H25+E25 | J25: 0.15 | K25: =I25/((A25-A24)*30)
A26: 560 | B26: 560 | C26: 梦境招募器 | D26: 15 | E26: =D26*_xlfn.XLOOKUP(C26,'道具价值表-汇总'!$B:$B,'道具价值表-汇总'!$D:$D,,0,1) | F26: 超能特饮 | G26: 100 | H26: 200 | I26: =H26+E26 | J26: 0.15 | K26: =I26/((A26-A25)*30)
A27: 800 | B27: 800 | C27: 梦境招募器 | D27: 15 | E27: =D27*_xlfn.XLOOKUP(C27,'道具价值表-汇总'!$B:$B,'道具价值表-汇总'!$D:$D,,0,1) | F27: 超能特饮 | G27: 100 | H27: 200 | I27: =H27+E27 | J27: 0.14 | K27: =I27/((A27-A26)*30) | N27: 需求头像框 | O27: 可以升星给属性
A28: 1200 | B28: 1200 | C28: 梦境招募器 | D28: 15 | E28: =D28*_xlfn.XLOOKUP(C28,'道具价值表-汇总'!$B:$B,'道具价值表-汇总'!$D:$D,,0,1) | F28: 超能特饮 | G28: 100 | H28: 200 | I28: =H28+E28 | J28: 0.09 | K28: =I28/((A28-A27)*30) | N28: 每个冲刺 | O28: 头像框或者聊天框不一样 | Q28: 给与一定的属性
D29: 75 | G29: 540 | I29: 3330 | J29: 0.1388
B31: 节点数值 | C31: 物品类型 | D31: 数量 | E31: 价值 | F31: 物品类型 | G31: 数量 | H31: 价值 | I31: 总价值 | J31: 返利比
A32: 160 | B32: 160 | C32: 梦境招募器 | D32: 15 | E32: 450 | F32: 超能特饮 | G32: 100 | H32: 200 | I32: =H32+E32 | J32: 0.18 | K32: =I32/((A32-A31)*30)
A33: 300 | B33: 300 | C33: 梦境招募器 | D33: 15 | E33: 450 | F33: 超能特饮 | G33: 100 | H33: 200 | I33: =H33+E33 | J33: 0.18 | K33: =I33/((A33-A32)*30)
A34: 500 | B34: 500 | C34: 梦境招募器 | D34: 15 | E34: 450 | F34: 超能特饮 | G34: 100 | H34: 200 | I34: =H34+E34 | J34: 0.14 | K34: =I34/((A34-A33)*30)
A35: 800 | B35: 800 | C35: 梦境招募器 | D35: 20 | E35: 600 | F35: 超能特饮 | G35: 120 | H35: 240 | I35: =H35+E35 | J35: 0.14 | K35: =I35/((A35-A34)*30)
A36: 1200 | B36: 1200 | C36: 梦境招募器 | D36: 20 | E36: 600 | F36: 超能特饮 | G36: 120 | H36: 240 | I36: =H36+E36 | J36: 0.1 | K36: =I36/((A36-A35)*30)
A37: 1600 | B37: 1600 | C37: 梦境招募器 | D37: 20 | E37: 600 | F37: 超能特饮 | G37: 120 | H37: 240 | I37: =H37+E37 | J37: 0.09 | K37: =I37/((A37-A36)*30)
D38: 105 | G38: 660 | I38: 4470 | J38: 0.1242
B40: 商店数值 | D40: A_活动商店_activity_shop_data.xml
B42: 礼包名称 | C42: 价格 | D42: 限购次数 | E42: 物品类型 | F42: 数量 | G42: 价值 | H42: 物品类型 | I42: 数量 | J42: 价值 | K42: 物品类型 | L42: 数量 | M42: 价值 | N42: 总价值 | O42: 返利比 | P42: 折扣 | Q42: 2.5 | W42: 活动充钱上限 | X42: 耗钻上限
B43: 每日免费礼包 | C43: 0 | D43: 1 | E43: 梦境招募器 | F43: 2 | G43: 60 | N43: =SUMIF($B$42:$P$42,"价值*",B43:M43) | W43: 1092 | X43: 36912
B44: 钻石礼包 | C44: 268 | D44: 3 | E44: 梦境招募器 | F44: 20 | G44: 600 | H44: 随机能量特饮 | I44: 50 | J44: =I44*1 | N44: =SUMIF($B$42:$P$42,"价值*",B44:M44) | O44: =N44/C44 | P44: =1/O44*10 | Q44: =N44+N46+N48+N49+N51 | R44: =C44+C46+C48+C49+C51 | S44: =Q44/R44
B45: 6元礼包 | C45: 6 | D45: 3 | E45: 钻石 | F45: 60 | G45: 60 | H45: 梦境招募器 | I45: 15 | J45: 450 | K45: 随机能量特饮 | L45: 100 | M45: 100 | N45: =SUMIF($B$42:$P$42,"价值*",B45:M45) | O45: =N45/C45/10 | P45: =1/O45*10
B46: 钻石礼包 | C46: 688 | D46: 5 | E46: 梦境招募器 | F46: 40 | G46: 1200 | H46: 随机能量特饮 | I46: 150 | J46: 150 | N46: =SUMIF($B$42:$P$42,"价值*",B46:M46) | O46: =N46/C46 | P46: =1/O46*10
B47: 30元礼包 | C47: 30 | D47: 3 | E47: 钻石 | F47: 300 | G47: 300 | H47: 梦境招募器 | I47: 50 | J47: 1500 | N47: =SUMIF($B$42:$P$42,"价值*",B47:M47) | O47: =N47/C47/10 | P47: =1/O47*10
B48: 钻石礼包 | C48: 1588 | D48: 5 | E48: 梦境招募器 | F48: 80 | G48: =F48*30 | H48: 随机能量特饮 | I48: 200 | J48: =I48*10 | N48: =SUMIF($B$42:$P$42,"价值*",B48:M48) | O48: =N48/C48 | P48: =1/O48*10
B49: 钻石礼包 | C49: 2288 | D49: 5 | E49: 梦境招募器 | F49: 100 | G49: =F49*30 | H49: 随机能量特饮 | I49: 300 | J49: =I49*1 | N49: =SUMIF($B$42:$P$42,"价值*",B49:M49) | O49: =N49/C49 | P49: =1/O49*10
B50: 328元礼包 | C50: 328 | D50: 3 | E50: 钻石 | F50: 3280 | G50: 3280 | H50: 梦境招募器 | I50: 150 | J50: 4500 | N50: =SUMIF($B$42:$P$42,"价值*",B50:M50) | O50: =N50/C50/10 | P50: =1/O50*10
B51: 钻石礼包 | C51: 4888 | D51: 3 | E51: 梦境招募器 | F51: 200 | G51: 6000 | H51: 随机能量特饮 | I51: 500 | J51: 500 | N51: =SUMIF($B$42:$P$42,"价值*",B51:M51) | O51: =N51/C51 | P51: =1/O51*10
B53: 排行榜数值 | D53: A_活动排行_activity_rank_data.xml
B55: 排名 | C55: 物品类型 | D55: 数量 | E55: 价值 | F55: 物品类型 | G55: 数量 | H55: 价值 | I55: 物品类型 | J55: 数量 | K55: 价值 | L55: 物品类型 | M55: 数量 | N55: 价值 | O55: 总价值
B56: 1 | C56: 心梦宝石 | D56: 300 | E56: 3000 | F56: 神话梦灵碎片 | G56: 30 | H56: 1440 | I56: 星辉秘契 | J56: 20 | K56: 5600 | L56: 超能特饮 | M56: 900 | N56: 1800 | O56: 11840
B57: 2 | C57: 心梦宝石 | D57: 250 | E57: 2500 | F57: 神话梦灵碎片 | G57: 20 | H57: 960 | I57: 星辉秘契 | J57: 18 | K57: 5040 | L57: 超能特饮 | M57: 750 | N57: 1500 | O57: 10000
B58: 3 | C58: 心梦宝石 | D58: 200 | E58: 2000 | F58: 神话梦灵碎片 | G58: 15 | H58: 720 | I58: 星辉秘契 | J58: 15 | K58: 4200 | L58: 超能特饮 | M58: 600 | N58: 1200 | O58: 8120
B59: 4~5 | C59: 心梦宝石 | D59: 150 | E59: 1500 | F59: 神话梦灵碎片 | G59: 12 | H59: 576 | I59: 星辉秘契 | J59: 13 | K59: 3640 | L59: 超能特饮 | M59: 300 | N59: 600 | O59: 6316
B60: 6~10 | C60: 心梦宝石 | D60: 130 | E60: 1300 | F60: 神话梦灵碎片 | G60: 10 | H60: 480 | I60: 星辉秘契 | J60: 10 | K60: 2800 | L60: 超能特饮 | M60: 200 | N60: 400 | O60: 4980
B61: 11~30 | C61: 心梦宝石 | D61: 100 | E61: 1000 | F61: 神话梦灵碎片 | G61: 8 | H61: 384 | I61: 星辉秘契 | J61: 10 | K61: 2800 | L61: 超能特饮 | M61: 180 | N61: 360 | O61: 4544
B62: 31~60 | C62: 心梦宝石 | D62: 80 | E62: 800 | F62: 神话梦灵碎片 | G62: 5 | H62: 240 | I62: 星辉秘契 | J62: 8 | K62: 2240 | L62: 超能特饮 | M62: 150 | N62: 300 | O62: 3580
B63: 61~100 | C63: 心梦宝石 | D63: 50 | E63: 500 | F63: 星辉秘契 | G63: 5 | H63: 1400 | I63: 超能特饮 | J63: 120 | K63: 240
B64: 101~150 | C64: 钻石 | D64: 300 | E64: 300 | F64: 星辉秘契 | G64: 3 | H64: 840 | I64: 超能特饮 | J64: 100 | K64: 200
B65: 151~200 | C65: 钻石 | D65: 100 | E65: 100 | F65: 星辉秘契 | G65: 2 | H65: 560 | I65: 超能特饮 | J65: 80 | K65: 160
B66: 201~300 | C66: 星辉秘契 | D66: 1 | E66: 280 | F66: 超能特饮 | G66: 50 | H66: 100
B67: 301~500 | C67: 星之初愿 | D67: 3 | E67: 150 | F67: 超能特饮 | G67: 30 | H67: 60
A70: 符文主题
C73: A_活动轮循任务_activity_round_cycle_data.xml | F73: 50 | H73: 280
C74: 节点数值 | E74: 星之初愿 | F74: 1 | G74: 星辉秘契 | H74: 5 | O74: 轮次数值 | P74: A_活动轮循任务_activity_round_cycle_data.xml
B75: 新节点
C76: 节点数值 | D76: 物品类型 | E76: 数量 | F76: 价值 | G76: 物品类型 | H76: 数量 | I76: 价值 | J76: 总价值 | K76: 返利比 | L76: 新返利比 | O76: 轮次 | P76: 物品类型 | Q76: 数量 | R76: 价值 | S76: 物品类型 | T76: 数量 | U76: 价值 | V76: 物品类型 | W76: 数量 | X76: 价值 | Y76: 总价值 | Z76: 原反比 | AA76: 原节点 | AB76: 现节点 | AC76: 现反比
B77: 30 | C77: 30 | D77: 星辉秘契 | E77: 1 | F77: =E77*_xlfn.XLOOKUP(D77,'道具价值表-汇总'!$B:$B,'道具价值表-汇总'!$D:$D,,0,1) | G77: 金币 | H77: 1000 | I77: =H77*_xlfn.XLOOKUP(G77,'道具价值表-汇总'!$B:$B,'道具价值表-汇总'!$D:$D,,0,1) | J77: =I77+F77 | K77: 0.33 | L77: =J77/((B77-B76)*50) | N77: 300 | O77: 第1轮 | P77: 钻石 | Q77: 100 | R77: =Q77*_xlfn.XLOOKUP(P77,'道具价值表-汇总'!$B:$B,'道具价值表-汇总'!$D:$D,,0,1) | S77: 幻梦晶核 | T77: 12 | U77: =T77*_xlfn.XLOOKUP(S77,'道具价值表-汇总'!$B:$B,'道具价值表-汇总'!$D:$D,,0,1) | V77: 超能特饮 | W77: 300 | X77: =W77*_xlfn.XLOOKUP(V77,'道具价值表-汇总'!$B:$B,'道具价值表-汇总'!$D:$D,,0,1) | Y77: =SUMIF($N$4:$W$4,"价值*",O77:X77) | Z77: =Y77/(AA77*50) | AA77: 200 | AB77: 300 | AC77: =Y77/(AB77*50)
B78: 60 | C78: 60 | D78: 星辉秘契 | E78: 1 | F78: =E78*_xlfn.XLOOKUP(D78,'道具价值表-汇总'!$B:$B,'道具价值表-汇总'!$D:$D,,0,1) | G78: 金币 | H78: 1000 | I78: =H78*_xlfn.XLOOKUP(G78,'道具价值表-汇总'!$B:$B,'道具价值表-汇总'!$D:$D,,0,1) | J78: =I78+F78 | K78: 0.22 | L78: =J78/((B78-B77)*50) | N78: 500 | O78: 第2轮 | P78: 钻石 | Q78: 150 | R78: =Q78*_xlfn.XLOOKUP(P78,'道具价值表-汇总'!$B:$B,'道具价值表-汇总'!$D:$D,,0,1) | S78: 幻梦晶核 | T78: 12 | U78: =T78*_xlfn.XLOOKUP(S78,'道具价值表-汇总'!$B:$B,'道具价值表-汇总'!$D:$D,,0,1) | V78: 超能特饮 | W78: 500 | X78: =W78*_xlfn.XLOOKUP(V78,'道具价值表-汇总'!$B:$B,'道具价值表-汇总'!$D:$D,,0,1) | Y78: =SUMIF($N$4:$W$4,"价值*",O78:X78) | Z78: =Y78/(AA78*50) | AA78: 400 | AB78: 500 | AC78: =Y78/(AB78*50)
B79: 100 | C79: 100 | D79: 星辉秘契 | E79: 1 | F79: =E79*_xlfn.XLOOKUP(D79,'道具价值表-汇总'!$B:$B,'道具价值表-汇总'!$D:$D,,0,1) | G79: 金币 | H79: 1000 | I79: =H79*_xlfn.XLOOKUP(G79,'道具价值表-汇总'!$B:$B,'道具价值表-汇总'!$D:$D,,0,1) | J79: =I79+F79 | K79: 0.22 | L79: =J79/((B79-B78)*50) | N79: 700 | O79: 第3轮 | P79: 心梦宝石 | Q79: 50 | R79: =Q79*_xlfn.XLOOKUP(P79,'道具价值表-汇总'!$B:$B,'道具价值表-汇总'!$D:$D,,0,1) | S79: 幻梦晶核 | T79: 24 | U79: =T79*_xlfn.XLOOKUP(S79,'道具价值表-汇总'!$B:$B,'道具价值表-汇总'!$D:$D,,0,1) | V79: 超能特饮 | W79: 800 | X79: =W79*_xlfn.XLOOKUP(V79,'道具价值表-汇总'!$B:$B,'道具价值表-汇总'!$D:$D,,0,1) | Y79: =SUMIF($N$4:$W$4,"价值*",O79:X79) | Z79: =Y79/(AA79*50) | AA79: 600 | AB79: 700 | AC79: =Y79/(AB79*50)
B80: 160 | C80: 160 | D80: 星辉秘契 | E80: 2 | F80: =E80*_xlfn.XLOOKUP(D80,'道具价值表-汇总'!$B:$B,'道具价值表-汇总'!$D:$D,,0,1) | G80: 金币 | H80: 2000 | I80: =H80*_xlfn.XLOOKUP(G80,'道具价值表-汇总'!$B:$B,'道具价值表-汇总'!$D:$D,,0,1) | J80: =I80+F80 | K80: 0.33 | L80: =J80/((B80-B79)*50) | N80: 1000 | O80: 第4轮 | P80: 心梦宝石 | Q80: 100 | R80: =Q80*_xlfn.XLOOKUP(P80,'道具价值表-汇总'!$B:$B,'道具价值表-汇总'!$D:$D,,0,1) | S80: 幻梦晶核 | T80: 36 | U80: =T80*_xlfn.XLOOKUP(S80,'道具价值表-汇总'!$B:$B,'道具价值表-汇总'!$D:$D,,0,1) | V80: 超能特饮 | W80: 1000 | X80: =W80*_xlfn.XLOOKUP(V80,'道具价值表-汇总'!$B:$B,'道具价值表-汇总'!$D:$D,,0,1) | Y80: =SUMIF($N$4:$W$4,"价值*",O80:X80) | Z80: =Y80/(AA80*50) | AA80: 800 | AB80: 1000 | AC80: =Y80/(AB80*50)
B81: 220 | C81: 220 | D81: 星辉秘契 | E81: 2 | F81: =E81*_xlfn.XLOOKUP(D81,'道具价值表-汇总'!$B:$B,'道具价值表-汇总'!$D:$D,,0,1) | G81: 金币 | H81: 2000 | I81: =H81*_xlfn.XLOOKUP(G81,'道具价值表-汇总'!$B:$B,'道具价值表-汇总'!$D:$D,,0,1) | J81: =I81+F81 | K81: 0.33 | L81: =J81/((B81-B80)*50)
B82: 300 | C82: 300 | D82: 星辉秘契 | E82: 2 | F82: =E82*_xlfn.XLOOKUP(D82,'道具价值表-汇总'!$B:$B,'道具价值表-汇总'!$D:$D,,0,1) | G82: 金币 | H82: 2000 | I82: =H82*_xlfn.XLOOKUP(G82,'道具价值表-汇总'!$B:$B,'道具价值表-汇总'!$D:$D,,0,1) | J82: =I82+F82 | K82: 0.33 | L82: =J82/((B82-B81)*50) | O82: 任务数值 | P82: A_活动任务_activity_tasks_data.xml
E83: 9 | H83: 9000 | J83: 2970 | K83: 0.053
O84: 任务 | P84: 奖励 | Q84: 数量 | R84: 价值 | S84: 运营验收
C85: 节点数值 | D85: 物品类型 | E85: 数量 | F85: 价值 | G85: 物品类型 | H85: 数量 | I85: 价值 | J85: 总价值 | K85: 返利比 | O85: 消耗200体力 | P85: 星之初愿 | Q85: 1 | R85: 50
B86: 60 | C86: 60 | D86: 星辉秘契 | E86: 1 | F86: =E86*_xlfn.XLOOKUP(D86,'道具价值表-汇总'!$B:$B,'道具价值表-汇总'!$D:$D,,0,1) | G86: 金币 | H86: 1000 | I86: =H86*_xlfn.XLOOKUP(G86,'道具价值表-汇总'!$B:$B,'道具价值表-汇总'!$D:$D,,0,1) | J86: =I86+F86 | K86: 0.17 | L86: =J86/((B86-B85)*50) | O86: 消耗500体力 | P86: 星之初愿 | Q86: 2 | R86: 100
B87: 120 | C87: 120 | D87: 星辉秘契 | E87: 1 | F87: =E87*_xlfn.XLOOKUP(D87,'道具价值表-汇总'!$B:$B,'道具价值表-汇总'!$D:$D,,0,1) | G87: 金币 | H87: 1000 | I87: =H87*_xlfn.XLOOKUP(G87,'道具价值表-汇总'!$B:$B,'道具价值表-汇总'!$D:$D,,0,1) | J87: =I87+F87 | K87: 0.11 | L87: =J87/((B87-B86)*50) | O87: 消耗1000体力 | P87: 钻石 | Q87: 188 | R87: 188
B88: 200 | C88: 200 | D88: 星辉秘契 | E88: 1 | F88: =E88*_xlfn.XLOOKUP(D88,'道具价值表-汇总'!$B:$B,'道具价值表-汇总'!$D:$D,,0,1) | G88: 金币 | H88: 1000 | I88: =H88*_xlfn.XLOOKUP(G88,'道具价值表-汇总'!$B:$B,'道具价值表-汇总'!$D:$D,,0,1) | J88: =I88+F88 | K88: 0.11 | L88: =J88/((B88-B87)*50) | O88: 参与5次竞技场 | P88: 星之初愿 | Q88: 1 | R88: 50
B89: 300 | C89: 300 | D89: 星辉秘契 | E89: 2 | F89: =E89*_xlfn.XLOOKUP(D89,'道具价值表-汇总'!$B:$B,'道具价值表-汇总'!$D:$D,,0,1) | G89: 金币 | H89: 2000 | I89: =H89*_xlfn.XLOOKUP(G89,'道具价值表-汇总'!$B:$B,'道具价值表-汇总'!$D:$D,,0,1) | J89: =I89+F89 | K89: 0.17 | L89: =J89/((B89-B88)*50) | O89: 参与10次竞技场 | P89: 星之初愿 | Q89: 2 | R89: 100
B90: 400 | C90: 400 | D90: 星辉秘契 | E90: 2 | F90: =E90*_xlfn.XLOOKUP(D90,'道具价值表-汇总'!$B:$B,'道具价值表-汇总'!$D:$D,,0,1) | G90: 金币 | H90: 2000 | I90: =H90*_xlfn.XLOOKUP(G90,'道具价值表-汇总'!$B:$B,'道具价值表-汇总'!$D:$D,,0,1) | J90: =I90+F90 | K90: 0.17 | L90: =J90/((B90-B89)*50) | O90: 参与20次竞技场 | P90: 星辉秘契 | Q90: 1 | R90: 280
B91: 500 | C91: 500 | D91: 星辉秘契 | E91: 2 | F91: =E91*_xlfn.XLOOKUP(D91,'道具价值表-汇总'!$B:$B,'道具价值表-汇总'!$D:$D,,0,1) | G91: 金币 | H91: 2000 | I91: =H91*_xlfn.XLOOKUP(G91,'道具价值表-汇总'!$B:$B,'道具价值表-汇总'!$D:$D,,0,1) | J91: =I91+F91 | K91: 0.17 | L91: =J91/((B91-B90)*50)
E92: 9 | H92: 9000 | J92: 2970 | K92: 0.0265
C94: 节点数值 | D94: 物品类型 | E94: 数量 | F94: 价值 | G94: 物品类型 | H94: 数量 | I94: 价值 | J94: 总价值 | K94: 返利比
B95: 100 | C95: 100 | D95: 星辉秘契 | E95: 2 | F95: =E95*_xlfn.XLOOKUP(D95,'道具价值表-汇总'!$B:$B,'道具价值表-汇总'!$D:$D,,0,1) | G95: 金币 | H95: 1000 | I95: =H95*_xlfn.XLOOKUP(G95,'道具价值表-汇总'!$B:$B,'道具价值表-汇总'!$D:$D,,0,1) | J95: =I95+F95 | K95: 0.2 | L95: =J95/((B95-B94)*50)
B96: 200 | C96: 200 | D96: 星辉秘契 | E96: 2 | F96: =E96*_xlfn.XLOOKUP(D96,'道具价值表-汇总'!$B:$B,'道具价值表-汇总'!$D:$D,,0,1) | G96: 金币 | H96: 1000 | I96: =H96*_xlfn.XLOOKUP(G96,'道具价值表-汇总'!$B:$B,'道具价值表-汇总'!$D:$D,,0,1) | J96: =I96+F96 | K96: 0.14 | L96: =J96/((B96-B95)*50)
B97: 320 | C97: 320 | D97: 星辉秘契 | E97: 2 | F97: =E97*_xlfn.XLOOKUP(D97,'道具价值表-汇总'!$B:$B,'道具价值表-汇总'!$D:$D,,0,1) | G97: 金币 | H97: 1000 | I97: =H97*_xlfn.XLOOKUP(G97,'道具价值表-汇总'!$B:$B,'道具价值表-汇总'!$D:$D,,0,1) | J97: =I97+F97 | K97: 0.14 | L97: =J97/((B97-B96)*50)
B98: 450 | C98: 450 | D98: 星辉秘契 | E98: 3 | F98: =E98*_xlfn.XLOOKUP(D98,'道具价值表-汇总'!$B:$B,'道具价值表-汇总'!$D:$D,,0,1) | G98: 金币 | H98: 2000 | I98: =H98*_xlfn.XLOOKUP(G98,'道具价值表-汇总'!$B:$B,'道具价值表-汇总'!$D:$D,,0,1) | J98: =I98+F98 | K98: 0.16 | L98: =J98/((B98-B97)*50)
B99: 560 | C99: 560 | D99: 星辉秘契 | E99: 3 | F99: =E99*_xlfn.XLOOKUP(D99,'道具价值表-汇总'!$B:$B,'道具价值表-汇总'!$D:$D,,0,1) | G99: 金币 | H99: 2000 | I99: =H99*_xlfn.XLOOKUP(G99,'道具价值表-汇总'!$B:$B,'道具价值表-汇总'!$D:$D,,0,1) | J99: =I99+F99 | K99: 0.16 | L99: =J99/((B99-B98)*50)
B100: 700 | C100: 700 | D100: 星辉秘契 | E100: 3 | F100: =E100*_xlfn.XLOOKUP(D100,'道具价值表-汇总'!$B:$B,'道具价值表-汇总'!$D:$D,,0,1) | G100: 金币 | H100: 2000 | I100: =H100*_xlfn.XLOOKUP(G100,'道具价值表-汇总'!$B:$B,'道具价值表-汇总'!$D:$D,,0,1) | J100: =I100+F100 | K100: 0.16 | L100: =J100/((B100-B99)*50)
E101: 15 | H101: 9000 | J101: 4650 | K101: 0.0277
C103: 节点数值 | D103: 物品类型 | E103: 数量 | F103: 价值 | G103: 物品类型 | H103: 数量 | I103: 价值 | J103: 总价值 | K103: 返利比
B104: 120 | C104: 120 | D104: 星辉秘契 | E104: 2 | F104: =E104*_xlfn.XLOOKUP(D104,'道具价值表-汇总'!$B:$B,'道具价值表-汇总'!$D:$D,,0,1) | G104: 金币 | H104: 1000 | I104: =H104*_xlfn.XLOOKUP(G104,'道具价值表-汇总'!$B:$B,'道具价值表-汇总'!$D:$D,,0,1) | J104: =I104+F104 | K104: 0.15 | L104: =J104/((B104-B103)*50)
B105: 240 | C105: 240 | D105: 星辉秘契 | E105: 2 | F105: =E105*_xlfn.XLOOKUP(D105,'道具价值表-汇总'!$B:$B,'道具价值表-汇总'!$D:$D,,0,1) | G105: 金币 | H105: 1000 | I105: =H105*_xlfn.XLOOKUP(G105,'道具价值表-汇总'!$B:$B,'道具价值表-汇总'!$D:$D,,0,1) | J105: =I105+F105 | K105: 0.1 | L105: =J105/((B105-B104)*50)
B106: 380 | C106: 380 | D106: 星辉秘契 | E106: 2 | F106: =E106*_xlfn.XLOOKUP(D106,'道具价值表-汇总'!$B:$B,'道具价值表-汇总'!$D:$D,,0,1) | G106: 金币 | H106: 1000 | I106: =H106*_xlfn.XLOOKUP(G106,'道具价值表-汇总'!$B:$B,'道具价值表-汇总'!$D:$D,,0,1) | J106: =I106+F106 | K106: 0.1 | L106: =J106/((B106-B105)*50)
B107: 560 | C107: 560 | D107: 星辉秘契 | E107: 3 | F107: =E107*_xlfn.XLOOKUP(D107,'道具价值表-汇总'!$B:$B,'道具价值表-汇总'!$D:$D,,0,1) | G107: 金币 | H107: 2000 | I107: =H107*_xlfn.XLOOKUP(G107,'道具价值表-汇总'!$B:$B,'道具价值表-汇总'!$D:$D,,0,1) | J107: =I107+F107 | K107: 0.12 | L107: =J107/((B107-B106)*50)
B108: 780 | C108: 780 | D108: 星辉秘契 | E108: 3 | F108: =E108*_xlfn.XLOOKUP(D108,'道具价值表-汇总'!$B:$B,'道具价值表-汇总'!$D:$D,,0,1) | G108: 金币 | H108: 2000 | I108: =H108*_xlfn.XLOOKUP(G108,'道具价值表-汇总'!$B:$B,'道具价值表-汇总'!$D:$D,,0,1) | J108: =I108+F108 | K108: 0.12 | L108: =J108/((B108-B107)*50)
B109: 1000 | C109: 1000 | D109: 星辉秘契 | E109: 3 | F109: =E109*_xlfn.XLOOKUP(D109,'道具价值表-汇总'!$B:$B,'道具价值表-汇总'!$D:$D,,0,1) | G109: 金币 | H109: 2000 | I109: =H109*_xlfn.XLOOKUP(G109,'道具价值表-汇总'!$B:$B,'道具价值表-汇总'!$D:$D,,0,1) | J109: =I109+F109 | K109: 0.12 | L109: =J109/((B109-B108)*50)
E110: 15 | H110: 9000 | J110: 4650 | K110: 0.0208
C112: 商店数值 | D112: A_活动商店_activity_shop_data.xml
C114: 礼包名称 | D114: 价格 | E114: 限购次数 | F114: 物品类型 | G114: 数量 | H114: 价值 | I114: 物品类型 | J114: 数量 | K114: 价值 | L114: 物品类型 | M114: 数量 | N114: 价值 | O114: 总价值 | P114: 返利比 | X114: 活动充钱上限 | Y114: 耗钻上限
...

Sheet 悬赏活动
A3: 第一层 | E3: 第一期商品 | K3: 第二期商品 | Q3: 第三期商品 | W3: 第四期商品
B4: 消耗代币 | C4: 道具id | D4: 代币数量 | E4: 奖励内容 | F4: 道具id | G4: 奖励数量 | H4: 单价 | I4: 价值 | K4: 奖励内容 | L4: 道具id | M4: 奖励数量 | N4: 单价 | O4: 价值 | Q4: 奖励内容 | R4: 道具id | S4: 奖励数量 | T4: 单价 | U4: 价值 | W4: 奖励内容 | X4: 道具id | Y4: 奖励数量 | Z4: 单价 | AA4: 价值
B5: 悬赏线索 | C5: 5600208 | D5: 200 | E5: 梦境招募器 | F5: 11 | G5: 20 | H5: 30 | I5: 600 | K5: 梦境招募器 | L5: 11 | M5: 20 | N5: 30 | O5: 600 | Q5: 梦境招募器 | R5: 11 | S5: 20 | T5: 30 | U5: 600 | W5: 梦境招募器 | X5: 11 | Y5: 20 | Z5: 30 | AA5: 600
B6: 悬赏线索 | C6: 5600208 | D6: 200 | E6: 装备图纸 | F6: 50002 | G6: 200 | H6: 3 | I6: 600 | K6: 星之初愿 | L6: 9 | M6: 10 | N6: 50 | O6: 500 | Q6: 星之初愿 | R6: 9 | S6: 10 | T6: 50 | U6: 500 | W6: 星之初愿 | X6: 9 | Y6: 10 | Z6: 50 | AA6: 500
B7: 悬赏线索 | C7: 5600208 | D7: 200 | E7: 随机能量特饮 | F7: 5103001 | G7: 500 | H7: 1 | I7: 500 | K7: 随机能量特饮 | L7: 5103001 | M7: 500 | N7: 1 | O7: 500 | Q7: 随机能量特饮 | R7: 5103001 | S7: 500 | T7: 1 | U7: 500 | W7: 随机能量特饮 | X7: 5103001 | Y7: 500 | Z7: 1 | AA7: 500
A9: 第二层 | G9: 解锁条件 | M9: 解锁条件 | S9: 解锁条件 | Y9: 解锁条件
B10: 消耗代币 | C10: 道具id | D10: 代币数量 | E10: 奖励内容 | F10: 道具id | G10: 奖励数量 | H10: 单价 | I10: 价值 | K10: 奖励内容 | L10: 道具id | M10: 奖励数量 | N10: 单价 | O10: 价值 | Q10: 奖励内容 | R10: 道具id | S10: 奖励数量 | T10: 单价 | U10: 价值 | W10: 奖励内容 | X10: 道具id | Y10: 奖励数量 | Z10: 单价 | AA10: 价值
B11: 悬赏线索 | C11: 5600208 | D11: 400 | E11: 星辉秘契 | F11: 30 | G11: 5 | H11: 280 | I11: 1400 | K11: 精密齿轮 | L11: 63 | M11: 1000 | N11: 1 | O11: 1000 | Q11: 精密齿轮 | R11: 63 | S11: 1000 | T11: 1 | U11: 1000 | W11: 精密齿轮 | X11: 63 | Y11: 1000 | Z11: 1 | AA11: 1000
B12: 悬赏线索 | C12: 5600208 | D12: 400 | E12: 转运石 | F12: 5523001 | G12: 3600 | H12: 0.33 | I12: 1188 | K12: 转运石 | L12: 5523001 | M12: 3600 | N12: 0.33 | O12: 1188 | Q12: 转运石 | R12: 5523001 | S12: 3600 | T12: 0.33 | U12: 1188 | W12: 转运石 | X12: 5523001 | Y12: 3600 | Z12: 0.33 | AA12: 1188
B13: 悬赏线索 | C13: 5600208 | D13: 400 | E13: 超能特饮 | F13: 5104001 | G13: 500 | H13: 2 | I13: 1000 | K13: 超能特饮 | L13: 5104001 | M13: 500 | N13: 2 | O13: 1000 | Q13: 超能特饮 | R13: 5104001 | S13: 500 | T13: 2 | U13: 1000 | W13: 超能特饮 | X13: 5104001 | Y13: 500 | Z13: 2 | AA13: 1000
A15: 第三层 | G15: 解锁条件 | M15: 解锁条件 | S15: 解锁条件 | Y15: 解锁条件
B16: 消耗代币 | C16: 道具id | D16: 代币数量 | E16: 奖励内容 | F16: 道具id | G16: 奖励数量 | H16: 单价 | I16: 价值 | K16: 奖励内容 | L16: 道具id | M16: 奖励数量 | N16: 单价 | O16: 价值 | Q16: 奖励内容 | R16: 道具id | S16: 奖励数量 | T16: 单价 | U16: 价值 | W16: 奖励内容 | X16: 道具id | Y16: 奖励数量 | Z16: 单价 | AA16: 价值
B17: 悬赏线索 | C17: 5600208 | D17: 600 | E17: 星辉秘契 | F17: 30 | G17: 8 | H17: 280 | I17: 2240 | K17: 星辉秘契 | L17: 30 | M17: 8 | N17: 280 | O17: 2240 | Q17: 星辉秘契 | R17: 30 | S17: 8 | T17: 280 | U17: 2240 | W17: 星辉秘契 | X17: 30 | Y17: 8 | Z17: 280 | AA17: 2240
B18: 悬赏线索 | C18: 5600208 | D18: 600 | E18: 梦愿水晶 | F18: 35 | G18: 3 | H18: 600 | I18: 1800 | K18: 梦愿水晶 | L18: 35 | M18: 5 | N18: 600 | O18: 3000 | Q18: 智械发条 | R18: 62 | S18: 10 | T18: 150 | U18: 1500 | W18: 智械发条 | X18: 62 | Y18: 10 | Z18: 150 | AA18: 1500
B19: 悬赏线索 | C19: 5600208 | D19: 600 | E19: 幻梦晶核 | F19: 5305001 | G19: 30 | H19: 60 | I19: 1800 | K19: 幻梦晶核 | L19: 5305001 | M19: 30 | N19: 60 | O19: 1800 | Q19: 幻梦晶核 | R19: 5305001 | S19: 30 | T19: 60 | U19: 1800 | W19: 幻梦晶核 | X19: 5305001 | Y19: 30 | Z19: 60 | AA19: 1800
A21: 第四层 | G21: 解锁条件 | M21: 解锁条件 | S21: 解锁条件 | Y21: 解锁条件
B22: 消耗代币 | C22: 道具id | D22: 代币数量 | E22: 奖励内容 | F22: 道具id | G22: 奖励数量 | H22: 单价 | I22: 价值 | K22: 奖励内容 | L22: 道具id | M22: 奖励数量 | N22: 单价 | O22: 价值 | Q22: 奖励内容 | R22: 道具id | S22: 奖励数量 | T22: 单价 | U22: 价值 | W22: 奖励内容 | X22: 道具id | Y22: 奖励数量 | Z22: 单价 | AA22: 价值
B23: 悬赏线索 | C23: 5600208 | D23: 800 | E23: 自选史诗藏品 | F23: 6220011 | G23: 1 | H23: 2400 | I23: 2400 | K23: 自选史诗藏品 | L23: 6220011 | M23: 1 | N23: 2400 | O23: 2400 | Q23: 自选史诗藏品 | R23: 6220011 | S23: 1 | T23: 2400 | U23: 2400 | W23: 自选史诗藏品 | X23: 6220011 | Y23: 1 | Z23: 2400 | AA23: 2400
B24: 悬赏线索 | C24: 5600208 | D24: 800 | E24: 绮梦随机礼盒Ⅱ | F24: 100122 | G24: 1 | H24: 4000 | I24: 4000 | K24: 传说祝福石 | L24: 5305010 | M24: 2 | N24: 1500 | O24: 3000 | Q24: 绮梦随机礼盒Ⅱ | R24: 100122 | S24: 1 | T24: 4000 | U24: 4000 | W24: 传说祝福石 | X24: 5305010 | Y24: 2 | Z24: 1500 | AA24: 3000
B25: 悬赏线索 | C25: 5600208 | D25: 800 | E25: 传说符文 | F25: 5305000 | G25: 1 | H25: 4000 | I25: 4000 | K25: 智械发条 | L25: 62 | M25: 20 | N25: 150 | O25: 3000 | Q25: 智械发条 | R25: 62 | S25: 20 | T25: 150 | U25: 3000 | W25: 智械发条 | X25: 62 | Y25: 20 | Z25: 150 | AA25: 3000
A27: 第五层 | G27: 解锁条件 | M27: 解锁条件 | S27: 解锁条件 | Y27: 解锁条件
B28: 消耗代币 | C28: 道具id | D28: 代币数量 | E28: 奖励内容 | F28: 道具id | G28: 奖励数量 | H28: 单价 | I28: 价值 | K28: 奖励内容 | L28: 道具id | M28: 奖励数量 | N28: 单价 | O28: 价值 | Q28: 奖励内容 | R28: 道具id | S28: 奖励数量 | T28: 单价 | U28: 价值 | W28: 奖励内容 | X28: 道具id | Y28: 奖励数量 | Z28: 单价 | AA28: 价值
B29: 悬赏线索 | C29: 5600208 | D29: 1300 | E29: 神话祝福石 | F29: 5305008 | G29: 2 | H29: 5000 | I29: 10000 | K29: 神话祝福石 | L29: 5305008 | M29: 2 | N29: 5000 | O29: 10000 | Q29: 神话祝福石 | R29: 5305008 | S29: 2 | T29: 5000 | U29: 10000 | W29: 神话符文 | X29: 5306000 | Y29: 1 | Z29: 16384 | AA29: 16384
B30: 悬赏线索 | C30: 5600208 | D30: 1300 | E30: 神话符文 | F30: 5306000 | G30: 1 | H30: 16384 | I30: 16384 | K30: 神话符文 | L30: 5306000 | M30: 1 | N30: 16384 | O30: 16384 | Q30: 随机创世零件 | R30: 6040004 | S30: 1 | T30: 16000 | U30: 16000 | W30: 随机创世零件 | X30: 6040004 | Y30: 1 | Z30: 16000 | AA30: 16000
B31: 悬赏线索 | C31: 5600208 | D31: 1300 | E31: 万福摇摇机 | F31: 6200011 | G31: 1 | H31: 4800 | I31: 4800 | K31: 双倍碰撞 | L31: 6200014 | M31: 1 | N31: 4800 | O31: 4800 | Q31: 意外之喜 | R31: 6200013 | S31: 1 | T31: 4800 | U31: 4800 | W31: 怦怦时刻 | X31: 6200012 | Y31: 1 | Z31: 4800 | AA31: 4800
G34: 冲刺活动
D35: 核心道具 | I35: 悬赏id
A36: 15 | B36: 1 | C36: 1 | D36: 神话祝福石 | E36: 神话符文 | F36: 万福摇摇机 | G36: 符文 | L36: 绮梦随机礼盒Ⅱ | M36: 随机传说符文
A37: =A36+7 | B37: 2 | C37: 2 | D37: 神话祝福石 | E37: 神话符文 | F37: 双倍碰撞 | G37: 秘宝 | L37: 传说祝福石 | M37: 智械发条
A38: =A37+7 | B38: 3 | C38: 3 | D38: 神话祝福石 | E38: 随机创世零件 | F38: 意外之喜 | G38: 招募 | L38: 绮梦随机礼盒Ⅱ | M38: 智械发条
A39: =A38+7 | B39: 4 | C39: 4 | D39: 神话符文 | E39: 随机创世零件 | F39: 怦怦时刻 | G39: 符文 | L39: 传说祝福石 | M39: 智械发条 | Q39: 3300
A40: =A39+7 | B40: 5 | C40: 2 | D40: 神话祝福石 | E40: 神话符文 | F40: 双倍碰撞 | G40: 秘宝 | L40: 传说祝福石 | M40: 智械发条
A41: =A40+7 | B41: 6 | C41: 3 | D41: 神话祝福石 | E41: 随机创世零件 | F41: 意外之喜 | G41: 招募 | L41: 绮梦随机礼盒Ⅱ | M41: 智械发条
A42: =A41+7 | B42: 7 | C42: 1 | D42: 神话祝福石 | E42: 神话符文 | F42: 万福摇摇机 | G42: 符文 | L42: 绮梦随机礼盒Ⅱ | M42: 随机传说符文
A43: =A42+7 | B43: 8 | C43: 4 | D43: 神话符文 | E43: 随机创世零件 | F43: 怦怦时刻 | G43: 秘宝 | L43: 传说祝福石 | M43: 智械发条
C44: 任务数值
C45: 类型 | D45: 任务详情 | E45: 奖励数值 | F45: 道具id | G45: 奖励数量 | K45: 奖励价值
C46: 每日 | D46: 今日上线登录 | E46: 悬赏线索 | F46: {=_xlfn.XLOOKUP(E46,item!$B$3:$B$100157,item!$A$3:$A$100157,0,0,1)} | G46: 20 | K46: =G46*3 | M46: 20 | N46: 怦怦时刻 | U46: 2 3 4循环
C47: 每日 | D47: 完成1次主线挑战 | E47: 悬赏线索 | F47: {=_xlfn.XLOOKUP(E47,item!$B$3:$B$100157,item!$A$3:$A$100157,0,0,1)} | G47: 30 | K47: =G47*3 | M47: 30
C48: 每日 | D48: 完成1次荧幕争锋 | E48: 悬赏线索 | F48: {=_xlfn.XLOOKUP(E48,item!$B$3:$B$100157,item!$A$3:$A$100157,0,0,1)} | G48: 20 | K48: =G48*3 | M48: 20
C49: 每日 | D49: 完成1次梦域巡航 | E49: 悬赏线索 | F49: {=_xlfn.XLOOKUP(E49,item!$B$3:$B$100157,item!$A$3:$A$100157,0,0,1)} | G49: 30 | K49: =G49*3 | M49: 30
C50: 每日 | D50: 扫荡1次海底捞金 | E50: 悬赏线索 | F50: {=_xlfn.XLOOKUP(E50,item!$B$3:$B$100157,item!$A$3:$A$100157,0,0,1)} | G50: 10 | K50: =G50*3 | M50: 10
C51: 每日 | D51: 完成1次贪吃大作战 | E51: 悬赏线索 | F51: {=_xlfn.XLOOKUP(E51,item!$B$3:$B$100157,item!$A$3:$A$100157,0,0,1)} | G51: 20 | K51: =G51*3 | M51: 20
C52: 每日 | D52: 完成1次小卖部砍价 | E52: 悬赏线索 | F52: {=_xlfn.XLOOKUP(E52,item!$B$3:$B$100157,item!$A$3:$A$100157,0,0,1)} | G52: 10 | K52: =G52*3 | M52: 10
B54: 一次性任务 | D54: 消耗150点体力 | E54: 悬赏线索 | F54: {=_xlfn.XLOOKUP(E54,item!$B$3:$B$100157,item!$A$3:$A$100157,0,0,1)} | G54: 20 | K54: =G54*3 | L54: =G54*0.7 | M54: 15
D55: 消耗300点体力 | E55: 悬赏线索 | F55: {=_xlfn.XLOOKUP(E55,item!$B$3:$B$100157,item!$A$3:$A$100157,0,0,1)} | G55: 40 | K55: =G55*3 | L55: =G55*0.7 | M55: 30
D56: 消耗500点体力 | E56: 悬赏线索 | F56: {=_xlfn.XLOOKUP(E56,item!$B$3:$B$100157,item!$A$3:$A$100157,0,0,1)} | G56: 60 | K56: =G56*3 | L56: =G56*0.7 | M56: 40
D57: 消耗800点体力 | E57: 悬赏线索 | F57: {=_xlfn.XLOOKUP(E57,item!$B$3:$B$100157,item!$A$3:$A$100157,0,0,1)} | G57: 60 | K57: =G57*3 | L57: =G57*0.7 | M57: 40
D58: 消耗198钻石 | E58: 悬赏线索 | F58: {=_xlfn.XLOOKUP(E58,item!$B$3:$B$100157,item!$A$3:$A$100157,0,0,1)} | G58: 20 | K58: =G58*3 | L58: =G58*0.7 | M58: 15
D59: 消耗400钻石 | E59: 悬赏线索 | F59: {=_xlfn.XLOOKUP(E59,item!$B$3:$B$100157,item!$A$3:$A$100157,0,0,1)} | G59: 40 | K59: =G59*3 | L59: =G59*0.7 | M59: 30
D60: 消耗700钻石 | E60: 悬赏线索 | F60: {=_xlfn.XLOOKUP(E60,item!$B$3:$B$100157,item!$A$3:$A$100157,0,0,1)} | G60: 60 | K60: =G60*3 | L60: =G60*0.7 | M60: 40
D61: 消耗1000钻石 | E61: 悬赏线索 | F61: {=_xlfn.XLOOKUP(E61,item!$B$3:$B$100157,item!$A$3:$A$100157,0,0,1)} | G61: 60 | K61: =G61*3 | L61: =G61*0.7 | M61: 40
D62: 消耗晶石3000个 | E62: 悬赏线索 | F62: {=_xlfn.XLOOKUP(E62,item!$B$3:$B$100157,item!$A$3:$A$100157,0,0,1)} | G62: 20 | K62: =G62*3 | L62: =G62*0.7 | M62: 15
D63: 消耗晶石5000个 | E63: 悬赏线索 | F63: {=_xlfn.XLOOKUP(E63,item!$B$3:$B$100157,item!$A$3:$A$100157,0,0,1)} | G63: 40 | K63: =G63*3 | L63: =G63*0.7 | M63: 30
D64: 消耗晶石8000个 | E64: 悬赏线索 | F64: {=_xlfn.XLOOKUP(E64,item!$B$3:$B$100157,item!$A$3:$A$100157,0,0,1)} | G64: 60 | K64: =G64*3 | L64: =G64*0.7 | M64: 40
D65: 消耗晶石10000个 | E65: 悬赏线索 | F65: {=_xlfn.XLOOKUP(E65,item!$B$3:$B$100157,item!$A$3:$A$100157,0,0,1)} | G65: 60 | K65: =G65*3 | L65: =G65*0.7 | M65: 40
D66: 消耗100招募券 | E66: 悬赏线索 | F66: {=_xlfn.XLOOKUP(E66,item!$B$3:$B$100157,item!$A$3:$A$100157,0,0,1)} | G66: 20 | K66: =G66*3 | L66: =G66*0.7 | M66: 15
... D68: 消耗300招募券 | E68: 悬赏线索 | F68: {=_xlfn.XLOOKUP(E68,item!$B$3:$B$100157,item!$A$3:$A$100157,0,0,1)} | G68: 60 | K68: =G68*3 | L68: =G68*0.7 | M68: 40
D69: 消耗500招募券 | E69: 悬赏线索 | F69: {=_xlfn.XLOOKUP(E69,item!$B$3:$B$100157,item!$A$3:$A$100157,0,0,1)} | G69: 60 | K69: =G69*3 | L69: =G69*0.7 | M69: 40 | N69: 7天一期2周拿1期 | O69: 40
G70: =SUM(G46:G52)*7+SUM(G54:G69) | H70: =H93/3 | I70: =H70/G70 | K70: =SUM(K46:K69) | M70: =SUM(M54:M69)+SUM(M46:M52)*7 | O70: 28
B72: 付费数值
D73: 礼包形式 | E73: 购买形式 | G73: 价格 | H73: 限购 | I73: 道具 | K73: 数量 | L73: 道具id | M73: 单价 | N73: 价值 | O73: 道具 | Q73: 数量 | R73: 道具id | S73: 单价 | T73: 价值 | U73: 道具
D74: 免费礼包 | E74: 免费 | G74: 0 | H74: 1 | I74: 悬赏线索 | K74: 10 | L74: {=_xlfn.XLOOKUP(I74,item!$B$2:$B$100157,item!$A$2:$A$100157,0,0,1)} | M74: {=I74} | N74: =M74*K74 | T74: =S74*Q74
D75: 悬赏礼包Ⅰ | E75: 钻石 | G75: 198 | H75: 1 | I75: 悬赏线索 | K75: 50 | L75: {=_xlfn.XLOOKUP(I75,item!$B$2:$B$100157,item!$A$2:$A$100157,0,0,1)} | M75: {=I75} | N75: =M75*K75 | O75: 梦境招募器 | Q75: 10 | R75: {=_xlfn.XLOOKUP(O75,item!$B$2:$B$100157,item!$A$2:$A$100157,0,0,1)} | S75: {=O75} | T75: =S75*Q75 | U75: 随机能量特饮
D76: 悬赏礼包Ⅱ | E76: 人民币 | G76: 6 | H76: 3 | I76: 钻石 | K76: 60 | L76: {=_xlfn.XLOOKUP(I76,item!$B$2:$B$100157,item!$A$2:$A$100157,0,0,1)} | M76: {=I76} | N76: =M76*K76 | O76: 悬赏线索 | Q76: 60 | R76: {=_xlfn.XLOOKUP(O76,item!$B$2:$B$100157,item!$A$2:$A$100157,0,0,1)} | S76: {=O76} | T76: =S76*Q76 | U76: 梦境招募器
D77: 悬赏礼包Ⅲ | E77: 钻石 | G77: 588 | H77: 3 | I77: 悬赏线索 | K77: 150 | L77: {=_xlfn.XLOOKUP(I77,item!$B$2:$B$100157,item!$A$2:$A$100157,0,0,1)} | M77: {=I77} | N77: =M77*K77 | O77: 梦境招募器 | Q77: 25 | R77: {=_xlfn.XLOOKUP(O77,item!$B$2:$B$100157,item!$A$2:$A$100157,0,0,1)} | S77: {=O77} | T77: =S77*Q77 | U77: 超能特饮
D78: 悬赏礼包Ⅳ | E78: 人民币 | G78: 30 | H78: 5 | I78: 钻石 | K78: 300 | L78: {=_xlfn.XLOOKUP(I78,item!$B$2:$B$100157,item!$A$2:$A$100157,0,0,1)} | M78: {=I78} | N78: =M78*K78 | O78: 悬赏线索 | Q78: 300 | R78: {=_xlfn.XLOOKUP(O78,item!$B$2:$B$100157,item!$A$2:$A$100157,0,0,1)} | S78: {=O78} | T78: =S78*Q78 | U78: 星之初愿
D79: 悬赏礼包Ⅴ | E79: 钻石 | G79: 1388 | H79: 3 | I79: 悬赏线索 | K79: 350 | L79: {=_xlfn.XLOOKUP(I79,item!$B$2:$B$100157,item!$A$2:$A$100157,0,0,1)} | M79: {=I79} | N79: =M79*K79 | O79: 星辉秘契 | Q79: 3 | R79: {=_xlfn.XLOOKUP(O79,item!$B$2:$B$100157,item!$A$2:$A$100157,0,0,1)} | S79: {=O79} | T79: =S79*Q79 | U79: 超能特饮
D80: 悬赏礼包Ⅵ | E80: 人民币 | G80: 98 | H80: 5 | I80: 钻石 | K80: 980 | L80: {=_xlfn.XLOOKUP(I80,item!$B$2:$B$100157,item!$A$2:$A$100157,0,0,1)} | M80: {=I80} | N80: =M80*K80 | O80: 悬赏线索 | Q80: 750 | R80: {=_xlfn.XLOOKUP(O80,item!$B$2:$B$100157,item!$A$2:$A$100157,0,0,1)} | S80: {=O80} | T80: =S80*Q80 | U80: 星辉秘契
D81: 悬赏礼包Ⅶ | E81: 钻石 | G81: 2188 | H81: 3 | I81: 悬赏线索 | K81: 600 | L81: {=_xlfn.XLOOKUP(I81,item!$B$2:$B$100157,item!$A$2:$A$100157,0,0,1)} | M81: {=I81} | N81: =M81*K81 | O81: 星辉秘契 | Q81: 5 | R81: {=_xlfn.XLOOKUP(O81,item!$B$2:$B$100157,item!$A$2:$A$100157,0,0,1)} | S81: {=O81} | T81: =S81*Q81 | U81: 转运石
K82: =K74*H74
K83: =K75*H75
Q84: =Q76*H76
K85: =K77*H77
Q86: =Q78*H78
G87: 3500 | K87: =K79*H79
Q88: =Q80*H80
K89: =K81*H81
K91: =SUM(K82:K89) | Q91: =SUM(Q82:Q89)
H93: =(D5+D29+D23+D17+D11)*3 | K93: =K91+G70+Q91
K95: =K93-H93

Sheet 月光炼梦
A1: 月光炼梦
A4: 活动与转盘核心
A5: 活动ID | B5: 时间 | C5: 门槛 | D5: 抽奖货币 | E5: 补足价 | F5: 轮数 | G5: 每轮格数 | H5: 大奖位置 | I5: 位置概率 | J5: 10轮最低 | K5: 10期望 | L5: 10最高
A6: 100342 | C6: 主线≥15关 | D6: 炼梦魔药 | E6: 120 | F6: 10 | G6: 10 | H6: 第8–10抽 | J6: =SUM(L32:L41) | K6: =SUM(M32:M41) | L6: =SUM(N32:N41)
A8: 转盘奖励库
A9: （神算诸葛 / 后羿 / 我爱沙）
A10: 位置 | B10: 当期奖励 | C10: 每轮数量 | D10: 10轮数量 | E10: 价格 | F10: 单次价值 | G10: 10轮固定价值 | H10: 权重 | I10: 单抽 | J10: 单抽价值 | K10: 前M抽必出 | L10: 前M抽禁出 | M10: 规则
A11: 1 | B11: 炼梦宝箱 | C11: 1 | D11: =C11*$F$6 | E11: 6000 | F11: =E11*C11 | G11: =F11*$F$6 | H11: 50 | I11: =H11/$H$21 | J11: =I11*F11 | K11: — | L11: 7 | M11: 大奖；前7抽禁出；抽中可跳轮
A12: 2 | B12: 随机神话梦灵 | C12: 1 | D12: =C12*$F$6 | E12: 480 | F12: =E12*C12 | G12: =F12*$F$6 | H12: 450 | I12: =H12/$H$21 | J12: =I12*F12 | K12: 4 | L12: — | M12: 前4抽内必出
A13: 3 | B13: 梦境招募器 | C13: 15 | D13: =C13*$F$6 | E13: 30 | F13: =E13*C13 | G13: =F13*$F$6 | H13: 600 | I13: =H13/$H$21 | J13: =I13*F13 | K13: — | L13: — | M13: 普通奖励；跳轮可能放弃
A14: 4 | B14: 幻梦晶核 | C14: 5 | D14: =C14*$F$6 | E14: 60 | F14: =E14*C14 | G14: =F14*$F$6 | H14: 850 | I14: =H14/$H$21 | J14: =I14*F14 | K14: — | L14: — | M14: 普通奖励；跳轮可能放弃
A15: 5 | B15: 星之初愿 | C15: 5 | D15: =C15*$F$6 | E15: 50 | F15: =E15*C15 | G15: =F15*$F$6 | H15: 950 | I15: =H15/$H$21 | J15: =I15*F15 | K15: — | L15: — | M15: 普通奖励；跳轮可能放弃
A16: 6 | B16: 星辉秘契 | C16: 1 | D16: =C16*$F$6 | E16: 280 | F16: =E16*C16 | G16: =F16*$F$6 | H16: 1300 | I16: =H16/$H$21 | J16: =I16*F16 | K16: — | L16: — | M16: 普通奖励；跳轮可能放弃
A17: 7 | B17: 超能特饮 | C17: 100 | D17: =C17*$F$6 | E17: 2 | F17: =E17*C17 | G17: =F17*$F$6 | H17: 1450 | I17: =H17/$H$21 | J17: =I17*F17 | K17: — | L17: — | M17: 普通奖励；跳轮可能放弃
A18: 8 | B18: 装备图纸 | C18: 50 | D18: =C18*$F$6 | E18: 3 | F18: =E18*C18 | G18: =F18*$F$6 | H18: 1450 | I18: =H18/$H$21 | J18: =I18*F18 | K18: — | L18: — | M18: 普通奖励；跳轮可能放弃
A19: 9 | B19: 转运石 | C19: 300 | D19: =C19*$F$6 | E19: 0.33 | F19: =E19*C19 | G19: =F19*$F$6 | H19: 1450 | I19: =H19/$H$21 | J19: =I19*F19 | K19: — | L19: — | M19: 普通奖励；跳轮可能放弃
A20: 10 | B20: 金币 | C20: 2000 | D20: =C20*$F$6 | E20: 0.05 | F20: =E20*C20 | G20: =F20*$F$6 | H20: 1450 | I20: =H20/$H$21 | J20: =I20*F20 | K20: — | L20: — | M20: 普通奖励；跳轮可能放弃
G21: =SUM(G11:G20) | H21: =SUM(H11:H20) | J21: =SUM(J11:J20) | K21: =J21/E6
F22: =120*46 | K22: 返利
A23: 大奖箱二级池
A24: 初始权重不是每次独立概率；条件锁定、限次和隐藏回退需按动态池理解。
A25: 类别 | B25: 初始权重 | C25: 最终内容 | D25: 价值 | E25: 道具价值 | F25: 单个箱子价值 | G25: 炼梦宝箱价值
A26: 天使套 | B26: 200 | D26: 8000 | E26: =D26*(B26/1000)
A27: 武器 | B27: 800 | D27: 4000 | E27: =D27*(B27/1000) | F27: 4800 | G27: 4800 | H27: 2次武器后第3次必然是天使套
A29: 轮次成本
A30: 逐抽成本与参考转盘表同样按轮次横向排列。
A31: 轮 | B31: 抽1 | C31: 抽2 | D31: 抽3 | E31: 抽4 | F31: 抽5 | G31: 抽6 | H31: 抽7 | I31: 抽8 | J31: 抽9 | K31: 抽10 | L31: 第8抽累计 | M31: 期望累计 | N31: 抽满累计
A32: 1 | B32: 1 | C32: 1 | D32: 2 | E32: 3 | F32: 4 | G32: 5 | H32: 6 | I32: 7 | J32: 8 | K32: 9 | L32: =SUM(B32:I32) | M32: =AVERAGE(L32,N32) | N32: =SUM(B32:K32)
A33: 2 | B33: 1 | C33: 1 | D33: 2 | E33: 3 | F33: 4 | G33: 5 | H33: 6 | I33: 8 | J33: 9 | K33: 10 | L33: =SUM(B33:I33) | M33: =AVERAGE(L33,N33) | N33: =SUM(B33:K33)
A34: 3 | B34: 1 | C34: 1 | D34: 2 | E34: 3 | F34: 4 | G34: 5 | H34: 6 | I34: 9 | J34: 10 | K34: 11 | L34: =SUM(B34:I34) | M34: =AVERAGE(L34,N34) | N34: =SUM(B34:K34)
A35: 4 | B35: 1 | C35: 1 | D35: 2 | E35: 3 | F35: 4 | G35: 5 | H35: 6 | I35: 10 | J35: 11 | K35: 12 | L35: =SUM(B35:I35) | M35: =AVERAGE(L35,N35) | N35: =SUM(B35:K35)
A36: 5 | B36: 1 | C36: 1 | D36: 2 | E36: 3 | F36: 4 | G36: 5 | H36: 6 | I36: 10 | J36: 12 | K36: 13 | L36: =SUM(B36:I36) | M36: =AVERAGE(L36,N36) | N36: =SUM(B36:K36)
A37: 6 | B37: 1 | C37: 1 | D37: 2 | E37: 3 | F37: 4 | G37: 5 | H37: 6 | I37: 10 | J37: 13 | K37: 15 | L37: =SUM(B37:I37) | M37: =AVERAGE(L37,N37) | N37: =SUM(B37:K37)
A38: 7 | B38: 1 | C38: 1 | D38: 2 | E38: 3 | F38: 4 | G38: 5 | H38: 6 | I38: 10 | J38: 13 | K38: 15 | L38: =SUM(B38:I38) | M38: =AVERAGE(L38,N38) | N38: =SUM(B38:K38)
A39: 8 | B39: 1 | C39: 1 | D39: 2 | E39: 3 | F39: 4 | G39: 5 | H39: 6 | I39: 10 | J39: 13 | K39: 15 | L39: =SUM(B39:I39) | M39: =AVERAGE(L39,N39) | N39: =SUM(B39:K39)
A40: 9 | B40: 1 | C40: 1 | D40: 2 | E40: 3 | F40: 4 | G40: 5 | H40: 6 | I40: 10 | J40: 13 | K40: 15 | L40: =SUM(B40:I40) | M40: =AVERAGE(L40,N40) | N40: =SUM(B40:K40)
A41: 10 | B41: 1 | C41: 1 | D41: 2 | E41: 3 | F41: 4 | G41: 5 | H41: 6 | I41: 10 | J41: 13 | K41: 15 | L41: =SUM(B41:I41) | M41: =AVERAGE(L41,N41) | N41: =SUM(B41:K41)
A43: 配套任务
A44: 完整3天做满共10瓶；仅列当期任务ID。
A45: 分类 | B45: 刷新 | C45: 任务 | D45: 最大次数 | E45: 奖励 | F45: 单次数量 | G45: 活动期数量 | H45: 任务ID | L45: =L41*120
A46: 日常 | B46: 每日重置 | C46: 每日登录游戏1次 | D46: 7 | E46: 炼梦魔药 | F46: 1 | G46: 7 | H46: 1100801
A47: 核心循环 | B47: 活动期一次性 | C47: 荧幕争锋挑战5次 | D47: 1 | E47: 炼梦魔药 | F47: 1 | G47: 1 | H47: 1100802
A48: 核心循环 | B48: 活动期一次性 | C48: 荧幕争锋挑战10次 | D48: 1 | E48: 炼梦魔药 | F48: 1 | G48: 1 | H48: 1100803
A49: 核心循环 | B49: 活动期一次性 | C49: 荧幕争锋挑战15次 | D49: 1 | E49: 炼梦魔药 | F49: 1 | G49: 1 | H49: 1100804
A50: 养成 | B50: 活动期一次性 | C50: 秘宝等级达到3级 | D50: 1 | E50: 炼梦魔药 | F50: 1 | G50: 1 | H50: 1100805
A51: 核心循环 | B51: 活动期一次性 | C51: 梦域巡航挑战5次 | D51: 1 | E51: 炼梦魔药 | F51: 1 | G51: 1 | H51: 1100806
A52: 核心循环 | B52: 活动期一次性 | C52: 梦域巡航挑战10次 | D52: 1 | E52: 炼梦魔药 | F52: 1 | G52: 1 | H52: 1100807 | J52: 7 | K52: 25
A53: 核心循环 | B53: 活动期一次性 | C53: 梦域巡航挑战15次 | D53: 1 | E53: 炼梦魔药 | F53: 1 | G53: 1 | H53: 1100808
G54: =SUM(G46:G53)
A55: 配套礼包
A56: 折扣为展示文案；价值按钻石+炼梦魔药×120钻石计算。
A57: 礼包 | B57: RMB | C57: 限购 | D57: 钻石 | E57: 魔药 | F57: 单次价值 | G57: 返利倍数 | H57: 展示折扣 | I57: 买满RMB | J57: 买满钻石 | K57: 买满魔药
A58: 炼梦礼包Ⅰ | B58: 6 | C58: 5 | D58: 60 | E58: 5 | F58: =E58*$E$6+D58 | G58: =F58/D58 | H58: 1折 | I58: =C58*B58 | J58: =C58*D58 | K58: =E58*C58 | N58: 5
A59: 炼梦礼包Ⅱ | B59: 30 | C59: 5 | D59: 300 | E59: 8 | F59: =E59*$E$6+D59 | G59: =F59/D59 | H59: 2折 | I59: =C59*B59 | J59: =C59*D59 | K59: =E59*C59 | N59: 8
A60: 炼梦礼包Ⅲ | B60: 98 | C60: 5 | D60: 980 | E60: 12 | F60: =E60*$E$6+D60 | G60: =F60/D60 | H60: 4折 | I60: =C60*B60 | J60: =C60*D60 | K60: =E60*C60 | N60: 15
A61: 全部买满 | B61: =B58*$C$58+B59*$C$59+B60*$C$60 | C61: — | D61: =D58*$C$58+D59*$C$59+D60*$C$60 | E61: =E58*$C$58+E59*$C$59+E60*$C$60 | F61: =E61*$E$6+D61 | G61: =F61/D61 | H61: — | I61: =SUM(I58:I60) | J61: =SUM(J58:J60) | K61: =SUM(K58:K60)
A63: 成本与投放结论
A64: 情景 | B64: 任务魔药 | C64: 礼包魔药 | D64: 礼包钻石 | E64: 总等价魔药 | F64: 目标成本 | G64: 缺魔药 | H64: 缺钻石 | I64: 性质 | J64: 保底
A65: 纯免费 | B65: 14 | C65: =K61 | D65: =D61 | E65: =G54 | F65: =L32 | G65: =F65-B65 | H65: =G65*120 | I65: 确定下限 | J65: =N32-E65 | L65: =G21
A66: 买满+任务｜10轮最低 | B66: =$B$65 | C66: =C$65 | D66: =D$65 | E66: =C66+B66+D66/120 | F66: =J6 | G66: =F66-E66 | H66: =G66*120 | I66: 确定下限 | K66: =H66+D66 | L66: =$L$65/K66
A67: 买满+任务｜10轮期望 | B67: =$B$65 | C67: =C$65 | D67: =D$65 | E67: =C67+B67+D67/120 | F67: =K6 | G67: =F67-E67 | H67: =G67*120 | I67: 配置推演 | K67: =H67+D67 | L67: =$L$65/K67
A68: 买满+任务｜10轮最高 | B68: =$B$65 | C68: =C$65 | D68: =D$65 | E68: =C68+B68+D68/120 | F68: =L6 | G68: =F68-E68 | H68: =G68*120 | I68: 确定上限 | K68: =H68+D68 | L68: =$L$65/K68
E69: 下限 | F69: 期望 | G69: 上限
D70: 1 | E70: =(L32-$E$65)*120/10 | F70: =(M32-$E$65)*120/10 | G70: =(N32-$E$65)*120/10
D71: 2 | E71: =(L33-$E$65)*120/10+E70 | F71: =(M33-$E$65)*120/10+F70 | G71: =(N33-$E$65)*120/10+G70 | J71: =172*120
D72: 3 | E72: =(L34-$E$65)*120/10+E71 | F72: =(M34-$E$65)*120/10+F71 | G72: =(N34-$E$65)*120/10+G71
D73: 4 | E73: =(L35-$E$65)*120/10+E72 | F73: =(M35-$E$65)*120/10+F72 | G73: =(N35-$E$65)*120/10+G72
D74: 5 | E74: =(L36-$E$65)*120/10+E73 | F74: =(M36-$E$65)*120/10+F73 | G74: =(N36-$E$65)*120/10+G73
D75: 6 | E75: =(L37-$E$65)*120/10+E74 | F75: =(M37-$E$65)*120/10+F74 | G75: =(N37-$E$65)*120/10+G74
D76: 7 | E76: =(L38-$E$65)*120/10+E75 | F76: =(M38-$E$65)*120/10+F75 | G76: =(N38-$E$65)*120/10+G75
D77: 8 | E77: =(L39-$E$65)*120/10+E76 | F77: =(M39-$E$65)*120/10+F76 | G77: =(N39-$E$65)*120/10+G76
D78: 9 | E78: =(L40-$E$65)*120/10+E77 | F78: =(M40-$E$65)*120/10+F77 | G78: =(N40-$E$65)*120/10+G77
D79: 10 | E79: =(L41-$E$65)*120/10+E78 | F79: =(M41-$E$65)*120/10+F78 | G79: =(N41-$E$65)*120/10+G78

Sheet 星轨探测
B2: 活动持续时间
B3: 卡池数值
C4: *钻石 | D4: *钻石
C5: 单抽价格 | D5: 五连价格 | E5: 保底 | F5: 期望 | G5: 实际概率 | H5: 期望比
C6: 100 | D6: 500 | E6: 90 | F6: 80 | G6: =1/F6 | H6: =F6/E6
T7: 450
C8: 物品类型 | D8: 数量 | E8: 价值 | F8: 权重 | G8: 抽取概率 | H8: 保底概率 | I8: 保底抽数 | J8: 单抽价值 | K8: 实际价值 | L8: 实际数量 | M8: 前N次不出 | N8: N次必出 | O8: 抽中后N次不出 | P8: 至多获取上限 | Q8: 展示概率 | T8: 450抽产出
A9: 8 | C9: 织梦补星机 | D9: 1 | E9: 12000 | F9: 10 | G9: =F9/$F$17 | H9: =1/I9 | I9: 90 | J9: =H9*E9 | K9: =J9 | L9: =H9*D9 | M9: 20 | N9: 90 | O9: 20 | P9: 5 | Q9: =H9 | R9: =Q9*10000 | S9: 织梦补星机 | T9: =$T$7*H9*D9
A10: 5 | C10: 探测器 | D10: 1 | E10: 100 | F10: 700 | G10: =F10/$F$17 | H10: =(1-$H$9)*(F10/($F$17-$F$9)) | I10: =1/H10 | J10: =H10*E10 | K10: =J10 | L10: =H10*D10 | Q10: =H10 | R10: =Q10*10000 | S10: 探测器 | T10: =$T$7*H10*D10
A11: 7 | C11: 智械发条 | D11: 1 | E11: 150 | F11: 600 | G11: =F11/$F$17 | H11: =(1-$H$9)*(F11/($F$17-$F$9)) | I11: =1/H11 | J11: =H11*E11 | K11: =J11 | L11: =H11*D11 | Q11: =H11 | R11: =Q11*10000 | S11: =C11 | T11: =$T$7*H11*D11
A12: 6 | C12: 幻梦晶核 | D12: 2 | E12: 120 | F12: 600 | G12: =F12/$F$17 | H12: =(1-$H$9)*(F12/($F$17-$F$9)) | I12: =1/H12 | J12: =H12*E12 | K12: =J12 | L12: =H12*D12 | Q12: =H12 | R12: =Q12*10000 | S12: 幻梦晶核 | T12: =$T$7*H12*D12
A13: 4 | C13: 精密齿轮 | D13: 50 | E13: 50 | F13: 2022 | G13: =F13/$F$17 | H13: =(1-$H$9)*(F13/($F$17-$F$9)) | I13: =1/H13 | J13: =H13*E13 | K13: =J13 | L13: =H13*D13 | Q13: =H13 | R13: =Q13*10000 | S13: =C13 | T13: =$T$7*H13*D13
A14: 3 | C14: 装备图纸 | D14: 10 | E14: 30 | F14: 2023 | G14: =F14/$F$17 | H14: =(1-$H$9)*(F14/($F$17-$F$9)) | I14: =1/H14 | J14: =H14*E14 | K14: =J14 | L14: =H14*D14 | Q14: =H14 | R14: =Q14*10000 | S14: 装备图纸 | T14: =$T$7*H14*D14
A15: 1 | C15: 转运石 | D15: 60 | E15: 20 | F15: 2023 | G15: =F15/$F$17 | H15: =(1-$H$9)*(F15/($F$17-$F$9)) | I15: =1/H15 | J15: =H15*E15 | K15: =J15 | L15: =H15*D15 | Q15: =H15 | R15: =Q15*10000 | S15: 转运石 | T15: =$T$7*H15*D15
A16: 2 | C16: 金币 | D16: 500 | E16: 25 | F16: 2022 | G16: =F16/$F$17 | H16: =(1-$H$9)*(F16/($F$17-$F$9)) | I16: =1/H16 | J16: =H16*E16 | K16: =J16 | L16: =H16*D16 | Q16: =H16 | R16: =Q16*10000 | S16: 金币 | T16: =$T$7*H16*D16
E17: =SUM(E9:E16) | F17: 10000 | J17: =SUM(J9:J16) | K17: =SUM(K9:K16) | L17: 197.88932
J18: 节点累抽 | K18: =G33 | L18: =L17+K18 | O18: 单抽返利比 | P18: =J17/C6
I19: 实际概率 | J19: 加节点的单抽 | K19: =K17+K18 | O19: 加累抽的返利比 | P19: =K19/C6
B20: 节点数值 | I20: =1/F6 | J20: =I20*E9
I21: 0.068291514 | J21: =I21*E10 | M21: 价值 | N21: 权重 | O21: 价值
C22: 抽取次数 | D22: 奖励内容 | E22: 奖励数量 | F22: 奖励价值 | G22: 返利比 | I22: 0.059392726 | J22: =I22*E11 | K22: 载具核心随机箱 | L22: 粉核心1（核心） | M22: 16000 | N22: 833 | O22: =N22*M22/$N$31
B23: 10 | C23: 10 | D23: 探测器 | E23: 2 | F23: =E23*$C$6 | G23: =F23/C23/60 | I23: 0.059392726 | J23: =I23*E12 | L23: 粉核心2（核心） | M23: 16000 | N23: 833 | O23: =N23*M23/$N$31
B24: 10 | C24: 20 | D24: 钻石 | E24: 150 | F24: 150 | G24: =F24/(C24-C23)/60 | I24: 0.20015349 | J24: =I24*E13 | L24: 粉核心3 | M24: 16000 | N24: 834 | O24: =N24*M24/$N$31
B25: 10 | C25: 30 | D25: B级时装·头饰 | E25: 1 | F25: 500 | G25: =F25/C25/60 | I25: 0.20025247 | J25: =I25*E14 | L25: 红零件1（核心） | M25: 8000 | N25: 2500 | O25: =N25*M25/$N$31
B26: 20 | C26: 50 | D26: B级时装·衣服 | E26: 1 | F26: 500 | G26: =F26/(C26-C25)/60 | I26: 0.20025247 | J26: =I26*E15 | L26: 红零件2（核心） | M26: 8000 | N26: 2500 | O26: =N26*M26/$N$31
B27: 20 | C27: 70 | D27: 探测器 | E27: 5 | F27: =E27*$C$6 | G27: =F27/C27/60 | I27: 0.20015349 | J27: =I27*E16 | L27: 红零件3 | M27: 8000 | N27: 2500 | O27: =N27*M27/$N$31
B28: 30 | C28: 100 | D28: 探测器 | E28: 10 | F28: =E28*$C$6 | G28: =F28/(C28-C27)/60
B29: 50 | C29: 150 | D29: 幻梦晶核 | E29: 30 | F29: 1800 | G29: =F29/C29/60 | J29: =SUM(J20:J28)
B30: 50 | C30: 200 | D30: 探测器 | E30: 10 | F30: =E30*$C$6 | G30: =F30/(C30-C29)/60
B31: 50 | C31: 250 | D31: 探测器 | E31: 10 | F31: =E31*$C$6 | G31: =F31/C31/60 | N31: =SUM(N21:N30) | O31: =SUM(O22:O30)
B32: 100 | C32: 350 | D32: 自选创世零件核心 | E32: 1 | F32: 8000 | G32: =F32/(C32-C31)/60
F33: =SUM(F23:F32) | G33: =F33/C32
B37: 任务数值
C38: 仅统计活动期 | D38: 任务汇总 | E38: 20
C39: 刷新频率 | D39: 任务类型 | E39: 数量 | F39: 奖励内容 | G39: 奖励数量 | H39: 奖励价值 | I39: 天数
B40: 日常 | C40: 每日刷新 | D40: 每日登录游戏 | F40: 探测器 | G40: 1 | H40: =G40*$C$6*I40 | I40: 5
B41: 核心循环 | C41: 一次性 | D41: 竞技场挑战次数 | E41: 5 | F41: 探测器 | G41: 1 | H41: =G41*$C$6
C42: 一次性 | D42: 竞技场挑战次数 | E42: 10 | F42: 探测器 | G42: 1 | H42: =G42*$C$6
C43: 一次性 | D43: 竞技场挑战次数 | E43: 15 | F43: 探测器 | G43: 2 | H43: =G43*$C$6
B44: 当期消耗 | C44: 一次性 | D44: 活动期间消耗体力 | E44: 100 | F44: 探测器 | G44: 1 | H44: =G44*$C$6
C45: 一次性 | D45: 活动期间消耗体力 | E45: 200 | F45: 探测器 | G45: 1 | H45: =G45*$C$6
C46: 一次性 | D46: 活动期间消耗体力 | E46: 300 | F46: 探测器 | G46: 1 | H46: =G46*$C$6
B47: 钻消&付费 | C47: 一次性 | D47: 活动期消耗钻石 | E47: 300 | F47: 探测器 | G47: 1 | H47: =G47*$C$6
C48: 一次性 | D48: 活动期消耗钻石 | E48: 600 | F48: 探测器 | G48: 1 | H48: =G48*$C$6
C49: 一次性 | D49: 任意充值次数 | E49: 1 | F49: 探测器 | G49: 2 | H49: =G49*$C$6
B50: 核心循环 | C50: 一次性 | D50: 合作本挑战 | E50: 5 | F50: 探测器 | G50: 2 | H50: =G50*$C$6
C51: 一次性 | D51: 合作本挑战 | E51: 10 | F51: 探测器 | G51: 2 | H51: =G51*$C$6
C52: 一次性 | D52: 合作本挑战 | E52: 15 | F52: 探测器 | G52: 2 | H52: =G52*$C$6
H53: =SUM(H40:H52)
B54: 商店数值
C56: 礼包名称 | D56: 价格（人民币） | E56: 限购次数 | F56: 物品类型 | G56: 数量 | H56: 价值 | I56: 物品类型 | J56: 数量 | K56: 价值 | L56: 总价值 | M56: 返利比 | N56: 展示折扣
C57: 6元礼包 | D57: 6 | E57: 5 | F57: 钻石 | G57: 60 | H57: =G57 | I57: 探测器 | J57: 6 | K57: =J57*$C$6 | L57: =K57+H57 | M57: =L57/H57 | N57: 1折
C58: 30元礼包 | D58: 30 | E58: 5 | F58: 钻石 | G58: 300 | H58: =G58 | I58: 探测器 | J58: 10 | K58: =J58*$C$6 | L58: =K58+H58 | M58: =L58/H58 | N58: 2折
C59: 98元礼包 | D59: 98 | E59: 5 | F59: 钻石 | G59: 980 | H59: =G59 | I59: 探测器 | J59: 15 | K59: =J59*$C$6 | L59: =K59+H59 | M59: =L59/H59 | N59: 3折
E60: =E57*D57 | J60: =J57*E57 | L60: =SUM(L57:L59)
E61: =E58*D58 | J61: =J58*E58
E62: =E59*D59 | J62: =J59*E59
E63: =SUM(E60:E62) | J63: =SUM(J60:J62) | K63: =D71-J63*100
B64: 成本计算 | D64: 累积值，单位为人民币
C66: 本体数量 | D66: 纯期望 | E66: 纯保底 | F66: 预期价格 | G66: 纯保底价格
C67: 1 | D67: 81 | E67: 90 | F67: =(D67*100-$H$53)/10 | G67: =(E67*100-$H$53)/10
C68: 2 | D68: =C68*D$67 | E68: =C68*E$67 | F68: =(D68*100-$H$53)/10 | G68: =(E68*100-$H$53)/10
C69: 3 | D69: =C69*D$67 | E69: =C69*E$67 | F69: =(D69*100-$H$53)/10 | G69: =(E69*100-$H$53)/10
C70: 4 | D70: =C70*D$67 | E70: =C70*E$67 | F70: =(D70*100-$H$53)/10 | G70: =(E70*100-$H$53)/10
C71: 5 | D71: =C71*D$67 | E71: =C71*E$67 | F71: =(D71*100-$H$53)/10 | G71: =(E71*100-$H$53)/10
B75: 权重递增 | M75: 402
C76: 【全局参数】 | F76: 【多段步长配置表】(支持修改起始抽和步长) | J76: 【核心宏观指标】
C77: 基础单抽概率 | D77: 0.0012 | F77: 阶段名称 | G77: 起始抽数(>=) | H77: 每抽增加的步长 | J77: 单卡数学期望(平均出金抽数) | K77: 71.081384
C78: 硬保底抽数 | D78: 80 | F78: 基础平滑期 | G78: 1 | H78: 0 | J78: 综合出金概率(含保底) | K78: 0.0141
F79: 一阶微提期 | G79: 65 | H79: 0.015
F80: 二阶强保底 | G80: 78 | H80: 0.2
C84: 当前抽数 | D84: 配置步长 | E84: 实际概率增量 | F84: 本抽触发概率（条件） | G84: 到达本抽概率（幸存率） | H84: 本抽恰好出金概率 | I84: 累计出金概率 | J84: 阶段说明
C85: 1 | D85: 0 | E85: 0 | F85: 0 | G85: 1 | H85: 0 | I85: 0 | J85: 禁出期
C86: 2 | D86: 0 | E86: 0 | F86: 0 | G86: 1 | H86: 0 | I86: 0 | J86: 禁出期
C87: 3 | D87: 0 | E87: 0 | F87: 0 | G87: 1 | H87: 0 | I87: 0 | J87: 禁出期
C88: 4 | D88: 0 | E88: 0 | F88: 0 | G88: 1 | H88: 0 | I88: 0 | J88: 禁出期
C89: 5 | D89: 0 | E89: 0 | F89: 0 | G89: 1 | H89: 0 | I89: 0 | J89: 禁出期
C90: 6 | D90: 0 | E90: 0 | F90: 0 | G90: 1 | H90: 0 | I90: 0 | J90: 禁出期
C91: 7 | D91: 0 | E91: 0 | F91: 0 | G91: 1 | H91: 0 | I91: 0 | J91: 禁出期
C92: 8 | D92: 0 | E92: 0 | F92: 0 | G92: 1 | H92: 0 | I92: 0 | J92: 禁出期
C93: 9 | D93: 0 | E93: 0 | F93: 0 | G93: 1 | H93: 0 | I93: 0 | J93: 禁出期
C94: 10 | D94: 0 | E94: 0 | F94: 0 | G94: 1 | H94: 0 | I94: 0 | J94: 禁出期
C95: 11 | D95: 0 | E95: 0 | F95: 0 | G95: 1 | H95: 0 | I95: 0 | J95: 禁出期
C96: 12 | D96: 0 | E96: 0 | F96: 0 | G96: 1 | H96: 0 | I96: 0 | J96: 禁出期
... C174: 90 | D174: 0 | E174: 0.4038 | F174: 1 | G174: 0.0517 | H174: 0.05174 | I174: 1 | J174: 硬保底覆盖

Sheet 首月活动
B2: 活跃数 | L2: 星愿棱晶 | M2: 橙色皮肤 | N2: 红色皮肤 | O2: 幻梦晶核
D3: 道具名 | E3: 产出途径 | F3: 数量 | L3: 1 | M3: 2 | N3: 3 | O3: 4
D4: 许愿券 | K4: 超能特饮 | L4: 5 | P4: 17 | Q4: 转运石 | R4: 大份
G5: 60 | K5: 金币 | L5: 6 | P5: 16 | Q5: 幻梦晶核
E6: 大地快 | F6: 75 | K6: 星之初愿 | L6: 7 | P6: 15 | Q6: 随机能量特饮 | R6: 大份
E7: 签到 | F7: 8 | K7: 装备图纸 | L7: 8 | P7: 14 | Q7: 梦境招募器
F8: =SUM(F4:F7) | G8: =F8*G5 | L8: 9 | M8: 10 | N8: 11 | O8: 12 | P8: 13 | V8: 1.16
C9: 抽奖池 | L9: 随机能量特饮 | M9: 装备图纸 | N9: 转运石 | O9: 星之初愿 | P9: 金币
D10: 保底 | E10: 期望 | F10: 实际概率
D11: 100 | E11: 79.27 | F11: 0.0126 | G11: 0.793 | V11: 1000抽
D12: 奖励库 | N12: 保底 | O12: 实际 | P12: 单抽价格 | S12: 概率预览 | U12: 单抽 | V12: 1000
D13: 位置 | E13: 道具名称 | F13: 数量 | G13: 价值 | H13: 权重 | I13: 前N次必不出 | J13: N次必出 | K13: 中后N次必不出 | L13: 抽取概率 | M13: 保底概率 | N13: 期望起抽 | O13: 单抽价值 | P13: 单抽价值 | S13: 类别 | T13: 概率 | U13: 期望数量 | V13: 期望产出
C14: 保底库 | D14: 1 | E14: 星愿棱晶 | F14: 2 | G14: 4000 | H14: 800 | J14: 100 | K14: 20 | L14: =H14/$H$31 | M14: 0.0126 | N14: =1/M14 | O14: =L14*G14 | P14: =M14*G14 | S14: 星愿棱晶 | T14: 0.0126 | U14: 0.03 | V14: =V12/N14*F14 | W14: 126 | X14: 12
A15: 100018 | B15: 绮梦自选礼盒（全） | C15: 橙色自选梦灵皮肤 | D15: 2 | F15: 1 | G15: 4000 | H15: 20 | K15: 20 | L15: =H15/$H$31 | M15: 0.0002 | N15: =1/M15 | O15: =L15*G15 | P15: =M15*G15 | S15: 橙色自选梦灵皮肤 | T15: 0.0002 | U15: 0 | V15: 0.2 | W15: 2 | X15: 0
A16: 100101 | B16: 繁星自选礼盒（全） | C16: 红色自选梦灵皮肤 | D16: 3 | F16: 1 | G16: 8000 | H16: 10 | K16: 20 | L16: =H16/$H$31 | M16: 0.0001 | N16: =1/M16 | O16: =L16*G16 | P16: =M16*G16 | S16: 红色自选梦灵皮肤 | T16: 0.0001 | U16: 0 | V16: 0.1 | W16: 1 | X16: 0
B17: 自选全部 | D17: 4 | E17: 幻梦晶核 | F17: 50 | G17: 3000 | H17: 20 | L17: =H17/$H$31 | M17: 0.0002 | N17: =1/M17 | O17: =L17*G17 | P17: =M17*G17 | S17: 幻梦晶核 | T17: 0.0599 | U17: 0.13 | V17: 129.4 | W17: 599 | X17: 48
D18: 5 | E18: 超能特饮 | F18: 100 | G18: 200 | H18: 3200 | L18: =H18/$H$31 | M18: 0.032 | N18: =1/M18 | O18: =L18*G18 | P18: =M18*G18 | S18: 超能特饮 | T18: 0.0319 | U18: 3.19 | V18: 3185.1 | W18: 319 | X18: 1100
D19: 12 | E19: 星之初愿 | F19: 1 | G19: 50 | H19: 12000 | L19: =H19/$H$31 | M19: 0.1194 | N19: =1/M19 | O19: =L19*G19 | P19: =M19*G19 | S19: 星之初愿 | T19: 0.1393 | U19: 0.16 | V19: 159.3 | W19: 1393 | X19: 63
D20: 7 | E20: 星之初愿 | F20: 2 | G20: 100 | H20: 2000 | L20: =H20/$H$31 | M20: 0.0199 | N20: =1/M20 | O20: =L20*G20 | P20: =M20*G20 | S20: 梦境招募器 | T20: 0.0513 | U20: 0.26 | V20: 256.3 | W20: 513 | X20: 101
D21: 16 | E21: 幻梦晶核 | F21: 2 | G21: 120 | H21: 6000 | L21: =H21/$H$31 | M21: 0.0597 | N21: =1/M21 | O21: =L21*G21 | P21: =M21*G21 | S21: 随机能量特饮 | T21: 0.1991 | U21: 11.94 | V21: 11944.2 | W21: 1991 | X21: 5390
D22: 14 | E22: 梦境招募器 | F22: 5 | G22: 150 | H22: 5150 | L22: =H22/$H$31 | M22: 0.0513 | N22: =1/M22 | O22: =L22*G22 | P22: =M22*G22 | S22: 装备图纸 | T22: 0.1642 | U22: 1.87 | V22: 1866.3 | W22: 1642 | X22: 928
D23: 9 | E23: 随机能量特饮 | F23: 50 | G23: 50 | H23: 16000 | L23: =H23/$H$31 | M23: 0.1593 | N23: =1/M23 | O23: =L23*G23 | P23: =M23*G23 | S23: 转运石 | T23: 0.1821 | U23: 26.64 | V23: 26635.5 | W23: 1821 | X23: 12480
D24: 15 | E24: 随机能量特饮 | F24: 100 | G24: 100 | H24: 4000 | L24: =H24/$H$31 | M24: 0.0398 | N24: =1/M24 | O24: =L24*G24 | P24: =M24*G24 | S24: 金币 | T24: 0.1593 | U24: 99.53 | V24: 99534.8 | W24: 1593 | X24: 40000
D25: 10 | E25: 装备图纸 | F25: 10 | G25: 30 | H25: 12000 | L25: =H25/$H$31 | M25: 0.1194 | N25: =1/M25 | O25: =L25*G25 | P25: =M25*G25
D26: 8 | E26: 装备图纸 | F26: 15 | G26: 45 | H26: 4500 | L26: =H26/$H$31 | M26: 0.0448 | N26: =1/M26 | O26: =L26*G26 | P26: =M26*G26
D27: 11 | E27: 转运石 | F27: 120 | G27: 40 | H27: 14300 | L27: =H27/$H$31 | M27: 0.1423 | N27: =1/M27 | O27: =L27*G27 | P27: =M27*G27
D28: 17 | E28: 转运石 | F28: 240 | G28: 80 | H28: 4000 | L28: =H28/$H$31 | M28: 0.0398 | N28: =1/M28 | O28: =L28*G28 | P28: =M28*G28
D29: 13 | E29: 金币 | F29: 500 | G29: 25 | H29: 12000 | L29: =H29/$H$31 | M29: 0.1194 | N29: =1/M29 | O29: =L29*G29 | P29: =M29*G29
D30: 6 | E30: 金币 | F30: 1000 | G30: 50 | H30: 4000 | L30: =H30/$H$31 | M30: 0.0398 | N30: =1/M30 | O30: =L30*G30 | P30: =M30*G30 | Q30: 计算节点 | R30: 计算节点
H31: 100000 | L31: =SUM(L14:L30) | M31: =SUM(M14:M30) | O31: =SUM(O14:O30) | P31: =SUM(P14:P30) | Q31: =P31+H68 | R31: =O31+H68
N32: 返比 | O32: =O31/$G$5 | P32: =P31/$G$5 | Q32: =Q31/60 | R32: =R31/60
C34: 节点数值 | Q34: =O74*P31
P35: 免费 | Q35: =O46
B36: 累计节点 | D36: 抽取次数 | E36: 奖励内容 | F36: 奖励数量 | G36: 奖励价值 | H36: 返利比 | Q36: =SUM(Q34:Q35)
A37: =B37*60 | B37: =C37 | C37: 5 | D37: 5 | E37: 许愿券 | F37: 2 | G37: 120 | H37: 0.4 | I37: =G37/(C37*60) | Q37: =Q36/O74+H68
A38: =B38*60 | B38: =C37+C38 | C38: 10 | D38: 15 | E38: 钻石 | F38: 100 | G38: 100 | H38: 0.17 | I38: =G38/(C38*60) | Q38: =Q37/60
A39: =B39*60 | B39: =C39+B38 | C39: 20 | D39: 35 | E39: 星愿棱晶 | F39: 1 | G39: 2000 | H39: 1.67 | I39: =G39/(C39*60)
A40: =B40*60 | B40: =C40+B39 | C40: 25 | D40: 60 | E40: 钻石 | F40: 150 | G40: 150 | H40: 0.1 | I40: =G40/(C40*60)
A41: =B41*60 | B41: =C41+B40 | C41: 25 | D41: 85 | E41: 许愿券 | F41: 3 | G41: 180 | H41: 0.12 | I41: =G41/(C41*60) | M41: 免费收益 | N41: 小地块 | O41: =J113 | P41: =O41/$O$46
A42: =B42*60 | B42: =C42+B41 | C42: 30 | D42: 115 | E42: 钻石 | F42: 150 | G42: 150 | H42: 0.08 | I42: =G42/(C42*60) | N42: 大地块 | O42: =J120 | P42: =O42/$O$46
A43: =B43*60 | B43: =C43+B42 | C43: 30 | D43: 145 | E43: 星愿棱晶 | F43: 1 | G43: 2000 | H43: 1.11 | I43: =G43/(C43*60) | J43: 随机橙卡皮肤1 | K43: [{100120,1}] | N43: 签到 | O43: =H204 | P43: =O43/$O$46
A44: =B44*60 | B44: =C44+B43 | C44: 30 | D44: 175 | E44: 许愿券 | F44: 3 | G44: 180 | H44: 0.1 | I44: =G44/(C44*60) | N44: 全服进度 | O44: =G133 | P44: =O44/$O$46
A45: =B45*60 | B45: =C45+B44 | C45: 30 | D45: 205 | E45: 钻石 | F45: 150 | G45: 150 | H45: 0.08 | I45: =G45/(C45*60) | N45: 单进度 | O45: =F158 | P45: =O45/$O$46
A46: =B46*60 | B46: =C46+B45 | C46: 45 | D46: 250 | E46: 许愿券 | F46: 5 | G46: 300 | H46: 0.11 | I46: =G46/(C46*60) | O46: =SUM(O41:O45)
A47: =B47*60 | B47: =C47+B46 | C47: 45 | D47: 295 | E47: 钻石 | F47: 150 | G47: 150 | H47: 0.06 | I47: =G47/(C47*60)
A48: =B48*60 | B48: =C48+B47 | C48: 45 | D48: 340 | E48: 许愿券 | F48: 5 | G48: 300 | H48: 0.11 | I48: =G48/(C48*60)
A49: =B49*60 | B49: =C49+B48 | C49: 45 | D49: 385 | E49: 钻石 | F49: 150 | G49: 150 | H49: 0.06 | I49: =G49/(C49*60)
A50: =B50*60 | B50: =C50+B49 | C50: 45 | D50: 430 | E50: 星愿棱晶 | F50: 1 | G50: 2000 | H50: 0.74 | I50: =G50/(C50*60) | J50: 随机橙卡皮肤2 | K50: [{100122,1}]
A51: =B51*60 | B51: =C51+B50 | C51: 70 | D51: 500 | E51: 许愿券 | F51: 5 | G51: 300 | H51: 0.07 | I51: =G51/(C51*60)
A52: =B52*60 | B52: =C52+B51 | C52: 75 | D52: 575 | E52: 钻石 | F52: 500 | G52: 500 | H52: 0.11 | I52: =G52/(C52*60)
A53: =B53*60 | B53: =C53+B52 | C53: 170 | D53: 745 | E53: 许愿券 | F53: 5 | G53: 300 | H53: 0.03 | I53: =G53/(C53*60)
A54: =B54*60 | B54: =C54+B53 | C54: 185 | D54: 930 | E54: 星愿棱晶 | F54: 2 | G54: 4000 | H54: 0.36 | I54: =G54/(C54*60) | J54: 自选全橙卡 | K54: [{100127,1}]
A55: =B55*60 | B55: =C55+B54 | C55: 210 | D55: 1140 | E55: 钻石 | F55: 500 | G55: 500 | H55: 0.04 | I55: =G55/(C55*60)
A56: =B56*60 | B56: =C56+B55 | C56: 310 | D56: 1450 | E56: 许愿券 | F56: 5 | G56: 300 | H56: 0.02 | I56: =G56/(C56*60) | J56: 自选全红卡 | K56: [{100126,1}]
A57: =B57*60 | B57: =C57+B56 | C57: 300 | D57: 1750 | E57: 钻石 | F57: 500 | G57: 500 | H57: 0.03 | I57: =G57/(C57*60)
A58: =B58*60 | B58: =C58+B57 | C58: 300 | D58: 2050 | E58: 许愿券 | F58: 5 | G58: 300 | H58: 0.02 | I58: =G58/(C58*60)
A59: =B59*60 | B59: =C59+B58 | C59: 400 | D59: 2450 | E59: 钻石 | F59: 500 | G59: 500 | H59: 0.02 | I59: =G59/(C59*60)
A60: =B60*60 | B60: =C60+B59 | C60: 400 | D60: 2850 | E60: 许愿券 | F60: 5 | G60: 300 | H60: 0.01 | I60: =G60/(C60*60)
A61: =B61*60 | B61: =C61+B60 | C61: 400 | D61: 3250 | E61: 钻石 | F61: 500 | G61: 500 | H61: 0.02 | I61: =G61/(C61*60)
A62: =B62*60 | B62: =C62+B61 | C62: 400 | D62: 3650 | E62: 许愿券 | F62: 5 | G62: 300 | H62: 0.01 | I62: =G62/(C62*60)
A63: =B63*60 | B63: =C63+B62 | C63: 500 | D63: 4150 | E63: 钻石 | F63: 500 | G63: 500 | H63: 0.02 | I63: =G63/(C63*60)
A64: =B64*60 | B64: =C64+B63 | C64: 500 | D64: 4650 | E64: 许愿券 | F64: 5 | G64: 300 | H64: 0.01 | I64: =G64/(C64*60)
A65: =B65*60 | B65: =C65+B64 | C65: 500 | D65: 5150 | E65: 钻石 | F65: 500 | G65: 500 | H65: 0.02 | I65: =G65/(C65*60)
A66: =B66*60 | B66: =C66+B65 | C66: 500 | D66: 5650 | E66: 许愿券 | F66: 5 | G66: 300 | H66: 0.01 | I66: =G66/(C66*60)
A67: =B67*60 | B67: =C67+B66 | C67: 500 | D67: 6150 | E67: 钻石 | F67: 500 | G67: 500 | H67: 0.02 | I67: =G67/(C67*60)
G68: =SUM(G37:G67) | H68: =G68/C67
C71: 兑换商店
A73: 100017 | B73: 繁星自选礼盒Ⅰ | D73: 物品名称 | E73: 数量 | F73: 价值 | G73: 可兑换次数 | H73: 兑换消耗 | I73: 数量 | J73: 价值 | K73: 折扣 | O73: 累计抽数
C74: 1 | D74: 红色自选梦灵皮肤 | E74: 1 | F74: 8000 | G74: 5 | H74: 星愿棱晶 | I74: 4 | J74: =I74*2000 | K74: =J74/F74 | M74: =I74*G74 | O74: =M79/F14*N14
C75: 2 | D75: 橙色自选梦灵皮肤 | E75: 1 | F75: 4000 | G75: 5 | H75: 星愿棱晶 | I75: 2 | J75: =I75*2000 | K75: =J75/F75 | M75: =I75*G75
C76: 3 | D76: 神话洗炼石 | E76: 1 | F76: 6000 | G76: 3 | H76: 星愿棱晶 | I76: 3 | J76: =I76*2000 | K76: =J76/F76 | L76: 必出 | M76: =I76*G76 | O76: =K93 | P76: =O76*4 | Q76: =E93*4
C77: 4 | D77: 幻梦晶核 | E77: 50 | F77: 3000 | G77: 20 | H77: 星愿棱晶 | I77: 1 | J77: =I77*2000 | K77: =J77/F77 | N77: =I77*G77
A78: 自选3个 | C78: 5 | D78: 星辉秘契 | E78: 5 | F78: 1400 | G78: 5 | H78: 星愿棱晶 | I78: 1 | J78: =I78*2000 | K78: =J78/F78 | M78: =SUM(M74:M77) | N78: =I78*G78 | P78: =O74-P76-F8 | Q78: =P78*60 | R78: =Q78/10
A79: 自选3个 | C79: 6 | D79: 梦境招募器 | E79: 50 | F79: 1500 | G79: 5 | H79: 星愿棱晶 | I79: 1 | J79: =I79*2000 | K79: =J79/F79 | M79: =M78-5 | N79: =I79*G79 | Q79: 总价格 | R79: =R78+Q76
C80: 7 | D80: 星之初愿 | E80: 30 | F80: 1500 | G80: 5 | H80: 星愿棱晶 | I80: 1 | J80: =I80*2000 | K80: =J80/F80 | N80: =I80*G80
C81: 8 | D81: 超能特饮 | E81: 500 | F81: 1000 | G81: 20 | H81: 星愿棱晶 | I81: 1 | J81: =I81*2000 | K81: =J81/F81 | N81: =I81*G81
C82: 9 | D82: 装备图纸 | E82: 500 | F82: 1500 | G82: 5 | H82: 星愿棱晶 | I82: 1 | J82: =I82*2000 | K82: =J82/F82 | N82: =I82*G82
N83: =SUM(N77:N82) | O83: =N83+M79 | P83: =O83/F14*E11
C84: 商店数值
D86: 礼包名称 | E86: 价格（人民币） | F86: 限购次数 | G86: 物品类型 | H86: 数量 | I86: 价值 | J86: 物品类型 | K86: 数量 | L86: 价值 | M86: 总价值 | N86: 返利比 | O86: 历史数据 | P86: 折扣
D87: 6元礼包 | E87: 6 | F87: 5 | G87: 钻石 | H87: 60 | I87: 60 | J87: 许愿券 | K87: 10 | L87: =K87*60 | M87: =L87+H87 | N87: =M87/H87 | O87: 5 | P87: 1折 | Q87: =H87/M87
D88: 30元礼包 | E88: 30 | F88: 5 | G88: 钻石 | H88: 300 | I88: 300 | J88: 许愿券 | K88: 15 | L88: =K88*60 | M88: =L88+H88 | N88: =M88/H88 | O88: 10 | P88: 2折 | Q88: =H88/M88
D89: 98元礼包 | E89: 98 | F89: 5 | G89: 钻石 | H89: 980 | I89: 980 | J89: 许愿券 | K89: 25 | L89: =K89*60 | M89: =L89+H89 | N89: =M89/H89 | O89: 25 | P89: 4折 | Q89: =H89/M89
E90: =F87*E87 | K90: =K87*F87
E91: =F88*E88 | K91: =K88*F88 | M91: 每周1更新3次
E92: =F89*E89 | K92: =K89*F89
E93: =SUM(E90:E92) | K93: =SUM(K90:K92)
C96: 踩格子活动
C97: 积分获得
D98: 首通对应的玩法类型，可获得积分。单关首通指该玩法的某个新关卡被首通时可获得的积分。
D99: 类型 | E99: 单关首通可 | F99: 非r前25分数 | G99: 氪佬前25分数 | I99: 非r前25分数 | J99: 氪佬前25分数
D100: 主线 | E100: 2 | F100: 128 | G100: 240 | I100: 64 | J100: 120
D101: 金币本 | E101: 3 | F101: 51 | G101: 90 | I101: 17 | J101: 30
D102: 组队本 | E102: 5 | F102: 30 | G102: 60 | I102: 6 | J102: 12
F103: =SUM(F100:F102) | G103: =SUM(G100:G102)
F104: 3594.8 | G104: 6708
C105: 小地块宝箱 | D105: 宝箱id: 100106 | F105: =F104/F103 | G105: =G104/G103
D106: 节点宝箱
D107: 物品 | E107: 数量 | F107: 价值 | G107: 权重 | H107: 概率 | K107: 每消耗1个积分可激活1个小地块，获得小地块宝箱
D108: 金币 | E108: 200 | F108: 10 | G108: 220 | H108: 0.22 | I108: 2.2 | K108: 单个地块累积消耗5积分时会激活该地块，获得大地块宝箱
...

Sheet 微信小游戏独立数值
A1: IAA
A2: 每日充值 | B2: 1次
A3: 日、周、月 | B3: 更新时候新增一次
A4: 活动开启 | B4: 免费后跟一次广告
A5: 玩法活动 | B5: 双倍奖励、次数新增
A6: 观影密藏 | B6: 每周1次 | C6: 每天5个广告 | D6: 给与一定的洗练石奖励
A7: 限时活动充值 | B7: 广告1次
A8: 主线关卡 | B8: 双倍奖励
A9: 具体规划下
A10: 快速扫荡 | B10: 2次
A12: 裂变
A13: 奖励可控
A21: 万抽、千抽
A23: 主要是形式，奖励简单一些

Sheet 符文规划
A1: 招募狂欢 | B1: 箱子品质 | C1: 目标梦灵 | D1: 价值判断 | E1: 道具1 | G1: 道具2 | I1: 道具3 | K1: 道具4 | M1: 道具5 | O1: 道具6 | R1: 价值
A2: 随机专属符文箱 | B2: 史诗 | C2: 传说 | D2: 本体 | E2: 进入战斗前60秒对怪物伤害 | G2: 怪物血量高70%增伤 | I2: 负面怪物增伤15% | K2: 攻击满血怪物暴击率25% | M2: 对精英和首领伤害 | O2: 职业攻击力 | T2: 传说祝福石调整到5次
A3: 自选专属符文箱 | B3: 史诗 | C3: 传说 | D3: 本体 | E3: 进入战斗前60秒对怪物伤害 | G3: 怪物血量高70%增伤 | I3: 负面怪物增伤15% | K3: 攻击满血怪物暴击率25% | M3: 对精英和首领伤害 | O3: 职业攻击力
A4: 随机稀有符文箱 | B4: 传说 | C4: 神话 | D4: 本体+洗炼 | E4: 载具满耐久时，伤害 | G4: 在80%~130%之间波动 | I4: 暴击伤害 | K4: 攻击满血怪物时，暴击率 | M4: 队长每触发一次暴击，所有梦灵伤害+1.5%，最多8次 | O4: 队长技能冷却缩短20%
X6: 连充活动
R8: 1 | S8: 普通
R9: 2 | S9: 普通 | T9: 神话祝福石调整到15次
R10: 3
R11: 4 | S11: 专属
R12: 5 | X12: 连充活动
R13: 6
R14: 7
R15: 8 | S15: 专属
R19: 冲刺
R20: 蔚蓝 | T20: 梦境
R21: 随机神话稀有符文 | S21: 红色稀有+红色专属 | T21: 神话稀有符文箱 | U21: 红色宝+红色稀有+红色专属
R22: 随机稀有符文（红色） | S22: 红色稀有+传说专属 | T22: 神话稀有符文箱 | U22: 红色宝+橙色宝+橙色稀有+橙色专属
R23: 随机稀有符文（红色） | S23: 红色稀有+传说专属 | T23: 神话稀有符文箱 | U23: 红色宝+橙色宝+橙色稀有+橙色专属
R24: 随机传说稀有符文 | S24: 橙色宝+橙色专属 | T24: 随机传说稀有符文 | U24: 橙色宝+橙色专属
R25: 随机稀有符文

Sheet 活动时间
A1: 2026年 | B1: 周一 | C1: 周二（先锋服更新） | D1: 周三（正式服更新） | E1: 周四 | F1: 周五 | G1: 周六 | H1: 周日
A2: 6月 | B2: 1 | C2: 2 | D2: 3 | E2: 4 | F2: 5 | G2: 6 | H2: 7
B3: 8 | C3: 9 | D3: 10 | E3: 11 | F3: 12 | G3: 13 | H3: 14
B4: 15 | C4: 16 | D4: 17 | E4: 18 | F4: 19 | G4: 20 | H4: 21
B5: 22 | C5: 23 | D5: 24 | E5: 25 | F5: 26 | G5: 27 | H5: 28 | I5: 线上最早活动 | J5: 1月活动 | K5: 30 | L5: 46113 | M5: =L5+K5-1 | N5: =K5
B6: 29 | C6: 30 | D6: 1 | E6: 2 | F6: 3 | G6: 4 | H6: 5 | J6: 2月活动 | K6: 30 | L6: =M5+1 | M6: =L6+K6-1 | N6: =K6+N5
A7: 2026年 | B7: 周一 | C7: 周二（先锋服更新） | D7: 周三（正式服更新） | E7: 周四 | F7: 周五 | G7: 周六 | H7: 周日 | J7: 3月活动 | K7: 45 | L7: =M6+1 | M7: =L7+K7-1 | N7: =K7+N6
A8: 7月 | B8: 6 | C8: 7 | D8: 8 | E8: 9 | F8: 10 | G8: 11 | H8: 12 | J8: 4月活动 | K8: 45 | L8: =M7+1 | M8: =L8+K8-1 | N8: =K8+N7
B9: 13 | C9: 14 | D9: 15-四月活动 | E9: 16-载具版本+大富翁 | F9: 17 | G9: 18 | H9: 19 | J9: 5月活动 | K9: 45 | L9: =M8+1 | M9: =L9+K9-1 | N9: =K9+N8
B10: 20 | C10: 21 | D10: 22 | E10: 23-四月活动抽奖 | F10: 24 | G10: 25 | H10: 26 | J10: 6月活动 | K10: 60 | L10: =M9+1 | M10: =L10+K10-1 | N10: =K10+N9 | P10: 拿骇客的改
B11: 27 | C11: 28 | D11: 29 | E11: 30-新粉卡+粉卡符文 | F11: 31 | G11: 1 | H11: 2
A12: 2026年 | B12: 周一 | C12: 周二（先锋服更新） | D12: 周三（正式服更新） | E12: 周四 | F12: 周五 | G12: 周六 | H12: 周日
A13: 8月 | B13: 3 | C13: 4 | D13: 5 | E13: 6 | F13: 7 | G13: 8 | H13: 9
B14: 10 | C14: 11 | D14: 12 | E14: 13 | F14: 14 | G14: 15 | H14: 16
B15: 17 | C15: 18 | D15: 19 | E15: 20 | F15: 21 | G15: 22 | H15: 23 | I15: 新服活动 | J15: 1月活动 | K15: 30 | L15: 46232 | M15: =L15+K15-1
B16: 24 | C16: 25 | D16: 26 | E16: 27 | F16: 28 | G16: 29-5月活动（粉卡） | H16: 30 | J16: 2月活动 | K16: 30 | L16: =M15+1 | M16: =L16+K16-1
B17: 31 | J17: 3月活动 | K17: 45 | L17: =M16+1 | M17: =L17+K17-1
A18: 2026年 | B18: 周一 | C18: 周二（先锋服更新） | D18: 周三（正式服更新） | E18: 周四 | F18: 周五 | G18: 周六 | H18: 周日 | J18: 4月活动 | K18: 45 | L18: =M17+1 | M18: =L18+K18-1
A19: 9月 | C19: 1 | D19: 2 | E19: 3 | F19: 4 | G19: 5 | H19: 6 | J19: 5月活动 | K19: 45 | L19: =M18+1 | M19: =L19+K19-1
B20: 7 | C20: 8 | D20: 9 | E20: 10 | F20: 11 | G20: 12 | H20: 13 | J20: 6月活动 | K20: 60 | L20: =M19+1 | M20: =L20+K20-1
B21: 14 | C21: 15 | D21: 16 | E21: 17 | F21: 18 | G21: 19 | H21: 20
B22: 21 | C22: 22 | D22: 23 | E22: 24 | F22: 25-中秋节 | G22: 26 | H22: 27
B23: 28 | C23: 29 | D23: 30
A24: 2026年 | B24: 周一 | C24: 周二（先锋服更新） | D24: 周三（正式服更新） | E24: 周四 | F24: 周五 | G24: 周六 | H24: 周日 | I24: 划断新服 | J24: 1月活动 | K24: 30 | L24: 46269 | M24: =L24+K24-1
A25: 10月 | E25: 1 | F25: 2 | G25: 3 | H25: 4 | J25: 2月活动 | K25: 30 | L25: =M24+1 | M25: =L25+K25-1 | N25: 零日骇客 | O25: 15天 | P25: 雅典娜活动15天
B26: 5 | C26: 6 | D26: 7 | E26: 8 | F26: 9 | G26: 10 | H26: 11 | J26: 3月活动 | K26: 45 | L26: =M25+1 | M26: =L26+K26-1 | N26: 红色皮肤 | O26: 30天
B27: 12 | C27: 13 | D27: 14 | E27: 15 | F27: 16 | G27: 17 | H27: 18 | J27: 4月活动 | K27: 45 | L27: =M26+1 | M27: =L27+K27-1
B28: 19 | C28: 20 | D28: 21 | E28: 22 | F28: 23 | G28: 24 | H28: 25 | J28: 5月活动 | K28: 45 | L28: =M27+1 | M28: =L28+K28-1
B29: 26 | C29: 27 | D29: 28 | E29: 29 | F29: 30 | G29: 31 | J29: 6月活动 | K29: 60 | L29: =M28+1 | M29: =L29+K29-1
B40: 46268 | C40: =B40-150
B41: 46267 | C41: =B41-1
B42: 46268 | C42: =B42-164 | I42: 当前 | J42: 修改 | K42: 提升
B43: 46144 | C43: =B43+150 | H43: 招募冲刺 | I43: 400 | J43: 500 | K43: =(J43-I43)/I43
I44: 600 | J44: 700 | K44: =(J44-I44)/I44
I45: 800 | J45: 1200 | K45: =(J45-I45)/I45
I46: 1200 | J46: 1600 | K46: =(J46-I46)/I46
H47: 汇总 | I47: =SUM(I43:I46) | J47: =SUM(J43:J46) | K47: =(J47-I47)/I47
I48: 当前 | J48: 修改 | K48: 提升
H49: 符文冲刺 | I49: 200 | J49: 300 | K49: =(J49-I49)/I49
I50: 400 | J50: 500 | K50: =(J50-I50)/I50
I51: 600 | J51: 700 | K51: =(J51-I51)/I51
I52: 800 | J52: 1000 | K52: =(J52-I52)/I52
H53: 汇总 | I53: =SUM(I49:I52) | J53: =SUM(J49:J52) | K53: =(J53-I53)/I53
I54: 当前 | J54: 修改 | K54: 提升
H55: 秘宝冲刺 | I55: 24000 | J55: 20000 | K55: =(J55-I55)/I55
I56: 36000 | J56: 40000 | K56: =(J56-I56)/I56
I57: 48000 | J57: 60000 | K57: =(J57-I57)/I57
I58: 64000 | J58: 120000 | K58: =(J58-I58)/I58
H59: 汇总 | I59: =SUM(I55:I58) | J59: =SUM(J55:J58) | K59: =(J59-I59)/I59

Sheet 活动页签
A1: 月奕山河
